Workbook
Name scenario: Inputs!$C$2
Name cohort_size: Inputs!$F$8
Name cohort_size_ng: Inputs!$J$8
Name mix_gig: Inputs!$F$9
Name mix_gig_ng: Inputs!$J$9
Name disc_rate: Inputs!$F$10
Name disc_rate_ng: Inputs!$J$10
Name usd_inr: Inputs!$F$11
Name usd_inr_ng: Inputs!$J$11
Name ret_m1: Inputs!$F$13
Name ret_m1_ng: Inputs!$J$13
Name ret_m3: Inputs!$F$14
Name ret_m3_ng: Inputs!$J$14
Name ret_m6: Inputs!$F$15
Name ret_m6_ng: Inputs!$J$15
Name ret_m12: Inputs!$F$16
Name ret_m12_ng: Inputs!$J$16
Name ret_m24: Inputs!$F$17
Name ret_m24_ng: Inputs!$J$17
Name churn_late: Inputs!$F$18
Name churn_late_ng: Inputs!$J$18
Name daily_amount: Inputs!$F$20
Name daily_amount_ng: Inputs!$J$20
Name amount_growth: Inputs!$F$21
Name amount_growth_ng: Inputs!$J$21
Name debits_scheduled: Inputs!$F$22
Name debits_scheduled_ng: Inputs!$J$22
Name debits_success: Inputs!$F$23
Name debits_success_ng: Inputs!$J$23
Name withdraw_rate: Inputs!$F$24
Name withdraw_rate_ng: Inputs!$J$24
Name leaver_withdraw: Inputs!$F$25
Name leaver_withdraw_ng: Inputs!$J$25
Name dormant_withdraw: Inputs!$F$26
Name dormant_withdraw_ng: Inputs!$J$26
Name fund_yield: Inputs!$F$27
Name fund_yield_ng: Inputs!$J$27
Name fd_share: Inputs!$F$28
Name fd_share_ng: Inputs!$J$28
Name fd_start: Inputs!$F$29
Name fd_start_ng: Inputs!$J$29
Name trail_liquid: Inputs!$F$31
Name trail_liquid_ng: Inputs!$J$31
Name fd_fee: Inputs!$F$32
Name fd_fee_ng: Inputs!$J$32
Name mf_incentive: Inputs!$F$33
Name mf_incentive_ng: Inputs!$J$33
Name first_time_share: Inputs!$F$34
Name first_time_share_ng: Inputs!$J$34
Name loan_start: Inputs!$F$36
Name loan_start_ng: Inputs!$J$36
Name loan_eligible: Inputs!$F$37
Name loan_eligible_ng: Inputs!$J$37
Name loan_apply: Inputs!$F$38
Name loan_apply_ng: Inputs!$J$38
Name loan_approval: Inputs!$F$39
Name loan_approval_ng: Inputs!$J$39
Name loan_ticket: Inputs!$F$40
Name loan_ticket_ng: Inputs!$J$40
Name loan_stepup: Inputs!$F$41

Sheet Inputs
A1: Inputs: every assumption, one row each
A2: Scenario (1 = bear, 2 = base, 3 = bull) | C2: 2 | D2: =CHOOSE(scenario,"Bear","Base","Bull")
A3: Blue = typed input. Black = formula. Green = link to another sheet. Yellow row = waiting on research, or a claim the pilot must prove. Every model cell uses the LIVE column, which follows the scenario switch in C2. Channel inputs sit on 'Funnel & CAC'; yearly growth inputs on 'Path to $100M'.
A5: id | B5: Assumption | C5: Bear | D5: Base | E5: Bull | F5: LIVE (gig) | G5: Non-gig bear | H5: Non-gig base | I5: Non-gig bull | J5: LIVE (non-gig) | K5: Unit | L5: Population | M5: Basis | N5: Non-gig basis | O5: Source | P5: As of | Q5: Notes
A6: Savings-first model (non-gig columns blank = same as gig)
B7: General
A8: cohort_size | B8: Activated savers in one monthly cohort | C8: 1000 | D8: 1000 | E8: 1000 | F8: =CHOOSE(scenario,C8,D8,E8) | J8: =IF(H8="",F8,CHOOSE(scenario,G8,H8,I8)) | K8: savers | L8: one monthly cohort | M8: definition | P8: 2026-09-30 | Q8: Activated = first successful auto-debit
A9: mix_gig | B9: Share of activated savers who are gig workers | C9: 0.5 | D9: 0.5 | E9: 0.5 | F9: =CHOOSE(scenario,C9,D9,E9) | J9: =IF(H9="",F9,CHOOSE(scenario,G9,H9,I9)) | K9: share | L9: each monthly cohort | M9: founder decision (2026-09-30) | P9: 2026-09-30 | Q9: Half gig (app delivery and ride), half non-gig (shopkeepers, self-employed trades, workers outside the apps, small business owners), from day one
A10: disc_rate | B10: Discount rate for LTV | C10: 0.2 | D10: 0.2 | E10: 0.2 | F10: =CHOOSE(scenario,C10,D10,E10) | J10: =IF(H10="",F10,CHOOSE(scenario,G10,H10,I10)) | K10: per year | L10: all cash flows | M10: assumption | P10: 2026-09-30 | Q10: Stated on every LTV figure
A11: usd_inr | B11: Rupees per US dollar | C11: 96.1 | D11: 96.1 | E11: 96.1 | F11: =CHOOSE(scenario,C11,D11,E11) | J11: =IF(H11="",F11,CHOOSE(scenario,G11,H11,I11)) | K11: INR per USD | L11: conversion for $ figures | M11: market rate | O11: OWN-01 | P11: 2026-09-30 | Q11: Spot rate on 30 Sep 2026
B12: Retention
A13: ret_m1 | B13: Share of activated savers still saving in month 1 | C13: 0.6 | D13: 0.7 | E13: 0.8 | F13: =CHOOSE(scenario,C13,D13,E13) | G13: 0.7 | H13: 0.72 | I13: 0.8 | J13: =IF(H13="",F13,CHOOSE(scenario,G13,H13,I13)) | K13: share | L13: per activated saver | M13: founder view (2026-09-30) | N13: benchmark proxies + judgement (no shopkeeper-specific data) | O13: INC-01 | P13: 2026-09-30 | Q13: Shape interpolated to meet the founder's 20 at 1 year / 10 at 2 years
A14: ret_m3 | B14: Still saving in month 3 | C14: 0.38 | D14: 0.48 | E14: 0.6 | F14: =CHOOSE(scenario,C14,D14,E14) | G14: 0.48 | H14: 0.53 | I14: 0.65 | J14: =IF(H14="",F14,CHOOSE(scenario,G14,H14,I14)) | K14: share | L14: per activated saver | M14: founder view (2026-09-30) | N14: benchmark proxies + judgement (no shopkeeper-specific data) | O14: INC-01 | P14: 2026-09-30
A15: ret_m6 | B15: Still saving in month 6 | C15: 0.24 | D15: 0.33 | E15: 0.45 | F15: =CHOOSE(scenario,C15,D15,E15) | G15: 0.33 | H15: 0.4 | I15: 0.53 | J15: =IF(H15="",F15,CHOOSE(scenario,G15,H15,I15)) | K15: share | L15: per activated saver | M15: founder view (2026-09-30) | N15: benchmark proxies + judgement (no shopkeeper-specific data); SBI daily Rs 250 SIP lost 35.6% of FY26 registrations within the year | O15: INC-01 | P15: 2026-09-30
A16: ret_m12 | B16: Still saving in month 12 | C16: 0.13 | D16: 0.2 | E16: 0.32 | F16: =CHOOSE(scenario,C16,D16,E16) | G16: 0.2 | H16: 0.25 | I16: 0.4 | J16: =IF(H16="",F16,CHOOSE(scenario,G16,H16,I16)) | K16: share | L16: per activated saver | M16: founder view (2026-09-30) | N16: benchmark proxies + judgement (no shopkeeper-specific data); bear = gig base | O16: INC-01 | P16: 2026-09-30 | Q16: Founder: of 100 who start, about 20 still saving after a year. Rider tenure averages about 13 months [INC-01].
A17: ret_m24 | B17: Still saving in month 24 | C17: 0.06 | D17: 0.1 | E17: 0.2 | F17: =CHOOSE(scenario,C17,D17,E17) | G17: 0.1 | H17: 0.15 | I17: 0.25 | J17: =IF(H17="",F17,CHOOSE(scenario,G17,H17,I17)) | K17: share | L17: per activated saver | M17: founder view (2026-09-30) | N17: benchmark proxies + judgement (no shopkeeper-specific data) | O17: INC-01 | P17: 2026-09-30 | Q17: Founder: about 10 of 100 still saving after two years.
A18: churn_late | B18: Monthly churn after month 24 | C18: 0.03 | D18: 0.02 | E18: 0.012 | F18: =CHOOSE(scenario,C18,D18,E18) | G18: 0.02 | H18: 0.015 | I18: 0.01 | J18: =IF(H18="",F18,CHOOSE(scenario,G18,H18,I18)) | K18: share per month | L18: active savers after month 24 | M18: assumption | N18: assumption | P18: 2026-09-30
B19: Saving
A20: daily_amount | B20: Amount per successful debit | C20: 25 | D20: 40 | E20: 60 | F20: =CHOOSE(scenario,C20,D20,E20) | G20: 30 | H20: 50 | I20: 100 | J20: =IF(H20="",F20,CHOOSE(scenario,G20,H20,I20)) | K20: INR per debit | L20: active savers year 1 | M20: assumption, sized against income | N20: benchmark: vendors save 2.2x drivers (Kenya RCT); Bachatt Rs 100-200/day and pigmy Rs 100+/day tickets; mix includes low earners. Income is NOT a clean comparison: PLFS self-employed earnings (Rs 23k urban) may be before business costs, gig Rs 18.8k is net | O20: INC-01, BAC-04, REG-043 | P20: 2026-09-30 | Q20: Daily design chosen by founder (2026-09-30). Rs 40 x 20 debits = Rs 800/month, about 4% of a full-time rider's net Rs 18,761. CONSTRAINT: daily fund saving needs at least Rs 100 a debit [REG-043]; Rs 10-99 a day works only with digital gold (gold_on) or by accumulating in the worker's own bank.
A21: amount_growth | B21: Yearly growth in amount per debit | C21: 0.05 | D21: 0.1 | E21: 0.15 | F21: =CHOOSE(scenario,C21,D21,E21) | J21: =IF(H21="",F21,CHOOSE(scenario,G21,H21,I21)) | K21: per year | L21: active savers | M21: assumption | P21: 2026-09-30
A22: debits_scheduled | B22: Debits scheduled per month | C22: 30 | D22: 30 | E22: 30 | F22: =CHOOSE(scenario,C22,D22,E22) | J22: =IF(H22="",F22,CHOOSE(scenario,G22,H22,I22)) | K22: debits per month | L22: active savers | M22: product design | P22: 2026-09-30 | Q22: Daily plan; set 4 for a weekly plan
A23: debits_success | B23: Successful debits per month | C23: 15 | D23: 20 | E23: 24 | F23: =CHOOSE(scenario,C23,D23,E23) | G23: 16 | H23: 22 | I23: 25 | J23: =IF(H23="",F23,CHOOSE(scenario,G23,H23,I23)) | K23: debits per month | L23: active savers | M23: assumption | N23: assumption: daily cash flow bounces fewer debits | O23: REG-047 | P23: 2026-09-30 | Q23: Daily plan. Debits may run only outside peak hours; one attempt plus three retries.
A24: withdraw_rate | B24: Share of balance withdrawn per month by active savers | C24: 0.15 | D24: 0.1 | E24: 0.06 | F24: =CHOOSE(scenario,C24,D24,E24) | J24: =IF(H24="",F24,CHOOSE(scenario,G24,H24,I24)) | K24: share per month | L24: active savers | M24: assumption | P24: 2026-09-30
A25: leaver_withdraw | B25: Share of balance withdrawn in the month a saver stops | C25: 0.8 | D25: 0.6 | E25: 0.4 | F25: =CHOOSE(scenario,C25,D25,E25) | J25: =IF(H25="",F25,CHOOSE(scenario,G25,H25,I25)) | K25: share | L25: savers who stop | M25: assumption | P25: 2026-09-30
A26: dormant_withdraw | B26: Share of dormant balance withdrawn per month | C26: 0.08 | D26: 0.05 | E26: 0.03 | F26: =CHOOSE(scenario,C26,D26,E26) | J26: =IF(H26="",F26,CHOOSE(scenario,G26,H26,I26)) | K26: share per month | L26: stopped savers' remaining balance | M26: assumption | P26: 2026-09-30
A27: fund_yield | B27: Liquid fund / FD yield to saver | C27: 0.05 | D27: 0.055 | E27: 0.06 | F27: =CHOOSE(scenario,C27,D27,E27) | J27: =IF(H27="",F27,CHOOSE(scenario,G27,H27,I27)) | K27: per year | L27: savings balance | M27: benchmark | O27: OWN-02 | P27: 2026 | Q27: Liquid funds 5-6% a year with repo at 5.25%; FDs at small banks pay somewhat more
A28: fd_share | B28: Share of savings balance held in bank FDs | C28: 0.2 | D28: 0.3 | E28: 0.4 | F28: =CHOOSE(scenario,C28,D28,E28) | J28: =IF(H28="",F28,CHOOSE(scenario,G28,H28,I28)) | K28: share | L28: savings balance from FD start month | M28: assumption | P28: 2026-09-30 | Q28: Goal money
A29: fd_start | B29: Month FDs start | C29: 6 | D29: 6 | E29: 6 | F29: =CHOOSE(scenario,C29,D29,E29) | J29: =IF(H29="",F29,CHOOSE(scenario,G29,H29,I29)) | K29: month | L29: cohort age | M29: product design | P29: 2026-09-30
B30: Revenue: savings
A31: trail_liquid | B31: Distributor trail on liquid-fund balance | C31: 0.0005 | D31: 0.0008 | E31: 0.0012 | F31: =CHOOSE(scenario,C31,D31,E31) | J31: =IF(H31="",F31,CHOOSE(scenario,G31,H31,I31)) | K31: per year | L31: liquid-fund balance (regular plan) | M31: benchmark: regular minus direct TER gap (an upper bound on trail) | O31: BM-01 | P31: 2026-08-31 | Q31: ICICI Pru Liquid 0.25% vs 0.17%; SBI Liquid 0.29% vs 0.17%. About Rs 4 a year on a Rs 5,000 balance.
A32: fd_fee | B32: Distribution fee on FD balance | C32: 0.0025 | D32: 0.005 | E32: 0.01 | F32: =CHOOSE(scenario,C32,D32,E32) | J32: =IF(H32="",F32,CHOOSE(scenario,G32,H32,I32)) | K32: per year | L32: FD balance | M32: benchmark, UNVERIFIED (anecdotal) | O32: BM-03 | P32: 2025-02 | Q32: Stable Money about 1% (anonymous source); Altcase 0.4%. Banks publish no rate. Modelled as a yearly % of FD balance, assuming 1-year FDs rebooked through us.
A33: mf_incentive | B33: One-time incentive per first-time MF investor | C33: 0 | D33: 0 | E33: 0 | F33: =CHOOSE(scenario,C33,D33,E33) | J33: =IF(H33="",F33,CHOOSE(scenario,G33,H33,I33)) | K33: INR per investor | L33: first-time investors starting a small SIP | M33: regulation: SEBI Choti SIP (not available to this design) | O33: REG-032, REG-033 | P33: 2025-08-11 | Q33: Rs 500 per new-to-MF investor, paid after 24 months, monthly Rs 250 equity SIP only. Forfeited if the investor holds ANY other SIP or lumpsum, and our liquid-fund saving comes first. So Rs 0 here.
A34: first_time_share | B34: Share of savers who are first-time MF investors | C34: 0.9 | D34: 0.9 | E34: 0.9 | F34: =CHOOSE(scenario,C34,D34,E34) | J34: =IF(H34="",F34,CHOOSE(scenario,G34,H34,I34)) | K34: share | L34: activated savers | M34: benchmark: company claim | O34: JAR-07 | P34: 2025-09-18 | Q34: Jar says more than 95% of its users save formally for the first time (method undisclosed).
B35: Revenue: loans
A36: loan_start | B36: Month a saver can first get a loan offer | C36: 6 | D36: 4 | E36: 3 | F36: =CHOOSE(scenario,C36,D36,E36) | J36: =IF(H36="",F36,CHOOSE(scenario,G36,H36,I36)) | K36: month | L36: cohort age | M36: product design | P36: 2026-09-30 | Q36: After a saving streak
A37: loan_eligible | B37: Share of active savers eligible for a loan offer | C37: 0.3 | D37: 0.5 | E37: 0.65 | F37: =CHOOSE(scenario,C37,D37,E37) | J37: =IF(H37="",F37,CHOOSE(scenario,G37,H37,I37)) | K37: share | L37: active savers from loan start | M37: assumption; cross-checked against the share who ever borrow | O37: LEND-04, CMP-07, CMP-05 | P37: 2026-09-30 | Q37: Benchmarks for share who ever borrow: 8% of Moneyview registered users, 11% of GCash lifetime users, 34% of eligible M-Shwari users.
A38: loan_apply | B38: Monthly application rate among eligible never-borrowed savers | C38: 0.02 | D38: 0.04 | E38: 0.06 | F38: =CHOOSE(scenario,C38,D38,E38) | J38: =IF(H38="",F38,CHOOSE(scenario,G38,H38,I38)) | K38: share per month | L38: eligible active savers who never borrowed | M38: assumption | P38: 2026-09-30
A39: loan_approval | B39: Partner approval rate for our applicants | C39: 0.4 | D39: 0.6 | E39: 0.75 | F39: =CHOOSE(scenario,C39,D39,E39) | G39: 0.35 | H39: 0.55 | I39: 0.7 | J39: =IF(H39="",F39,CHOOSE(scenario,G39,H39,I39)) | K39: share | L39: applications from eligible savers | M39: assumption (claim 2: pilot must prove) | N39: assumption: more new-to-credit, no payslip or platform data | O39: EVD-02, EVD-03 | P39: 2026-09-30 | Q39: No evidence yet that savings behaviour predicts repayment in this segment. Platform-app data does predict creditworthiness (RappiCard, EVD-02).
A40: loan_ticket | B40: Unsecured loan size (loan 5 onward) | C40: 10000 | D40: 15000 | E40: 20000 | F40: =CHOOSE(scenario,C40,D40,E40) | J40: =IF(H40="",F40,CHOOSE(scenario,G40,H40,I40)) | K40: INR | L40: unsecured loans on the ladder (loan 5+) | M40: assumption | P40: 2026-09-30 | Q40: Ladder (founder, 2 Oct 2026): loans 1-2 secured against savings, 3-4 part secured, 5+ unsecured at this size. Bueno first loans Rs 10k-25k.
A41: loan_stepup | B41: Repeat loan size as a multiple of the first | C41: 1 | D41: 1.2 | E41: 1.4 | F41: =CHOOSE(scenario,C41,D41,E41) | J41: =IF(H41="",F41,CHOOSE(scenario,G41,H41,I41)) | K41: multiple | L41: repeat loans | M41: assumption | P41: 2026-09-30 | Q41: Not used by the ladder (kept for reference).
A42: loan_tenor | B42: Loan length | C42: 6 | D42: 6 | E42: 6 | F42: =CHOOSE(scenario,C42,D42,E42) | J42: =IF(H42="",F42,CHOOSE(scenario,G42,H42,I42)) | K42: months | L42: all loans | M42: assumption | P42: 2026-09-30
A43: loan_repeat | B43: Share of repaid loans followed by another loan | C43: 0.3 | D43: 0.45 | E43: 0.6 | F43: =CHOOSE(scenario,C43,D43,E43) | J43: =IF(H43="",F43,CHOOSE(scenario,G43,H43,I43)) | K43: share | L43: repaid loans of still-active savers | M43: assumption | P43: 2026-09-30 | Q43: Bueno: 30-50% of repayers took a 2nd loan
A44: loan_dpd90 | B44: Share of loans that go 90+ days late | C44: 0.07 | D44: 0.045 | E44: 0.03 | F44: =CHOOSE(scenario,C44,D44,E44) | G44: 0.12 | H44: 0.07 | I44: 0.05 | J44: =IF(H44="",F44,CHOOSE(scenario,G44,H44,I44)) | K44: share of loans (count) | L44: loans to savers | M44: assumption (claim 2: pilot must prove); segment benchmark 6-7% | N44: benchmark (claim 2 applies): self-employed small unsecured loans peak 10.2% at 90+; PM SVANidhi NPA 12-16% | O44: MAC-03 | P44: 2025-01-17 | Q44: CRIF H1 FY25: Rs 10-50k loans peak 90+ at 6.0% (all lenders) / 7.2% (NBFCs), count-based. Bueno: 6-7% of loans 90+ (founder). Base assumes savers do better. NOT USED since 2 Oct 2026: the ladder uses ladder_dpd90 on unsecured money only (founder: savers self-select and graduate).
A45: loan_ead | B45: Share of the loan still owed when it goes 90+ late | C45: 0.9 | D45: 0.8 | E45: 0.7 | F45: =CHOOSE(scenario,C45,D45,E45) | J45: =IF(H45="",F45,CHOOSE(scenario,G45,H45,I45)) | K45: share of loan | L45: loans that go 90+ late | M45: founder experience (Bueno) applied to saver loans | P45: 2026-09-30 | Q45: At Bueno nearly all of a loan was still unpaid when it went 90+ late; saver loans run 6 months, so slightly less.
A46: loan_lgd | B46: Share of that never recovered | C46: 0.6 | D46: 0.5 | E46: 0.4 | F46: =CHOOSE(scenario,C46,D46,E46) | J46: =IF(H46="",F46,CHOOSE(scenario,G46,H46,I46)) | K46: share | L46: amount owed at 90+ late | M46: founder experience (Bueno) applied to saver loans | P46: 2026-09-30 | Q46: Bueno recovered about half of what was owed on loans 90+ days late.
A47: secured_ltv | B47: Secured loan as a share of the saver's fund + FD money | C47: 0.85 | D47: 0.85 | E47: 0.85 | F47: =CHOOSE(scenario,C47,D47,E47) | J47: =IF(H47="",F47,CHOOSE(scenario,G47,H47,I47)) | K47: share | L47: loans 1-4 on the ladder | M47: RBI loans against securities: 85% LTV for debt fund units; FD lenders often lend more | O47: REG-028 | P47: 2026-10-02 | Q47: Gold is excluded: no loans against digital gold [REG-023].
A48: secured_fee | B48: Our revenue on the secured part of a loan | C48: 0.02 | D48: 0.02 | E48: 0.02 | F48: =CHOOSE(scenario,C48,D48,E48) | J48: =IF(H48="",F48,CHOOSE(scenario,G48,H48,I48)) | K48: share | L48: secured money lent | M48: founder estimate (2 Oct 2026): 1% fee + 0.5% origination + 0.5% blended late fee | O48: founder | P48: 2026-10-02 | Q48: No loss cover on secured money: the lender holds the saver's FD or fund units.
A49: part_unsec_multiple | B49: Unsecured top-up on loans 3-4, as a multiple of the secured part | C49: 1 | D49: 1 | E49: 1 | F49: =CHOOSE(scenario,C49,D49,E49) | J49: =IF(H49="",F49,CHOOSE(scenario,G49,H49,I49)) | K49: multiple | L49: loans 3-4 on the ladder | M49: assumption (2 Oct 2026): loans 3-4 are half secured, half unsecured; founder to confirm | P49: 2026-10-02
A50: ladder_dpd90 | B50: Share of unsecured money that goes 90+ days late (loan 3 onward) | C50: 0.02 | D50: 0.015 | E50: 0.01 | F50: =CHOOSE(scenario,C50,D50,E50) | J50: =IF(H50="",F50,CHOOSE(scenario,G50,H50,I50)) | K50: share of loans (count) | L50: unsecured part of ladder loans, borrowers who repaid 2+ loans | M50: founder data: repeat loans 1-2% 90+ late; founder view (2 Oct 2026) that savers self-select | O50: founder | P50: 2026-10-02 | Q50: Applied to unsecured money only; secured money has no credit loss.
A51: lsp_fee | B51: Our fee as loan service provider | C51: 0.01 | D51: 0.015 | E51: 0.03 | F51: =CHOOSE(scenario,C51,D51,E51) | J51: =IF(H51="",F51,CHOOSE(scenario,G51,H51,I51)) | K51: share of disbursal | L51: loans sourced | M51: benchmark (origination only, no servicing) | O51: LEV-009, LEV-065, BM-07 | P51: 2026 | Q51: DSAs get 1-3% from NBFCs, 0.5-1.5% from banks; Paisabazaar's revenue/disbursal is at most 4.7% incl. cards. The lender pays; never the borrower [REG-011].
A52: dlg_on | B52: Do we give the lender a default-loss guarantee? (1 = yes) | C52: 1 | D52: 1 | E52: 1 | F52: =CHOOSE(scenario,C52,D52,E52) | J52: =IF(H52="",F52,CHOOSE(scenario,G52,H52,I52)) | K52: switch | L52: loans sourced | M52: founder's chosen plan (2026-09-30): 5% loss cover + gold | O52: REG-003, LEV-002 | P52: 2026-09-30 | Q52: Set to 0 to see the idea as briefed (savings + distribution only).
A53: dlg_cap | B53: Guarantee cap | C53: 0.05 | D53: 0.05 | E53: 0.05 | F53: =CHOOSE(scenario,C53,D53,E53) | J53: =IF(H53="",F53,CHOOSE(scenario,G53,H53,I53)) | K53: share of portfolio | L53: loans sourced | M53: regulation + practice | O53: REG-003, LEV-002 | P53: 2026-09 | Q53: Cap 5% of the amount disbursed. Moneyview posts 4.5-4.8% of guaranteed disbursals as lien-marked deposits.
A54: dlg_fee_uplift | B54: Extra fee a lender pays when we give a guarantee | C54: 0.03 | D54: 0.055 | E54: 0.07 | F54: =CHOOSE(scenario,C54,D54,E54) | J54: =IF(H54="",F54,CHOOSE(scenario,G54,H54,I54)) | K54: share of disbursal | L54: loans sourced | M54: benchmark (derived from filings) + judgment | O54: LEV-059, LEV-064, LEV-008 | P54: 2026-09 | Q54: Total fee with a 5% guarantee + servicing: 4 / 7 / 10% of disbursal, minus the no-guarantee fee. Moneyview partner fees about 11% of partner disbursal (derived); Kissht 17.4% of off-book AUM a year. No source splits guarantee vs no-guarantee fees.
A55: loan_ops_cost | B55: Our cost per loan | C55: 150 | D55: 100 | E55: 75 | F55: =CHOOSE(scenario,C55,D55,E55) | J55: =IF(H55="",F55,CHOOSE(scenario,G55,H55,I55)) | K55: INR per loan | L55: loans sourced | M55: assumption | P55: 2026-09-30
B56: Lever: own NBFC
A57: nbfc_on | B57: Lend from our own NBFC? (1 = yes) | C57: 0 | D57: 0 | E57: 0 | F57: =CHOOSE(scenario,C57,D57,E57) | J57: =IF(H57="",F57,CHOOSE(scenario,G57,H57,I57)) | K57: switch | L57: all loans | M57: lever switch | P57: 2026-09-30 | Q57: When 1, loans sit on our books: we earn interest and bear all losses; the LSP fee and guarantee switch are ignored
A58: nbfc_apr | B58: Yearly interest rate charged to savers | C58: 0.25 | D58: 0.28 | E58: 0.3 | F58: =CHOOSE(scenario,C58,D58,E58) | J58: =IF(H58="",F58,CHOOSE(scenario,G58,H58,I58)) | K58: annual rate | L58: own-book loans | M58: benchmark | O58: LEV-062, LEV-064, LEV-011, LEV-013 | P58: 2026 | Q58: Yield on loans at Moneyview 27.6%, Kissht 30.7%
A59: nbfc_proc_fee | B59: Processing fee | C59: 0.02 | D59: 0.03 | E59: 0.04 | F59: =CHOOSE(scenario,C59,D59,E59) | J59: =IF(H59="",F59,CHOOSE(scenario,G59,H59,I59)) | K59: share of loan | L59: own-book loans | M59: benchmark | O59: LEV-011, LEV-013 | P59: 2026 | Q59: Moneyview from 2%; KreditBee up to 5.5%
A60: nbfc_cof | B60: Our cost of borrowing to fund loans | C60: 0.16 | D60: 0.14 | E60: 0.12 | F60: =CHOOSE(scenario,C60,D60,E60) | J60: =IF(H60="",F60,CHOOSE(scenario,G60,H60,I60)) | K60: annual rate | L60: own-book loans | M60: benchmark | O60: LEV-015, LEV-028, LEV-062 | P60: 2026 | Q60: Moneyview's NBFC 14.44-14.74%, Kissht 13.3-13.7%, Amica (parent-subsidised) 11.5-12.5%
B61: Revenue: loans
A62: service_cost | B62: Collection and servicing cost per loan when we service it (guarantee or own NBFC) | C62: 350 | D62: 250 | E62: 150 | F62: =CHOOSE(scenario,C62,D62,E62) | J62: =IF(H62="",F62,CHOOSE(scenario,G62,H62,I62)) | K62: INR per loan | L62: own-book loans | M62: founder data + benchmark | O62: LEV-018, LEV-019 | P62: 2026 | Q62: Collection and servicing per loan when WE service it (under the guarantee or our own NBFC). Bueno: Rs 100-300 per loan in collections.
B63: Lever: own NBFC
A64: nbfc_equity | B64: Equity needed per rupee of loan book | C64: 0.5 | D64: 0.33 | E64: 0.25 | F64: =CHOOSE(scenario,C64,D64,E64) | J64: =IF(H64="",F64,CHOOSE(scenario,G64,H64,I64)) | K64: share of book | L64: own-book loans | M64: benchmark | O64: LEV-023, LEV-024, LEV-063 | P64: 2026 | Q64: Peers run 1-3x debt/equity (equity = 1/(1+D/E)); the 15% CRAR floor does not bind (peers hold 24-48%)
A65: nbfc_nof_cr | B65: Minimum net owned fund | C65: 10 | D65: 10 | E65: 10 | F65: =CHOOSE(scenario,C65,D65,E65) | J65: =IF(H65="",F65,CHOOSE(scenario,G65,H65,I65)) | K65: INR crore | L65: the NBFC | M65: regulation | O65: REG-017 | P65: 2021-10-22 | Q65: Rs 10 crore by 31 Mar 2027
A66: nbfc_fixed_cr | B66: Extra fixed cost of running an NBFC (compliance, risk, audit) | C66: 8 | D66: 5 | E66: 3 | F66: =CHOOSE(scenario,C66,D66,E66) | J66: =IF(H66="",F66,CHOOSE(scenario,G66,H66,I66)) | K66: INR crore per year | L66: the NBFC, from the year it starts | M66: assumption | O66: LEV-028, LEV-029 | P66: 2026-09-30 | Q66: Jupiter (Amica) and Groww (Creditserv) both lost money in their NBFCs' first year
B67: Lever: digital gold
A68: gold_on | B68: Offer digital gold? (1 = yes) | C68: 1 | D68: 1 | E68: 1 | F68: =CHOOSE(scenario,C68,D68,E68) | J68: =IF(H68="",F68,CHOOSE(scenario,G68,H68,I68)) | K68: switch | L68: savings | M68: founder's chosen plan (2026-09-30): 5% loss cover + gold | O68: REG-022, REG-023, REG-024, LEV-041, LEV-043 | P68: 2026-09-30 | Q68: Gold takes Rs 10 saves [LEV-039]; unregulated, framework under consultation, cannot back a loan. Set to 0 for the idea as briefed.
A69: gold_share | B69: Share of each rupee saved that goes into gold | C69: 0.5 | D69: 0.5 | E69: 0.5 | F69: =CHOOSE(scenario,C69,D69,E69) | J69: =IF(H69="",F69,CHOOSE(scenario,G69,H69,I69)) | K69: share | L69: money saved | M69: founder decision (2 Oct 2026): half of savings in gold, half in fund/FD so it can back a loan | O69: REG-043, LEV-039 | P69: 2026-10-02 | Q69: Was 0.5/0.7/0.8. Gold cannot back a loan or card [REG-022/023]; the fund and FD half can. Daily saves under Rs 100 still go to gold first.
A70: gold_margin | B70: Our margin on gold bought | C70: 0.01 | D70: 0.015 | E70: 0.024 | F70: =CHOOSE(scenario,C70,D70,E70) | J70: =IF(H70="",F70,CHOOSE(scenario,G70,H70,I70)) | K70: share of gold bought | L70: gold purchases | M70: benchmark, UNVERIFIED (distributor commission) | O70: LEV-036, LEV-071, LEV-035, LEV-037 | P70: 2026 | Q70: Only published figure: Jar about 2.4% as a distributor (case study). Augmont confirms a per-transaction commission, rate undisclosed. Savers pay a 2-3% spread + 3% GST: a round trip inside a year loses them money.
B71: Revenue: cards
A72: card_start | B72: Month a saver can get an FD-secured card | C72: 9 | D72: 6 | E72: 6 | F72: =CHOOSE(scenario,C72,D72,E72) | J72: =IF(H72="",F72,CHOOSE(scenario,G72,H72,I72)) | K72: month | L72: cohort age | M72: product design | P72: 2026-09-30
A73: card_eligible | B73: Share of active savers eligible (enough in FD) | C73: 0.25 | D73: 0.4 | E73: 0.5 | F73: =CHOOSE(scenario,C73,D73,E73) | J73: =IF(H73="",F73,CHOOSE(scenario,G73,H73,I73)) | K73: share | L73: active savers | M73: assumption | P73: 2026-09-30
A74: card_uptake | B74: Monthly take-up among eligible savers without a card | C74: 0.015 | D74: 0.03 | E74: 0.045 | F74: =CHOOSE(scenario,C74,D74,E74) | J74: =IF(H74="",F74,CHOOSE(scenario,G74,H74,I74)) | K74: share per month | L74: eligible active savers | M74: assumption | P74: 2026-09-30
A75: card_fee | B75: Fee per FD-secured card issued | C75: 200 | D75: 500 | E75: 1000 | F75: =CHOOSE(scenario,C75,D75,E75) | J75: =IF(H75="",F75,CHOOSE(scenario,G75,H75,I75)) | K75: INR per card | L75: cards issued | M75: assumption: no FD-secured card payout found | O75: BM-08 | P75: 2026-09-30 | Q75: Unsecured-card affiliate payouts are Rs 500-2,000; secured-card payouts are probably lower.
A76: card_churn | B76: Monthly share of card holders who stop | C76: 0.04 | D76: 0.025 | E76: 0.015 | F76: =CHOOSE(scenario,C76,D76,E76) | J76: =IF(H76="",F76,CHOOSE(scenario,G76,H76,I76)) | K76: share per month | L76: card holders | M76: assumption | P76: 2026-09-30
A77: card_spend | B77: Monthly spend per card holder | C77: 1500 | D77: 3000 | E77: 5000 | F77: =CHOOSE(scenario,C77,D77,E77) | J77: =IF(H77="",F77,CHOOSE(scenario,G77,H77,I77)) | K77: INR per month | L77: card holders | M77: assumption | P77: 2026-09-30
A78: card_ic_share | B78: Our share of card spend (interchange share) | C78: 0 | D78: 0 | E78: 0.0025 | F78: =CHOOSE(scenario,C78,D78,E78) | J78: =IF(H78="",F78,CHOOSE(scenario,G78,H78,I78)) | K78: share of spend | L78: card spend | M78: assumption | O78: REG-087 | P78: 2022-04-21 | Q78: A sourcing partner gets no card-transaction data and usually no ongoing share. Bull assumes a co-brand deal that shares 0.25% of spend.
A79: card_ops_cost | B79: Our cost per card issued | C79: 150 | D79: 100 | E79: 75 | F79: =CHOOSE(scenario,C79,D79,E79) | J79: =IF(H79="",F79,CHOOSE(scenario,G79,H79,I79)) | K79: INR per card | L79: cards issued | M79: assumption | P79: 2026-09-30
A80: unsec_start | B80: Month FD-card holders can move to an unsecured card | C80: 24 | D80: 18 | E80: 15 | F80: =CHOOSE(scenario,C80,D80,E80) | J80: =IF(H80="",F80,CHOOSE(scenario,G80,H80,I80)) | K80: month | L80: cohort age | M80: product design | P80: 2026-09-30
A81: unsec_grad | B81: Monthly share of FD-card holders who move to an unsecured card | C81: 0.005 | D81: 0.01 | E81: 0.02 | F81: =CHOOSE(scenario,C81,D81,E81) | J81: =IF(H81="",F81,CHOOSE(scenario,G81,H81,I81)) | K81: share per month | L81: FD-card holders not yet moved | M81: assumption | P81: 2026-09-30
A82: unsec_fee | B82: Fee per unsecured card issued | C82: 500 | D82: 1000 | E82: 2000 | F82: =CHOOSE(scenario,C82,D82,E82) | J82: =IF(H82="",F82,CHOOSE(scenario,G82,H82,I82)) | K82: INR per card | L82: unsecured cards issued | M82: benchmark, UNVERIFIED (affiliate blogs) | O82: BM-08 | P82: 2026-09-30 | Q82: Rs 500-2,000 per approved card typical.
B83: Revenue: SIP
A84: sip_start | B84: Month a saver is offered an equity SIP | C84: 9 | D84: 6 | E84: 6 | F84: =CHOOSE(scenario,C84,D84,E84) | J84: =IF(H84="",F84,CHOOSE(scenario,G84,H84,I84)) | K84: month | L84: cohort age | M84: product design | P84: 2026-09-30
A85: sip_eligible | B85: Share of active savers who could start a SIP | C85: 1 | D85: 1 | E85: 1 | F85: =CHOOSE(scenario,C85,D85,E85) | J85: =IF(H85="",F85,CHOOSE(scenario,G85,H85,I85)) | K85: share | L85: active savers | M85: product design | P85: 2026-09-30
A86: sip_uptake | B86: Monthly take-up among savers without a SIP | C86: 0.005 | D86: 0.01 | E86: 0.02 | F86: =CHOOSE(scenario,C86,D86,E86) | J86: =IF(H86="",F86,CHOOSE(scenario,G86,H86,I86)) | K86: share per month | L86: active savers without a SIP | M86: assumption | P86: 2026-09-30
A87: sip_stop | B87: Monthly share of SIP holders who stop | C87: 0.05 | D87: 0.03 | E87: 0.02 | F87: =CHOOSE(scenario,C87,D87,E87) | J87: =IF(H87="",F87,CHOOSE(scenario,G87,H87,I87)) | K87: share per month | L87: SIP holders | M87: assumption | P87: 2026-09-30
A88: sip_amount | B88: SIP amount | C88: 250 | D88: 500 | E88: 750 | F88: =CHOOSE(scenario,C88,D88,E88) | J88: =IF(H88="",F88,CHOOSE(scenario,G88,H88,I88)) | K88: INR per month | L88: SIP holders | M88: assumption | P88: 2026-09-30 | Q88: SBI JanNivesh minimum Rs 250
A89: sip_return | B89: Equity fund return | C89: 0.08 | D89: 0.1 | E89: 0.12 | F89: =CHOOSE(scenario,C89,D89,E89) | J89: =IF(H89="",F89,CHOOSE(scenario,G89,H89,I89)) | K89: per year | L89: SIP balance | M89: assumption | P89: 2026-09-30
A90: sip_redeem | B90: Share of SIP balance redeemed per month | C90: 0.03 | D90: 0.02 | E90: 0.01 | F90: =CHOOSE(scenario,C90,D90,E90) | J90: =IF(H90="",F90,CHOOSE(scenario,G90,H90,I90)) | K90: share per month | L90: SIP balance | M90: assumption | P90: 2026-09-30
A91: trail_equity | B91: Distributor trail on equity SIP balance | C91: 0.005 | D91: 0.0075 | E91: 0.01 | F91: =CHOOSE(scenario,C91,D91,E91) | J91: =IF(H91="",F91,CHOOSE(scenario,G91,H91,I91)) | K91: per year | L91: equity SIP balance (regular plan) | M91: benchmark: regular minus direct TER gap | O91: OWN-04 | P91: 2026 | Q91: Equity funds 0.5-1.0% a year; an upper bound on trail actually paid
B92: Revenue: insurance
A93: ins_start | B93: Month a saver is offered insurance | C93: 6 | D93: 3 | E93: 3 | F93: =CHOOSE(scenario,C93,D93,E93) | J93: =IF(H93="",F93,CHOOSE(scenario,G93,H93,I93)) | K93: month | L93: cohort age | M93: product design | P93: 2026-09-30
A94: ins_eligible | B94: Share of active savers who could buy | C94: 0.8 | D94: 0.9 | E94: 1 | F94: =CHOOSE(scenario,C94,D94,E94) | J94: =IF(H94="",F94,CHOOSE(scenario,G94,H94,I94)) | K94: share | L94: active savers | M94: assumption | P94: 2026-09-30
A95: ins_uptake | B95: Monthly take-up among savers never insured | C95: 0.01 | D95: 0.02 | E95: 0.03 | F95: =CHOOSE(scenario,C95,D95,E95) | J95: =IF(H95="",F95,CHOOSE(scenario,G95,H95,I95)) | K95: share per month | L95: active savers never insured | M95: assumption | P95: 2026-09-30
A96: ins_premium | B96: Annual premium per policy | C96: 1500 | D96: 3000 | E96: 5000 | F96: =CHOOSE(scenario,C96,D96,E96) | J96: =IF(H96="",F96,CHOOSE(scenario,G96,H96,I96)) | K96: INR per year | L96: policies | M96: assumption | P96: 2026-09-30 | Q96: Mix of accident / health / term
A97: ins_comm_first | B97: First-year commission | C97: 0.05 | D97: 0.12 | E97: 0.15 | F97: =CHOOSE(scenario,C97,D97,E97) | J97: =IF(H97="",F97,CHOOSE(scenario,G97,H97,I97)) | K97: share of premium | L97: first-year premium | M97: regulation (draft) + benchmark | O97: BM-09, BM-10 | P97: 2026-09-29 | Q97: IRDAI draft 23 Sep 2026: 15% first sale (health/PA), 5% if packaged with a loan. FY25 actual 14-20% of net premium.
A98: ins_comm_renew | B98: Renewal commission | C98: 0.03 | D98: 0.05 | E98: 0.05 | F98: =CHOOSE(scenario,C98,D98,E98) | J98: =IF(H98="",F98,CHOOSE(scenario,G98,H98,I98)) | K98: share of premium | L98: renewal premium | M98: regulation (draft) | O98: BM-10 | P98: 2026-09-29 | Q98: Draft renewal cap 5%.
A99: ins_persist | B99: Share of policies renewed each year | C99: 0.4 | D99: 0.55 | E99: 0.7 | F99: =CHOOSE(scenario,C99,D99,E99) | J99: =IF(H99="",F99,CHOOSE(scenario,G99,H99,I99)) | K99: share | L99: policies due for renewal | M99: assumption | P99: 2026-09-30
A100: ins_ops_cost | B100: Our cost per new policy | C100: 100 | D100: 60 | E100: 40 | F100: =CHOOSE(scenario,C100,D100,E100) | J100: =IF(H100="",F100,CHOOSE(scenario,G100,H100,I100)) | K100: INR per policy | L100: new policies | M100: assumption | P100: 2026-09-30
B101: Cost to serve
...

Sheet Funnel & CAC
A1: Funnel & CAC: fully loaded cost per ACTIVATED saver (first successful auto-debit), by channel
A2: CAC per activated saver = cost per install × scenario multiplier ÷ (install→activated) + KYC cost ÷ (KYC→activated) + mandate cost ÷ (mandate→first debit) + reward + referral bonus + partner fee.
A4: Channel | B4: Share of its segment | C4: Cost per install (₹) | D4: Install → KYC | E4: KYC → mandate | F4: Mandate → first debit | G4: KYC cost per KYC (₹) | H4: Mandate cost per mandate (₹) | I4: Joining reward (₹) | J4: Referral bonus (₹) | K4: Partner fee (₹) | L4: Install → activated | M4: Acquisition per activated (₹) | N4: KYC per activated (₹) | O4: Mandate per activated (₹) | P4: Rewards + referral + partner (₹) | Q4: CAC per activated saver (₹) | R4: Basis | S4: Notes | T4: Install weight (share of all savers ÷ install→activated)
A5: Gig · Save at source (platform / fleet payouts) | B5: 0.3 | C5: 60 | D5: 0.7 | E5: 0.85 | F5: 0.9 | G5: 40 | H5: 5 | I5: 0 | J5: 0 | K5: 50 | L5: =D5*E5*F5 | M5: =C5*cac_mult/L5 | N5: =G5/(E5*F5) | O5: =H5/F5 | P5: =I5+J5+K5 | Q5: =M5+N5+O5+P5 | R5: assumption: no savings-app CAC found [BM-04, BM-05]; Bueno cost per applicant under Rs 150 is the founder anchor | S5: Field staff at hubs co-branded with a platform; partner fee assumed | KYC Rs 40 = Aadhaar e-KYC Rs 3 (UIDAI) + vendor + KRA upload Rs 30 + CKYC [REG-068, REG-045, REG-069]; mandate Rs 5 (list Rs 7.5) [REG-050] | T5: =B5*mix_gig/L5
A6: Gig · Rider hubs and dark stores (field agents) | B6: 0.3 | C6: 50 | D6: 0.6 | E6: 0.7 | F6: 0.85 | G6: 40 | H6: 5 | I6: 0 | J6: 0 | K6: 0 | L6: =D6*E6*F6 | M6: =C6*cac_mult/L6 | N6: =G6/(E6*F6) | O6: =H6/F6 | P6: =I6+J6+K6 | Q6: =M6+N6+O6+P6 | R6: assumption: no savings-app CAC found [BM-04, BM-05]; Bueno cost per applicant under Rs 150 is the founder anchor | S6: Rs 25k/month agent / 25 days / 20 installs a day = Rs 50 | KYC Rs 40 = Aadhaar e-KYC Rs 3 (UIDAI) + vendor + KRA upload Rs 30 + CKYC [REG-068, REG-045, REG-069]; mandate Rs 5 (list Rs 7.5) [REG-050] | T6: =B6*mix_gig/L6
A7: Gig · Savings-buddy referrals | B7: 0.2 | C7: 0 | D7: 0.5 | E7: 0.7 | F7: 0.85 | G7: 40 | H7: 5 | I7: 0 | J7: 0 | K7: 0 | L7: =D7*E7*F7 | M7: =C7*cac_mult/L7 | N7: =G7/(E7*F7) | O7: =H7/F7 | P7: =I7+J7+K7 | Q7: =M7+N7+O7+P7 | R7: assumption: no savings-app CAC found [BM-04, BM-05]; Bueno cost per applicant under Rs 150 is the founder anchor | S7: Non-cash: shared goals and streaks with a friend. No cash bonus, because distributors may not reward fund investment [REG-082]. No pooling, because that would be a chit [REG-080]. | KYC Rs 40 = Aadhaar e-KYC Rs 3 (UIDAI) + vendor + KRA upload Rs 30 + CKYC [REG-068, REG-045, REG-069]; mandate Rs 5 (list Rs 7.5) [REG-050] | T7: =B7*mix_gig/L7
A8: Gig · Local-language creators and WhatsApp groups | B8: 0.1 | C8: 40 | D8: 0.4 | E8: 0.6 | F8: 0.8 | G8: 40 | H8: 5 | I8: 0 | J8: 0 | K8: 0 | L8: =D8*E8*F8 | M8: =C8*cac_mult/L8 | N8: =G8/(E8*F8) | O8: =H8/F8 | P8: =I8+J8+K8 | Q8: =M8+N8+O8+P8 | R8: assumption: no savings-app CAC found [BM-04, BM-05]; Bueno cost per applicant under Rs 150 is the founder anchor | S8: KYC Rs 40 = Aadhaar e-KYC Rs 3 (UIDAI) + vendor + KRA upload Rs 30 + CKYC [REG-068, REG-045, REG-069]; mandate Rs 5 (list Rs 7.5) [REG-050] | T8: =B8*mix_gig/L8
A9: Gig · Paid ads (benchmark only) | B9: 0.1 | C9: 80 | D9: 0.3 | E9: 0.55 | F9: 0.75 | G9: 40 | H9: 5 | I9: 0 | J9: 0 | K9: 0 | L9: =D9*E9*F9 | M9: =C9*cac_mult/L9 | N9: =G9/(E9*F9) | O9: =H9/F9 | P9: =I9+J9+K9 | Q9: =M9+N9+O9+P9 | R9: assumption: no savings-app CAC found [BM-04, BM-05]; Bueno cost per applicant under Rs 150 is the founder anchor | S9: KYC Rs 40 = Aadhaar e-KYC Rs 3 (UIDAI) + vendor + KRA upload Rs 30 + CKYC [REG-068, REG-045, REG-069]; mandate Rs 5 (list Rs 7.5) [REG-050] | T9: =B9*mix_gig/L9
A10: Non-gig · Field agents in markets | B10: 0.35 | C10: 50 | D10: 0.55 | E10: 0.7 | F10: 0.85 | G10: 40 | H10: 5 | I10: 0 | J10: 0 | K10: 0 | L10: =D10*E10*F10 | M10: =C10*cac_mult_ng/L10 | N10: =G10/(E10*F10) | O10: =H10/F10 | P10: =I10+J10+K10 | Q10: =M10+N10+O10+P10 | R10: assumption: merchant onboarding cost not disclosed by any payments firm [NG-043]; PhonePe has about 358 merchant devices per field staff (derived) [NG-029] | S10: Agents walk market streets and sign shops up. Staff who explain funds need NISM certification; no sign-up gifts for fund investing [OWN-05, REG-082] | T10: =B10*(1-mix_gig)/L10
A11: Non-gig · Supplier and distributor networks | B11: 0.25 | C11: 30 | D11: 0.5 | E11: 0.7 | F11: 0.85 | G11: 40 | H11: 5 | I11: 0 | J11: 0 | K11: 50 | L11: =D11*E11*F11 | M11: =C11*cac_mult_ng/L11 | N11: =G11/(E11*F11) | O11: =H11/F11 | P11: =I11+J11+K11 | Q11: =M11+N11+O11+P11 | R11: assumption: supplier-network finance found so far is trade credit only, with no published referral fee [NG-044] | S11: FMCG or wholesale distributors who visit shops weekly. LEGAL: they may be paid for fund sign-ups only if they register as ARN sub-distributors (staff NISM-certified); never for insurance leads (Insurance Act s.40). The Rs 50 fee is modelled as a gold-referral fee [OWN-05, OWN-06] | T11: =B11*(1-mix_gig)/L11
A12: Non-gig · Trader associations, cooperatives, self-help groups | B12: 0.15 | C12: 20 | D12: 0.45 | E12: 0.7 | F12: 0.85 | G12: 40 | H12: 5 | I12: 0 | J12: 0 | K12: 0 | L12: =D12*E12*F12 | M12: =C12*cac_mult_ng/L12 | N12: =G12/(E12*F12) | O12: =H12/F12 | P12: =I12+J12+K12 | Q12: =M12+N12+O12+P12 | R12: assumption: no cost data found; pigmy agents are paid 2.5% of collections [NG-041] | S12: Group sessions at trader associations, cooperatives and self-help groups; each member saves into their own account (no pooling: chit rules) [REG-080]. No payment to the association for fund or insurance sales [OWN-05, OWN-06] | T12: =B12*(1-mix_gig)/L12
A13: Non-gig · Save from daily UPI sales (payment partner) | B13: 0.25 | C13: 40 | D13: 0.55 | E13: 0.8 | F13: 0.9 | G13: 40 | H13: 5 | I13: 0 | J13: 0 | K13: 30 | L13: =D13*E13*F13 | M13: =C13*cac_mult_ng/L13 | N13: =G13/(E13*F13) | O13: =H13/F13 | P13: =I13+J13+K13 | Q13: =M13+N13+O13+P13 | R13: assumption: no live product saves from a merchant's daily UPI sales [NG-046]; small merchants' UPI money lands straight in their own account [NG-030], so this is a mandate timed after the day's collections | S13: A payment partner prompts the shop to save part of each day's UPI collections. For funds, the money must settle into the shop's own bank first, then its own mandate debits [REG-066, OWN-07]. The Rs 30 is a flat service fee to the payment partner, not a commission on fund or insurance sales (legal opinion needed) | T13: =B13*(1-mix_gig)/L13
A14: Gig blended (channel mix) | B14: =SUM(B5:B9) | L14: =SUMPRODUCT($B$5:$B$9,L5:L9)/$B$14 | M14: =SUMPRODUCT($B$5:$B$9,M5:M9)/$B$14 | N14: =SUMPRODUCT($B$5:$B$9,N5:N9)/$B$14 | O14: =SUMPRODUCT($B$5:$B$9,O5:O9)/$B$14 | P14: =SUMPRODUCT($B$5:$B$9,P5:P9)/$B$14 | Q14: =SUMPRODUCT($B$5:$B$9,Q5:Q9)/$B$14
A15: Non-gig blended (channel mix) | B15: =SUM(B10:B13) | L15: =SUMPRODUCT($B$10:$B$13,L10:L13)/$B$15 | M15: =SUMPRODUCT($B$10:$B$13,M10:M13)/$B$15 | N15: =SUMPRODUCT($B$10:$B$13,N10:N13)/$B$15 | O15: =SUMPRODUCT($B$10:$B$13,O10:O13)/$B$15 | P15: =SUMPRODUCT($B$10:$B$13,P10:P13)/$B$15 | Q15: =SUMPRODUCT($B$10:$B$13,Q10:Q13)/$B$15
A16: All savers (segment mix from Inputs) | Q16: =mix_gig*cac_gig+(1-mix_gig)*cac_ng
A19: The funnel for 1,000 installs across both segments, and how many are still saving later
A20: Stage | B20: People | C20: Share of installs
A21: Installs | B21: =1000 | C21: =B21/$B$21
A22: KYC done | B22: =1000*SUMPRODUCT($T$5:$T$13,D5:D13)/SUM($T$5:$T$13) | C22: =B22/$B$21
A23: Mandate set up | B23: =1000*SUMPRODUCT($T$5:$T$13,D5:D13,E5:E13)/SUM($T$5:$T$13) | C23: =B23/$B$21
A24: First auto-debit (activated saver) | B24: =1000*SUMPRODUCT($T$5:$T$13,L5:L13)/SUM($T$5:$T$13) | C24: =B24/$B$21
A25: Still saving, month 1 | B25: =B24*(mix_gig*ret_m1+(1-mix_gig)*ret_m1_ng) | C25: =B25/$B$21
A26: Still saving, month 3 | B26: =B24*(mix_gig*ret_m3+(1-mix_gig)*ret_m3_ng) | C26: =B26/$B$21
A27: Still saving, month 6 | B27: =B24*(mix_gig*ret_m6+(1-mix_gig)*ret_m6_ng) | C27: =B27/$B$21
A28: Still saving, month 12 | B28: =B24*(mix_gig*ret_m12+(1-mix_gig)*ret_m12_ng) | C28: =B28/$B$21
A29: Still saving, month 24 | B29: =B24*(mix_gig*ret_m24+(1-mix_gig)*ret_m24_ng) | C29: =B29/$B$21

Sheet Cohort gig
A1: Cohort: the GIG savers (app delivery and ride) in one monthly cohort, followed for 60 months (scenario from Inputs!C2)
A2: Month 0 (column C) holds the starting state. Loan, card and insurance economics are booked in the month the loan, card or policy is issued. Numbers are for the whole cohort unless the row says 'per activated saver'.
A4: Month of cohort life | B4: unit | C4: 0 | D4: 1 | E4: 2 | F4: 3 | G4: 4 | H4: 5 | I4: 6 | J4: 7 | K4: 8 | L4: 9 | M4: 10 | N4: 11 | O4: 12 | P4: 13 | Q4: 14 | R4: 15 | S4: 16 | T4: 17 | U4: 18 | V4: 19 | W4: 20 | X4: 21 | Y4: 22 | Z4: 23 | AA4: 24 | AB4: 25 | AC4: 26 | AD4: 27 | AE4: 28 | AF4: 29 | AG4: 30 | AH4: 31 | AI4: 32 | AJ4: 33 | AK4: 34 | AL4: 35 | AM4: 36 | AN4: 37 | AO4: 38 | AP4: 39 | AQ4: 40 | AR4: 41 | AS4: 42 | AT4: 43 | AU4: 44 | AV4: 45 | AW4: 46 | AX4: 47 | AY4: 48 | AZ4: 49 | BA4: 50 | BB4: 51 | BC4: 52 | BD4: 53 | BE4: 54 | BF4: 55 | BG4: 56 | BH4: 57 | BI4: 58 | BJ4: 59 | BK4: 60
A5: Savers
A6: Share of activated savers still saving | B6: share | C6: 1 | D6: =IF(D$4<=1,ret_m1^D$4,IF(D$4<=3,ret_m1*(ret_m3/ret_m1)^((D$4-1)/2),IF(D$4<=6,ret_m3*(ret_m6/ret_m3)^((D$4-3)/3),IF(D$4<=12,ret_m6*(ret_m12/ret_m6)^((D$4-6)/6),IF(D$4<=24,ret_m12*(ret_m24/ret_m12)^((D$4-12)/12),ret_m24*(1-churn_late)^(D$4-24)))))) | E6: =IF(E$4<=1,ret_m1^E$4,IF(E$4<=3,ret_m1*(ret_m3/ret_m1)^((E$4-1)/2),IF(E$4<=6,ret_m3*(ret_m6/ret_m3)^((E$4-3)/3),IF(E$4<=12,ret_m6*(ret_m12/ret_m6)^((E$4-6)/6),IF(E$4<=24,ret_m12*(ret_m24/ret_m12)^((E$4-12)/12),ret_m24*(1-churn_late)^(E$4-24)))))) | F6: =IF(F$4<=1,ret_m1^F$4,IF(F$4<=3,ret_m1*(ret_m3/ret_m1)^((F$4-1)/2),IF(F$4<=6,ret_m3*(ret_m6/ret_m3)^((F$4-3)/3),IF(F$4<=12,ret_m6*(ret_m12/ret_m6)^((F$4-6)/6),IF(F$4<=24,ret_m12*(ret_m24/ret_m12)^((F$4-12)/12),ret_m24*(1-churn_late)^(F$4-24)))))) | G6: =IF(G$4<=1,ret_m1^G$4,IF(G$4<=3,ret_m1*(ret_m3/ret_m1)^((G$4-1)/2),IF(G$4<=6,ret_m3*(ret_m6/ret_m3)^((G$4-3)/3),IF(G$4<=12,ret_m6*(ret_m12/ret_m6)^((G$4-6)/6),IF(G$4<=24,ret_m12*(ret_m24/ret_m12)^((G$4-12)/12),ret_m24*(1-churn_late)^(G$4-24)))))) | H6: =IF(H$4<=1,ret_m1^H$4,IF(H$4<=3,ret_m1*(ret_m3/ret_m1)^((H$4-1)/2),IF(H$4<=6,ret_m3*(ret_m6/ret_m3)^((H$4-3)/3),IF(H$4<=12,ret_m6*(ret_m12/ret_m6)^((H$4-6)/6),IF(H$4<=24,ret_m12*(ret_m24/ret_m12)^((H$4-12)/12),ret_m24*(1-churn_late)^(H$4-24)))))) | I6: =IF(I$4<=1,ret_m1^I$4,IF(I$4<=3,ret_m1*(ret_m3/ret_m1)^((I$4-1)/2),IF(I$4<=6,ret_m3*(ret_m6/ret_m3)^((I$4-3)/3),IF(I$4<=12,ret_m6*(ret_m12/ret_m6)^((I$4-6)/6),IF(I$4<=24,ret_m12*(ret_m24/ret_m12)^((I$4-12)/12),ret_m24*(1-churn_late)^(I$4-24)))))) | J6: =IF(J$4<=1,ret_m1^J$4,IF(J$4<=3,ret_m1*(ret_m3/ret_m1)^((J$4-1)/2),IF(J$4<=6,ret_m3*(ret_m6/ret_m3)^((J$4-3)/3),IF(J$4<=12,ret_m6*(ret_m12/ret_m6)^((J$4-6)/6),IF(J$4<=24,ret_m12*(ret_m24/ret_m12)^((J$4-12)/12),ret_m24*(1-churn_late)^(J$4-24)))))) | K6: =IF(K$4<=1,ret_m1^K$4,IF(K$4<=3,ret_m1*(ret_m3/ret_m1)^((K$4-1)/2),IF(K$4<=6,ret_m3*(ret_m6/ret_m3)^((K$4-3)/3),IF(K$4<=12,ret_m6*(ret_m12/ret_m6)^((K$4-6)/6),IF(K$4<=24,ret_m12*(ret_m24/ret_m12)^((K$4-12)/12),ret_m24*(1-churn_late)^(K$4-24)))))) | ... BK6: =IF(BK$4<=1,ret_m1^BK$4,IF(BK$4<=3,ret_m1*(ret_m3/ret_m1)^((BK$4-1)/2),IF(BK$4<=6,ret_m3*(ret_m6/ret_m3)^((BK$4-3)/3),IF(BK$4<=12,ret_m6*(ret_m12/ret_m6)^((BK$4-6)/6),IF(BK$4<=24,ret_m12*(ret_m24/ret_m12)^((BK$4-12)/12),ret_m24*(1-churn_late)^(BK$4-24))))))
A7: Active savers | B7: savers | D7: =seg_n_gig*D6 | E7: =seg_n_gig*E6 | F7: =seg_n_gig*F6 | G7: =seg_n_gig*G6 | H7: =seg_n_gig*H6 | I7: =seg_n_gig*I6 | J7: =seg_n_gig*J6 | K7: =seg_n_gig*K6 | ... BK7: =seg_n_gig*BK6
A8: Money saved per active saver | B8: ₹ per month | D8: =daily_amount*(1+amount_growth)^INT((D$4-1)/12)*debits_success | E8: =daily_amount*(1+amount_growth)^INT((E$4-1)/12)*debits_success | F8: =daily_amount*(1+amount_growth)^INT((F$4-1)/12)*debits_success | G8: =daily_amount*(1+amount_growth)^INT((G$4-1)/12)*debits_success | H8: =daily_amount*(1+amount_growth)^INT((H$4-1)/12)*debits_success | I8: =daily_amount*(1+amount_growth)^INT((I$4-1)/12)*debits_success | J8: =daily_amount*(1+amount_growth)^INT((J$4-1)/12)*debits_success | K8: =daily_amount*(1+amount_growth)^INT((K$4-1)/12)*debits_success | ... BK8: =daily_amount*(1+amount_growth)^INT((BK$4-1)/12)*debits_success
A9: Money saved (contributions) | B9: ₹ | D9: =D7*D8 | E9: =E7*E8 | F9: =F7*F8 | G9: =G7*G8 | H9: =H7*H8 | I9: =I7*I8 | J9: =J7*J8 | K9: =K7*K8 | ... BK9: =BK7*BK8
A10: Balances (money sits with the fund house or bank, never with us)
A11: Share of last month's savers still saving | B11: share | D11: =D6/C6 | E11: =E6/D6 | F11: =F6/E6 | G11: =G6/F6 | H11: =H6/G6 | I11: =I6/H6 | J11: =J6/I6 | K11: =K6/J6 | ... BK11: =BK6/BJ6
A12: Last month's active balance after returns | B12: ₹ | D12: =C15*(1+fund_yield/12) | E12: =D15*(1+fund_yield/12) | F12: =E15*(1+fund_yield/12) | G12: =F15*(1+fund_yield/12) | H12: =G15*(1+fund_yield/12) | I12: =H15*(1+fund_yield/12) | J12: =I15*(1+fund_yield/12) | K12: =J15*(1+fund_yield/12) | ... BK12: =BJ15*(1+fund_yield/12)
A13: …belonging to savers who stay | B13: ₹ | D13: =D12*D11 | E13: =E12*E11 | F13: =F12*F11 | G13: =G12*G11 | H13: =H12*H11 | I13: =I12*I11 | J13: =J12*J11 | K13: =K12*K11 | ... BK13: =BK12*BK11
A14: …belonging to savers who stop this month | B14: ₹ | D14: =D12*(1-D11) | E14: =E12*(1-E11) | F14: =F12*(1-F11) | G14: =G12*(1-G11) | H14: =H12*(1-H11) | I14: =I12*(1-I11) | J14: =J12*(1-J11) | K14: =K12*(1-K11) | ... BK14: =BK12*(1-BK11)
A15: Balance of active savers | B15: ₹ | C15: 0 | D15: =D13*(1-withdraw_rate)+D9 | E15: =E13*(1-withdraw_rate)+E9 | F15: =F13*(1-withdraw_rate)+F9 | G15: =G13*(1-withdraw_rate)+G9 | H15: =H13*(1-withdraw_rate)+H9 | I15: =I13*(1-withdraw_rate)+I9 | J15: =J13*(1-withdraw_rate)+J9 | K15: =K13*(1-withdraw_rate)+K9 | ... BK15: =BK13*(1-withdraw_rate)+BK9
A16: Balance left behind by savers who stopped | B16: ₹ | C16: 0 | D16: =C16*(1+fund_yield/12)*(1-dormant_withdraw)+D14*(1-leaver_withdraw) | E16: =D16*(1+fund_yield/12)*(1-dormant_withdraw)+E14*(1-leaver_withdraw) | F16: =E16*(1+fund_yield/12)*(1-dormant_withdraw)+F14*(1-leaver_withdraw) | G16: =F16*(1+fund_yield/12)*(1-dormant_withdraw)+G14*(1-leaver_withdraw) | H16: =G16*(1+fund_yield/12)*(1-dormant_withdraw)+H14*(1-leaver_withdraw) | I16: =H16*(1+fund_yield/12)*(1-dormant_withdraw)+I14*(1-leaver_withdraw) | J16: =I16*(1+fund_yield/12)*(1-dormant_withdraw)+J14*(1-leaver_withdraw) | K16: =J16*(1+fund_yield/12)*(1-dormant_withdraw)+K14*(1-leaver_withdraw) | ... BK16: =BJ16*(1+fund_yield/12)*(1-dormant_withdraw)+BK14*(1-leaver_withdraw)
A17: Withdrawals | B17: ₹ | D17: =D13*withdraw_rate+D14*leaver_withdraw+C16*(1+fund_yield/12)*dormant_withdraw | E17: =E13*withdraw_rate+E14*leaver_withdraw+D16*(1+fund_yield/12)*dormant_withdraw | F17: =F13*withdraw_rate+F14*leaver_withdraw+E16*(1+fund_yield/12)*dormant_withdraw | G17: =G13*withdraw_rate+G14*leaver_withdraw+F16*(1+fund_yield/12)*dormant_withdraw | H17: =H13*withdraw_rate+H14*leaver_withdraw+G16*(1+fund_yield/12)*dormant_withdraw | I17: =I13*withdraw_rate+I14*leaver_withdraw+H16*(1+fund_yield/12)*dormant_withdraw | J17: =J13*withdraw_rate+J14*leaver_withdraw+I16*(1+fund_yield/12)*dormant_withdraw | K17: =K13*withdraw_rate+K14*leaver_withdraw+J16*(1+fund_yield/12)*dormant_withdraw | ... BK17: =BK13*withdraw_rate+BK14*leaver_withdraw+BJ16*(1+fund_yield/12)*dormant_withdraw
A18: Total savings balance | B18: ₹ | C18: 0 | D18: =D15+D16 | E18: =E15+E16 | F18: =F15+F16 | G18: =G15+G16 | H18: =H15+H16 | I18: =I15+I16 | J18: =J15+J16 | K18: =K15+K16 | ... BK18: =BK15+BK16
A19: …held in digital gold (lever) | B19: ₹ | C19: 0 | D19: =D18*gold_on*gold_share | E19: =E18*gold_on*gold_share | F19: =F18*gold_on*gold_share | G19: =G18*gold_on*gold_share | H19: =H18*gold_on*gold_share | I19: =I18*gold_on*gold_share | J19: =J18*gold_on*gold_share | K19: =K18*gold_on*gold_share | ... BK19: =BK18*gold_on*gold_share
A20: …held in bank FDs | B20: ₹ | C20: 0 | D20: =IF(D$4>=fd_start,(D18-D19)*fd_share,0) | E20: =IF(E$4>=fd_start,(E18-E19)*fd_share,0) | F20: =IF(F$4>=fd_start,(F18-F19)*fd_share,0) | G20: =IF(G$4>=fd_start,(G18-G19)*fd_share,0) | H20: =IF(H$4>=fd_start,(H18-H19)*fd_share,0) | I20: =IF(I$4>=fd_start,(I18-I19)*fd_share,0) | J20: =IF(J$4>=fd_start,(J18-J19)*fd_share,0) | K20: =IF(K$4>=fd_start,(K18-K19)*fd_share,0) | ... BK20: =IF(BK$4>=fd_start,(BK18-BK19)*fd_share,0)
A21: …held in the liquid fund | B21: ₹ | C21: 0 | D21: =D18-D19-D20 | E21: =E18-E19-E20 | F21: =F18-F19-F20 | G21: =G18-G19-G20 | H21: =H18-H19-H20 | I21: =I18-I19-I20 | J21: =J18-J19-J20 | K21: =K18-K19-K20 | ... BK21: =BK18-BK19-BK20
A22: Loans through partner lenders (we are the loan service provider; the lender's money)
A23: Share of active savers who have borrowed | B23: share | C23: 0 | D23: =IF(D$4>=loan_start,C23+(loan_eligible-C23)*loan_apply*loan_approval,0) | E23: =IF(E$4>=loan_start,D23+(loan_eligible-D23)*loan_apply*loan_approval,0) | F23: =IF(F$4>=loan_start,E23+(loan_eligible-E23)*loan_apply*loan_approval,0) | G23: =IF(G$4>=loan_start,F23+(loan_eligible-F23)*loan_apply*loan_approval,0) | H23: =IF(H$4>=loan_start,G23+(loan_eligible-G23)*loan_apply*loan_approval,0) | I23: =IF(I$4>=loan_start,H23+(loan_eligible-H23)*loan_apply*loan_approval,0) | J23: =IF(J$4>=loan_start,I23+(loan_eligible-I23)*loan_apply*loan_approval,0) | K23: =IF(K$4>=loan_start,J23+(loan_eligible-J23)*loan_apply*loan_approval,0) | ... BK23: =IF(BK$4>=loan_start,BJ23+(loan_eligible-BJ23)*loan_apply*loan_approval,0)
A24: Loan 1 (secured against savings): first loans | B24: loans | C24: 0 | D24: =IF(D$4>=loan_start,D7*(loan_eligible-C23)*loan_apply*loan_approval,0) | E24: =IF(E$4>=loan_start,E7*(loan_eligible-D23)*loan_apply*loan_approval,0) | F24: =IF(F$4>=loan_start,F7*(loan_eligible-E23)*loan_apply*loan_approval,0) | G24: =IF(G$4>=loan_start,G7*(loan_eligible-F23)*loan_apply*loan_approval,0) | H24: =IF(H$4>=loan_start,H7*(loan_eligible-G23)*loan_apply*loan_approval,0) | I24: =IF(I$4>=loan_start,I7*(loan_eligible-H23)*loan_apply*loan_approval,0) | J24: =IF(J$4>=loan_start,J7*(loan_eligible-I23)*loan_apply*loan_approval,0) | K24: =IF(K$4>=loan_start,K7*(loan_eligible-J23)*loan_apply*loan_approval,0) | ... BK24: =IF(BK$4>=loan_start,BK7*(loan_eligible-BJ23)*loan_apply*loan_approval,0)
A25: Loan 2 (secured): repaid loan 1, still saving, borrowed again | B25: loans | C25: 0 | D25: =IF(D$4>loan_tenor,loan_repeat*(1-ladder_dpd90)*INDEX($C$24:C$24,1,D$4-loan_tenor+1)*D6/INDEX($C$6:C$6,1,D$4-loan_tenor+1),0) | E25: =IF(E$4>loan_tenor,loan_repeat*(1-ladder_dpd90)*INDEX($C$24:D$24,1,E$4-loan_tenor+1)*E6/INDEX($C$6:D$6,1,E$4-loan_tenor+1),0) | F25: =IF(F$4>loan_tenor,loan_repeat*(1-ladder_dpd90)*INDEX($C$24:E$24,1,F$4-loan_tenor+1)*F6/INDEX($C$6:E$6,1,F$4-loan_tenor+1),0) | G25: =IF(G$4>loan_tenor,loan_repeat*(1-ladder_dpd90)*INDEX($C$24:F$24,1,G$4-loan_tenor+1)*G6/INDEX($C$6:F$6,1,G$4-loan_tenor+1),0) | H25: =IF(H$4>loan_tenor,loan_repeat*(1-ladder_dpd90)*INDEX($C$24:G$24,1,H$4-loan_tenor+1)*H6/INDEX($C$6:G$6,1,H$4-loan_tenor+1),0) | I25: =IF(I$4>loan_tenor,loan_repeat*(1-ladder_dpd90)*INDEX($C$24:H$24,1,I$4-loan_tenor+1)*I6/INDEX($C$6:H$6,1,I$4-loan_tenor+1),0) | J25: =IF(J$4>loan_tenor,loan_repeat*(1-ladder_dpd90)*INDEX($C$24:I$24,1,J$4-loan_tenor+1)*J6/INDEX($C$6:I$6,1,J$4-loan_tenor+1),0) | K25: =IF(K$4>loan_tenor,loan_repeat*(1-ladder_dpd90)*INDEX($C$24:J$24,1,K$4-loan_tenor+1)*K6/INDEX($C$6:J$6,1,K$4-loan_tenor+1),0) | ... BK25: =IF(BK$4>loan_tenor,loan_repeat*(1-ladder_dpd90)*INDEX($C$24:BJ$24,1,BK$4-loan_tenor+1)*BK6/INDEX($C$6:BJ$6,1,BK$4-loan_tenor+1),0)
A26: Loan 3 (part secured) | B26: loans | C26: 0 | D26: =IF(D$4>loan_tenor,loan_repeat*(1-ladder_dpd90)*INDEX($C$25:C$25,1,D$4-loan_tenor+1)*D6/INDEX($C$6:C$6,1,D$4-loan_tenor+1),0) | E26: =IF(E$4>loan_tenor,loan_repeat*(1-ladder_dpd90)*INDEX($C$25:D$25,1,E$4-loan_tenor+1)*E6/INDEX($C$6:D$6,1,E$4-loan_tenor+1),0) | F26: =IF(F$4>loan_tenor,loan_repeat*(1-ladder_dpd90)*INDEX($C$25:E$25,1,F$4-loan_tenor+1)*F6/INDEX($C$6:E$6,1,F$4-loan_tenor+1),0) | G26: =IF(G$4>loan_tenor,loan_repeat*(1-ladder_dpd90)*INDEX($C$25:F$25,1,G$4-loan_tenor+1)*G6/INDEX($C$6:F$6,1,G$4-loan_tenor+1),0) | H26: =IF(H$4>loan_tenor,loan_repeat*(1-ladder_dpd90)*INDEX($C$25:G$25,1,H$4-loan_tenor+1)*H6/INDEX($C$6:G$6,1,H$4-loan_tenor+1),0) | I26: =IF(I$4>loan_tenor,loan_repeat*(1-ladder_dpd90)*INDEX($C$25:H$25,1,I$4-loan_tenor+1)*I6/INDEX($C$6:H$6,1,I$4-loan_tenor+1),0) | J26: =IF(J$4>loan_tenor,loan_repeat*(1-ladder_dpd90)*INDEX($C$25:I$25,1,J$4-loan_tenor+1)*J6/INDEX($C$6:I$6,1,J$4-loan_tenor+1),0) | K26: =IF(K$4>loan_tenor,loan_repeat*(1-ladder_dpd90)*INDEX($C$25:J$25,1,K$4-loan_tenor+1)*K6/INDEX($C$6:J$6,1,K$4-loan_tenor+1),0) | ... BK26: =IF(BK$4>loan_tenor,loan_repeat*(1-ladder_dpd90)*INDEX($C$25:BJ$25,1,BK$4-loan_tenor+1)*BK6/INDEX($C$6:BJ$6,1,BK$4-loan_tenor+1),0)
A27: Loan 4 (part secured) | B27: loans | C27: 0 | D27: =IF(D$4>loan_tenor,loan_repeat*(1-ladder_dpd90)*INDEX($C$26:C$26,1,D$4-loan_tenor+1)*D6/INDEX($C$6:C$6,1,D$4-loan_tenor+1),0) | E27: =IF(E$4>loan_tenor,loan_repeat*(1-ladder_dpd90)*INDEX($C$26:D$26,1,E$4-loan_tenor+1)*E6/INDEX($C$6:D$6,1,E$4-loan_tenor+1),0) | F27: =IF(F$4>loan_tenor,loan_repeat*(1-ladder_dpd90)*INDEX($C$26:E$26,1,F$4-loan_tenor+1)*F6/INDEX($C$6:E$6,1,F$4-loan_tenor+1),0) | G27: =IF(G$4>loan_tenor,loan_repeat*(1-ladder_dpd90)*INDEX($C$26:F$26,1,G$4-loan_tenor+1)*G6/INDEX($C$6:F$6,1,G$4-loan_tenor+1),0) | H27: =IF(H$4>loan_tenor,loan_repeat*(1-ladder_dpd90)*INDEX($C$26:G$26,1,H$4-loan_tenor+1)*H6/INDEX($C$6:G$6,1,H$4-loan_tenor+1),0) | I27: =IF(I$4>loan_tenor,loan_repeat*(1-ladder_dpd90)*INDEX($C$26:H$26,1,I$4-loan_tenor+1)*I6/INDEX($C$6:H$6,1,I$4-loan_tenor+1),0) | J27: =IF(J$4>loan_tenor,loan_repeat*(1-ladder_dpd90)*INDEX($C$26:I$26,1,J$4-loan_tenor+1)*J6/INDEX($C$6:I$6,1,J$4-loan_tenor+1),0) | K27: =IF(K$4>loan_tenor,loan_repeat*(1-ladder_dpd90)*INDEX($C$26:J$26,1,K$4-loan_tenor+1)*K6/INDEX($C$6:J$6,1,K$4-loan_tenor+1),0) | ... BK27: =IF(BK$4>loan_tenor,loan_repeat*(1-ladder_dpd90)*INDEX($C$26:BJ$26,1,BK$4-loan_tenor+1)*BK6/INDEX($C$6:BJ$6,1,BK$4-loan_tenor+1),0)
A28: …first unsecured loans (loan 5) | B28: loans | C28: 0 | D28: =IF(D$4>loan_tenor,loan_repeat*(1-ladder_dpd90)*INDEX($C$27:C$27,1,D$4-loan_tenor+1)*D6/INDEX($C$6:C$6,1,D$4-loan_tenor+1),0) | E28: =IF(E$4>loan_tenor,loan_repeat*(1-ladder_dpd90)*INDEX($C$27:D$27,1,E$4-loan_tenor+1)*E6/INDEX($C$6:D$6,1,E$4-loan_tenor+1),0) | F28: =IF(F$4>loan_tenor,loan_repeat*(1-ladder_dpd90)*INDEX($C$27:E$27,1,F$4-loan_tenor+1)*F6/INDEX($C$6:E$6,1,F$4-loan_tenor+1),0) | G28: =IF(G$4>loan_tenor,loan_repeat*(1-ladder_dpd90)*INDEX($C$27:F$27,1,G$4-loan_tenor+1)*G6/INDEX($C$6:F$6,1,G$4-loan_tenor+1),0) | H28: =IF(H$4>loan_tenor,loan_repeat*(1-ladder_dpd90)*INDEX($C$27:G$27,1,H$4-loan_tenor+1)*H6/INDEX($C$6:G$6,1,H$4-loan_tenor+1),0) | I28: =IF(I$4>loan_tenor,loan_repeat*(1-ladder_dpd90)*INDEX($C$27:H$27,1,I$4-loan_tenor+1)*I6/INDEX($C$6:H$6,1,I$4-loan_tenor+1),0) | J28: =IF(J$4>loan_tenor,loan_repeat*(1-ladder_dpd90)*INDEX($C$27:I$27,1,J$4-loan_tenor+1)*J6/INDEX($C$6:I$6,1,J$4-loan_tenor+1),0) | K28: =IF(K$4>loan_tenor,loan_repeat*(1-ladder_dpd90)*INDEX($C$27:J$27,1,K$4-loan_tenor+1)*K6/INDEX($C$6:J$6,1,K$4-loan_tenor+1),0) | ... BK28: =IF(BK$4>loan_tenor,loan_repeat*(1-ladder_dpd90)*INDEX($C$27:BJ$27,1,BK$4-loan_tenor+1)*BK6/INDEX($C$6:BJ$6,1,BK$4-loan_tenor+1),0)
A29: Loans 5+ (unsecured) | B29: loans | C29: 0 | D29: =IF(D$4>loan_tenor,D28+loan_repeat*(1-ladder_dpd90)*INDEX($C$29:C$29,1,D$4-loan_tenor+1)*D6/INDEX($C$6:C$6,1,D$4-loan_tenor+1),0) | E29: =IF(E$4>loan_tenor,E28+loan_repeat*(1-ladder_dpd90)*INDEX($C$29:D$29,1,E$4-loan_tenor+1)*E6/INDEX($C$6:D$6,1,E$4-loan_tenor+1),0) | F29: =IF(F$4>loan_tenor,F28+loan_repeat*(1-ladder_dpd90)*INDEX($C$29:E$29,1,F$4-loan_tenor+1)*F6/INDEX($C$6:E$6,1,F$4-loan_tenor+1),0) | G29: =IF(G$4>loan_tenor,G28+loan_repeat*(1-ladder_dpd90)*INDEX($C$29:F$29,1,G$4-loan_tenor+1)*G6/INDEX($C$6:F$6,1,G$4-loan_tenor+1),0) | H29: =IF(H$4>loan_tenor,H28+loan_repeat*(1-ladder_dpd90)*INDEX($C$29:G$29,1,H$4-loan_tenor+1)*H6/INDEX($C$6:G$6,1,H$4-loan_tenor+1),0) | I29: =IF(I$4>loan_tenor,I28+loan_repeat*(1-ladder_dpd90)*INDEX($C$29:H$29,1,I$4-loan_tenor+1)*I6/INDEX($C$6:H$6,1,I$4-loan_tenor+1),0) | J29: =IF(J$4>loan_tenor,J28+loan_repeat*(1-ladder_dpd90)*INDEX($C$29:I$29,1,J$4-loan_tenor+1)*J6/INDEX($C$6:I$6,1,J$4-loan_tenor+1),0) | K29: =IF(K$4>loan_tenor,K28+loan_repeat*(1-ladder_dpd90)*INDEX($C$29:J$29,1,K$4-loan_tenor+1)*K6/INDEX($C$6:J$6,1,K$4-loan_tenor+1),0) | ... BK29: =IF(BK$4>loan_tenor,BK28+loan_repeat*(1-ladder_dpd90)*INDEX($C$29:BJ$29,1,BK$4-loan_tenor+1)*BK6/INDEX($C$6:BJ$6,1,BK$4-loan_tenor+1),0)
A30: Repeat loans (loans 2+) | B30: loans | C30: 0 | D30: =D25+D26+D27+D29 | E30: =E25+E26+E27+E29 | F30: =F25+F26+F27+F29 | G30: =G25+G26+G27+G29 | H30: =H25+H26+H27+H29 | I30: =I25+I26+I27+I29 | J30: =J25+J26+J27+J29 | K30: =K25+K26+K27+K29 | ... BK30: =BK25+BK26+BK27+BK29
A31: All loans | B31: loans | C31: 0 | D31: =D24+D30 | E31: =E24+E30 | F31: =F24+F30 | G31: =G24+G30 | H31: =H24+H30 | I31: =I24+I30 | J31: =J24+J30 | K31: =K24+K30 | ... BK31: =BK24+BK30
A32: Savings that can back a loan, per active saver (fund + FD; gold cannot) | B32: ₹ | C32: 0 | D32: =IF(D7>0,D15/D7,0)*(1-gold_on*gold_share) | E32: =IF(E7>0,E15/E7,0)*(1-gold_on*gold_share) | F32: =IF(F7>0,F15/F7,0)*(1-gold_on*gold_share) | G32: =IF(G7>0,G15/G7,0)*(1-gold_on*gold_share) | H32: =IF(H7>0,H15/H7,0)*(1-gold_on*gold_share) | I32: =IF(I7>0,I15/I7,0)*(1-gold_on*gold_share) | J32: =IF(J7>0,J15/J7,0)*(1-gold_on*gold_share) | K32: =IF(K7>0,K15/K7,0)*(1-gold_on*gold_share) | ... BK32: =IF(BK7>0,BK15/BK7,0)*(1-gold_on*gold_share)
A33: Secured loan size (secured_ltv of that) | B33: ₹ | C33: 0 | D33: =secured_ltv*D32 | E33: =secured_ltv*E32 | F33: =secured_ltv*F32 | G33: =secured_ltv*G32 | H33: =secured_ltv*H32 | I33: =secured_ltv*I32 | J33: =secured_ltv*J32 | K33: =secured_ltv*K32 | ... BK33: =secured_ltv*BK32
A34: Secured money lent (loans 1-4) | B34: ₹ | C34: 0 | D34: =(D24+D25+D26+D27)*D33 | E34: =(E24+E25+E26+E27)*E33 | F34: =(F24+F25+F26+F27)*F33 | G34: =(G24+G25+G26+G27)*G33 | H34: =(H24+H25+H26+H27)*H33 | I34: =(I24+I25+I26+I27)*I33 | J34: =(J24+J25+J26+J27)*J33 | K34: =(K24+K25+K26+K27)*K33 | ... BK34: =(BK24+BK25+BK26+BK27)*BK33
A35: Unsecured money lent (top-ups on loans 3-4, all of loans 5+) | B35: ₹ | C35: 0 | D35: =(D26+D27)*D33*part_unsec_multiple+D29*loan_ticket | E35: =(E26+E27)*E33*part_unsec_multiple+E29*loan_ticket | F35: =(F26+F27)*F33*part_unsec_multiple+F29*loan_ticket | G35: =(G26+G27)*G33*part_unsec_multiple+G29*loan_ticket | H35: =(H26+H27)*H33*part_unsec_multiple+H29*loan_ticket | I35: =(I26+I27)*I33*part_unsec_multiple+I29*loan_ticket | J35: =(J26+J27)*J33*part_unsec_multiple+J29*loan_ticket | K35: =(K26+K27)*K33*part_unsec_multiple+K29*loan_ticket | ... BK35: =(BK26+BK27)*BK33*part_unsec_multiple+BK29*loan_ticket
A36: Money lent (by partners, or by our NBFC if that lever is on) | B36: ₹ | C36: 0 | D36: =D34+D35 | E36: =E34+E35 | F36: =F34+F35 | G36: =G34+G35 | H36: =H34+H35 | I36: =I34+I35 | J36: =J34+J35 | K36: =K34+K35 | ... BK36: =BK34+BK35
A37: Unsecured money lent in the last loan-length months (sets the guarantee deposit) | B37: ₹ | C37: 0 | D37: =C37+D35-IF(D$4>loan_tenor,INDEX($C$35:C$35,1,D$4-loan_tenor+1),0) | E37: =D37+E35-IF(E$4>loan_tenor,INDEX($C$35:D$35,1,E$4-loan_tenor+1),0) | F37: =E37+F35-IF(F$4>loan_tenor,INDEX($C$35:E$35,1,F$4-loan_tenor+1),0) | G37: =F37+G35-IF(G$4>loan_tenor,INDEX($C$35:F$35,1,G$4-loan_tenor+1),0) | H37: =G37+H35-IF(H$4>loan_tenor,INDEX($C$35:G$35,1,H$4-loan_tenor+1),0) | I37: =H37+I35-IF(I$4>loan_tenor,INDEX($C$35:H$35,1,I$4-loan_tenor+1),0) | J37: =I37+J35-IF(J$4>loan_tenor,INDEX($C$35:I$35,1,J$4-loan_tenor+1),0) | K37: =J37+K35-IF(K$4>loan_tenor,INDEX($C$35:J$35,1,K$4-loan_tenor+1),0) | ... BK37: =BJ37+BK35-IF(BK$4>loan_tenor,INDEX($C$35:BJ$35,1,BK$4-loan_tenor+1),0)
A38: All money lent in the last loan-length months (an own NBFC's book) | B38: ₹ | C38: 0 | D38: =C38+D36-IF(D$4>loan_tenor,INDEX($C$36:C$36,1,D$4-loan_tenor+1),0) | E38: =D38+E36-IF(E$4>loan_tenor,INDEX($C$36:D$36,1,E$4-loan_tenor+1),0) | F38: =E38+F36-IF(F$4>loan_tenor,INDEX($C$36:E$36,1,F$4-loan_tenor+1),0) | G38: =F38+G36-IF(G$4>loan_tenor,INDEX($C$36:F$36,1,G$4-loan_tenor+1),0) | H38: =G38+H36-IF(H$4>loan_tenor,INDEX($C$36:G$36,1,H$4-loan_tenor+1),0) | I38: =H38+I36-IF(I$4>loan_tenor,INDEX($C$36:H$36,1,I$4-loan_tenor+1),0) | J38: =I38+J36-IF(J$4>loan_tenor,INDEX($C$36:I$36,1,J$4-loan_tenor+1),0) | K38: =J38+K36-IF(K$4>loan_tenor,INDEX($C$36:J$36,1,K$4-loan_tenor+1),0) | ... BK38: =BJ38+BK36-IF(BK$4>loan_tenor,INDEX($C$36:BJ$36,1,BK$4-loan_tenor+1),0)
A39: Capital locked: guarantee deposit, or NBFC equity for the loan book | B39: ₹ | C39: 0 | D39: =IF(nbfc_on=1,nbfc_equity*nbfc_avg_frac*D38,dlg_on*dlg_cap*D37) | E39: =IF(nbfc_on=1,nbfc_equity*nbfc_avg_frac*E38,dlg_on*dlg_cap*E37) | F39: =IF(nbfc_on=1,nbfc_equity*nbfc_avg_frac*F38,dlg_on*dlg_cap*F37) | G39: =IF(nbfc_on=1,nbfc_equity*nbfc_avg_frac*G38,dlg_on*dlg_cap*G37) | H39: =IF(nbfc_on=1,nbfc_equity*nbfc_avg_frac*H38,dlg_on*dlg_cap*H37) | I39: =IF(nbfc_on=1,nbfc_equity*nbfc_avg_frac*I38,dlg_on*dlg_cap*I37) | J39: =IF(nbfc_on=1,nbfc_equity*nbfc_avg_frac*J38,dlg_on*dlg_cap*J37) | K39: =IF(nbfc_on=1,nbfc_equity*nbfc_avg_frac*K38,dlg_on*dlg_cap*K37) | ... BK39: =IF(nbfc_on=1,nbfc_equity*nbfc_avg_frac*BK38,dlg_on*dlg_cap*BK37)
A40: Cards (issued by a partner bank)
A41: Share of active savers with an FD-secured card | B41: share | C41: 0 | D41: =IF(D$4>=card_start,C41*(1-card_churn)+(card_eligible*(1-gold_on*gold_share)-C41)*card_uptake,0) | E41: =IF(E$4>=card_start,D41*(1-card_churn)+(card_eligible*(1-gold_on*gold_share)-D41)*card_uptake,0) | F41: =IF(F$4>=card_start,E41*(1-card_churn)+(card_eligible*(1-gold_on*gold_share)-E41)*card_uptake,0) | G41: =IF(G$4>=card_start,F41*(1-card_churn)+(card_eligible*(1-gold_on*gold_share)-F41)*card_uptake,0) | H41: =IF(H$4>=card_start,G41*(1-card_churn)+(card_eligible*(1-gold_on*gold_share)-G41)*card_uptake,0) | I41: =IF(I$4>=card_start,H41*(1-card_churn)+(card_eligible*(1-gold_on*gold_share)-H41)*card_uptake,0) | J41: =IF(J$4>=card_start,I41*(1-card_churn)+(card_eligible*(1-gold_on*gold_share)-I41)*card_uptake,0) | K41: =IF(K$4>=card_start,J41*(1-card_churn)+(card_eligible*(1-gold_on*gold_share)-J41)*card_uptake,0) | ... BK41: =IF(BK$4>=card_start,BJ41*(1-card_churn)+(card_eligible*(1-gold_on*gold_share)-BJ41)*card_uptake,0)
A42: New FD-secured cards (only FD money, not gold, can back a card) | B42: cards | C42: 0 | D42: =IF(D$4>=card_start,D7*(card_eligible*(1-gold_on*gold_share)-C41)*card_uptake,0) | E42: =IF(E$4>=card_start,E7*(card_eligible*(1-gold_on*gold_share)-D41)*card_uptake,0) | F42: =IF(F$4>=card_start,F7*(card_eligible*(1-gold_on*gold_share)-E41)*card_uptake,0) | G42: =IF(G$4>=card_start,G7*(card_eligible*(1-gold_on*gold_share)-F41)*card_uptake,0) | H42: =IF(H$4>=card_start,H7*(card_eligible*(1-gold_on*gold_share)-G41)*card_uptake,0) | I42: =IF(I$4>=card_start,I7*(card_eligible*(1-gold_on*gold_share)-H41)*card_uptake,0) | J42: =IF(J$4>=card_start,J7*(card_eligible*(1-gold_on*gold_share)-I41)*card_uptake,0) | K42: =IF(K$4>=card_start,K7*(card_eligible*(1-gold_on*gold_share)-J41)*card_uptake,0) | ... BK42: =IF(BK$4>=card_start,BK7*(card_eligible*(1-gold_on*gold_share)-BJ41)*card_uptake,0)
A43: Card holders | B43: cards | C43: 0 | D43: =D7*D41 | E43: =E7*E41 | F43: =F7*F41 | G43: =G7*G41 | H43: =H7*H41 | I43: =I7*I41 | J43: =J7*J41 | K43: =K7*K41 | ... BK43: =BK7*BK41
A44: Share moved to an unsecured card | B44: share | C44: 0 | D44: =IF(D$4>=unsec_start,C44+MAX(0,C41-C44)*unsec_grad,C44) | E44: =IF(E$4>=unsec_start,D44+MAX(0,D41-D44)*unsec_grad,D44) | F44: =IF(F$4>=unsec_start,E44+MAX(0,E41-E44)*unsec_grad,E44) | G44: =IF(G$4>=unsec_start,F44+MAX(0,F41-F44)*unsec_grad,F44) | H44: =IF(H$4>=unsec_start,G44+MAX(0,G41-G44)*unsec_grad,G44) | I44: =IF(I$4>=unsec_start,H44+MAX(0,H41-H44)*unsec_grad,H44) | J44: =IF(J$4>=unsec_start,I44+MAX(0,I41-I44)*unsec_grad,I44) | K44: =IF(K$4>=unsec_start,J44+MAX(0,J41-J44)*unsec_grad,J44) | ... BK44: =IF(BK$4>=unsec_start,BJ44+MAX(0,BJ41-BJ44)*unsec_grad,BJ44)
A45: New unsecured cards | B45: cards | C45: 0 | D45: =D7*(D44-C44) | E45: =E7*(E44-D44) | F45: =F7*(F44-E44) | G45: =G7*(G44-F44) | H45: =H7*(H44-G44) | I45: =I7*(I44-H44) | J45: =J7*(J44-I44) | K45: =K7*(K44-J44) | ... BK45: =BK7*(BK44-BJ44)
A46: Equity SIPs beyond the daily savings
A47: Share of active savers with an equity SIP | B47: share | C47: 0 | D47: =IF(D$4>=sip_start,C47*(1-sip_stop)+(sip_eligible-C47)*sip_uptake,0) | E47: =IF(E$4>=sip_start,D47*(1-sip_stop)+(sip_eligible-D47)*sip_uptake,0) | F47: =IF(F$4>=sip_start,E47*(1-sip_stop)+(sip_eligible-E47)*sip_uptake,0) | G47: =IF(G$4>=sip_start,F47*(1-sip_stop)+(sip_eligible-F47)*sip_uptake,0) | H47: =IF(H$4>=sip_start,G47*(1-sip_stop)+(sip_eligible-G47)*sip_uptake,0) | I47: =IF(I$4>=sip_start,H47*(1-sip_stop)+(sip_eligible-H47)*sip_uptake,0) | J47: =IF(J$4>=sip_start,I47*(1-sip_stop)+(sip_eligible-I47)*sip_uptake,0) | K47: =IF(K$4>=sip_start,J47*(1-sip_stop)+(sip_eligible-J47)*sip_uptake,0) | ... BK47: =IF(BK$4>=sip_start,BJ47*(1-sip_stop)+(sip_eligible-BJ47)*sip_uptake,0)
A48: New SIPs | B48: SIPs | C48: 0 | D48: =IF(D$4>=sip_start,D7*(sip_eligible-C47)*sip_uptake,0) | E48: =IF(E$4>=sip_start,E7*(sip_eligible-D47)*sip_uptake,0) | F48: =IF(F$4>=sip_start,F7*(sip_eligible-E47)*sip_uptake,0) | G48: =IF(G$4>=sip_start,G7*(sip_eligible-F47)*sip_uptake,0) | H48: =IF(H$4>=sip_start,H7*(sip_eligible-G47)*sip_uptake,0) | I48: =IF(I$4>=sip_start,I7*(sip_eligible-H47)*sip_uptake,0) | J48: =IF(J$4>=sip_start,J7*(sip_eligible-I47)*sip_uptake,0) | K48: =IF(K$4>=sip_start,K7*(sip_eligible-J47)*sip_uptake,0) | ... BK48: =IF(BK$4>=sip_start,BK7*(sip_eligible-BJ47)*sip_uptake,0)
A49: SIP balance | B49: ₹ | C49: 0 | D49: =C49*(1+sip_return/12)*(1-sip_redeem)+D7*D47*sip_amount | E49: =D49*(1+sip_return/12)*(1-sip_redeem)+E7*E47*sip_amount | F49: =E49*(1+sip_return/12)*(1-sip_redeem)+F7*F47*sip_amount | G49: =F49*(1+sip_return/12)*(1-sip_redeem)+G7*G47*sip_amount | H49: =G49*(1+sip_return/12)*(1-sip_redeem)+H7*H47*sip_amount | I49: =H49*(1+sip_return/12)*(1-sip_redeem)+I7*I47*sip_amount | J49: =I49*(1+sip_return/12)*(1-sip_redeem)+J7*J47*sip_amount | K49: =J49*(1+sip_return/12)*(1-sip_redeem)+K7*K47*sip_amount | ... BK49: =BJ49*(1+sip_return/12)*(1-sip_redeem)+BK7*BK47*sip_amount
A50: Insurance (annual policies from partner insurers)
A51: Share of active savers ever insured | B51: share | C51: 0 | D51: =IF(D$4>=ins_start,C51+(ins_eligible-C51)*ins_uptake,0) | E51: =IF(E$4>=ins_start,D51+(ins_eligible-D51)*ins_uptake,0) | F51: =IF(F$4>=ins_start,E51+(ins_eligible-E51)*ins_uptake,0) | G51: =IF(G$4>=ins_start,F51+(ins_eligible-F51)*ins_uptake,0) | H51: =IF(H$4>=ins_start,G51+(ins_eligible-G51)*ins_uptake,0) | I51: =IF(I$4>=ins_start,H51+(ins_eligible-H51)*ins_uptake,0) | J51: =IF(J$4>=ins_start,I51+(ins_eligible-I51)*ins_uptake,0) | K51: =IF(K$4>=ins_start,J51+(ins_eligible-J51)*ins_uptake,0) | ... BK51: =IF(BK$4>=ins_start,BJ51+(ins_eligible-BJ51)*ins_uptake,0)
A52: New policies | B52: policies | C52: 0 | D52: =IF(D$4>=ins_start,D7*(ins_eligible-C51)*ins_uptake,0) | E52: =IF(E$4>=ins_start,E7*(ins_eligible-D51)*ins_uptake,0) | F52: =IF(F$4>=ins_start,F7*(ins_eligible-E51)*ins_uptake,0) | G52: =IF(G$4>=ins_start,G7*(ins_eligible-F51)*ins_uptake,0) | H52: =IF(H$4>=ins_start,H7*(ins_eligible-G51)*ins_uptake,0) | I52: =IF(I$4>=ins_start,I7*(ins_eligible-H51)*ins_uptake,0) | J52: =IF(J$4>=ins_start,J7*(ins_eligible-I51)*ins_uptake,0) | K52: =IF(K$4>=ins_start,K7*(ins_eligible-J51)*ins_uptake,0) | ... BK52: =IF(BK$4>=ins_start,BK7*(ins_eligible-BJ51)*ins_uptake,0)
A53: Renewed policies | B53: policies | C53: 0 | D53: =IF(D$4>12,(INDEX($C$52:C$52,1,D$4-12+1)+INDEX($C$53:C$53,1,D$4-12+1))*ins_persist,0) | E53: =IF(E$4>12,(INDEX($C$52:D$52,1,E$4-12+1)+INDEX($C$53:D$53,1,E$4-12+1))*ins_persist,0) | F53: =IF(F$4>12,(INDEX($C$52:E$52,1,F$4-12+1)+INDEX($C$53:E$53,1,F$4-12+1))*ins_persist,0) | G53: =IF(G$4>12,(INDEX($C$52:F$52,1,G$4-12+1)+INDEX($C$53:F$53,1,G$4-12+1))*ins_persist,0) | H53: =IF(H$4>12,(INDEX($C$52:G$52,1,H$4-12+1)+INDEX($C$53:G$53,1,H$4-12+1))*ins_persist,0) | I53: =IF(I$4>12,(INDEX($C$52:H$52,1,I$4-12+1)+INDEX($C$53:H$53,1,I$4-12+1))*ins_persist,0) | J53: =IF(J$4>12,(INDEX($C$52:I$52,1,J$4-12+1)+INDEX($C$53:I$53,1,J$4-12+1))*ins_persist,0) | K53: =IF(K$4>12,(INDEX($C$52:J$52,1,K$4-12+1)+INDEX($C$53:J$53,1,K$4-12+1))*ins_persist,0) | ... BK53: =IF(BK$4>12,(INDEX($C$52:BJ$52,1,BK$4-12+1)+INDEX($C$53:BJ$53,1,BK$4-12+1))*ins_persist,0)
A54: Revenue
A55: Liquid-fund trail commission | B55: ₹ | C55: 0 | D55: =D21*trail_liquid/12 | E55: =E21*trail_liquid/12 | F55: =F21*trail_liquid/12 | G55: =G21*trail_liquid/12 | H55: =H21*trail_liquid/12 | I55: =I21*trail_liquid/12 | J55: =J21*trail_liquid/12 | K55: =K21*trail_liquid/12 | ... BK55: =BK21*trail_liquid/12
A56: FD distribution fee | B56: ₹ | C56: 0 | D56: =D20*fd_fee/12 | E56: =E20*fd_fee/12 | F56: =F20*fd_fee/12 | G56: =G20*fd_fee/12 | H56: =H20*fd_fee/12 | I56: =I20*fd_fee/12 | J56: =J20*fd_fee/12 | K56: =K20*fd_fee/12 | ... BK56: =BK20*fd_fee/12
A57: Margin on digital gold bought (lever) | B57: ₹ | C57: 0 | D57: =D9*gold_on*gold_share*gold_margin | E57: =E9*gold_on*gold_share*gold_margin | F57: =F9*gold_on*gold_share*gold_margin | G57: =G9*gold_on*gold_share*gold_margin | H57: =H9*gold_on*gold_share*gold_margin | I57: =I9*gold_on*gold_share*gold_margin | J57: =J9*gold_on*gold_share*gold_margin | K57: =K9*gold_on*gold_share*gold_margin | ... BK57: =BK9*gold_on*gold_share*gold_margin
A58: Loans: sourcing fee, or net interest if own NBFC | B58: ₹ | C58: 0 | D58: =IF(nbfc_on=1,D36*(nbfc_int_r*(1-ladder_dpd90)+nbfc_proc_fee-nbfc_cof_r),D34*secured_fee+D35*(lsp_fee+dlg_on*dlg_fee_uplift)) | E58: =IF(nbfc_on=1,E36*(nbfc_int_r*(1-ladder_dpd90)+nbfc_proc_fee-nbfc_cof_r),E34*secured_fee+E35*(lsp_fee+dlg_on*dlg_fee_uplift)) | F58: =IF(nbfc_on=1,F36*(nbfc_int_r*(1-ladder_dpd90)+nbfc_proc_fee-nbfc_cof_r),F34*secured_fee+F35*(lsp_fee+dlg_on*dlg_fee_uplift)) | G58: =IF(nbfc_on=1,G36*(nbfc_int_r*(1-ladder_dpd90)+nbfc_proc_fee-nbfc_cof_r),G34*secured_fee+G35*(lsp_fee+dlg_on*dlg_fee_uplift)) | H58: =IF(nbfc_on=1,H36*(nbfc_int_r*(1-ladder_dpd90)+nbfc_proc_fee-nbfc_cof_r),H34*secured_fee+H35*(lsp_fee+dlg_on*dlg_fee_uplift)) | I58: =IF(nbfc_on=1,I36*(nbfc_int_r*(1-ladder_dpd90)+nbfc_proc_fee-nbfc_cof_r),I34*secured_fee+I35*(lsp_fee+dlg_on*dlg_fee_uplift)) | J58: =IF(nbfc_on=1,J36*(nbfc_int_r*(1-ladder_dpd90)+nbfc_proc_fee-nbfc_cof_r),J34*secured_fee+J35*(lsp_fee+dlg_on*dlg_fee_uplift)) | K58: =IF(nbfc_on=1,K36*(nbfc_int_r*(1-ladder_dpd90)+nbfc_proc_fee-nbfc_cof_r),K34*secured_fee+K35*(lsp_fee+dlg_on*dlg_fee_uplift)) | ... BK58: =IF(nbfc_on=1,BK36*(nbfc_int_r*(1-ladder_dpd90)+nbfc_proc_fee-nbfc_cof_r),BK34*secured_fee+BK35*(lsp_fee+dlg_on*dlg_fee_uplift))
A59: Card fees and interchange share | B59: ₹ | C59: 0 | D59: =D42*card_fee+D43*card_spend*card_ic_share+D45*unsec_fee | E59: =E42*card_fee+E43*card_spend*card_ic_share+E45*unsec_fee | F59: =F42*card_fee+F43*card_spend*card_ic_share+F45*unsec_fee | G59: =G42*card_fee+G43*card_spend*card_ic_share+G45*unsec_fee | H59: =H42*card_fee+H43*card_spend*card_ic_share+H45*unsec_fee | I59: =I42*card_fee+I43*card_spend*card_ic_share+I45*unsec_fee | J59: =J42*card_fee+J43*card_spend*card_ic_share+J45*unsec_fee | K59: =K42*card_fee+K43*card_spend*card_ic_share+K45*unsec_fee | ... BK59: =BK42*card_fee+BK43*card_spend*card_ic_share+BK45*unsec_fee
A60: SIP trail commission | B60: ₹ | C60: 0 | D60: =D49*trail_equity/12 | E60: =E49*trail_equity/12 | F60: =F49*trail_equity/12 | G60: =G49*trail_equity/12 | H60: =H49*trail_equity/12 | I60: =I49*trail_equity/12 | J60: =J49*trail_equity/12 | K60: =K49*trail_equity/12 | ... BK60: =BK49*trail_equity/12
A61: First-time investor incentive | B61: ₹ | C61: 0 | D61: =D48*first_time_share*mf_incentive | E61: =E48*first_time_share*mf_incentive | F61: =F48*first_time_share*mf_incentive | G61: =G48*first_time_share*mf_incentive | H61: =H48*first_time_share*mf_incentive | I61: =I48*first_time_share*mf_incentive | J61: =J48*first_time_share*mf_incentive | K61: =K48*first_time_share*mf_incentive | ... BK61: =BK48*first_time_share*mf_incentive
A62: Insurance commission | B62: ₹ | C62: 0 | D62: =(D52*ins_comm_first+D53*ins_comm_renew)*ins_premium | E62: =(E52*ins_comm_first+E53*ins_comm_renew)*ins_premium | F62: =(F52*ins_comm_first+F53*ins_comm_renew)*ins_premium | G62: =(G52*ins_comm_first+G53*ins_comm_renew)*ins_premium | H62: =(H52*ins_comm_first+H53*ins_comm_renew)*ins_premium | I62: =(I52*ins_comm_first+I53*ins_comm_renew)*ins_premium | J62: =(J52*ins_comm_first+J53*ins_comm_renew)*ins_premium | K62: =(K52*ins_comm_first+K53*ins_comm_renew)*ins_premium | ... BK62: =(BK52*ins_comm_first+BK53*ins_comm_renew)*ins_premium
A63: Total revenue | B63: ₹ | C63: 0 | D63: =D55+D56+D57+D58+D59+D60+D61+D62 | E63: =E55+E56+E57+E58+E59+E60+E61+E62 | F63: =F55+F56+F57+F58+F59+F60+F61+F62 | G63: =G55+G56+G57+G58+G59+G60+G61+G62 | H63: =H55+H56+H57+H58+H59+H60+H61+H62 | I63: =I55+I56+I57+I58+I59+I60+I61+I62 | J63: =J55+J56+J57+J58+J59+J60+J61+J62 | K63: =K55+K56+K57+K58+K59+K60+K61+K62 | ... BK63: =BK55+BK56+BK57+BK58+BK59+BK60+BK61+BK62
A64: Variable cost
A65: Loans: our cost (+ losses we bear under a guarantee or own NBFC) | B65: ₹ | C65: 0 | D65: =IF(nbfc_on=1,D35*loan_lost+D31*(loan_ops_cost+service_cost),D31*loan_ops_cost+dlg_on*(MIN(loan_lost,dlg_cap)*D35+(D26+D27+D29)*service_cost)) | E65: =IF(nbfc_on=1,E35*loan_lost+E31*(loan_ops_cost+service_cost),E31*loan_ops_cost+dlg_on*(MIN(loan_lost,dlg_cap)*E35+(E26+E27+E29)*service_cost)) | F65: =IF(nbfc_on=1,F35*loan_lost+F31*(loan_ops_cost+service_cost),F31*loan_ops_cost+dlg_on*(MIN(loan_lost,dlg_cap)*F35+(F26+F27+F29)*service_cost)) | G65: =IF(nbfc_on=1,G35*loan_lost+G31*(loan_ops_cost+service_cost),G31*loan_ops_cost+dlg_on*(MIN(loan_lost,dlg_cap)*G35+(G26+G27+G29)*service_cost)) | H65: =IF(nbfc_on=1,H35*loan_lost+H31*(loan_ops_cost+service_cost),H31*loan_ops_cost+dlg_on*(MIN(loan_lost,dlg_cap)*H35+(H26+H27+H29)*service_cost)) | I65: =IF(nbfc_on=1,I35*loan_lost+I31*(loan_ops_cost+service_cost),I31*loan_ops_cost+dlg_on*(MIN(loan_lost,dlg_cap)*I35+(I26+I27+I29)*service_cost)) | J65: =IF(nbfc_on=1,J35*loan_lost+J31*(loan_ops_cost+service_cost),J31*loan_ops_cost+dlg_on*(MIN(loan_lost,dlg_cap)*J35+(J26+J27+J29)*service_cost)) | K65: =IF(nbfc_on=1,K35*loan_lost+K31*(loan_ops_cost+service_cost),K31*loan_ops_cost+dlg_on*(MIN(loan_lost,dlg_cap)*K35+(K26+K27+K29)*service_cost)) | ... BK65: =IF(nbfc_on=1,BK35*loan_lost+BK31*(loan_ops_cost+service_cost),BK31*loan_ops_cost+dlg_on*(MIN(loan_lost,dlg_cap)*BK35+(BK26+BK27+BK29)*service_cost))
A66: Cards: our cost | B66: ₹ | C66: 0 | D66: =(D42+D45)*card_ops_cost | E66: =(E42+E45)*card_ops_cost | F66: =(F42+F45)*card_ops_cost | G66: =(G42+G45)*card_ops_cost | H66: =(H42+H45)*card_ops_cost | I66: =(I42+I45)*card_ops_cost | J66: =(J42+J45)*card_ops_cost | K66: =(K42+K45)*card_ops_cost | ... BK66: =(BK42+BK45)*card_ops_cost
A67: Insurance: our cost | B67: ₹ | C67: 0 | D67: =D52*ins_ops_cost | E67: =E52*ins_ops_cost | F67: =F52*ins_ops_cost | G67: =G52*ins_ops_cost | H67: =H52*ins_ops_cost | I67: =I52*ins_ops_cost | J67: =J52*ins_ops_cost | K67: =K52*ins_ops_cost | ... BK67: =BK52*ins_ops_cost
A68: Debits, pre-debit notices and failed debits | B68: ₹ | C68: 0 | D68: =D7*(debits_success*cost_debit+debits_scheduled*cost_notice+MAX(0,debits_scheduled-debits_success)*cost_failed) | E68: =E7*(debits_success*cost_debit+debits_scheduled*cost_notice+MAX(0,debits_scheduled-debits_success)*cost_failed) | F68: =F7*(debits_success*cost_debit+debits_scheduled*cost_notice+MAX(0,debits_scheduled-debits_success)*cost_failed) | G68: =G7*(debits_success*cost_debit+debits_scheduled*cost_notice+MAX(0,debits_scheduled-debits_success)*cost_failed) | H68: =H7*(debits_success*cost_debit+debits_scheduled*cost_notice+MAX(0,debits_scheduled-debits_success)*cost_failed) | I68: =I7*(debits_success*cost_debit+debits_scheduled*cost_notice+MAX(0,debits_scheduled-debits_success)*cost_failed) | J68: =J7*(debits_success*cost_debit+debits_scheduled*cost_notice+MAX(0,debits_scheduled-debits_success)*cost_failed) | K68: =K7*(debits_success*cost_debit+debits_scheduled*cost_notice+MAX(0,debits_scheduled-debits_success)*cost_failed) | ... BK68: =BK7*(debits_success*cost_debit+debits_scheduled*cost_notice+MAX(0,debits_scheduled-debits_success)*cost_failed)
A69: Support, tech and streak rewards | B69: ₹ | C69: 0 | D69: =D7*(cost_support+cost_tech+cost_rewards) | E69: =E7*(cost_support+cost_tech+cost_rewards) | F69: =F7*(cost_support+cost_tech+cost_rewards) | G69: =G7*(cost_support+cost_tech+cost_rewards) | H69: =H7*(cost_support+cost_tech+cost_rewards) | I69: =I7*(cost_support+cost_tech+cost_rewards) | J69: =J7*(cost_support+cost_tech+cost_rewards) | K69: =K7*(cost_support+cost_tech+cost_rewards) | ... BK69: =BK7*(cost_support+cost_tech+cost_rewards)
A70: Fraud | B70: ₹ | C70: 0 | D70: =D9*cost_fraud | E70: =E9*cost_fraud | F70: =F9*cost_fraud | G70: =G9*cost_fraud | H70: =H9*cost_fraud | I70: =I9*cost_fraud | J70: =J9*cost_fraud | K70: =K9*cost_fraud | ... BK70: =BK9*cost_fraud
A71: Total variable cost | B71: ₹ | C71: 0 | D71: =D65+D66+D67+D68+D69+D70 | E71: =E65+E66+E67+E68+E69+E70 | F71: =F65+F66+F67+F68+F69+F70 | G71: =G65+G66+G67+G68+G69+G70 | H71: =H65+H66+H67+H68+H69+H70 | I71: =I65+I66+I67+I68+I69+I70 | J71: =J65+J66+J67+J68+J69+J70 | K71: =K65+K66+K67+K68+K69+K70 | ... BK71: =BK65+BK66+BK67+BK68+BK69+BK70
A72: Contribution
A73: Contribution margin (revenue − variable cost) | B73: ₹ | C73: 0 | D73: =D63-D71 | E73: =E63-E71 | F73: =F63-F71 | G73: =G63-G71 | H73: =H63-H71 | I73: =I63-I71 | J73: =J63-J71 | K73: =K63-K71 | ... BK73: =BK63-BK71
A74: …per activated saver | B74: ₹ | C74: 0 | D74: =D73/seg_n_gig | E74: =E73/seg_n_gig | F74: =F73/seg_n_gig | G74: =G73/seg_n_gig | H74: =H73/seg_n_gig | I74: =I73/seg_n_gig | J74: =J73/seg_n_gig | K74: =K73/seg_n_gig | ... BK74: =BK73/seg_n_gig
A75: Cumulative contribution per activated saver | B75: ₹ | C75: 0 | D75: =C75+D74 | E75: =D75+E74 | F75: =E75+F74 | G75: =F75+G74 | H75: =G75+H74 | I75: =H75+I74 | J75: =I75+J74 | K75: =J75+K74 | ... BK75: =BJ75+BK74
A76: Discounted contribution per activated saver | B76: ₹ | C76: 0 | D76: =D74/(1+disc_rate)^(D$4/12) | E76: =E74/(1+disc_rate)^(E$4/12) | F76: =F74/(1+disc_rate)^(F$4/12) | G76: =G74/(1+disc_rate)^(G$4/12) | H76: =H74/(1+disc_rate)^(H$4/12) | I76: =I74/(1+disc_rate)^(I$4/12) | J76: =J74/(1+disc_rate)^(J$4/12) | K76: =K74/(1+disc_rate)^(K$4/12) | ... BK76: =BK74/(1+disc_rate)^(BK$4/12)
A77: Payback flag (month if cumulative ≥ CAC, else 999) | B77: month | D77: =IF(D75>=cac_gig,D$4,999) | E77: =IF(E75>=cac_gig,E$4,999) | F77: =IF(F75>=cac_gig,F$4,999) | G77: =IF(G75>=cac_gig,G$4,999) | H77: =IF(H75>=cac_gig,H$4,999) | I77: =IF(I75>=cac_gig,I$4,999) | J77: =IF(J75>=cac_gig,J$4,999) | K77: =IF(K75>=cac_gig,K$4,999) | ... BK77: =IF(BK75>=cac_gig,BK$4,999)

Sheet Cohort non-gig
A1: Cohort: the NON-GIG savers (shopkeepers, self-employed trades, workers outside the apps, small business owners) in one monthly cohort, followed for 60 months (scenario from Inputs!C2)
A2: Month 0 (column C) holds the starting state. Loan, card and insurance economics are booked in the month the loan, card or policy is issued. Numbers are for the whole cohort unless the row says 'per activated saver'.
A4: Month of cohort life | B4: unit | C4: 0 | D4: 1 | E4: 2 | F4: 3 | G4: 4 | H4: 5 | I4: 6 | J4: 7 | K4: 8 | L4: 9 | M4: 10 | N4: 11 | O4: 12 | P4: 13 | Q4: 14 | R4: 15 | S4: 16 | T4: 17 | U4: 18 | V4: 19 | W4: 20 | X4: 21 | Y4: 22 | Z4: 23 | AA4: 24 | AB4: 25 | AC4: 26 | AD4: 27 | AE4: 28 | AF4: 29 | AG4: 30 | AH4: 31 | AI4: 32 | AJ4: 33 | AK4: 34 | AL4: 35 | AM4: 36 | AN4: 37 | AO4: 38 | AP4: 39 | AQ4: 40 | AR4: 41 | AS4: 42 | AT4: 43 | AU4: 44 | AV4: 45 | AW4: 46 | AX4: 47 | AY4: 48 | AZ4: 49 | BA4: 50 | BB4: 51 | BC4: 52 | BD4: 53 | BE4: 54 | BF4: 55 | BG4: 56 | BH4: 57 | BI4: 58 | BJ4: 59 | BK4: 60
A5: Savers
A6: Share of activated savers still saving | B6: share | C6: 1 | D6: =IF(D$4<=1,ret_m1_ng^D$4,IF(D$4<=3,ret_m1_ng*(ret_m3_ng/ret_m1_ng)^((D$4-1)/2),IF(D$4<=6,ret_m3_ng*(ret_m6_ng/ret_m3_ng)^((D$4-3)/3),IF(D$4<=12,ret_m6_ng*(ret_m12_ng/ret_m6_ng)^((D$4-6)/6),IF(D$4<=24,ret_m12_ng*(ret_m24_ng/ret_m12_ng)^((D$4-12)/12),ret_m24_ng*(1-churn_late_ng)^(D$4-24)))))) | E6: =IF(E$4<=1,ret_m1_ng^E$4,IF(E$4<=3,ret_m1_ng*(ret_m3_ng/ret_m1_ng)^((E$4-1)/2),IF(E$4<=6,ret_m3_ng*(ret_m6_ng/ret_m3_ng)^((E$4-3)/3),IF(E$4<=12,ret_m6_ng*(ret_m12_ng/ret_m6_ng)^((E$4-6)/6),IF(E$4<=24,ret_m12_ng*(ret_m24_ng/ret_m12_ng)^((E$4-12)/12),ret_m24_ng*(1-churn_late_ng)^(E$4-24)))))) | F6: =IF(F$4<=1,ret_m1_ng^F$4,IF(F$4<=3,ret_m1_ng*(ret_m3_ng/ret_m1_ng)^((F$4-1)/2),IF(F$4<=6,ret_m3_ng*(ret_m6_ng/ret_m3_ng)^((F$4-3)/3),IF(F$4<=12,ret_m6_ng*(ret_m12_ng/ret_m6_ng)^((F$4-6)/6),IF(F$4<=24,ret_m12_ng*(ret_m24_ng/ret_m12_ng)^((F$4-12)/12),ret_m24_ng*(1-churn_late_ng)^(F$4-24)))))) | G6: =IF(G$4<=1,ret_m1_ng^G$4,IF(G$4<=3,ret_m1_ng*(ret_m3_ng/ret_m1_ng)^((G$4-1)/2),IF(G$4<=6,ret_m3_ng*(ret_m6_ng/ret_m3_ng)^((G$4-3)/3),IF(G$4<=12,ret_m6_ng*(ret_m12_ng/ret_m6_ng)^((G$4-6)/6),IF(G$4<=24,ret_m12_ng*(ret_m24_ng/ret_m12_ng)^((G$4-12)/12),ret_m24_ng*(1-churn_late_ng)^(G$4-24)))))) | H6: =IF(H$4<=1,ret_m1_ng^H$4,IF(H$4<=3,ret_m1_ng*(ret_m3_ng/ret_m1_ng)^((H$4-1)/2),IF(H$4<=6,ret_m3_ng*(ret_m6_ng/ret_m3_ng)^((H$4-3)/3),IF(H$4<=12,ret_m6_ng*(ret_m12_ng/ret_m6_ng)^((H$4-6)/6),IF(H$4<=24,ret_m12_ng*(ret_m24_ng/ret_m12_ng)^((H$4-12)/12),ret_m24_ng*(1-churn_late_ng)^(H$4-24)))))) | I6: =IF(I$4<=1,ret_m1_ng^I$4,IF(I$4<=3,ret_m1_ng*(ret_m3_ng/ret_m1_ng)^((I$4-1)/2),IF(I$4<=6,ret_m3_ng*(ret_m6_ng/ret_m3_ng)^((I$4-3)/3),IF(I$4<=12,ret_m6_ng*(ret_m12_ng/ret_m6_ng)^((I$4-6)/6),IF(I$4<=24,ret_m12_ng*(ret_m24_ng/ret_m12_ng)^((I$4-12)/12),ret_m24_ng*(1-churn_late_ng)^(I$4-24)))))) | J6: =IF(J$4<=1,ret_m1_ng^J$4,IF(J$4<=3,ret_m1_ng*(ret_m3_ng/ret_m1_ng)^((J$4-1)/2),IF(J$4<=6,ret_m3_ng*(ret_m6_ng/ret_m3_ng)^((J$4-3)/3),IF(J$4<=12,ret_m6_ng*(ret_m12_ng/ret_m6_ng)^((J$4-6)/6),IF(J$4<=24,ret_m12_ng*(ret_m24_ng/ret_m12_ng)^((J$4-12)/12),ret_m24_ng*(1-churn_late_ng)^(J$4-24)))))) | K6: =IF(K$4<=1,ret_m1_ng^K$4,IF(K$4<=3,ret_m1_ng*(ret_m3_ng/ret_m1_ng)^((K$4-1)/2),IF(K$4<=6,ret_m3_ng*(ret_m6_ng/ret_m3_ng)^((K$4-3)/3),IF(K$4<=12,ret_m6_ng*(ret_m12_ng/ret_m6_ng)^((K$4-6)/6),IF(K$4<=24,ret_m12_ng*(ret_m24_ng/ret_m12_ng)^((K$4-12)/12),ret_m24_ng*(1-churn_late_ng)^(K$4-24)))))) | ... BK6: =IF(BK$4<=1,ret_m1_ng^BK$4,IF(BK$4<=3,ret_m1_ng*(ret_m3_ng/ret_m1_ng)^((BK$4-1)/2),IF(BK$4<=6,ret_m3_ng*(ret_m6_ng/ret_m3_ng)^((BK$4-3)/3),IF(BK$4<=12,ret_m6_ng*(ret_m12_ng/ret_m6_ng)^((BK$4-6)/6),IF(BK$4<=24,ret_m12_ng*(ret_m24_ng/ret_m12_ng)^((BK$4-12)/12),ret_m24_ng*(1-churn_late_ng)^(BK$4-24))))))
A7: Active savers | B7: savers | D7: =seg_n_ng*D6 | E7: =seg_n_ng*E6 | F7: =seg_n_ng*F6 | G7: =seg_n_ng*G6 | H7: =seg_n_ng*H6 | I7: =seg_n_ng*I6 | J7: =seg_n_ng*J6 | K7: =seg_n_ng*K6 | ... BK7: =seg_n_ng*BK6
A8: Money saved per active saver | B8: ₹ per month | D8: =daily_amount_ng*(1+amount_growth_ng)^INT((D$4-1)/12)*debits_success_ng | E8: =daily_amount_ng*(1+amount_growth_ng)^INT((E$4-1)/12)*debits_success_ng | F8: =daily_amount_ng*(1+amount_growth_ng)^INT((F$4-1)/12)*debits_success_ng | G8: =daily_amount_ng*(1+amount_growth_ng)^INT((G$4-1)/12)*debits_success_ng | H8: =daily_amount_ng*(1+amount_growth_ng)^INT((H$4-1)/12)*debits_success_ng | I8: =daily_amount_ng*(1+amount_growth_ng)^INT((I$4-1)/12)*debits_success_ng | J8: =daily_amount_ng*(1+amount_growth_ng)^INT((J$4-1)/12)*debits_success_ng | K8: =daily_amount_ng*(1+amount_growth_ng)^INT((K$4-1)/12)*debits_success_ng | ... BK8: =daily_amount_ng*(1+amount_growth_ng)^INT((BK$4-1)/12)*debits_success_ng
A9: Money saved (contributions) | B9: ₹ | D9: =D7*D8 | E9: =E7*E8 | F9: =F7*F8 | G9: =G7*G8 | H9: =H7*H8 | I9: =I7*I8 | J9: =J7*J8 | K9: =K7*K8 | ... BK9: =BK7*BK8
A10: Balances (money sits with the fund house or bank, never with us)
A11: Share of last month's savers still saving | B11: share | D11: =D6/C6 | E11: =E6/D6 | F11: =F6/E6 | G11: =G6/F6 | H11: =H6/G6 | I11: =I6/H6 | J11: =J6/I6 | K11: =K6/J6 | ... BK11: =BK6/BJ6
A12: Last month's active balance after returns | B12: ₹ | D12: =C15*(1+fund_yield_ng/12) | E12: =D15*(1+fund_yield_ng/12) | F12: =E15*(1+fund_yield_ng/12) | G12: =F15*(1+fund_yield_ng/12) | H12: =G15*(1+fund_yield_ng/12) | I12: =H15*(1+fund_yield_ng/12) | J12: =I15*(1+fund_yield_ng/12) | K12: =J15*(1+fund_yield_ng/12) | ... BK12: =BJ15*(1+fund_yield_ng/12)
A13: …belonging to savers who stay | B13: ₹ | D13: =D12*D11 | E13: =E12*E11 | F13: =F12*F11 | G13: =G12*G11 | H13: =H12*H11 | I13: =I12*I11 | J13: =J12*J11 | K13: =K12*K11 | ... BK13: =BK12*BK11
A14: …belonging to savers who stop this month | B14: ₹ | D14: =D12*(1-D11) | E14: =E12*(1-E11) | F14: =F12*(1-F11) | G14: =G12*(1-G11) | H14: =H12*(1-H11) | I14: =I12*(1-I11) | J14: =J12*(1-J11) | K14: =K12*(1-K11) | ... BK14: =BK12*(1-BK11)
A15: Balance of active savers | B15: ₹ | C15: 0 | D15: =D13*(1-withdraw_rate_ng)+D9 | E15: =E13*(1-withdraw_rate_ng)+E9 | F15: =F13*(1-withdraw_rate_ng)+F9 | G15: =G13*(1-withdraw_rate_ng)+G9 | H15: =H13*(1-withdraw_rate_ng)+H9 | I15: =I13*(1-withdraw_rate_ng)+I9 | J15: =J13*(1-withdraw_rate_ng)+J9 | K15: =K13*(1-withdraw_rate_ng)+K9 | ... BK15: =BK13*(1-withdraw_rate_ng)+BK9
A16: Balance left behind by savers who stopped | B16: ₹ | C16: 0 | D16: =C16*(1+fund_yield_ng/12)*(1-dormant_withdraw_ng)+D14*(1-leaver_withdraw_ng) | E16: =D16*(1+fund_yield_ng/12)*(1-dormant_withdraw_ng)+E14*(1-leaver_withdraw_ng) | F16: =E16*(1+fund_yield_ng/12)*(1-dormant_withdraw_ng)+F14*(1-leaver_withdraw_ng) | G16: =F16*(1+fund_yield_ng/12)*(1-dormant_withdraw_ng)+G14*(1-leaver_withdraw_ng) | H16: =G16*(1+fund_yield_ng/12)*(1-dormant_withdraw_ng)+H14*(1-leaver_withdraw_ng) | I16: =H16*(1+fund_yield_ng/12)*(1-dormant_withdraw_ng)+I14*(1-leaver_withdraw_ng) | J16: =I16*(1+fund_yield_ng/12)*(1-dormant_withdraw_ng)+J14*(1-leaver_withdraw_ng) | K16: =J16*(1+fund_yield_ng/12)*(1-dormant_withdraw_ng)+K14*(1-leaver_withdraw_ng) | ... BK16: =BJ16*(1+fund_yield_ng/12)*(1-dormant_withdraw_ng)+BK14*(1-leaver_withdraw_ng)
A17: Withdrawals | B17: ₹ | D17: =D13*withdraw_rate_ng+D14*leaver_withdraw_ng+C16*(1+fund_yield_ng/12)*dormant_withdraw_ng | E17: =E13*withdraw_rate_ng+E14*leaver_withdraw_ng+D16*(1+fund_yield_ng/12)*dormant_withdraw_ng | F17: =F13*withdraw_rate_ng+F14*leaver_withdraw_ng+E16*(1+fund_yield_ng/12)*dormant_withdraw_ng | G17: =G13*withdraw_rate_ng+G14*leaver_withdraw_ng+F16*(1+fund_yield_ng/12)*dormant_withdraw_ng | H17: =H13*withdraw_rate_ng+H14*leaver_withdraw_ng+G16*(1+fund_yield_ng/12)*dormant_withdraw_ng | I17: =I13*withdraw_rate_ng+I14*leaver_withdraw_ng+H16*(1+fund_yield_ng/12)*dormant_withdraw_ng | J17: =J13*withdraw_rate_ng+J14*leaver_withdraw_ng+I16*(1+fund_yield_ng/12)*dormant_withdraw_ng | K17: =K13*withdraw_rate_ng+K14*leaver_withdraw_ng+J16*(1+fund_yield_ng/12)*dormant_withdraw_ng | ... BK17: =BK13*withdraw_rate_ng+BK14*leaver_withdraw_ng+BJ16*(1+fund_yield_ng/12)*dormant_withdraw_ng
A18: Total savings balance | B18: ₹ | C18: 0 | D18: =D15+D16 | E18: =E15+E16 | F18: =F15+F16 | G18: =G15+G16 | H18: =H15+H16 | I18: =I15+I16 | J18: =J15+J16 | K18: =K15+K16 | ... BK18: =BK15+BK16
A19: …held in digital gold (lever) | B19: ₹ | C19: 0 | D19: =D18*gold_on_ng*gold_share_ng | E19: =E18*gold_on_ng*gold_share_ng | F19: =F18*gold_on_ng*gold_share_ng | G19: =G18*gold_on_ng*gold_share_ng | H19: =H18*gold_on_ng*gold_share_ng | I19: =I18*gold_on_ng*gold_share_ng | J19: =J18*gold_on_ng*gold_share_ng | K19: =K18*gold_on_ng*gold_share_ng | ... BK19: =BK18*gold_on_ng*gold_share_ng
A20: …held in bank FDs | B20: ₹ | C20: 0 | D20: =IF(D$4>=fd_start_ng,(D18-D19)*fd_share_ng,0) | E20: =IF(E$4>=fd_start_ng,(E18-E19)*fd_share_ng,0) | F20: =IF(F$4>=fd_start_ng,(F18-F19)*fd_share_ng,0) | G20: =IF(G$4>=fd_start_ng,(G18-G19)*fd_share_ng,0) | H20: =IF(H$4>=fd_start_ng,(H18-H19)*fd_share_ng,0) | I20: =IF(I$4>=fd_start_ng,(I18-I19)*fd_share_ng,0) | J20: =IF(J$4>=fd_start_ng,(J18-J19)*fd_share_ng,0) | K20: =IF(K$4>=fd_start_ng,(K18-K19)*fd_share_ng,0) | ... BK20: =IF(BK$4>=fd_start_ng,(BK18-BK19)*fd_share_ng,0)
A21: …held in the liquid fund | B21: ₹ | C21: 0 | D21: =D18-D19-D20 | E21: =E18-E19-E20 | F21: =F18-F19-F20 | G21: =G18-G19-G20 | H21: =H18-H19-H20 | I21: =I18-I19-I20 | J21: =J18-J19-J20 | K21: =K18-K19-K20 | ... BK21: =BK18-BK19-BK20
A22: Loans through partner lenders (we are the loan service provider; the lender's money)
A23: Share of active savers who have borrowed | B23: share | C23: 0 | D23: =IF(D$4>=loan_start_ng,C23+(loan_eligible_ng-C23)*loan_apply_ng*loan_approval_ng,0) | E23: =IF(E$4>=loan_start_ng,D23+(loan_eligible_ng-D23)*loan_apply_ng*loan_approval_ng,0) | F23: =IF(F$4>=loan_start_ng,E23+(loan_eligible_ng-E23)*loan_apply_ng*loan_approval_ng,0) | G23: =IF(G$4>=loan_start_ng,F23+(loan_eligible_ng-F23)*loan_apply_ng*loan_approval_ng,0) | H23: =IF(H$4>=loan_start_ng,G23+(loan_eligible_ng-G23)*loan_apply_ng*loan_approval_ng,0) | I23: =IF(I$4>=loan_start_ng,H23+(loan_eligible_ng-H23)*loan_apply_ng*loan_approval_ng,0) | J23: =IF(J$4>=loan_start_ng,I23+(loan_eligible_ng-I23)*loan_apply_ng*loan_approval_ng,0) | K23: =IF(K$4>=loan_start_ng,J23+(loan_eligible_ng-J23)*loan_apply_ng*loan_approval_ng,0) | ... BK23: =IF(BK$4>=loan_start_ng,BJ23+(loan_eligible_ng-BJ23)*loan_apply_ng*loan_approval_ng,0)
A24: Loan 1 (secured against savings): first loans | B24: loans | C24: 0 | D24: =IF(D$4>=loan_start_ng,D7*(loan_eligible_ng-C23)*loan_apply_ng*loan_approval_ng,0) | E24: =IF(E$4>=loan_start_ng,E7*(loan_eligible_ng-D23)*loan_apply_ng*loan_approval_ng,0) | F24: =IF(F$4>=loan_start_ng,F7*(loan_eligible_ng-E23)*loan_apply_ng*loan_approval_ng,0) | G24: =IF(G$4>=loan_start_ng,G7*(loan_eligible_ng-F23)*loan_apply_ng*loan_approval_ng,0) | H24: =IF(H$4>=loan_start_ng,H7*(loan_eligible_ng-G23)*loan_apply_ng*loan_approval_ng,0) | I24: =IF(I$4>=loan_start_ng,I7*(loan_eligible_ng-H23)*loan_apply_ng*loan_approval_ng,0) | J24: =IF(J$4>=loan_start_ng,J7*(loan_eligible_ng-I23)*loan_apply_ng*loan_approval_ng,0) | K24: =IF(K$4>=loan_start_ng,K7*(loan_eligible_ng-J23)*loan_apply_ng*loan_approval_ng,0) | ... BK24: =IF(BK$4>=loan_start_ng,BK7*(loan_eligible_ng-BJ23)*loan_apply_ng*loan_approval_ng,0)
A25: Loan 2 (secured): repaid loan 1, still saving, borrowed again | B25: loans | C25: 0 | D25: =IF(D$4>loan_tenor_ng,loan_repeat_ng*(1-ladder_dpd90_ng)*INDEX($C$24:C$24,1,D$4-loan_tenor_ng+1)*D6/INDEX($C$6:C$6,1,D$4-loan_tenor_ng+1),0) | E25: =IF(E$4>loan_tenor_ng,loan_repeat_ng*(1-ladder_dpd90_ng)*INDEX($C$24:D$24,1,E$4-loan_tenor_ng+1)*E6/INDEX($C$6:D$6,1,E$4-loan_tenor_ng+1),0) | F25: =IF(F$4>loan_tenor_ng,loan_repeat_ng*(1-ladder_dpd90_ng)*INDEX($C$24:E$24,1,F$4-loan_tenor_ng+1)*F6/INDEX($C$6:E$6,1,F$4-loan_tenor_ng+1),0) | G25: =IF(G$4>loan_tenor_ng,loan_repeat_ng*(1-ladder_dpd90_ng)*INDEX($C$24:F$24,1,G$4-loan_tenor_ng+1)*G6/INDEX($C$6:F$6,1,G$4-loan_tenor_ng+1),0) | H25: =IF(H$4>loan_tenor_ng,loan_repeat_ng*(1-ladder_dpd90_ng)*INDEX($C$24:G$24,1,H$4-loan_tenor_ng+1)*H6/INDEX($C$6:G$6,1,H$4-loan_tenor_ng+1),0) | I25: =IF(I$4>loan_tenor_ng,loan_repeat_ng*(1-ladder_dpd90_ng)*INDEX($C$24:H$24,1,I$4-loan_tenor_ng+1)*I6/INDEX($C$6:H$6,1,I$4-loan_tenor_ng+1),0) | J25: =IF(J$4>loan_tenor_ng,loan_repeat_ng*(1-ladder_dpd90_ng)*INDEX($C$24:I$24,1,J$4-loan_tenor_ng+1)*J6/INDEX($C$6:I$6,1,J$4-loan_tenor_ng+1),0) | K25: =IF(K$4>loan_tenor_ng,loan_repeat_ng*(1-ladder_dpd90_ng)*INDEX($C$24:J$24,1,K$4-loan_tenor_ng+1)*K6/INDEX($C$6:J$6,1,K$4-loan_tenor_ng+1),0) | ... BK25: =IF(BK$4>loan_tenor_ng,loan_repeat_ng*(1-ladder_dpd90_ng)*INDEX($C$24:BJ$24,1,BK$4-loan_tenor_ng+1)*BK6/INDEX($C$6:BJ$6,1,BK$4-loan_tenor_ng+1),0)
A26: Loan 3 (part secured) | B26: loans | C26: 0 | D26: =IF(D$4>loan_tenor_ng,loan_repeat_ng*(1-ladder_dpd90_ng)*INDEX($C$25:C$25,1,D$4-loan_tenor_ng+1)*D6/INDEX($C$6:C$6,1,D$4-loan_tenor_ng+1),0) | E26: =IF(E$4>loan_tenor_ng,loan_repeat_ng*(1-ladder_dpd90_ng)*INDEX($C$25:D$25,1,E$4-loan_tenor_ng+1)*E6/INDEX($C$6:D$6,1,E$4-loan_tenor_ng+1),0) | F26: =IF(F$4>loan_tenor_ng,loan_repeat_ng*(1-ladder_dpd90_ng)*INDEX($C$25:E$25,1,F$4-loan_tenor_ng+1)*F6/INDEX($C$6:E$6,1,F$4-loan_tenor_ng+1),0) | G26: =IF(G$4>loan_tenor_ng,loan_repeat_ng*(1-ladder_dpd90_ng)*INDEX($C$25:F$25,1,G$4-loan_tenor_ng+1)*G6/INDEX($C$6:F$6,1,G$4-loan_tenor_ng+1),0) | H26: =IF(H$4>loan_tenor_ng,loan_repeat_ng*(1-ladder_dpd90_ng)*INDEX($C$25:G$25,1,H$4-loan_tenor_ng+1)*H6/INDEX($C$6:G$6,1,H$4-loan_tenor_ng+1),0) | I26: =IF(I$4>loan_tenor_ng,loan_repeat_ng*(1-ladder_dpd90_ng)*INDEX($C$25:H$25,1,I$4-loan_tenor_ng+1)*I6/INDEX($C$6:H$6,1,I$4-loan_tenor_ng+1),0) | J26: =IF(J$4>loan_tenor_ng,loan_repeat_ng*(1-ladder_dpd90_ng)*INDEX($C$25:I$25,1,J$4-loan_tenor_ng+1)*J6/INDEX($C$6:I$6,1,J$4-loan_tenor_ng+1),0) | K26: =IF(K$4>loan_tenor_ng,loan_repeat_ng*(1-ladder_dpd90_ng)*INDEX($C$25:J$25,1,K$4-loan_tenor_ng+1)*K6/INDEX($C$6:J$6,1,K$4-loan_tenor_ng+1),0) | ... BK26: =IF(BK$4>loan_tenor_ng,loan_repeat_ng*(1-ladder_dpd90_ng)*INDEX($C$25:BJ$25,1,BK$4-loan_tenor_ng+1)*BK6/INDEX($C$6:BJ$6,1,BK$4-loan_tenor_ng+1),0)
A27: Loan 4 (part secured) | B27: loans | C27: 0 | D27: =IF(D$4>loan_tenor_ng,loan_repeat_ng*(1-ladder_dpd90_ng)*INDEX($C$26:C$26,1,D$4-loan_tenor_ng+1)*D6/INDEX($C$6:C$6,1,D$4-loan_tenor_ng+1),0) | E27: =IF(E$4>loan_tenor_ng,loan_repeat_ng*(1-ladder_dpd90_ng)*INDEX($C$26:D$26,1,E$4-loan_tenor_ng+1)*E6/INDEX($C$6:D$6,1,E$4-loan_tenor_ng+1),0) | F27: =IF(F$4>loan_tenor_ng,loan_repeat_ng*(1-ladder_dpd90_ng)*INDEX($C$26:E$26,1,F$4-loan_tenor_ng+1)*F6/INDEX($C$6:E$6,1,F$4-loan_tenor_ng+1),0) | G27: =IF(G$4>loan_tenor_ng,loan_repeat_ng*(1-ladder_dpd90_ng)*INDEX($C$26:F$26,1,G$4-loan_tenor_ng+1)*G6/INDEX($C$6:F$6,1,G$4-loan_tenor_ng+1),0) | H27: =IF(H$4>loan_tenor_ng,loan_repeat_ng*(1-ladder_dpd90_ng)*INDEX($C$26:G$26,1,H$4-loan_tenor_ng+1)*H6/INDEX($C$6:G$6,1,H$4-loan_tenor_ng+1),0) | I27: =IF(I$4>loan_tenor_ng,loan_repeat_ng*(1-ladder_dpd90_ng)*INDEX($C$26:H$26,1,I$4-loan_tenor_ng+1)*I6/INDEX($C$6:H$6,1,I$4-loan_tenor_ng+1),0) | J27: =IF(J$4>loan_tenor_ng,loan_repeat_ng*(1-ladder_dpd90_ng)*INDEX($C$26:I$26,1,J$4-loan_tenor_ng+1)*J6/INDEX($C$6:I$6,1,J$4-loan_tenor_ng+1),0) | K27: =IF(K$4>loan_tenor_ng,loan_repeat_ng*(1-ladder_dpd90_ng)*INDEX($C$26:J$26,1,K$4-loan_tenor_ng+1)*K6/INDEX($C$6:J$6,1,K$4-loan_tenor_ng+1),0) | ... BK27: =IF(BK$4>loan_tenor_ng,loan_repeat_ng*(1-ladder_dpd90_ng)*INDEX($C$26:BJ$26,1,BK$4-loan_tenor_ng+1)*BK6/INDEX($C$6:BJ$6,1,BK$4-loan_tenor_ng+1),0)
A28: …first unsecured loans (loan 5) | B28: loans | C28: 0 | D28: =IF(D$4>loan_tenor_ng,loan_repeat_ng*(1-ladder_dpd90_ng)*INDEX($C$27:C$27,1,D$4-loan_tenor_ng+1)*D6/INDEX($C$6:C$6,1,D$4-loan_tenor_ng+1),0) | E28: =IF(E$4>loan_tenor_ng,loan_repeat_ng*(1-ladder_dpd90_ng)*INDEX($C$27:D$27,1,E$4-loan_tenor_ng+1)*E6/INDEX($C$6:D$6,1,E$4-loan_tenor_ng+1),0) | F28: =IF(F$4>loan_tenor_ng,loan_repeat_ng*(1-ladder_dpd90_ng)*INDEX($C$27:E$27,1,F$4-loan_tenor_ng+1)*F6/INDEX($C$6:E$6,1,F$4-loan_tenor_ng+1),0) | G28: =IF(G$4>loan_tenor_ng,loan_repeat_ng*(1-ladder_dpd90_ng)*INDEX($C$27:F$27,1,G$4-loan_tenor_ng+1)*G6/INDEX($C$6:F$6,1,G$4-loan_tenor_ng+1),0) | H28: =IF(H$4>loan_tenor_ng,loan_repeat_ng*(1-ladder_dpd90_ng)*INDEX($C$27:G$27,1,H$4-loan_tenor_ng+1)*H6/INDEX($C$6:G$6,1,H$4-loan_tenor_ng+1),0) | I28: =IF(I$4>loan_tenor_ng,loan_repeat_ng*(1-ladder_dpd90_ng)*INDEX($C$27:H$27,1,I$4-loan_tenor_ng+1)*I6/INDEX($C$6:H$6,1,I$4-loan_tenor_ng+1),0) | J28: =IF(J$4>loan_tenor_ng,loan_repeat_ng*(1-ladder_dpd90_ng)*INDEX($C$27:I$27,1,J$4-loan_tenor_ng+1)*J6/INDEX($C$6:I$6,1,J$4-loan_tenor_ng+1),0) | K28: =IF(K$4>loan_tenor_ng,loan_repeat_ng*(1-ladder_dpd90_ng)*INDEX($C$27:J$27,1,K$4-loan_tenor_ng+1)*K6/INDEX($C$6:J$6,1,K$4-loan_tenor_ng+1),0) | ... BK28: =IF(BK$4>loan_tenor_ng,loan_repeat_ng*(1-ladder_dpd90_ng)*INDEX($C$27:BJ$27,1,BK$4-loan_tenor_ng+1)*BK6/INDEX($C$6:BJ$6,1,BK$4-loan_tenor_ng+1),0)
A29: Loans 5+ (unsecured) | B29: loans | C29: 0 | D29: =IF(D$4>loan_tenor_ng,D28+loan_repeat_ng*(1-ladder_dpd90_ng)*INDEX($C$29:C$29,1,D$4-loan_tenor_ng+1)*D6/INDEX($C$6:C$6,1,D$4-loan_tenor_ng+1),0) | E29: =IF(E$4>loan_tenor_ng,E28+loan_repeat_ng*(1-ladder_dpd90_ng)*INDEX($C$29:D$29,1,E$4-loan_tenor_ng+1)*E6/INDEX($C$6:D$6,1,E$4-loan_tenor_ng+1),0) | F29: =IF(F$4>loan_tenor_ng,F28+loan_repeat_ng*(1-ladder_dpd90_ng)*INDEX($C$29:E$29,1,F$4-loan_tenor_ng+1)*F6/INDEX($C$6:E$6,1,F$4-loan_tenor_ng+1),0) | G29: =IF(G$4>loan_tenor_ng,G28+loan_repeat_ng*(1-ladder_dpd90_ng)*INDEX($C$29:F$29,1,G$4-loan_tenor_ng+1)*G6/INDEX($C$6:F$6,1,G$4-loan_tenor_ng+1),0) | H29: =IF(H$4>loan_tenor_ng,H28+loan_repeat_ng*(1-ladder_dpd90_ng)*INDEX($C$29:G$29,1,H$4-loan_tenor_ng+1)*H6/INDEX($C$6:G$6,1,H$4-loan_tenor_ng+1),0) | I29: =IF(I$4>loan_tenor_ng,I28+loan_repeat_ng*(1-ladder_dpd90_ng)*INDEX($C$29:H$29,1,I$4-loan_tenor_ng+1)*I6/INDEX($C$6:H$6,1,I$4-loan_tenor_ng+1),0) | J29: =IF(J$4>loan_tenor_ng,J28+loan_repeat_ng*(1-ladder_dpd90_ng)*INDEX($C$29:I$29,1,J$4-loan_tenor_ng+1)*J6/INDEX($C$6:I$6,1,J$4-loan_tenor_ng+1),0) | K29: =IF(K$4>loan_tenor_ng,K28+loan_repeat_ng*(1-ladder_dpd90_ng)*INDEX($C$29:J$29,1,K$4-loan_tenor_ng+1)*K6/INDEX($C$6:J$6,1,K$4-loan_tenor_ng+1),0) | ... BK29: =IF(BK$4>loan_tenor_ng,BK28+loan_repeat_ng*(1-ladder_dpd90_ng)*INDEX($C$29:BJ$29,1,BK$4-loan_tenor_ng+1)*BK6/INDEX($C$6:BJ$6,1,BK$4-loan_tenor_ng+1),0)
A30: Repeat loans (loans 2+) | B30: loans | C30: 0 | D30: =D25+D26+D27+D29 | E30: =E25+E26+E27+E29 | F30: =F25+F26+F27+F29 | G30: =G25+G26+G27+G29 | H30: =H25+H26+H27+H29 | I30: =I25+I26+I27+I29 | J30: =J25+J26+J27+J29 | K30: =K25+K26+K27+K29 | ... BK30: =BK25+BK26+BK27+BK29
A31: All loans | B31: loans | C31: 0 | D31: =D24+D30 | E31: =E24+E30 | F31: =F24+F30 | G31: =G24+G30 | H31: =H24+H30 | I31: =I24+I30 | J31: =J24+J30 | K31: =K24+K30 | ... BK31: =BK24+BK30
A32: Savings that can back a loan, per active saver (fund + FD; gold cannot) | B32: ₹ | C32: 0 | D32: =IF(D7>0,D15/D7,0)*(1-gold_on_ng*gold_share_ng) | E32: =IF(E7>0,E15/E7,0)*(1-gold_on_ng*gold_share_ng) | F32: =IF(F7>0,F15/F7,0)*(1-gold_on_ng*gold_share_ng) | G32: =IF(G7>0,G15/G7,0)*(1-gold_on_ng*gold_share_ng) | H32: =IF(H7>0,H15/H7,0)*(1-gold_on_ng*gold_share_ng) | I32: =IF(I7>0,I15/I7,0)*(1-gold_on_ng*gold_share_ng) | J32: =IF(J7>0,J15/J7,0)*(1-gold_on_ng*gold_share_ng) | K32: =IF(K7>0,K15/K7,0)*(1-gold_on_ng*gold_share_ng) | ... BK32: =IF(BK7>0,BK15/BK7,0)*(1-gold_on_ng*gold_share_ng)
A33: Secured loan size (secured_ltv of that) | B33: ₹ | C33: 0 | D33: =secured_ltv_ng*D32 | E33: =secured_ltv_ng*E32 | F33: =secured_ltv_ng*F32 | G33: =secured_ltv_ng*G32 | H33: =secured_ltv_ng*H32 | I33: =secured_ltv_ng*I32 | J33: =secured_ltv_ng*J32 | K33: =secured_ltv_ng*K32 | ... BK33: =secured_ltv_ng*BK32
A34: Secured money lent (loans 1-4) | B34: ₹ | C34: 0 | D34: =(D24+D25+D26+D27)*D33 | E34: =(E24+E25+E26+E27)*E33 | F34: =(F24+F25+F26+F27)*F33 | G34: =(G24+G25+G26+G27)*G33 | H34: =(H24+H25+H26+H27)*H33 | I34: =(I24+I25+I26+I27)*I33 | J34: =(J24+J25+J26+J27)*J33 | K34: =(K24+K25+K26+K27)*K33 | ... BK34: =(BK24+BK25+BK26+BK27)*BK33
A35: Unsecured money lent (top-ups on loans 3-4, all of loans 5+) | B35: ₹ | C35: 0 | D35: =(D26+D27)*D33*part_unsec_multiple_ng+D29*loan_ticket_ng | E35: =(E26+E27)*E33*part_unsec_multiple_ng+E29*loan_ticket_ng | F35: =(F26+F27)*F33*part_unsec_multiple_ng+F29*loan_ticket_ng | G35: =(G26+G27)*G33*part_unsec_multiple_ng+G29*loan_ticket_ng | H35: =(H26+H27)*H33*part_unsec_multiple_ng+H29*loan_ticket_ng | I35: =(I26+I27)*I33*part_unsec_multiple_ng+I29*loan_ticket_ng | J35: =(J26+J27)*J33*part_unsec_multiple_ng+J29*loan_ticket_ng | K35: =(K26+K27)*K33*part_unsec_multiple_ng+K29*loan_ticket_ng | ... BK35: =(BK26+BK27)*BK33*part_unsec_multiple_ng+BK29*loan_ticket_ng
A36: Money lent (by partners, or by our NBFC if that lever is on) | B36: ₹ | C36: 0 | D36: =D34+D35 | E36: =E34+E35 | F36: =F34+F35 | G36: =G34+G35 | H36: =H34+H35 | I36: =I34+I35 | J36: =J34+J35 | K36: =K34+K35 | ... BK36: =BK34+BK35
A37: Unsecured money lent in the last loan-length months (sets the guarantee deposit) | B37: ₹ | C37: 0 | D37: =C37+D35-IF(D$4>loan_tenor_ng,INDEX($C$35:C$35,1,D$4-loan_tenor_ng+1),0) | E37: =D37+E35-IF(E$4>loan_tenor_ng,INDEX($C$35:D$35,1,E$4-loan_tenor_ng+1),0) | F37: =E37+F35-IF(F$4>loan_tenor_ng,INDEX($C$35:E$35,1,F$4-loan_tenor_ng+1),0) | G37: =F37+G35-IF(G$4>loan_tenor_ng,INDEX($C$35:F$35,1,G$4-loan_tenor_ng+1),0) | H37: =G37+H35-IF(H$4>loan_tenor_ng,INDEX($C$35:G$35,1,H$4-loan_tenor_ng+1),0) | I37: =H37+I35-IF(I$4>loan_tenor_ng,INDEX($C$35:H$35,1,I$4-loan_tenor_ng+1),0) | J37: =I37+J35-IF(J$4>loan_tenor_ng,INDEX($C$35:I$35,1,J$4-loan_tenor_ng+1),0) | K37: =J37+K35-IF(K$4>loan_tenor_ng,INDEX($C$35:J$35,1,K$4-loan_tenor_ng+1),0) | ... BK37: =BJ37+BK35-IF(BK$4>loan_tenor_ng,INDEX($C$35:BJ$35,1,BK$4-loan_tenor_ng+1),0)
A38: All money lent in the last loan-length months (an own NBFC's book) | B38: ₹ | C38: 0 | D38: =C38+D36-IF(D$4>loan_tenor_ng,INDEX($C$36:C$36,1,D$4-loan_tenor_ng+1),0) | E38: =D38+E36-IF(E$4>loan_tenor_ng,INDEX($C$36:D$36,1,E$4-loan_tenor_ng+1),0) | F38: =E38+F36-IF(F$4>loan_tenor_ng,INDEX($C$36:E$36,1,F$4-loan_tenor_ng+1),0) | G38: =F38+G36-IF(G$4>loan_tenor_ng,INDEX($C$36:F$36,1,G$4-loan_tenor_ng+1),0) | H38: =G38+H36-IF(H$4>loan_tenor_ng,INDEX($C$36:G$36,1,H$4-loan_tenor_ng+1),0) | I38: =H38+I36-IF(I$4>loan_tenor_ng,INDEX($C$36:H$36,1,I$4-loan_tenor_ng+1),0) | J38: =I38+J36-IF(J$4>loan_tenor_ng,INDEX($C$36:I$36,1,J$4-loan_tenor_ng+1),0) | K38: =J38+K36-IF(K$4>loan_tenor_ng,INDEX($C$36:J$36,1,K$4-loan_tenor_ng+1),0) | ... BK38: =BJ38+BK36-IF(BK$4>loan_tenor_ng,INDEX($C$36:BJ$36,1,BK$4-loan_tenor_ng+1),0)
A39: Capital locked: guarantee deposit, or NBFC equity for the loan book | B39: ₹ | C39: 0 | D39: =IF(nbfc_on_ng=1,nbfc_equity_ng*nbfc_avg_frac_ng*D38,dlg_on_ng*dlg_cap_ng*D37) | E39: =IF(nbfc_on_ng=1,nbfc_equity_ng*nbfc_avg_frac_ng*E38,dlg_on_ng*dlg_cap_ng*E37) | F39: =IF(nbfc_on_ng=1,nbfc_equity_ng*nbfc_avg_frac_ng*F38,dlg_on_ng*dlg_cap_ng*F37) | G39: =IF(nbfc_on_ng=1,nbfc_equity_ng*nbfc_avg_frac_ng*G38,dlg_on_ng*dlg_cap_ng*G37) | H39: =IF(nbfc_on_ng=1,nbfc_equity_ng*nbfc_avg_frac_ng*H38,dlg_on_ng*dlg_cap_ng*H37) | I39: =IF(nbfc_on_ng=1,nbfc_equity_ng*nbfc_avg_frac_ng*I38,dlg_on_ng*dlg_cap_ng*I37) | J39: =IF(nbfc_on_ng=1,nbfc_equity_ng*nbfc_avg_frac_ng*J38,dlg_on_ng*dlg_cap_ng*J37) | K39: =IF(nbfc_on_ng=1,nbfc_equity_ng*nbfc_avg_frac_ng*K38,dlg_on_ng*dlg_cap_ng*K37) | ... BK39: =IF(nbfc_on_ng=1,nbfc_equity_ng*nbfc_avg_frac_ng*BK38,dlg_on_ng*dlg_cap_ng*BK37)
A40: Cards (issued by a partner bank)
A41: Share of active savers with an FD-secured card | B41: share | C41: 0 | D41: =IF(D$4>=card_start_ng,C41*(1-card_churn_ng)+(card_eligible_ng*(1-gold_on_ng*gold_share_ng)-C41)*card_uptake_ng,0) | E41: =IF(E$4>=card_start_ng,D41*(1-card_churn_ng)+(card_eligible_ng*(1-gold_on_ng*gold_share_ng)-D41)*card_uptake_ng,0) | F41: =IF(F$4>=card_start_ng,E41*(1-card_churn_ng)+(card_eligible_ng*(1-gold_on_ng*gold_share_ng)-E41)*card_uptake_ng,0) | G41: =IF(G$4>=card_start_ng,F41*(1-card_churn_ng)+(card_eligible_ng*(1-gold_on_ng*gold_share_ng)-F41)*card_uptake_ng,0) | H41: =IF(H$4>=card_start_ng,G41*(1-card_churn_ng)+(card_eligible_ng*(1-gold_on_ng*gold_share_ng)-G41)*card_uptake_ng,0) | I41: =IF(I$4>=card_start_ng,H41*(1-card_churn_ng)+(card_eligible_ng*(1-gold_on_ng*gold_share_ng)-H41)*card_uptake_ng,0) | J41: =IF(J$4>=card_start_ng,I41*(1-card_churn_ng)+(card_eligible_ng*(1-gold_on_ng*gold_share_ng)-I41)*card_uptake_ng,0) | K41: =IF(K$4>=card_start_ng,J41*(1-card_churn_ng)+(card_eligible_ng*(1-gold_on_ng*gold_share_ng)-J41)*card_uptake_ng,0) | ... BK41: =IF(BK$4>=card_start_ng,BJ41*(1-card_churn_ng)+(card_eligible_ng*(1-gold_on_ng*gold_share_ng)-BJ41)*card_uptake_ng,0)
A42: New FD-secured cards (only FD money, not gold, can back a card) | B42: cards | C42: 0 | D42: =IF(D$4>=card_start_ng,D7*(card_eligible_ng*(1-gold_on_ng*gold_share_ng)-C41)*card_uptake_ng,0) | E42: =IF(E$4>=card_start_ng,E7*(card_eligible_ng*(1-gold_on_ng*gold_share_ng)-D41)*card_uptake_ng,0) | F42: =IF(F$4>=card_start_ng,F7*(card_eligible_ng*(1-gold_on_ng*gold_share_ng)-E41)*card_uptake_ng,0) | G42: =IF(G$4>=card_start_ng,G7*(card_eligible_ng*(1-gold_on_ng*gold_share_ng)-F41)*card_uptake_ng,0) | H42: =IF(H$4>=card_start_ng,H7*(card_eligible_ng*(1-gold_on_ng*gold_share_ng)-G41)*card_uptake_ng,0) | I42: =IF(I$4>=card_start_ng,I7*(card_eligible_ng*(1-gold_on_ng*gold_share_ng)-H41)*card_uptake_ng,0) | J42: =IF(J$4>=card_start_ng,J7*(card_eligible_ng*(1-gold_on_ng*gold_share_ng)-I41)*card_uptake_ng,0) | K42: =IF(K$4>=card_start_ng,K7*(card_eligible_ng*(1-gold_on_ng*gold_share_ng)-J41)*card_uptake_ng,0) | ... BK42: =IF(BK$4>=card_start_ng,BK7*(card_eligible_ng*(1-gold_on_ng*gold_share_ng)-BJ41)*card_uptake_ng,0)
A43: Card holders | B43: cards | C43: 0 | D43: =D7*D41 | E43: =E7*E41 | F43: =F7*F41 | G43: =G7*G41 | H43: =H7*H41 | I43: =I7*I41 | J43: =J7*J41 | K43: =K7*K41 | ... BK43: =BK7*BK41
A44: Share moved to an unsecured card | B44: share | C44: 0 | D44: =IF(D$4>=unsec_start_ng,C44+MAX(0,C41-C44)*unsec_grad_ng,C44) | E44: =IF(E$4>=unsec_start_ng,D44+MAX(0,D41-D44)*unsec_grad_ng,D44) | F44: =IF(F$4>=unsec_start_ng,E44+MAX(0,E41-E44)*unsec_grad_ng,E44) | G44: =IF(G$4>=unsec_start_ng,F44+MAX(0,F41-F44)*unsec_grad_ng,F44) | H44: =IF(H$4>=unsec_start_ng,G44+MAX(0,G41-G44)*unsec_grad_ng,G44) | I44: =IF(I$4>=unsec_start_ng,H44+MAX(0,H41-H44)*unsec_grad_ng,H44) | J44: =IF(J$4>=unsec_start_ng,I44+MAX(0,I41-I44)*unsec_grad_ng,I44) | K44: =IF(K$4>=unsec_start_ng,J44+MAX(0,J41-J44)*unsec_grad_ng,J44) | ... BK44: =IF(BK$4>=unsec_start_ng,BJ44+MAX(0,BJ41-BJ44)*unsec_grad_ng,BJ44)
A45: New unsecured cards | B45: cards | C45: 0 | D45: =D7*(D44-C44) | E45: =E7*(E44-D44) | F45: =F7*(F44-E44) | G45: =G7*(G44-F44) | H45: =H7*(H44-G44) | I45: =I7*(I44-H44) | J45: =J7*(J44-I44) | K45: =K7*(K44-J44) | ... BK45: =BK7*(BK44-BJ44)
A46: Equity SIPs beyond the daily savings
A47: Share of active savers with an equity SIP | B47: share | C47: 0 | D47: =IF(D$4>=sip_start_ng,C47*(1-sip_stop_ng)+(sip_eligible_ng-C47)*sip_uptake_ng,0) | E47: =IF(E$4>=sip_start_ng,D47*(1-sip_stop_ng)+(sip_eligible_ng-D47)*sip_uptake_ng,0) | F47: =IF(F$4>=sip_start_ng,E47*(1-sip_stop_ng)+(sip_eligible_ng-E47)*sip_uptake_ng,0) | G47: =IF(G$4>=sip_start_ng,F47*(1-sip_stop_ng)+(sip_eligible_ng-F47)*sip_uptake_ng,0) | H47: =IF(H$4>=sip_start_ng,G47*(1-sip_stop_ng)+(sip_eligible_ng-G47)*sip_uptake_ng,0) | I47: =IF(I$4>=sip_start_ng,H47*(1-sip_stop_ng)+(sip_eligible_ng-H47)*sip_uptake_ng,0) | J47: =IF(J$4>=sip_start_ng,I47*(1-sip_stop_ng)+(sip_eligible_ng-I47)*sip_uptake_ng,0) | K47: =IF(K$4>=sip_start_ng,J47*(1-sip_stop_ng)+(sip_eligible_ng-J47)*sip_uptake_ng,0) | ... BK47: =IF(BK$4>=sip_start_ng,BJ47*(1-sip_stop_ng)+(sip_eligible_ng-BJ47)*sip_uptake_ng,0)
A48: New SIPs | B48: SIPs | C48: 0 | D48: =IF(D$4>=sip_start_ng,D7*(sip_eligible_ng-C47)*sip_uptake_ng,0) | E48: =IF(E$4>=sip_start_ng,E7*(sip_eligible_ng-D47)*sip_uptake_ng,0) | F48: =IF(F$4>=sip_start_ng,F7*(sip_eligible_ng-E47)*sip_uptake_ng,0) | G48: =IF(G$4>=sip_start_ng,G7*(sip_eligible_ng-F47)*sip_uptake_ng,0) | H48: =IF(H$4>=sip_start_ng,H7*(sip_eligible_ng-G47)*sip_uptake_ng,0) | I48: =IF(I$4>=sip_start_ng,I7*(sip_eligible_ng-H47)*sip_uptake_ng,0) | J48: =IF(J$4>=sip_start_ng,J7*(sip_eligible_ng-I47)*sip_uptake_ng,0) | K48: =IF(K$4>=sip_start_ng,K7*(sip_eligible_ng-J47)*sip_uptake_ng,0) | ... BK48: =IF(BK$4>=sip_start_ng,BK7*(sip_eligible_ng-BJ47)*sip_uptake_ng,0)
A49: SIP balance | B49: ₹ | C49: 0 | D49: =C49*(1+sip_return_ng/12)*(1-sip_redeem_ng)+D7*D47*sip_amount_ng | E49: =D49*(1+sip_return_ng/12)*(1-sip_redeem_ng)+E7*E47*sip_amount_ng | F49: =E49*(1+sip_return_ng/12)*(1-sip_redeem_ng)+F7*F47*sip_amount_ng | G49: =F49*(1+sip_return_ng/12)*(1-sip_redeem_ng)+G7*G47*sip_amount_ng | H49: =G49*(1+sip_return_ng/12)*(1-sip_redeem_ng)+H7*H47*sip_amount_ng | I49: =H49*(1+sip_return_ng/12)*(1-sip_redeem_ng)+I7*I47*sip_amount_ng | J49: =I49*(1+sip_return_ng/12)*(1-sip_redeem_ng)+J7*J47*sip_amount_ng | K49: =J49*(1+sip_return_ng/12)*(1-sip_redeem_ng)+K7*K47*sip_amount_ng | ... BK49: =BJ49*(1+sip_return_ng/12)*(1-sip_redeem_ng)+BK7*BK47*sip_amount_ng
A50: Insurance (annual policies from partner insurers)
A51: Share of active savers ever insured | B51: share | C51: 0 | D51: =IF(D$4>=ins_start_ng,C51+(ins_eligible_ng-C51)*ins_uptake_ng,0) | E51: =IF(E$4>=ins_start_ng,D51+(ins_eligible_ng-D51)*ins_uptake_ng,0) | F51: =IF(F$4>=ins_start_ng,E51+(ins_eligible_ng-E51)*ins_uptake_ng,0) | G51: =IF(G$4>=ins_start_ng,F51+(ins_eligible_ng-F51)*ins_uptake_ng,0) | H51: =IF(H$4>=ins_start_ng,G51+(ins_eligible_ng-G51)*ins_uptake_ng,0) | I51: =IF(I$4>=ins_start_ng,H51+(ins_eligible_ng-H51)*ins_uptake_ng,0) | J51: =IF(J$4>=ins_start_ng,I51+(ins_eligible_ng-I51)*ins_uptake_ng,0) | K51: =IF(K$4>=ins_start_ng,J51+(ins_eligible_ng-J51)*ins_uptake_ng,0) | ... BK51: =IF(BK$4>=ins_start_ng,BJ51+(ins_eligible_ng-BJ51)*ins_uptake_ng,0)
A52: New policies | B52: policies | C52: 0 | D52: =IF(D$4>=ins_start_ng,D7*(ins_eligible_ng-C51)*ins_uptake_ng,0) | E52: =IF(E$4>=ins_start_ng,E7*(ins_eligible_ng-D51)*ins_uptake_ng,0) | F52: =IF(F$4>=ins_start_ng,F7*(ins_eligible_ng-E51)*ins_uptake_ng,0) | G52: =IF(G$4>=ins_start_ng,G7*(ins_eligible_ng-F51)*ins_uptake_ng,0) | H52: =IF(H$4>=ins_start_ng,H7*(ins_eligible_ng-G51)*ins_uptake_ng,0) | I52: =IF(I$4>=ins_start_ng,I7*(ins_eligible_ng-H51)*ins_uptake_ng,0) | J52: =IF(J$4>=ins_start_ng,J7*(ins_eligible_ng-I51)*ins_uptake_ng,0) | K52: =IF(K$4>=ins_start_ng,K7*(ins_eligible_ng-J51)*ins_uptake_ng,0) | ... BK52: =IF(BK$4>=ins_start_ng,BK7*(ins_eligible_ng-BJ51)*ins_uptake_ng,0)
A53: Renewed policies | B53: policies | C53: 0 | D53: =IF(D$4>12,(INDEX($C$52:C$52,1,D$4-12+1)+INDEX($C$53:C$53,1,D$4-12+1))*ins_persist_ng,0) | E53: =IF(E$4>12,(INDEX($C$52:D$52,1,E$4-12+1)+INDEX($C$53:D$53,1,E$4-12+1))*ins_persist_ng,0) | F53: =IF(F$4>12,(INDEX($C$52:E$52,1,F$4-12+1)+INDEX($C$53:E$53,1,F$4-12+1))*ins_persist_ng,0) | G53: =IF(G$4>12,(INDEX($C$52:F$52,1,G$4-12+1)+INDEX($C$53:F$53,1,G$4-12+1))*ins_persist_ng,0) | H53: =IF(H$4>12,(INDEX($C$52:G$52,1,H$4-12+1)+INDEX($C$53:G$53,1,H$4-12+1))*ins_persist_ng,0) | I53: =IF(I$4>12,(INDEX($C$52:H$52,1,I$4-12+1)+INDEX($C$53:H$53,1,I$4-12+1))*ins_persist_ng,0) | J53: =IF(J$4>12,(INDEX($C$52:I$52,1,J$4-12+1)+INDEX($C$53:I$53,1,J$4-12+1))*ins_persist_ng,0) | K53: =IF(K$4>12,(INDEX($C$52:J$52,1,K$4-12+1)+INDEX($C$53:J$53,1,K$4-12+1))*ins_persist_ng,0) | ... BK53: =IF(BK$4>12,(INDEX($C$52:BJ$52,1,BK$4-12+1)+INDEX($C$53:BJ$53,1,BK$4-12+1))*ins_persist_ng,0)
A54: Revenue
A55: Liquid-fund trail commission | B55: ₹ | C55: 0 | D55: =D21*trail_liquid_ng/12 | E55: =E21*trail_liquid_ng/12 | F55: =F21*trail_liquid_ng/12 | G55: =G21*trail_liquid_ng/12 | H55: =H21*trail_liquid_ng/12 | I55: =I21*trail_liquid_ng/12 | J55: =J21*trail_liquid_ng/12 | K55: =K21*trail_liquid_ng/12 | ... BK55: =BK21*trail_liquid_ng/12
A56: FD distribution fee | B56: ₹ | C56: 0 | D56: =D20*fd_fee_ng/12 | E56: =E20*fd_fee_ng/12 | F56: =F20*fd_fee_ng/12 | G56: =G20*fd_fee_ng/12 | H56: =H20*fd_fee_ng/12 | I56: =I20*fd_fee_ng/12 | J56: =J20*fd_fee_ng/12 | K56: =K20*fd_fee_ng/12 | ... BK56: =BK20*fd_fee_ng/12
A57: Margin on digital gold bought (lever) | B57: ₹ | C57: 0 | D57: =D9*gold_on_ng*gold_share_ng*gold_margin_ng | E57: =E9*gold_on_ng*gold_share_ng*gold_margin_ng | F57: =F9*gold_on_ng*gold_share_ng*gold_margin_ng | G57: =G9*gold_on_ng*gold_share_ng*gold_margin_ng | H57: =H9*gold_on_ng*gold_share_ng*gold_margin_ng | I57: =I9*gold_on_ng*gold_share_ng*gold_margin_ng | J57: =J9*gold_on_ng*gold_share_ng*gold_margin_ng | K57: =K9*gold_on_ng*gold_share_ng*gold_margin_ng | ... BK57: =BK9*gold_on_ng*gold_share_ng*gold_margin_ng
A58: Loans: sourcing fee, or net interest if own NBFC | B58: ₹ | C58: 0 | D58: =IF(nbfc_on_ng=1,D36*(nbfc_int_r_ng*(1-ladder_dpd90_ng)+nbfc_proc_fee_ng-nbfc_cof_r_ng),D34*secured_fee_ng+D35*(lsp_fee_ng+dlg_on_ng*dlg_fee_uplift_ng)) | E58: =IF(nbfc_on_ng=1,E36*(nbfc_int_r_ng*(1-ladder_dpd90_ng)+nbfc_proc_fee_ng-nbfc_cof_r_ng),E34*secured_fee_ng+E35*(lsp_fee_ng+dlg_on_ng*dlg_fee_uplift_ng)) | F58: =IF(nbfc_on_ng=1,F36*(nbfc_int_r_ng*(1-ladder_dpd90_ng)+nbfc_proc_fee_ng-nbfc_cof_r_ng),F34*secured_fee_ng+F35*(lsp_fee_ng+dlg_on_ng*dlg_fee_uplift_ng)) | G58: =IF(nbfc_on_ng=1,G36*(nbfc_int_r_ng*(1-ladder_dpd90_ng)+nbfc_proc_fee_ng-nbfc_cof_r_ng),G34*secured_fee_ng+G35*(lsp_fee_ng+dlg_on_ng*dlg_fee_uplift_ng)) | H58: =IF(nbfc_on_ng=1,H36*(nbfc_int_r_ng*(1-ladder_dpd90_ng)+nbfc_proc_fee_ng-nbfc_cof_r_ng),H34*secured_fee_ng+H35*(lsp_fee_ng+dlg_on_ng*dlg_fee_uplift_ng)) | I58: =IF(nbfc_on_ng=1,I36*(nbfc_int_r_ng*(1-ladder_dpd90_ng)+nbfc_proc_fee_ng-nbfc_cof_r_ng),I34*secured_fee_ng+I35*(lsp_fee_ng+dlg_on_ng*dlg_fee_uplift_ng)) | J58: =IF(nbfc_on_ng=1,J36*(nbfc_int_r_ng*(1-ladder_dpd90_ng)+nbfc_proc_fee_ng-nbfc_cof_r_ng),J34*secured_fee_ng+J35*(lsp_fee_ng+dlg_on_ng*dlg_fee_uplift_ng)) | K58: =IF(nbfc_on_ng=1,K36*(nbfc_int_r_ng*(1-ladder_dpd90_ng)+nbfc_proc_fee_ng-nbfc_cof_r_ng),K34*secured_fee_ng+K35*(lsp_fee_ng+dlg_on_ng*dlg_fee_uplift_ng)) | ... BK58: =IF(nbfc_on_ng=1,BK36*(nbfc_int_r_ng*(1-ladder_dpd90_ng)+nbfc_proc_fee_ng-nbfc_cof_r_ng),BK34*secured_fee_ng+BK35*(lsp_fee_ng+dlg_on_ng*dlg_fee_uplift_ng))
A59: Card fees and interchange share | B59: ₹ | C59: 0 | D59: =D42*card_fee_ng+D43*card_spend_ng*card_ic_share_ng+D45*unsec_fee_ng | E59: =E42*card_fee_ng+E43*card_spend_ng*card_ic_share_ng+E45*unsec_fee_ng | F59: =F42*card_fee_ng+F43*card_spend_ng*card_ic_share_ng+F45*unsec_fee_ng | G59: =G42*card_fee_ng+G43*card_spend_ng*card_ic_share_ng+G45*unsec_fee_ng | H59: =H42*card_fee_ng+H43*card_spend_ng*card_ic_share_ng+H45*unsec_fee_ng | I59: =I42*card_fee_ng+I43*card_spend_ng*card_ic_share_ng+I45*unsec_fee_ng | J59: =J42*card_fee_ng+J43*card_spend_ng*card_ic_share_ng+J45*unsec_fee_ng | K59: =K42*card_fee_ng+K43*card_spend_ng*card_ic_share_ng+K45*unsec_fee_ng | ... BK59: =BK42*card_fee_ng+BK43*card_spend_ng*card_ic_share_ng+BK45*unsec_fee_ng
A60: SIP trail commission | B60: ₹ | C60: 0 | D60: =D49*trail_equity_ng/12 | E60: =E49*trail_equity_ng/12 | F60: =F49*trail_equity_ng/12 | G60: =G49*trail_equity_ng/12 | H60: =H49*trail_equity_ng/12 | I60: =I49*trail_equity_ng/12 | J60: =J49*trail_equity_ng/12 | K60: =K49*trail_equity_ng/12 | ... BK60: =BK49*trail_equity_ng/12
A61: First-time investor incentive | B61: ₹ | C61: 0 | D61: =D48*first_time_share_ng*mf_incentive_ng | E61: =E48*first_time_share_ng*mf_incentive_ng | F61: =F48*first_time_share_ng*mf_incentive_ng | G61: =G48*first_time_share_ng*mf_incentive_ng | H61: =H48*first_time_share_ng*mf_incentive_ng | I61: =I48*first_time_share_ng*mf_incentive_ng | J61: =J48*first_time_share_ng*mf_incentive_ng | K61: =K48*first_time_share_ng*mf_incentive_ng | ... BK61: =BK48*first_time_share_ng*mf_incentive_ng
A62: Insurance commission | B62: ₹ | C62: 0 | D62: =(D52*ins_comm_first_ng+D53*ins_comm_renew_ng)*ins_premium_ng | E62: =(E52*ins_comm_first_ng+E53*ins_comm_renew_ng)*ins_premium_ng | F62: =(F52*ins_comm_first_ng+F53*ins_comm_renew_ng)*ins_premium_ng | G62: =(G52*ins_comm_first_ng+G53*ins_comm_renew_ng)*ins_premium_ng | H62: =(H52*ins_comm_first_ng+H53*ins_comm_renew_ng)*ins_premium_ng | I62: =(I52*ins_comm_first_ng+I53*ins_comm_renew_ng)*ins_premium_ng | J62: =(J52*ins_comm_first_ng+J53*ins_comm_renew_ng)*ins_premium_ng | K62: =(K52*ins_comm_first_ng+K53*ins_comm_renew_ng)*ins_premium_ng | ... BK62: =(BK52*ins_comm_first_ng+BK53*ins_comm_renew_ng)*ins_premium_ng
A63: Total revenue | B63: ₹ | C63: 0 | D63: =D55+D56+D57+D58+D59+D60+D61+D62 | E63: =E55+E56+E57+E58+E59+E60+E61+E62 | F63: =F55+F56+F57+F58+F59+F60+F61+F62 | G63: =G55+G56+G57+G58+G59+G60+G61+G62 | H63: =H55+H56+H57+H58+H59+H60+H61+H62 | I63: =I55+I56+I57+I58+I59+I60+I61+I62 | J63: =J55+J56+J57+J58+J59+J60+J61+J62 | K63: =K55+K56+K57+K58+K59+K60+K61+K62 | ... BK63: =BK55+BK56+BK57+BK58+BK59+BK60+BK61+BK62
A64: Variable cost
A65: Loans: our cost (+ losses we bear under a guarantee or own NBFC) | B65: ₹ | C65: 0 | D65: =IF(nbfc_on_ng=1,D35*loan_lost_ng+D31*(loan_ops_cost_ng+service_cost_ng),D31*loan_ops_cost_ng+dlg_on_ng*(MIN(loan_lost_ng,dlg_cap_ng)*D35+(D26+D27+D29)*service_cost_ng)) | E65: =IF(nbfc_on_ng=1,E35*loan_lost_ng+E31*(loan_ops_cost_ng+service_cost_ng),E31*loan_ops_cost_ng+dlg_on_ng*(MIN(loan_lost_ng,dlg_cap_ng)*E35+(E26+E27+E29)*service_cost_ng)) | F65: =IF(nbfc_on_ng=1,F35*loan_lost_ng+F31*(loan_ops_cost_ng+service_cost_ng),F31*loan_ops_cost_ng+dlg_on_ng*(MIN(loan_lost_ng,dlg_cap_ng)*F35+(F26+F27+F29)*service_cost_ng)) | G65: =IF(nbfc_on_ng=1,G35*loan_lost_ng+G31*(loan_ops_cost_ng+service_cost_ng),G31*loan_ops_cost_ng+dlg_on_ng*(MIN(loan_lost_ng,dlg_cap_ng)*G35+(G26+G27+G29)*service_cost_ng)) | H65: =IF(nbfc_on_ng=1,H35*loan_lost_ng+H31*(loan_ops_cost_ng+service_cost_ng),H31*loan_ops_cost_ng+dlg_on_ng*(MIN(loan_lost_ng,dlg_cap_ng)*H35+(H26+H27+H29)*service_cost_ng)) | I65: =IF(nbfc_on_ng=1,I35*loan_lost_ng+I31*(loan_ops_cost_ng+service_cost_ng),I31*loan_ops_cost_ng+dlg_on_ng*(MIN(loan_lost_ng,dlg_cap_ng)*I35+(I26+I27+I29)*service_cost_ng)) | J65: =IF(nbfc_on_ng=1,J35*loan_lost_ng+J31*(loan_ops_cost_ng+service_cost_ng),J31*loan_ops_cost_ng+dlg_on_ng*(MIN(loan_lost_ng,dlg_cap_ng)*J35+(J26+J27+J29)*service_cost_ng)) | K65: =IF(nbfc_on_ng=1,K35*loan_lost_ng+K31*(loan_ops_cost_ng+service_cost_ng),K31*loan_ops_cost_ng+dlg_on_ng*(MIN(loan_lost_ng,dlg_cap_ng)*K35+(K26+K27+K29)*service_cost_ng)) | ... BK65: =IF(nbfc_on_ng=1,BK35*loan_lost_ng+BK31*(loan_ops_cost_ng+service_cost_ng),BK31*loan_ops_cost_ng+dlg_on_ng*(MIN(loan_lost_ng,dlg_cap_ng)*BK35+(BK26+BK27+BK29)*service_cost_ng))
A66: Cards: our cost | B66: ₹ | C66: 0 | D66: =(D42+D45)*card_ops_cost_ng | E66: =(E42+E45)*card_ops_cost_ng | F66: =(F42+F45)*card_ops_cost_ng | G66: =(G42+G45)*card_ops_cost_ng | H66: =(H42+H45)*card_ops_cost_ng | I66: =(I42+I45)*card_ops_cost_ng | J66: =(J42+J45)*card_ops_cost_ng | K66: =(K42+K45)*card_ops_cost_ng | ... BK66: =(BK42+BK45)*card_ops_cost_ng
A67: Insurance: our cost | B67: ₹ | C67: 0 | D67: =D52*ins_ops_cost_ng | E67: =E52*ins_ops_cost_ng | F67: =F52*ins_ops_cost_ng | G67: =G52*ins_ops_cost_ng | H67: =H52*ins_ops_cost_ng | I67: =I52*ins_ops_cost_ng | J67: =J52*ins_ops_cost_ng | K67: =K52*ins_ops_cost_ng | ... BK67: =BK52*ins_ops_cost_ng
A68: Debits, pre-debit notices and failed debits | B68: ₹ | C68: 0 | D68: =D7*(debits_success_ng*cost_debit_ng+debits_scheduled_ng*cost_notice_ng+MAX(0,debits_scheduled_ng-debits_success_ng)*cost_failed_ng) | E68: =E7*(debits_success_ng*cost_debit_ng+debits_scheduled_ng*cost_notice_ng+MAX(0,debits_scheduled_ng-debits_success_ng)*cost_failed_ng) | F68: =F7*(debits_success_ng*cost_debit_ng+debits_scheduled_ng*cost_notice_ng+MAX(0,debits_scheduled_ng-debits_success_ng)*cost_failed_ng) | G68: =G7*(debits_success_ng*cost_debit_ng+debits_scheduled_ng*cost_notice_ng+MAX(0,debits_scheduled_ng-debits_success_ng)*cost_failed_ng) | H68: =H7*(debits_success_ng*cost_debit_ng+debits_scheduled_ng*cost_notice_ng+MAX(0,debits_scheduled_ng-debits_success_ng)*cost_failed_ng) | I68: =I7*(debits_success_ng*cost_debit_ng+debits_scheduled_ng*cost_notice_ng+MAX(0,debits_scheduled_ng-debits_success_ng)*cost_failed_ng) | J68: =J7*(debits_success_ng*cost_debit_ng+debits_scheduled_ng*cost_notice_ng+MAX(0,debits_scheduled_ng-debits_success_ng)*cost_failed_ng) | K68: =K7*(debits_success_ng*cost_debit_ng+debits_scheduled_ng*cost_notice_ng+MAX(0,debits_scheduled_ng-debits_success_ng)*cost_failed_ng) | ... BK68: =BK7*(debits_success_ng*cost_debit_ng+debits_scheduled_ng*cost_notice_ng+MAX(0,debits_scheduled_ng-debits_success_ng)*cost_failed_ng)
A69: Support, tech and streak rewards | B69: ₹ | C69: 0 | D69: =D7*(cost_support_ng+cost_tech_ng+cost_rewards_ng) | E69: =E7*(cost_support_ng+cost_tech_ng+cost_rewards_ng) | F69: =F7*(cost_support_ng+cost_tech_ng+cost_rewards_ng) | G69: =G7*(cost_support_ng+cost_tech_ng+cost_rewards_ng) | H69: =H7*(cost_support_ng+cost_tech_ng+cost_rewards_ng) | I69: =I7*(cost_support_ng+cost_tech_ng+cost_rewards_ng) | J69: =J7*(cost_support_ng+cost_tech_ng+cost_rewards_ng) | K69: =K7*(cost_support_ng+cost_tech_ng+cost_rewards_ng) | ... BK69: =BK7*(cost_support_ng+cost_tech_ng+cost_rewards_ng)
A70: Fraud | B70: ₹ | C70: 0 | D70: =D9*cost_fraud_ng | E70: =E9*cost_fraud_ng | F70: =F9*cost_fraud_ng | G70: =G9*cost_fraud_ng | H70: =H9*cost_fraud_ng | I70: =I9*cost_fraud_ng | J70: =J9*cost_fraud_ng | K70: =K9*cost_fraud_ng | ... BK70: =BK9*cost_fraud_ng
A71: Total variable cost | B71: ₹ | C71: 0 | D71: =D65+D66+D67+D68+D69+D70 | E71: =E65+E66+E67+E68+E69+E70 | F71: =F65+F66+F67+F68+F69+F70 | G71: =G65+G66+G67+G68+G69+G70 | H71: =H65+H66+H67+H68+H69+H70 | I71: =I65+I66+I67+I68+I69+I70 | J71: =J65+J66+J67+J68+J69+J70 | K71: =K65+K66+K67+K68+K69+K70 | ... BK71: =BK65+BK66+BK67+BK68+BK69+BK70
A72: Contribution
A73: Contribution margin (revenue − variable cost) | B73: ₹ | C73: 0 | D73: =D63-D71 | E73: =E63-E71 | F73: =F63-F71 | G73: =G63-G71 | H73: =H63-H71 | I73: =I63-I71 | J73: =J63-J71 | K73: =K63-K71 | ... BK73: =BK63-BK71
A74: …per activated saver | B74: ₹ | C74: 0 | D74: =D73/seg_n_ng | E74: =E73/seg_n_ng | F74: =F73/seg_n_ng | G74: =G73/seg_n_ng | H74: =H73/seg_n_ng | I74: =I73/seg_n_ng | J74: =J73/seg_n_ng | K74: =K73/seg_n_ng | ... BK74: =BK73/seg_n_ng
A75: Cumulative contribution per activated saver | B75: ₹ | C75: 0 | D75: =C75+D74 | E75: =D75+E74 | F75: =E75+F74 | G75: =F75+G74 | H75: =G75+H74 | I75: =H75+I74 | J75: =I75+J74 | K75: =J75+K74 | ... BK75: =BJ75+BK74
A76: Discounted contribution per activated saver | B76: ₹ | C76: 0 | D76: =D74/(1+disc_rate_ng)^(D$4/12) | E76: =E74/(1+disc_rate_ng)^(E$4/12) | F76: =F74/(1+disc_rate_ng)^(F$4/12) | G76: =G74/(1+disc_rate_ng)^(G$4/12) | H76: =H74/(1+disc_rate_ng)^(H$4/12) | I76: =I74/(1+disc_rate_ng)^(I$4/12) | J76: =J74/(1+disc_rate_ng)^(J$4/12) | K76: =K74/(1+disc_rate_ng)^(K$4/12) | ... BK76: =BK74/(1+disc_rate_ng)^(BK$4/12)
A77: Payback flag (month if cumulative ≥ CAC, else 999) | B77: month | D77: =IF(D75>=cac_ng,D$4,999) | E77: =IF(E75>=cac_ng,E$4,999) | F77: =IF(F75>=cac_ng,F$4,999) | G77: =IF(G75>=cac_ng,G$4,999) | H77: =IF(H75>=cac_ng,H$4,999) | I77: =IF(I75>=cac_ng,I$4,999) | J77: =IF(J75>=cac_ng,J$4,999) | K77: =IF(K75>=cac_ng,K$4,999) | ... BK77: =IF(BK75>=cac_ng,BK$4,999)

Sheet Cohort total
A1: Cohort total: gig + non-gig savers in one monthly cohort of `cohort_size` activated savers
A2: Adds the two segment sheets month by month. LTV, payback and the path use these rows.
A4: Month of cohort life | C4: 0 | D4: 1 | E4: 2 | F4: 3 | G4: 4 | H4: 5 | I4: 6 | J4: 7 | K4: 8 | L4: 9 | M4: 10 | N4: 11 | O4: 12 | P4: 13 | Q4: 14 | R4: 15 | S4: 16 | T4: 17 | U4: 18 | V4: 19 | W4: 20 | X4: 21 | Y4: 22 | Z4: 23 | AA4: 24 | AB4: 25 | AC4: 26 | AD4: 27 | AE4: 28 | AF4: 29 | AG4: 30 | AH4: 31 | AI4: 32 | AJ4: 33 | AK4: 34 | AL4: 35 | AM4: 36 | AN4: 37 | AO4: 38 | AP4: 39 | AQ4: 40 | AR4: 41 | AS4: 42 | AT4: 43 | AU4: 44 | AV4: 45 | AW4: 46 | AX4: 47 | AY4: 48 | AZ4: 49 | BA4: 50 | BB4: 51 | BC4: 52 | BD4: 53 | BE4: 54 | BF4: 55 | BG4: 56 | BH4: 57 | BI4: 58 | BJ4: 59 | BK4: 60
A5: Active savers (both segments) | C5: ='Cohort gig'!C7+'Cohort non-gig'!C7 | D5: ='Cohort gig'!D7+'Cohort non-gig'!D7 | E5: ='Cohort gig'!E7+'Cohort non-gig'!E7 | F5: ='Cohort gig'!F7+'Cohort non-gig'!F7 | G5: ='Cohort gig'!G7+'Cohort non-gig'!G7 | H5: ='Cohort gig'!H7+'Cohort non-gig'!H7 | I5: ='Cohort gig'!I7+'Cohort non-gig'!I7 | J5: ='Cohort gig'!J7+'Cohort non-gig'!J7 | ... BK5: ='Cohort gig'!BK7+'Cohort non-gig'!BK7
A6: Total revenue | C6: ='Cohort gig'!C63+'Cohort non-gig'!C63 | D6: ='Cohort gig'!D63+'Cohort non-gig'!D63 | E6: ='Cohort gig'!E63+'Cohort non-gig'!E63 | F6: ='Cohort gig'!F63+'Cohort non-gig'!F63 | G6: ='Cohort gig'!G63+'Cohort non-gig'!G63 | H6: ='Cohort gig'!H63+'Cohort non-gig'!H63 | I6: ='Cohort gig'!I63+'Cohort non-gig'!I63 | J6: ='Cohort gig'!J63+'Cohort non-gig'!J63 | ... BK6: ='Cohort gig'!BK63+'Cohort non-gig'!BK63
A7: Total variable cost | C7: ='Cohort gig'!C71+'Cohort non-gig'!C71 | D7: ='Cohort gig'!D71+'Cohort non-gig'!D71 | E7: ='Cohort gig'!E71+'Cohort non-gig'!E71 | F7: ='Cohort gig'!F71+'Cohort non-gig'!F71 | G7: ='Cohort gig'!G71+'Cohort non-gig'!G71 | H7: ='Cohort gig'!H71+'Cohort non-gig'!H71 | I7: ='Cohort gig'!I71+'Cohort non-gig'!I71 | J7: ='Cohort gig'!J71+'Cohort non-gig'!J71 | ... BK7: ='Cohort gig'!BK71+'Cohort non-gig'!BK71
A8: Contribution margin | C8: ='Cohort gig'!C73+'Cohort non-gig'!C73 | D8: ='Cohort gig'!D73+'Cohort non-gig'!D73 | E8: ='Cohort gig'!E73+'Cohort non-gig'!E73 | F8: ='Cohort gig'!F73+'Cohort non-gig'!F73 | G8: ='Cohort gig'!G73+'Cohort non-gig'!G73 | H8: ='Cohort gig'!H73+'Cohort non-gig'!H73 | I8: ='Cohort gig'!I73+'Cohort non-gig'!I73 | J8: ='Cohort gig'!J73+'Cohort non-gig'!J73 | ... BK8: ='Cohort gig'!BK73+'Cohort non-gig'!BK73
A9: Capital locked | C9: ='Cohort gig'!C39+'Cohort non-gig'!C39 | D9: ='Cohort gig'!D39+'Cohort non-gig'!D39 | E9: ='Cohort gig'!E39+'Cohort non-gig'!E39 | F9: ='Cohort gig'!F39+'Cohort non-gig'!F39 | G9: ='Cohort gig'!G39+'Cohort non-gig'!G39 | H9: ='Cohort gig'!H39+'Cohort non-gig'!H39 | I9: ='Cohort gig'!I39+'Cohort non-gig'!I39 | J9: ='Cohort gig'!J39+'Cohort non-gig'!J39 | ... BK9: ='Cohort gig'!BK39+'Cohort non-gig'!BK39
A10: …per activated saver | C10: 0 | D10: =D8/cohort_size | E10: =E8/cohort_size | F10: =F8/cohort_size | G10: =G8/cohort_size | H10: =H8/cohort_size | I10: =I8/cohort_size | J10: =J8/cohort_size | K10: =K8/cohort_size | ... BK10: =BK8/cohort_size
A11: Cumulative contribution per activated saver | C11: 0 | D11: =C11+D10 | E11: =D11+E10 | F11: =E11+F10 | G11: =F11+G10 | H11: =G11+H10 | I11: =H11+I10 | J11: =I11+J10 | K11: =J11+K10 | ... BK11: =BJ11+BK10
A12: Discounted contribution per activated saver | C12: 0 | D12: =D10/(1+disc_rate)^(D$4/12) | E12: =E10/(1+disc_rate)^(E$4/12) | F12: =F10/(1+disc_rate)^(F$4/12) | G12: =G10/(1+disc_rate)^(G$4/12) | H12: =H10/(1+disc_rate)^(H$4/12) | I12: =I10/(1+disc_rate)^(I$4/12) | J12: =J10/(1+disc_rate)^(J$4/12) | K12: =K10/(1+disc_rate)^(K$4/12) | ... BK12: =BK10/(1+disc_rate)^(BK$4/12)
A13: Payback flag (month if cumulative ≥ blended CAC, else 999) | D13: =IF(D11>=cac_blended,D$4,999) | E13: =IF(E11>=cac_blended,E$4,999) | F13: =IF(F11>=cac_blended,F$4,999) | G13: =IF(G11>=cac_blended,G$4,999) | H13: =IF(H11>=cac_blended,H$4,999) | I13: =IF(I11>=cac_blended,I$4,999) | J13: =IF(J11>=cac_blended,J$4,999) | K13: =IF(K11>=cac_blended,K$4,999) | ... BK13: =IF(BK11>=cac_blended,BK$4,999)

Sheet Revenue lines
A1: Revenue lines: each line's mechanics, by cohort year (cohort of activated savers, gross revenue to us)
A3: Revenue per cohort (₹)
A4: Line | B4: How it is calculated | C4: Key input (LIVE) | D4: Cohort year 1 | E4: Cohort year 2 | F4: Cohort year 3 | G4: Cohort year 4 | H4: Cohort year 5
A5: Savings: liquid fund | B5: Trail commission on the liquid-fund balance (regular plan). Balance × trail ÷ 12. | C5: =trail_liquid | D5: =SUM('Cohort gig'!D55:O55)+SUM('Cohort non-gig'!D55:O55) | E5: =SUM('Cohort gig'!P55:AA55)+SUM('Cohort non-gig'!P55:AA55) | F5: =SUM('Cohort gig'!AB55:AM55)+SUM('Cohort non-gig'!AB55:AM55) | G5: =SUM('Cohort gig'!AN55:AY55)+SUM('Cohort non-gig'!AN55:AY55) | H5: =SUM('Cohort gig'!AZ55:BK55)+SUM('Cohort non-gig'!AZ55:BK55)
A6: Savings: FDs | B6: Distribution fee from partner banks on FDs booked through us, taken as a yearly % of the FD balance. | C6: =fd_fee | D6: =SUM('Cohort gig'!D56:O56)+SUM('Cohort non-gig'!D56:O56) | E6: =SUM('Cohort gig'!P56:AA56)+SUM('Cohort non-gig'!P56:AA56) | F6: =SUM('Cohort gig'!AB56:AM56)+SUM('Cohort non-gig'!AB56:AM56) | G6: =SUM('Cohort gig'!AN56:AY56)+SUM('Cohort non-gig'!AN56:AY56) | H6: =SUM('Cohort gig'!AZ56:BK56)+SUM('Cohort non-gig'!AZ56:BK56)
A7: Savings: gold | B7: Lever: margin on the share of each rupee saved that goes into digital gold. | C7: =gold_margin | D7: =SUM('Cohort gig'!D57:O57)+SUM('Cohort non-gig'!D57:O57) | E7: =SUM('Cohort gig'!P57:AA57)+SUM('Cohort non-gig'!P57:AA57) | F7: =SUM('Cohort gig'!AB57:AM57)+SUM('Cohort non-gig'!AB57:AM57) | G7: =SUM('Cohort gig'!AN57:AY57)+SUM('Cohort non-gig'!AN57:AY57) | H7: =SUM('Cohort gig'!AZ57:BK57)+SUM('Cohort non-gig'!AZ57:BK57)
A8: Loans (partner) | B8: Sourcing fee as a % of money the partner lends; we hold no loan book. With a guarantee (dlg_on) the fee rises and we bear losses up to the 5% cap. With our own NBFC (nbfc_on) this line is net interest + processing fee − our borrowing cost. | C8: =lsp_fee | D8: =SUM('Cohort gig'!D58:O58)+SUM('Cohort non-gig'!D58:O58) | E8: =SUM('Cohort gig'!P58:AA58)+SUM('Cohort non-gig'!P58:AA58) | F8: =SUM('Cohort gig'!AB58:AM58)+SUM('Cohort non-gig'!AB58:AM58) | G8: =SUM('Cohort gig'!AN58:AY58)+SUM('Cohort non-gig'!AN58:AY58) | H8: =SUM('Cohort gig'!AZ58:BK58)+SUM('Cohort non-gig'!AZ58:BK58)
A9: Cards | B9: Fee per FD-secured card issued, plus a share of card spend; later a fee per unsecured card. | C9: =card_fee | D9: =SUM('Cohort gig'!D59:O59)+SUM('Cohort non-gig'!D59:O59) | E9: =SUM('Cohort gig'!P59:AA59)+SUM('Cohort non-gig'!P59:AA59) | F9: =SUM('Cohort gig'!AB59:AM59)+SUM('Cohort non-gig'!AB59:AM59) | G9: =SUM('Cohort gig'!AN59:AY59)+SUM('Cohort non-gig'!AN59:AY59) | H9: =SUM('Cohort gig'!AZ59:BK59)+SUM('Cohort non-gig'!AZ59:BK59)
A10: SIPs | B10: Trail on equity SIP balances, plus any one-time incentive for first-time investors. | C10: =trail_equity | D10: =SUM('Cohort gig'!D60:O60)+SUM('Cohort non-gig'!D60:O60)+SUM('Cohort gig'!D61:O61)+SUM('Cohort non-gig'!D61:O61) | E10: =SUM('Cohort gig'!P60:AA60)+SUM('Cohort non-gig'!P60:AA60)+SUM('Cohort gig'!P61:AA61)+SUM('Cohort non-gig'!P61:AA61) | F10: =SUM('Cohort gig'!AB60:AM60)+SUM('Cohort non-gig'!AB60:AM60)+SUM('Cohort gig'!AB61:AM61)+SUM('Cohort non-gig'!AB61:AM61) | G10: =SUM('Cohort gig'!AN60:AY60)+SUM('Cohort non-gig'!AN60:AY60)+SUM('Cohort gig'!AN61:AY61)+SUM('Cohort non-gig'!AN61:AY61) | H10: =SUM('Cohort gig'!AZ60:BK60)+SUM('Cohort non-gig'!AZ60:BK60)+SUM('Cohort gig'!AZ61:BK61)+SUM('Cohort non-gig'!AZ61:BK61)
A11: Insurance | B11: Commission on first-year and renewal premiums at the capped rates. | C11: =ins_comm_first | D11: =SUM('Cohort gig'!D62:O62)+SUM('Cohort non-gig'!D62:O62) | E11: =SUM('Cohort gig'!P62:AA62)+SUM('Cohort non-gig'!P62:AA62) | F11: =SUM('Cohort gig'!AB62:AM62)+SUM('Cohort non-gig'!AB62:AM62) | G11: =SUM('Cohort gig'!AN62:AY62)+SUM('Cohort non-gig'!AN62:AY62) | H11: =SUM('Cohort gig'!AZ62:BK62)+SUM('Cohort non-gig'!AZ62:BK62)
A12: Total | D12: =SUM(D5:D11) | E12: =SUM(E5:E11) | F12: =SUM(F5:F11) | G12: =SUM(G5:G11) | H12: =SUM(H5:H11)
A14: Revenue per ACTIVE saver per year (₹) = cohort revenue ÷ average active savers that year
A15: Line | D15: Cohort year 1 | E15: Cohort year 2 | F15: Cohort year 3 | G15: Cohort year 4 | H15: Cohort year 5
A16: Average active savers in the year | D16: =(SUM('Cohort gig'!D7:O7)+SUM('Cohort non-gig'!D7:O7))/12 | E16: =(SUM('Cohort gig'!P7:AA7)+SUM('Cohort non-gig'!P7:AA7))/12 | F16: =(SUM('Cohort gig'!AB7:AM7)+SUM('Cohort non-gig'!AB7:AM7))/12 | G16: =(SUM('Cohort gig'!AN7:AY7)+SUM('Cohort non-gig'!AN7:AY7))/12 | H16: =(SUM('Cohort gig'!AZ7:BK7)+SUM('Cohort non-gig'!AZ7:BK7))/12
A17: Savings: liquid fund | D17: =D5/D$16 | E17: =E5/E$16 | F17: =F5/F$16 | G17: =G5/G$16 | H17: =H5/H$16
A18: Savings: FDs | D18: =D6/D$16 | E18: =E6/E$16 | F18: =F6/F$16 | G18: =G6/G$16 | H18: =H6/H$16
A19: Savings: gold | D19: =D7/D$16 | E19: =E7/E$16 | F19: =F7/F$16 | G19: =G7/G$16 | H19: =H7/H$16
A20: Loans (partner) | D20: =D8/D$16 | E20: =E8/E$16 | F20: =F8/F$16 | G20: =G8/G$16 | H20: =H8/H$16
A21: Cards | D21: =D9/D$16 | E21: =E9/E$16 | F21: =F9/F$16 | G21: =G9/G$16 | H21: =H9/H$16
A22: SIPs | D22: =D10/D$16 | E22: =E10/E$16 | F22: =F10/F$16 | G22: =G10/G$16 | H22: =H10/H$16
A23: Insurance | D23: =D11/D$16 | E23: =E11/E$16 | F23: =F11/F$16 | G23: =G11/G$16 | H23: =H11/H$16
A24: Total | D24: =SUM(D17:D23) | E24: =SUM(E17:E23) | F24: =SUM(F17:F23) | G24: =SUM(G17:G23) | H24: =SUM(H17:H23)

Sheet Cost to serve
A1: Cost to serve: variable cost by line and cohort year (cohort of activated savers)
A3: Variable cost per cohort (₹)
A4: Line | B4: How it is calculated | C4: Key input (LIVE) | D4: Cohort year 1 | E4: Cohort year 2 | F4: Cohort year 3 | G4: Cohort year 4 | H4: Cohort year 5
A5: Debits, notices, failed debits | B5: Per successful debit + per pre-debit notice (every scheduled debit) + per failed debit. | D5: =SUM('Cohort gig'!D68:O68)+SUM('Cohort non-gig'!D68:O68) | E5: =SUM('Cohort gig'!P68:AA68)+SUM('Cohort non-gig'!P68:AA68) | F5: =SUM('Cohort gig'!AB68:AM68)+SUM('Cohort non-gig'!AB68:AM68) | G5: =SUM('Cohort gig'!AN68:AY68)+SUM('Cohort non-gig'!AN68:AY68) | H5: =SUM('Cohort gig'!AZ68:BK68)+SUM('Cohort non-gig'!AZ68:BK68)
A6: Support, tech, streak rewards | B6: Per active saver per month. | D6: =SUM('Cohort gig'!D69:O69)+SUM('Cohort non-gig'!D69:O69) | E6: =SUM('Cohort gig'!P69:AA69)+SUM('Cohort non-gig'!P69:AA69) | F6: =SUM('Cohort gig'!AB69:AM69)+SUM('Cohort non-gig'!AB69:AM69) | G6: =SUM('Cohort gig'!AN69:AY69)+SUM('Cohort non-gig'!AN69:AY69) | H6: =SUM('Cohort gig'!AZ69:BK69)+SUM('Cohort non-gig'!AZ69:BK69)
A7: Fraud | B7: Share of money saved. | D7: =SUM('Cohort gig'!D70:O70)+SUM('Cohort non-gig'!D70:O70) | E7: =SUM('Cohort gig'!P70:AA70)+SUM('Cohort non-gig'!P70:AA70) | F7: =SUM('Cohort gig'!AB70:AM70)+SUM('Cohort non-gig'!AB70:AM70) | G7: =SUM('Cohort gig'!AN70:AY70)+SUM('Cohort non-gig'!AN70:AY70) | H7: =SUM('Cohort gig'!AZ70:BK70)+SUM('Cohort non-gig'!AZ70:BK70)
A8: Loans: our cost | B8: Per loan, plus guarantee losses if we give one. | D8: =SUM('Cohort gig'!D65:O65)+SUM('Cohort non-gig'!D65:O65) | E8: =SUM('Cohort gig'!P65:AA65)+SUM('Cohort non-gig'!P65:AA65) | F8: =SUM('Cohort gig'!AB65:AM65)+SUM('Cohort non-gig'!AB65:AM65) | G8: =SUM('Cohort gig'!AN65:AY65)+SUM('Cohort non-gig'!AN65:AY65) | H8: =SUM('Cohort gig'!AZ65:BK65)+SUM('Cohort non-gig'!AZ65:BK65)
A9: Cards: our cost | B9: Per card issued. | D9: =SUM('Cohort gig'!D66:O66)+SUM('Cohort non-gig'!D66:O66) | E9: =SUM('Cohort gig'!P66:AA66)+SUM('Cohort non-gig'!P66:AA66) | F9: =SUM('Cohort gig'!AB66:AM66)+SUM('Cohort non-gig'!AB66:AM66) | G9: =SUM('Cohort gig'!AN66:AY66)+SUM('Cohort non-gig'!AN66:AY66) | H9: =SUM('Cohort gig'!AZ66:BK66)+SUM('Cohort non-gig'!AZ66:BK66)
A10: Insurance: our cost | B10: Per new policy. | D10: =SUM('Cohort gig'!D67:O67)+SUM('Cohort non-gig'!D67:O67) | E10: =SUM('Cohort gig'!P67:AA67)+SUM('Cohort non-gig'!P67:AA67) | F10: =SUM('Cohort gig'!AB67:AM67)+SUM('Cohort non-gig'!AB67:AM67) | G10: =SUM('Cohort gig'!AN67:AY67)+SUM('Cohort non-gig'!AN67:AY67) | H10: =SUM('Cohort gig'!AZ67:BK67)+SUM('Cohort non-gig'!AZ67:BK67)
A11: Total | D11: =SUM(D5:D10) | E11: =SUM(E5:E10) | F11: =SUM(F5:F10) | G11: =SUM(G5:G10) | H11: =SUM(H5:H10)
A13: Variable cost per ACTIVE saver per year (₹)
A14: Line | D14: Cohort year 1 | E14: Cohort year 2 | F14: Cohort year 3 | G14: Cohort year 4 | H14: Cohort year 5
A15: Average active savers in the year | D15: =(SUM('Cohort gig'!D7:O7)+SUM('Cohort non-gig'!D7:O7))/12 | E15: =(SUM('Cohort gig'!P7:AA7)+SUM('Cohort non-gig'!P7:AA7))/12 | F15: =(SUM('Cohort gig'!AB7:AM7)+SUM('Cohort non-gig'!AB7:AM7))/12 | G15: =(SUM('Cohort gig'!AN7:AY7)+SUM('Cohort non-gig'!AN7:AY7))/12 | H15: =(SUM('Cohort gig'!AZ7:BK7)+SUM('Cohort non-gig'!AZ7:BK7))/12
A16: Debits, notices, failed debits | D16: =D5/D$15 | E16: =E5/E$15 | F16: =F5/F$15 | G16: =G5/G$15 | H16: =H5/H$15
A17: Support, tech, streak rewards | D17: =D6/D$15 | E17: =E6/E$15 | F17: =F6/F$15 | G17: =G6/G$15 | H17: =H6/H$15
A18: Fraud | D18: =D7/D$15 | E18: =E7/E$15 | F18: =F7/F$15 | G18: =G7/G$15 | H18: =H7/H$15
A19: Loans: our cost | D19: =D8/D$15 | E19: =E8/E$15 | F19: =F8/F$15 | G19: =G8/G$15 | H19: =H8/H$15
A20: Cards: our cost | D20: =D9/D$15 | E20: =E9/E$15 | F20: =F9/F$15 | G20: =G9/G$15 | H20: =H9/H$15
A21: Insurance: our cost | D21: =D10/D$15 | E21: =E10/E$15 | F21: =F10/F$15 | G21: =G10/G$15 | H21: =H10/H$15
A22: Total | D22: =SUM(D16:D21) | E22: =SUM(E16:E21) | F22: =SUM(F16:F21) | G22: =SUM(G16:G21) | H22: =SUM(H16:H21)
A25: Cost to serve one active saver for one month (₹), before any cross-sell
A26: Successful debits | D26: =debits_success*cost_debit
A27: Pre-debit notices (one per scheduled debit) | D27: =debits_scheduled*cost_notice
A28: Failed debits | D28: =MAX(0,debits_scheduled-debits_success)*cost_failed
A29: Support | D29: =cost_support
A30: Tech and cloud | D30: =cost_tech
A31: Streak rewards | D31: =cost_rewards
A32: Total per active saver per month | D32: =SUM(D26:D31)
A33: …per year | D33: =D32*12

Sheet Outputs
A1: Outputs: the only numbers the deck quotes
A2: ="Scenario shown: "&CHOOSE(scenario,"Bear","Base","Bull")&" (switch at Inputs!C2). LTV is on contribution margin, discounted at "&TEXT(disc_rate,"0%")&" a year. CAC is fully loaded, per activated saver."
A4: Metric | B4: Savings-first | C4: Lending-first (Bueno-style) | H4: Population / definition
A5: CAC (₹) | B5: =cac_blended | C5: =lf_cac | H5: Savings: per activated saver. Lending: per disbursed borrower.
A6: CAC per good borrower (₹) | C6: =lf_cac_good | H6: Per applicant ÷ (approval × share who repay the first loan)
A7: CAC payback (months) | B7: =IF(MIN('Cohort total'!D13:BK13)=999,"not within 60 months",MIN('Cohort total'!D13:BK13)) | C7: =lf_payback | H7: Months until cumulative contribution (undiscounted) covers CAC
A8: LTV, 36 months (₹) | B8: =SUM('Cohort total'!D12:AM12) | C8: =lf_ltv36 | H8: Discounted contribution margin
A9: LTV, 60 months (₹) | B9: =SUM('Cohort total'!D12:BK12) | C9: =lf_ltv60 | H9: Discounted contribution margin
A10: LTV/CAC, 36 months | B10: =B8/B5 | C10: =lf_ltv36_cac
A11: LTV/CAC, 60 months | B11: =B9/B5 | C11: =lf_ltv60_cac
A12: Year-1 contribution per activated saver / per borrower (₹) | B12: =SUM('Cohort total'!D10:O10) | C12: =lf_y1_cm | H12: Undiscounted
A13: Capital locked per ₹1 of yearly revenue (₹) | B13: =IFERROR(SUM('Cohort total'!D9:O9)/12/SUM('Cohort total'!D6:O6),0) | C13: =lf_cap_per_rev | H13: Year 1, average capital locked ÷ revenue. Savings-first: guarantee deposit or NBFC equity (0 with neither lever). Lending-first: equity to hold the book in our own NBFC.
A16: Savings-first, per ACTIVE saver per year (₹), by cohort year: stacked by product
A17: Revenue line | B17: Year 1 | C17: Year 2 | D17: Year 3 | E17: Year 4 | F17: Year 5 | H17: Population
A18: Savings: liquid fund | B18: ='Revenue lines'!D17 | C18: ='Revenue lines'!E17 | D18: ='Revenue lines'!F17 | E18: ='Revenue lines'!G17 | F18: ='Revenue lines'!H17 | H18: per active saver, cohort year
A19: Savings: FDs | B19: ='Revenue lines'!D18 | C19: ='Revenue lines'!E18 | D19: ='Revenue lines'!F18 | E19: ='Revenue lines'!G18 | F19: ='Revenue lines'!H18 | H19: per active saver, cohort year
A20: Savings: gold | B20: ='Revenue lines'!D19 | C20: ='Revenue lines'!E19 | D20: ='Revenue lines'!F19 | E20: ='Revenue lines'!G19 | F20: ='Revenue lines'!H19 | H20: per active saver, cohort year
A21: Loans (partner) | B21: ='Revenue lines'!D20 | C21: ='Revenue lines'!E20 | D21: ='Revenue lines'!F20 | E21: ='Revenue lines'!G20 | F21: ='Revenue lines'!H20 | H21: per active saver, cohort year
A22: Cards | B22: ='Revenue lines'!D21 | C22: ='Revenue lines'!E21 | D22: ='Revenue lines'!F21 | E22: ='Revenue lines'!G21 | F22: ='Revenue lines'!H21 | H22: per active saver, cohort year
A23: SIPs | B23: ='Revenue lines'!D22 | C23: ='Revenue lines'!E22 | D23: ='Revenue lines'!F22 | E23: ='Revenue lines'!G22 | F23: ='Revenue lines'!H22 | H23: per active saver, cohort year
A24: Insurance | B24: ='Revenue lines'!D23 | C24: ='Revenue lines'!E23 | D24: ='Revenue lines'!F23 | E24: ='Revenue lines'!G23 | F24: ='Revenue lines'!H23 | H24: per active saver, cohort year
A25: Revenue per active saver | B25: ='Revenue lines'!D24 | C25: ='Revenue lines'!E24 | D25: ='Revenue lines'!F24 | E25: ='Revenue lines'!G24 | F25: ='Revenue lines'!H24
A26: Variable cost per active saver | B26: ='Cost to serve'!D22 | C26: ='Cost to serve'!E22 | D26: ='Cost to serve'!F22 | E26: ='Cost to serve'!G22 | F26: ='Cost to serve'!H22
A27: Contribution margin per active saver | B27: =B25-B26 | C27: =C25-C26 | D27: =D25-D26 | E27: =E25-E26 | F27: =F25-F26
A30: Savings-first, per ACTIVATED saver (the cohort's starting 1,000), by cohort year
A31: Metric | B31: Year 1 | C31: Year 2 | D31: Year 3 | E31: Year 4 | F31: Year 5
A32: Revenue per activated saver (₹) | B32: =SUM('Cohort total'!D6:O6)/cohort_size | C32: =SUM('Cohort total'!P6:AA6)/cohort_size | D32: =SUM('Cohort total'!AB6:AM6)/cohort_size | E32: =SUM('Cohort total'!AN6:AY6)/cohort_size | F32: =SUM('Cohort total'!AZ6:BK6)/cohort_size
A33: Contribution per activated saver (₹) | B33: =SUM('Cohort total'!D8:O8)/cohort_size | C33: =SUM('Cohort total'!P8:AA8)/cohort_size | D33: =SUM('Cohort total'!AB8:AM8)/cohort_size | E33: =SUM('Cohort total'!AN8:AY8)/cohort_size | F33: =SUM('Cohort total'!AZ8:BK8)/cohort_size
A34: Capital locked per activated saver, average in year (₹) | B34: =SUM('Cohort total'!D9:O9)/12/cohort_size | C34: =SUM('Cohort total'!P9:AA9)/12/cohort_size | D34: =SUM('Cohort total'!AB9:AM9)/12/cohort_size | E34: =SUM('Cohort total'!AN9:AY9)/12/cohort_size | F34: =SUM('Cohort total'!AZ9:BK9)/12/cohort_size
A35: Average active savers per activated saver | B35: =SUM('Cohort total'!D5:O5)/12/cohort_size | C35: =SUM('Cohort total'!P5:AA5)/12/cohort_size | D35: =SUM('Cohort total'!AB5:AM5)/12/cohort_size | E35: =SUM('Cohort total'!AN5:AY5)/12/cohort_size | F35: =SUM('Cohort total'!AZ5:BK5)/12/cohort_size
A38: By segment (per activated saver of that segment, base on the scenario switch)
A39: Metric | B39: Gig | C39: Non-gig
A40: CAC (₹) | B40: =cac_gig | C40: =cac_ng
A41: LTV, 60 months (₹) | B41: =SUM('Cohort gig'!D76:BK76) | C41: =SUM('Cohort non-gig'!D76:BK76)
A42: LTV/CAC, 60 months | B42: =B41/B40 | C42: =C41/C40
A43: CAC payback (months) | B43: =IF(MIN('Cohort gig'!D77:BK77)=999,"not within 60 months",MIN('Cohort gig'!D77:BK77)) | C43: =IF(MIN('Cohort non-gig'!D77:BK77)=999,"not within 60 months",MIN('Cohort non-gig'!D77:BK77))
A44: Revenue per active saver, year 2 (₹) | B44: =SUM('Cohort gig'!P63:AA63)/(SUM('Cohort gig'!P7:AA7)/12) | C44: =SUM('Cohort non-gig'!P63:AA63)/(SUM('Cohort non-gig'!P7:AA7)/12)
A45: Still saving at month 12 | B45: ='Cohort gig'!O6 | C45: ='Cohort non-gig'!O6
A47: Path to $100M (see that tab)
A48: First year revenue reaches $100M | B48: =path_year_100m
A49: Revenue in year 5 ($ million) | B49: =path_rev_usd_y5
A50: Revenue in year 10 ($ million) | B50: =path_rev_usd_y10
A51: Active savers in year 10 (million) | B51: =path_active_y10
A52: Capital needed to reach year 2 (₹ crore) | B52: =path_need_y2
A53: Capital needed to reach year 5 (₹ crore) | B53: =path_need_y5
A54: Peak capital needed over 10 years (₹ crore) | B54: =path_peak_capital
A57: Story deck: what an active saver costs us per year (₹), by line and cohort year
A58: Cost line | B58: Year 1 | C58: Year 2 | D58: Year 3 | E58: Year 4 | F58: Year 5 | H58: Population
A59: Debits, notices, failed debits | B59: ='Cost to serve'!D16 | C59: ='Cost to serve'!E16 | D59: ='Cost to serve'!F16 | E59: ='Cost to serve'!G16 | F59: ='Cost to serve'!H16 | H59: per active saver, cohort year
A60: Support, tech, streak rewards | B60: ='Cost to serve'!D17 | C60: ='Cost to serve'!E17 | D60: ='Cost to serve'!F17 | E60: ='Cost to serve'!G17 | F60: ='Cost to serve'!H17 | H60: per active saver, cohort year
A61: Fraud | B61: ='Cost to serve'!D18 | C61: ='Cost to serve'!E18 | D61: ='Cost to serve'!F18 | E61: ='Cost to serve'!G18 | F61: ='Cost to serve'!H18 | H61: per active saver, cohort year
A62: Loans: our cost | B62: ='Cost to serve'!D19 | C62: ='Cost to serve'!E19 | D62: ='Cost to serve'!F19 | E62: ='Cost to serve'!G19 | F62: ='Cost to serve'!H19 | H62: per active saver, cohort year
A63: Cards: our cost | B63: ='Cost to serve'!D20 | C63: ='Cost to serve'!E20 | D63: ='Cost to serve'!F20 | E63: ='Cost to serve'!G20 | F63: ='Cost to serve'!H20 | H63: per active saver, cohort year
A64: Insurance: our cost | B64: ='Cost to serve'!D21 | C64: ='Cost to serve'!E21 | D64: ='Cost to serve'!F21 | E64: ='Cost to serve'!G21 | F64: ='Cost to serve'!H21 | H64: per active saver, cohort year
A67: Story deck: how many savers ever borrow, and what each borrower costs to find
A68: Metric | B68: Value | H68: Population / definition
A69: Activated savers who took a first loan by month 12 | B69: =(SUM('Cohort gig'!D24:O24)+SUM('Cohort non-gig'!D24:O24))/cohort_size | H69: first loans ÷ activated savers (both halves)
A70: Activated savers who took a first loan by month 24 | B70: =(SUM('Cohort gig'!D24:AA24)+SUM('Cohort non-gig'!D24:AA24))/cohort_size | H70: first loans ÷ activated savers (both halves)
A71: Activated savers who took a first loan by month 60 | B71: =(SUM('Cohort gig'!D24:BK24)+SUM('Cohort non-gig'!D24:BK24))/cohort_size | H71: first loans ÷ activated savers (both halves)
A72: CAC per saver who ever borrows (₹) | B72: =cac_blended/B71 | H72: CAC per activated saver ÷ share who took a first loan within 60 months
A73: Activated savers who reached loan 3 (part secured) within 60 months | B73: =(SUM('Cohort gig'!D26:BK26)+SUM('Cohort non-gig'!D26:BK26))/cohort_size | H73: loans on that rung ÷ activated savers (both halves)
A74: Activated savers who reached loan 5 (first unsecured) within 60 months | B74: =(SUM('Cohort gig'!D28:BK28)+SUM('Cohort non-gig'!D28:BK28))/cohort_size | H74: loans on that rung ÷ activated savers (both halves)
A75: Secured loan size when loans start (₹, average active saver) | B75: =(INDEX('Cohort gig'!$D$33:$BK$33,1,loan_start)*INDEX('Cohort gig'!$D$7:$BK$7,1,loan_start)+INDEX('Cohort non-gig'!$D$33:$BK$33,1,loan_start)*INDEX('Cohort non-gig'!$D$7:$BK$7,1,loan_start))/(INDEX('Cohort gig'!$D$7:$BK$7,1,loan_start)+INDEX('Cohort non-gig'!$D$7:$BK$7,1,loan_start)) | H75: secured_ltv × fund + FD money per active saver, active-weighted across halves
A76: Secured loan size at month 12 (₹, average active saver) | B76: =(INDEX('Cohort gig'!$D$33:$BK$33,1,12)*INDEX('Cohort gig'!$D$7:$BK$7,1,12)+INDEX('Cohort non-gig'!$D$33:$BK$33,1,12)*INDEX('Cohort non-gig'!$D$7:$BK$7,1,12))/(INDEX('Cohort gig'!$D$7:$BK$7,1,12)+INDEX('Cohort non-gig'!$D$7:$BK$7,1,12)) | H76: secured_ltv × fund + FD money per active saver, active-weighted across halves
A77: Share of 60-month revenue from digital gold | B77: =(SUM('Cohort gig'!D57:BK57)+SUM('Cohort non-gig'!D57:BK57))/(SUM('Cohort gig'!D63:BK63)+SUM('Cohort non-gig'!D63:BK63)) | H77: cohort revenue over 60 months, undiscounted
A78: Share of 60-month revenue from loans | B78: =(SUM('Cohort gig'!D58:BK58)+SUM('Cohort non-gig'!D58:BK58))/(SUM('Cohort gig'!D63:BK63)+SUM('Cohort non-gig'!D63:BK63)) | H78: cohort revenue over 60 months, undiscounted
A79: Share of 60-month revenue from insurance | B79: =(SUM('Cohort gig'!D62:BK62)+SUM('Cohort non-gig'!D62:BK62))/(SUM('Cohort gig'!D63:BK63)+SUM('Cohort non-gig'!D63:BK63)) | H79: cohort revenue over 60 months, undiscounted

Sheet Lending-first
A1: Lending-first comparison: a Bueno-style cohort of 1,000 applicants, from founder data
A2: As Bueno ran it: a partner NBFC lent, we paid it a fixed yearly return and bore ALL default losses. RBI now caps a loan service provider's loss guarantee at 5% of the portfolio, so this exact structure would need our own NBFC today (see capital row).
A4: Per-loan economics (scenario from Inputs!C2)
A5: Borrowers (applicants × approval) | B5: =lf_applicants*lf_approval
A6: Interest and fees per loan, contract (₹) | B6: =PMT(lf_irr/12,lf_tenor,-lf_ticket)*lf_tenor-lf_ticket
A7: Paid to NBFC per loan (₹) | B7: =PMT(lf_cof/12,lf_tenor,-lf_ticket)*lf_tenor-lf_ticket
A8: Average balance as share of loan | B8: =((1+lf_irr/12)^lf_tenor-((1+lf_irr/12)^lf_tenor-1)/(lf_tenor*lf_irr/12))/((1+lf_irr/12)^lf_tenor-1)
A9: Fixed cost per loan: collection + ops + platform fee (₹) | B9: =lf_collection+lf_ops_cost+lf_platform_share*lf_platform_fee
A10: Contribution of a FIRST loan (₹) | B10: =lf_interest*(1-lf_dpd90_first)-lf_cof_loan-lf_dpd90_first*lf_ead*lf_lgd*lf_ticket*lf_risk_share-lf_fixed
A11: Contribution of a REPEAT loan (₹) | B11: =lf_interest*(1-lf_dpd90_repeat)-lf_cof_loan-lf_dpd90_repeat*lf_ead*lf_lgd*lf_ticket*lf_risk_share-lf_fixed
A12: CAC per applicant, fully loaded (₹) | B12: =lf_cost_per_applicant+lf_underwrite_cost
A13: CAC per disbursed borrower (₹) | B13: =lf_cac_app/lf_approval
A14: CAC per good borrower (₹) = CAC per applicant ÷ (approval × share who repay) | B14: =lf_cac_app/(lf_approval*(1-lf_dpd90_first))
A16: Monthly cohort (month 0 in column C)
A17: Month | C17: 0 | D17: 1 | E17: 2 | F17: 3 | G17: 4 | H17: 5 | I17: 6 | J17: 7 | K17: 8 | L17: 9 | M17: 10 | N17: 11 | O17: 12 | P17: 13 | Q17: 14 | R17: 15 | S17: 16 | T17: 17 | U17: 18 | V17: 19 | W17: 20 | X17: 21 | Y17: 22 | Z17: 23 | AA17: 24 | AB17: 25 | AC17: 26 | AD17: 27 | AE17: 28 | AF17: 29 | AG17: 30 | AH17: 31 | AI17: 32 | AJ17: 33 | AK17: 34 | AL17: 35 | AM17: 36 | AN17: 37 | AO17: 38 | AP17: 39 | AQ17: 40 | AR17: 41 | AS17: 42 | AT17: 43 | AU17: 44 | AV17: 45 | AW17: 46 | AX17: 47 | AY17: 48 | AZ17: 49 | BA17: 50 | BB17: 51 | BC17: 52 | BD17: 53 | BE17: 54 | BF17: 55 | BG17: 56 | BH17: 57 | BI17: 58 | BJ17: 59 | BK17: 60
A18: First loans | C18: 0 | D18: =IF(D$17=1,borrowers_lf,0) | E18: =IF(E$17=1,borrowers_lf,0) | F18: =IF(F$17=1,borrowers_lf,0) | G18: =IF(G$17=1,borrowers_lf,0) | H18: =IF(H$17=1,borrowers_lf,0) | I18: =IF(I$17=1,borrowers_lf,0) | J18: =IF(J$17=1,borrowers_lf,0) | K18: =IF(K$17=1,borrowers_lf,0) | ... BK18: =IF(BK$17=1,borrowers_lf,0)
A19: Repeat loans | C19: 0 | D19: =IF(D$17>lf_tenor,lf_repeat*((1-lf_dpd90_first)*INDEX($C$18:C$18,1,D$17-lf_tenor+1)+(1-lf_dpd90_repeat)*INDEX($C$19:C$19,1,D$17-lf_tenor+1)),0) | E19: =IF(E$17>lf_tenor,lf_repeat*((1-lf_dpd90_first)*INDEX($C$18:D$18,1,E$17-lf_tenor+1)+(1-lf_dpd90_repeat)*INDEX($C$19:D$19,1,E$17-lf_tenor+1)),0) | F19: =IF(F$17>lf_tenor,lf_repeat*((1-lf_dpd90_first)*INDEX($C$18:E$18,1,F$17-lf_tenor+1)+(1-lf_dpd90_repeat)*INDEX($C$19:E$19,1,F$17-lf_tenor+1)),0) | G19: =IF(G$17>lf_tenor,lf_repeat*((1-lf_dpd90_first)*INDEX($C$18:F$18,1,G$17-lf_tenor+1)+(1-lf_dpd90_repeat)*INDEX($C$19:F$19,1,G$17-lf_tenor+1)),0) | H19: =IF(H$17>lf_tenor,lf_repeat*((1-lf_dpd90_first)*INDEX($C$18:G$18,1,H$17-lf_tenor+1)+(1-lf_dpd90_repeat)*INDEX($C$19:G$19,1,H$17-lf_tenor+1)),0) | I19: =IF(I$17>lf_tenor,lf_repeat*((1-lf_dpd90_first)*INDEX($C$18:H$18,1,I$17-lf_tenor+1)+(1-lf_dpd90_repeat)*INDEX($C$19:H$19,1,I$17-lf_tenor+1)),0) | J19: =IF(J$17>lf_tenor,lf_repeat*((1-lf_dpd90_first)*INDEX($C$18:I$18,1,J$17-lf_tenor+1)+(1-lf_dpd90_repeat)*INDEX($C$19:I$19,1,J$17-lf_tenor+1)),0) | K19: =IF(K$17>lf_tenor,lf_repeat*((1-lf_dpd90_first)*INDEX($C$18:J$18,1,K$17-lf_tenor+1)+(1-lf_dpd90_repeat)*INDEX($C$19:J$19,1,K$17-lf_tenor+1)),0) | ... BK19: =IF(BK$17>lf_tenor,lf_repeat*((1-lf_dpd90_first)*INDEX($C$18:BJ$18,1,BK$17-lf_tenor+1)+(1-lf_dpd90_repeat)*INDEX($C$19:BJ$19,1,BK$17-lf_tenor+1)),0)
A20: Net revenue (interest and fees received − paid to NBFC) | C20: 0 | D20: =D18*(lf_interest*(1-lf_dpd90_first)-lf_cof_loan)+D19*(lf_interest*(1-lf_dpd90_repeat)-lf_cof_loan) | E20: =E18*(lf_interest*(1-lf_dpd90_first)-lf_cof_loan)+E19*(lf_interest*(1-lf_dpd90_repeat)-lf_cof_loan) | F20: =F18*(lf_interest*(1-lf_dpd90_first)-lf_cof_loan)+F19*(lf_interest*(1-lf_dpd90_repeat)-lf_cof_loan) | G20: =G18*(lf_interest*(1-lf_dpd90_first)-lf_cof_loan)+G19*(lf_interest*(1-lf_dpd90_repeat)-lf_cof_loan) | H20: =H18*(lf_interest*(1-lf_dpd90_first)-lf_cof_loan)+H19*(lf_interest*(1-lf_dpd90_repeat)-lf_cof_loan) | I20: =I18*(lf_interest*(1-lf_dpd90_first)-lf_cof_loan)+I19*(lf_interest*(1-lf_dpd90_repeat)-lf_cof_loan) | J20: =J18*(lf_interest*(1-lf_dpd90_first)-lf_cof_loan)+J19*(lf_interest*(1-lf_dpd90_repeat)-lf_cof_loan) | K20: =K18*(lf_interest*(1-lf_dpd90_first)-lf_cof_loan)+K19*(lf_interest*(1-lf_dpd90_repeat)-lf_cof_loan) | ... BK20: =BK18*(lf_interest*(1-lf_dpd90_first)-lf_cof_loan)+BK19*(lf_interest*(1-lf_dpd90_repeat)-lf_cof_loan)
A21: Default losses we bear | C21: 0 | D21: =(D18*lf_dpd90_first+D19*lf_dpd90_repeat)*lf_ead*lf_lgd*lf_ticket*lf_risk_share | E21: =(E18*lf_dpd90_first+E19*lf_dpd90_repeat)*lf_ead*lf_lgd*lf_ticket*lf_risk_share | F21: =(F18*lf_dpd90_first+F19*lf_dpd90_repeat)*lf_ead*lf_lgd*lf_ticket*lf_risk_share | G21: =(G18*lf_dpd90_first+G19*lf_dpd90_repeat)*lf_ead*lf_lgd*lf_ticket*lf_risk_share | H21: =(H18*lf_dpd90_first+H19*lf_dpd90_repeat)*lf_ead*lf_lgd*lf_ticket*lf_risk_share | I21: =(I18*lf_dpd90_first+I19*lf_dpd90_repeat)*lf_ead*lf_lgd*lf_ticket*lf_risk_share | J21: =(J18*lf_dpd90_first+J19*lf_dpd90_repeat)*lf_ead*lf_lgd*lf_ticket*lf_risk_share | K21: =(K18*lf_dpd90_first+K19*lf_dpd90_repeat)*lf_ead*lf_lgd*lf_ticket*lf_risk_share | ... BK21: =(BK18*lf_dpd90_first+BK19*lf_dpd90_repeat)*lf_ead*lf_lgd*lf_ticket*lf_risk_share
A22: Total cost (losses + collection + ops + platform fee) | C22: 0 | D22: =D21+(D18+D19)*lf_fixed | E22: =E21+(E18+E19)*lf_fixed | F22: =F21+(F18+F19)*lf_fixed | G22: =G21+(G18+G19)*lf_fixed | H22: =H21+(H18+H19)*lf_fixed | I22: =I21+(I18+I19)*lf_fixed | J22: =J21+(J18+J19)*lf_fixed | K22: =K21+(K18+K19)*lf_fixed | ... BK22: =BK21+(BK18+BK19)*lf_fixed
A23: Contribution margin | C23: 0 | D23: =D20-D22 | E23: =E20-E22 | F23: =F20-F22 | G23: =G20-G22 | H23: =H20-H22 | I23: =I20-I22 | J23: =J20-J22 | K23: =K20-K22 | ... BK23: =BK20-BK22
A24: Loan-months of balance started (for capital) | C24: 0 | D24: =(D18+D19)*lf_ticket*lf_avg_frac*lf_tenor | E24: =(E18+E19)*lf_ticket*lf_avg_frac*lf_tenor | F24: =(F18+F19)*lf_ticket*lf_avg_frac*lf_tenor | G24: =(G18+G19)*lf_ticket*lf_avg_frac*lf_tenor | H24: =(H18+H19)*lf_ticket*lf_avg_frac*lf_tenor | I24: =(I18+I19)*lf_ticket*lf_avg_frac*lf_tenor | J24: =(J18+J19)*lf_ticket*lf_avg_frac*lf_tenor | K24: =(K18+K19)*lf_ticket*lf_avg_frac*lf_tenor | ... BK24: =(BK18+BK19)*lf_ticket*lf_avg_frac*lf_tenor
A25: …per disbursed borrower | C25: 0 | D25: =D23/borrowers_lf | E25: =E23/borrowers_lf | F25: =F23/borrowers_lf | G25: =G23/borrowers_lf | H25: =H23/borrowers_lf | I25: =I23/borrowers_lf | J25: =J23/borrowers_lf | K25: =K23/borrowers_lf | ... BK25: =BK23/borrowers_lf
A26: Cumulative per disbursed borrower | C26: 0 | D26: =C26+D25 | E26: =D26+E25 | F26: =E26+F25 | G26: =F26+G25 | H26: =G26+H25 | I26: =H26+I25 | J26: =I26+J25 | K26: =J26+K25 | ... BK26: =BJ26+BK25
A27: Discounted per disbursed borrower | C27: 0 | D27: =D25/(1+disc_rate)^(D$17/12) | E27: =E25/(1+disc_rate)^(E$17/12) | F27: =F25/(1+disc_rate)^(F$17/12) | G27: =G25/(1+disc_rate)^(G$17/12) | H27: =H25/(1+disc_rate)^(H$17/12) | I27: =I25/(1+disc_rate)^(I$17/12) | J27: =J25/(1+disc_rate)^(J$17/12) | K27: =K25/(1+disc_rate)^(K$17/12) | ... BK27: =BK25/(1+disc_rate)^(BK$17/12)
A28: Payback flag | C28: 0 | D28: =IF(D26>=lf_cac,D$17,999) | E28: =IF(E26>=lf_cac,E$17,999) | F28: =IF(F26>=lf_cac,F$17,999) | G28: =IF(G26>=lf_cac,G$17,999) | H28: =IF(H26>=lf_cac,H$17,999) | I28: =IF(I26>=lf_cac,I$17,999) | J28: =IF(J26>=lf_cac,J$17,999) | K28: =IF(K26>=lf_cac,K$17,999) | ... BK28: =IF(BK26>=lf_cac,BK$17,999)
A31: Lending-first outputs (per disbursed borrower)
A32: CAC payback (months) | B32: =IF(MIN(D28:BK28)=999,"not within 60 months",MIN(D28:BK28))
A33: LTV, 36 months (₹, discounted) | B33: =SUM(D27:AM27)
A34: LTV, 60 months (₹, discounted) | B34: =SUM(D27:BK27)
A35: LTV/CAC, 36 months | B35: =lf_ltv36/lf_cac
A36: LTV/CAC, 60 months | B36: =lf_ltv60/lf_cac
A37: Year-1 net revenue per borrower (₹) | B37: =SUM(D20:O20)/borrowers_lf
A38: Year-1 contribution per borrower (₹) | B38: =SUM(D23:O23)/borrowers_lf
A39: Equity locked per ₹1 of yearly net revenue, if run through our own NBFC | B39: =IFERROR(lf_equity_ratio*SUM(D24:O24)/12/SUM(D20:O20),0)

Sheet Sensitivity
A1: Sensitivity: bear / base / bull, and the inputs that move LTV/CAC most
A2: These values are written by engine.py (the same logic as the live sheets). To see any scenario live, set Inputs!C2; verify.py checks the live workbook reproduces this table for all three scenarios.
A4: Metric | B4: Bear | C4: Base | D4: Bull
A5: CAC per activated saver (₹) | B5: 366.60569 | C5: 256.08192 | D5: 211.18516
A6: CAC payback (months; blank = not within 60) | D6: 15
A7: LTV 36 months (₹) | B7: -573.31167 | C7: -271.83203 | D7: 431.73734
A8: LTV 60 months (₹) | B8: -632.5368 | C8: -304.03099 | D8: 604.99841
A9: LTV/CAC 36 months | B9: -1.5638373 | C9: -1.0615042 | D9: 2.0443546
A10: LTV/CAC 60 months | B10: -1.7253873 | C10: -1.1872412 | D10: 2.8647772
A11: Revenue per active saver, year 1 (₹) | B11: 30.568273 | C11: 160.71413 | D11: 578.57038
A12: Revenue per active saver, year 2 (₹) | B12: 42.841929 | C12: 246.522 | D12: 1009.2599
A13: Revenue per active saver, year 3 (₹) | B13: 47.121811 | C13: 278.60724 | D13: 1246.6583
A14: Revenue per active saver, year 4 (₹) | B14: 49.220276 | C14: 286.79516 | D14: 1292.9953
A15: Revenue per active saver, year 5 (₹) | B15: 51.358776 | C15: 294.69593 | D15: 1320.3694
A16: Lending-first CAC per borrower (₹) | B16: 840 | C16: 760 | D16: 480
A17: Lending-first LTV/CAC 60 months | B17: -0.73359238 | C17: 0.070922019 | D17: 2.3251247
A20: Tornado: LTV/CAC (60 months) when ONE input moves from its bear to its bull value, all else at base
A21: Input | B21: Bear value | C21: Base value | D21: Bull value | E21: LTV/CAC at bear | F21: LTV/CAC at bull | G21: Swing
A22: cost_debit | B22: 5 | C22: 2 | D22: 0.5 | E22: -3.0888936 | F22: -0.23641495 | G22: 2.8524786
A23: cac_mult | B23: 1.3 | C23: 1 | D23: 0.8 | E23: -0.82931334 | F23: -1.4396419 | G23: 0.61032853
A24: ret_m24 | B24: 0.06 | C24: 0.1 | D24: 0.2 | E24: -1.0491371 | F24: -1.4773669 | G24: 0.42822981
A25: debits_success | B25: 15 | C25: 20 | D25: 24 | E25: -0.96205945 | F25: -1.3275558 | G25: 0.36549639
A26: daily_amount | B26: 25 | C26: 40 | D26: 60 | E26: -1.2861191 | F26: -0.97946964 | G26: 0.30664945
A27: cost_failed | B27: 1 | C27: 0.25 | D27: 0 | E27: -1.3869878 | F27: -1.1206589 | G27: 0.2663289
A28: gold_margin | B28: 0.01 | C28: 0.015 | D28: 0.024 | E28: -1.2666602 | F28: -1.0442869 | G28: 0.22237323
A29: ret_m12 | B29: 0.13 | C29: 0.2 | D29: 0.32 | E29: -1.1224877 | F29: -1.3159716 | G29: 0.19348398
A30: ins_premium | B30: 1500 | C30: 3000 | D30: 5000 | E30: -1.2680604 | F30: -1.0794821 | G30: 0.18857835
A31: cost_support | B31: 8 | C31: 5 | D31: 3 | E31: -1.2772625 | F31: -1.127227 | G31: 0.15003551
A32: cost_tech | B32: 6 | C32: 4 | D32: 2 | E32: -1.2472554 | F32: -1.127227 | G32: 0.1200284
A33: ret_m6 | B33: 0.24 | C33: 0.33 | D33: 0.45 | E33: -1.1396941 | F33: -1.2555688 | G33: 0.11587467

Sheet Assumption register
A1: Assumption register: every uncertain input, its distribution, the evidence for it and how much it matters
A2: One row per input per segment (gig / ng = self-employed / all). Distribution = what the Monte Carlo samples. Status: triangulated = checked against independent sources (see Evidence); provisional = bear/base/bull widened, no independent check yet (yellow); fixed = founder decision or product design. Variance share = share of the spread in net value per saver this input explains (Monte Carlo, independent variant).
A4: Register
A5: input | B5: segment | C5: assumption | D5: dist | E5: low | F5: mode | G5: high | H5: status | I5: verdict | J5: basis | K5: evidence | L5: variance_share
A6: pay_flat | B6: all | C6: Payment pricing: flat Rs 5 + GST per debit (1) or a % of the debit (0) | D6: bernoulli | E6: 0 | F6: 0.5 | G6: 1 | H6: assumption | I6: no plan value | J6: payment pricing: 1 = flat list price Rs 5 + 18% GST per debit (Cashfree, Zoho); 0 = a % of the debit (Razorpay reported, PhonePe PG 1.99%). Which a new app gets is unknown: 50/50 is an assumption | K6: TC-02, TC-06, TC-15, TC-16, TC-17 | L6: 0.73825103
A7: cac_target | B7: ng | C7: Cost to win a saver who makes a first debit (Rs) | D7: lognormal | E7: 186 | F7: 499.2394 | G7: 1340 | H7: triangulated | I7: plan optimistic | J7: as gig x 1.1: no payments firm publishes merchant acquisition cost | K7: TB-18..TB-22, NG-043 | L7: 0.098749254
A8: cac_target | B8: gig | C8: Cost to win a saver who makes a first debit (Rs) | D8: lognormal | E8: 168 | F8: 450.12 | G8: 1206 | H8: triangulated | I8: plan optimistic | J8: CAC per activated saver, Rs: Groww Rs 796-1,374 with 83% organic; finance-app CPI Rs 100-300; Jar/Stable Money clear Rs 249 only if half of sign-ups save | K8: TB-18..TB-22, TB-37, TB-38, BM-04, BM-05 | L8: 0.080545286
A9: fail_billed | B9: all | C9: Failed debits billed at the flat price? (flat pricing only) | D9: bernoulli | E9: 0 | F9: 0.5 | G9: 1 | H9: assumption | I9: no plan value | J9: under flat pricing, are failed debits billed at Rs 5.90? No payment company says; 50/50 | K9: TC-05, TC-15 | L9: 0.030650193
A10: ret_m12 | B10: ng | C10: Share of savers still saving at month 12 | D10: beta | E10: 0.1099 | F10: 0.25 | G10: 0.4191 | H10: triangulated | I10: plan within evidence | J10: as gig, without platform churn | K10: TB-01..TB-08, TB-11, NG-033 | L10: 0.028417988
A11: churn_late | B11: all | C11: Monthly churn after month 24 | D11: triangular | E11: 0.008 | F11: 0.015 | G11: 0.03 | H11: triangulated | I11: plan within evidence | J11: Acorns ~1-1.3% monthly churn after year one | K11: TB-11 | L11: 0.0060495526
A12: ret_m12 | B12: gig | C12: Share of savers still saving at month 12 | D12: beta | E12: 0.0753 | F12: 0.2 | G12: 0.3594 | H12: triangulated | I12: plan within evidence | J12: small Indian SIPs ~38% at 12m (ceiling); RCTs 3-45%; Jar actives 4-7% of registered; Zomato rider churn high | K12: TB-01..TB-08, TB-11, TB-12, TB-16, NG-033 | L12: 0.0060495526
A13: cost_support | B13: all | C13: Support cost | D13: lognormal | E13: 2.4 | F13: 6 | G13: 15 | H13: triangulated | I13: plan leans optimistic | J13: a support contact costs Rs 50-150; Groww non-tech opex Rs 32 per active user (upper bound); no direct data | K13: TC-37, TC-38 | L13: 0.0032397451
A14: ret_m24_ratio | B14: all | C14: Month-24 retention as a share of month-12 | D14: triangular | E14: 0.4 | F14: 0.6 | G14: 0.8 | H14: triangulated | I14: plan cautious | J14: month 24 as a share of month 12: churn flattens after year one (Acorns, SIP vintages, PMJJBY) | K14: TB-01, TB-02, TB-11, TB-23 | L14: 0.0018970333
A15: pay_pct | B15: all | C15: Payment fee as a share of each debit (percentage pricing) | D15: triangular | E15: 0.015 | F15: 0.02 | G15: 0.034 | H15: triangulated | I15: no plan value | J15: percentage pricing: share of each debit, incl. GST | K15: TC-15, TC-16, TC-17 | L15: 0.0012127951
A16: debits_success | B16: ng | C16: Successful debits per month | D16: triangular | E16: 12 | F16: 19 | G16: 25 | H16: triangulated | I16: plan optimistic | J16: as gig; daily UPI receipts help | K16: TB-13, TB-36, TC-05 | L16: 0.00074960312
A17: cost_tech | B17: all | C17: Tech and cloud cost | D17: triangular | E17: 2 | F17: 4 | G17: 10 | H17: triangulated | I17: plan leans optimistic | J17: Jar cloud Rs 0.6-0.8 per registered user; Groww Rs 28.6 tech + transaction per active user | K17: TC-20, TC-36 | L17: 0.00069684436
... A21: cost_notice | B21: all | C21: Cost per pre-debit notice | D21: uniform | E21: 0 | F21: 0.075 | G21: 0.15 | H21: triangulated | I21: plan optimistic | J21: pre-debit notice triggered through the payment company; whether billed is unknown | K21: TC-03, REG-048 | L21: 0.00032587596
A22: withdraw_rate | B22: all | C22: Share of balance withdrawn per month by active savers | D22: triangular | E22: 0.015 | F22: 0.1 | G22: 0.195 | H22: provisional | I22: plan within evidence | J22: bear/base/bull widened by half a range each side | L22: 0.00014905788
A23: cost_fraud | B23: all | C23: Fraud and chargeback loss | D23: triangular | E23: 0.0002 | F23: 0.0005 | G23: 0.002 | H23: triangulated | I23: plan within evidence | J23: 98.5% of fraud value is in payments over Rs 10,000; system ~0.01% of value | K23: TC-40 | L23: 0.00013601307
A24: daily_amount | B24: gig | C24: Amount per successful debit | D24: lognormal | E24: 20 | F24: 36.0555 | G24: 65 | H24: triangulated | I24: plan leans optimistic | J24: Jar average purchase ~Rs 64 incl. lump sums; Gullak ~Rs 580 a month; most riders have no buffer | K24: TB-15, TB-17, TB-40 | L24: 0.00012673156
A25: card_fee | B25: all | C25: Fee per FD-secured card issued | D25: triangular | E25: 0 | F25: 500 | G25: 1400 | H25: provisional | I25: plan within evidence | J25: bear/base/bull widened by half a range each side | K25: BM-08 | L25: 0.00012053883
A26: card_eligible | B26: all | C26: Share of active savers eligible (enough in FD) | D26: triangular | E26: 0.125 | F26: 0.4 | G26: 0.625 | H26: provisional | I26: plan within evidence | J26: bear/base/bull widened by half a range each side | L26: 9.8850741e-05
A27: cost_rewards | B27: all | C27: Ongoing streak rewards | D27: triangular | E27: 0 | F27: 0 | G27: 4.5 | H27: provisional | I27: plan optimistic | J27: bear/base/bull widened by half a range each side | K27: REG-082, REG-083 | L27: 8.3357136e-05
A28: card_uptake | B28: all | C28: Monthly take-up among eligible savers without a card | D28: uniform | E28: 0.005 | F28: 0.0175 | G28: 0.03 | H28: unevidenced | I28: plan optimistic | J28: no data on FD-secured card take-up: unevidenced | K28: TB-35, BM-08 | L28: 8.1544327e-05
A29: card_churn | B29: all | C29: Monthly share of card holders who stop | D29: triangular | E29: 0.0025 | F29: 0.025 | G29: 0.0525 | H29: provisional | I29: plan within evidence | J29: bear/base/bull widened by half a range each side | L29: 3.9953632e-05
A30: loan_apply | B30: all | C30: Monthly application rate among eligible never-borrowed savers | D30: triangular | E30: 0.005 | F30: 0.015 | G30: 0.04 | H30: triangulated | I30: plan optimistic | J30: Paytm ~0.9% of users take any product a quarter; Moneyview 8%, GCash 11% ever borrowed; secured-on-own-savings demand weak | K30: TB-08, TB-31, TB-33, TB-44, LEND-04 | L30: 3.8574125e-05
A31: loan_repeat | B31: all | C31: Share of repaid loans followed by another loan | D31: triangular | E31: 0.3 | F31: 0.5 | G31: 0.65 | H31: triangulated | I31: plan within evidence | J31: repeat share >50% (Paytm merchant), ~73% (Kissht), 68% PM SVANidhi second loan | K31: TB-31, TB-43, NG-014 | L31: 3.629909e-05
A32: ins_comm_renew | B32: all | C32: Renewal commission | D32: triangular | E32: 0.025 | F32: 0.04 | G32: 0.05 | H32: triangulated | I32: plan optimistic | J32: draft cap 5%; 2.5% if sold with a loan | K32: TC-30 | L32: 3.5951644e-05
A33: sip_uptake | B33: all | C33: Monthly take-up among savers without a SIP | D33: triangular | E33: 0 | F33: 0.01 | G33: 0.0275 | H33: provisional | I33: plan within evidence | J33: bear/base/bull widened by half a range each side | L33: 3.5801935e-05
A34: ins_eligible | B34: all | C34: Share of active savers who could buy | D34: triangular | E34: 0.7 | F34: 0.9 | G34: 1 | H34: provisional | I34: plan leans optimistic | J34: bear/base/bull widened by half a range each side | L34: 2.8591724e-05
A35: dlg_fee_uplift | B35: all | C35: Extra fee a lender pays when we give a guarantee | D35: triangular | E35: 0.025 | F35: 0.045 | G35: 0.07 | H35: triangulated | I35: plan leans optimistic | J35: uplift prices ~3% losses (Moneyview's cover paid 2.9-3.4%); low losses invite a lower uplift | K35: TC-41 | L35: 2.8233397e-05
A36: loan_ead | B36: all | C36: Share of the loan still owed when it goes 90+ late | D36: triangular | E36: 0.6 | F36: 0.8 | G36: 1 | H36: provisional | I36: plan within evidence | J36: bear/base/bull widened by half a range each side | L36: 2.5257408e-05
A37: ins_uptake | B37: ng | C37: Monthly take-up among savers never insured | D37: triangular | E37: 0.002 | F37: 0.012 | G37: 0.025 | H37: triangulated | I37: plan optimistic | J37: as gig, but no platform cover | K37: TB-25, TB-26, TB-31, TB-41 | L37: 2.3017696e-05
A38: amount_growth | B38: all | C38: Yearly growth in amount per debit | D38: triangular | E38: 0 | F38: 0.1 | G38: 0.2 | H38: provisional | I38: plan within evidence | J38: bear/base/bull widened by half a range each side | L38: 2.1884283e-05
A39: card_ops_cost | B39: all | C39: Our cost per card issued | D39: triangular | E39: 37.5 | F39: 100 | G39: 187.5 | H39: provisional | I39: plan within evidence | J39: bear/base/bull widened by half a range each side | L39: 1.9950535e-05
A40: ins_premium | B40: all | C40: Annual premium per policy | D40: triangular | E40: 300 | F40: 800 | G40: 1500 | H40: triangulated | I40: plan optimistic | J40: what this group buys: accident cover Rs 50-100, hospital cash from ~Rs 799, the IRDAI Bima Vistaar bundle Rs 1,500 (the top); riders already get ~Rs 2,100 of free cover (updated 2 Oct 2026 from Rs 500/1,500/3,500) | K40: TC-26, TC-27, TC-28, XO-30, XO-34, XO-35 | L40: 1.8996118e-05
A41: card_ic_share | B41: all | C41: Our share of card spend (interchange share) | D41: triangular | E41: 0 | F41: 0 | G41: 0.00375 | H41: provisional | I41: plan cautious | J41: bear/base/bull widened by half a range each side | K41: REG-087 | L41: 1.8805499e-05
A42: ins_comm_first | B42: all | C42: First-year commission | D42: triangular | E42: 0.05 | F42: 0.1 | G42: 0.15 | H42: triangulated | I42: plan optimistic | J42: draft caps 15% / 5% with a loan / 2.5-5% group; Bima Vistaar pays 10% | K42: TC-29, TC-30, REG-054 | L42: 1.5686907e-05
A43: loan_ops_cost | B43: all | C43: Our cost per loan | D43: triangular | E43: 37.5 | F43: 100 | G43: 187.5 | H43: provisional | I43: plan within evidence | J43: bear/base/bull widened by half a range each side | L43: 1.5516919e-05
A44: secured_fee | B44: all | C44: Our revenue on the secured part of a loan | D44: triangular | E44: 0.0025 | F44: 0.0075 | G44: 0.02 | H44: triangulated | I44: plan optimistic | J44: bank margin on loans against FD 1-2% a year, fees nil-0.5%; no lender found for Rs 2-6k secured loans (founder's 2% is the top) | K44: TC-31, TC-32, TC-33 | L44: 1.3666749e-05
A45: leaver_withdraw | B45: all | C45: Share of balance withdrawn in the month a saver stops | D45: triangular | E45: 0.2 | F45: 0.6 | G45: 1 | H45: provisional | I45: plan within evidence | J45: bear/base/bull widened by half a range each side | L45: 1.0401529e-05
A46: fd_share | B46: all | C46: Share of savings balance held in bank FDs | D46: triangular | E46: 0.1 | F46: 0.3 | G46: 0.5 | H46: provisional | I46: plan within evidence | J46: bear/base/bull widened by half a range each side | L46: 1.0286291e-05
A47: trail_equity | B47: all | C47: Distributor trail on equity SIP balance | D47: triangular | E47: 0.0025 | F47: 0.0075 | G47: 0.0125 | H47: provisional | I47: plan within evidence | J47: bear/base/bull widened by half a range each side | K47: OWN-04 | L47: 1.0191041e-05
A48: ladder_dpd90 | B48: all | C48: Share of unsecured money that goes 90+ days late (loan 3 onward) | D48: triangular | E48: 0.005 | F48: 0.015 | G48: 0.03 | H48: triangulated | I48: plan leans optimistic | J48: founder's repeat-loan rate 1-2%; no Indian study shows savers default less | K48: founder, TB-30 | L48: 9.8469944e-06
A49: ins_uptake | B49: gig | C49: Monthly take-up among savers never insured | D49: triangular | E49: 0.002 | F49: 0.008 | G49: 0.025 | H49: triangulated | I49: plan optimistic | J49: PhonePe ~1-2% of users a YEAR; Paytm <1% a quarter for all products; riders have free platform cover | K49: TB-25, TB-26, TB-27, TB-31, TB-41 | L49: 9.3858847e-06
A50: service_cost | B50: all | C50: Collection and servicing cost per loan when we service it (guarantee or own NBFC) | D50: triangular | E50: 50 | F50: 250 | G50: 450 | H50: provisional | I50: plan within evidence | J50: bear/base/bull widened by half a range each side | K50: LEV-018, LEV-019 | L50: 7.201698e-06
A51: ins_persist | B51: all | C51: Share of policies renewed each year | D51: beta | E51: 0.2087 | F51: 0.45 | G51: 0.7032 | H51: triangulated | I51: plan leans optimistic | J51: voluntary micro-insurance renewal 23% -> 46% after redesign; auto-debited PMJJBY/PMSBY 51-70% | K51: TB-23, TB-24, TB-41 | L51: 5.8618134e-06
A52: loan_approval | B52: gig | C52: Partner approval rate for our applicants | D52: triangular | E52: 0.225 | F52: 0.6 | G52: 0.925 | H52: provisional | I52: plan within evidence | J52: bear/base/bull widened by half a range each side | K52: EVD-02, EVD-03 | L52: 5.7161631e-06
A53: ins_ops_cost | B53: all | C53: Our cost per new policy | D53: triangular | E53: 10 | F53: 60 | G53: 130 | H53: provisional | I53: plan within evidence | J53: bear/base/bull widened by half a range each side | L53: 5.0895191e-06
A54: fd_fee | B54: all | C54: Distribution fee on FD balance | D54: triangular | E54: 0.001 | F54: 0.003 | G54: 0.006 | H54: triangulated | I54: plan optimistic | J54: RBI allows only a sourcing fee for deposits; Stable Money implies <= 0.3-0.4% | K54: TC-24, TC-25, BM-03 | L54: 4.5433823e-06
A55: fund_yield | B55: all | C55: Liquid fund / FD yield to saver | D55: triangular | E55: 0.045 | F55: 0.055 | G55: 0.065 | H55: provisional | I55: plan within evidence | J55: bear/base/bull widened by half a range each side | K55: OWN-02 | L55: 3.2949745e-06
A56: loan_approval | B56: ng | C56: Partner approval rate for our applicants | D56: triangular | E56: 0.175 | F56: 0.55 | G56: 0.875 | H56: provisional | I56: plan within evidence | J56: bear/base/bull widened by half a range each side | K56: EVD-02, EVD-03 | L56: 2.7969934e-06
A57: sip_stop | B57: all | C57: Monthly share of SIP holders who stop | D57: triangular | E57: 0.005 | F57: 0.03 | G57: 0.065 | H57: provisional | I57: plan within evidence | J57: bear/base/bull widened by half a range each side | L57: 2.3706679e-06
A58: unsec_grad | B58: all | C58: Monthly share of FD-card holders who move to an unsecured card | D58: triangular | E58: 0 | F58: 0.01 | G58: 0.0275 | H58: provisional | I58: plan within evidence | J58: bear/base/bull widened by half a range each side | L58: 1.4939294e-06
A59: card_spend | B59: all | C59: Monthly spend per card holder | D59: triangular | E59: 0 | F59: 3000 | G59: 6750 | H59: provisional | I59: plan within evidence | J59: bear/base/bull widened by half a range each side | L59: 9.8380115e-07
A60: sip_amount | B60: all | C60: SIP amount | D60: triangular | E60: 0 | F60: 500 | G60: 1000 | H60: provisional | I60: plan within evidence | J60: bear/base/bull widened by half a range each side | L60: 8.2936582e-07
A61: dormant_withdraw | B61: all | C61: Share of dormant balance withdrawn per month | D61: triangular | E61: 0.005 | F61: 0.05 | G61: 0.105 | H61: provisional | I61: plan within evidence | J61: bear/base/bull widened by half a range each side | L61: 4.5753082e-07
A62: sip_redeem | B62: all | C62: Share of SIP balance redeemed per month | D62: triangular | E62: 0 | F62: 0.02 | G62: 0.04 | H62: provisional | I62: plan within evidence | J62: bear/base/bull widened by half a range each side | L62: 2.0659674e-07
A63: wk_success | B63: all | C63: Weekly design: successful debits a month | D63: triangular | E63: 3 | F63: 3.9 | G63: 4.3 | H63: triangulated | I63: no plan value | J63: WEEKLY design only: successful debits a month when one debit lands just after payout day (variants.csv) | K63: variants.csv weekly_payday | L63: 8.881446e-08
A64: loan_eligible | B64: all | C64: Share of active savers eligible for a loan offer | D64: triangular | E64: 0.125 | F64: 0.5 | G64: 0.825 | H64: provisional | I64: plan within evidence | J64: bear/base/bull widened by half a range each side | K64: LEND-04, CMP-07, CMP-05 | L64: 5.1961513e-08
A65: lsp_fee | B65: all | C65: Our fee as loan service provider | D65: triangular | E65: 0.0075 | F65: 0.015 | G65: 0.025 | H65: triangulated | I65: plan within evidence | J65: lead-based sourcing pays 1-3% | K65: TC-34, LEV-009 | L65: 4.7044072e-08
A66: trail_liquid | B66: all | C66: Distributor trail on liquid-fund balance | D66: triangular | E66: 0.00025 | F66: 0.0005 | G66: 0.001 | H66: triangulated | I66: plan optimistic | J66: trail actually paid: ~0.05% at 5 of 6 fund houses | K66: TC-21, TC-22 | L66: 3.3300075e-09
A67: loan_lgd | B67: all | C67: Share of that never recovered | D67: triangular | E67: 0.3 | F67: 0.5 | G67: 0.7 | H67: provisional | I67: plan within evidence | J67: bear/base/bull widened by half a range each side | L67: 2.5602003e-09
A68: unsec_fee | B68: all | C68: Fee per unsecured card issued | D68: triangular | E68: 0 | F68: 1000 | G68: 2750 | H68: provisional | I68: plan within evidence | J68: bear/base/bull widened by half a range each side | K68: BM-08 | L68: 1.4473505e-09
A69: sip_return | B69: all | C69: Equity fund return | D69: triangular | E69: 0.06 | F69: 0.1 | G69: 0.14 | H69: provisional | I69: plan within evidence | J69: bear/base/bull widened by half a range each side | L69: 8.0900811e-10

Sheet Monte Carlo
A1: Monte Carlo: how likely is a profitable saver, given what we know about each input
A2: Written by model/mc.py from tables/distributions.csv: 10,000 draws, fixed seed 20261002, each run through the reference engine (which verify.py checks against this workbook's formulas). 'independent' = inputs drawn independently except the retention curve, which moves as one; 'correlated' = an engagement factor links retention, amounts and take-up (rho 0.5). Net = LTV (60 months, discounted) minus CAC, per activated saver, Rs.
A4: Outputs: percentiles across draws (base_case = the deterministic middle case)
A5: variant | B5: metric | C5: base_case | D5: mean | E5: p5 | F5: p10 | G5: p25 | H5: p50 | I5: p75 | J5: p90 | K5: p95
A6: independent | B6: net | C6: -560.11291 | D6: -1273.8015 | E6: -2504.9615 | F6: -2200.7721 | G6: -1698.4741 | H6: -1134.2702 | I6: -746.10559 | J6: -564.39308 | K6: -489.59227
A7: independent | B7: ratio | C7: -1.1872412 | D7: -1.5045042 | E7: -4.6170202 | F7: -3.5219583 | G7: -2.1386854 | H7: -0.92183693 | I7: -0.39478435 | J7: -0.23958522 | K7: -0.17861785
A8: independent | B8: ltv60 | C8: -304.03099 | D8: -704.40707 | E8: -1859.1012 | F8: -1573.5466 | G8: -1099.3393 | H8: -476.36793 | I8: -205.26929 | J8: -144.51046 | K8: -119.1194
A9: independent | B9: cac | C9: 256.08192 | D9: 569.39447 | E9: 252.81092 | F9: 297.09461 | G9: 383.51344 | H9: 517.83648 | I9: 693.79341 | J9: 905.31621 | K9: 1070.7917
A10: independent | B10: payback | C10: 61 | D10: 61 | E10: 61 | F10: 61 | G10: 61 | H10: 61 | I10: 61 | J10: 61 | K10: 61
A11: independent | B11: rev_pa_y2 | C11: 246.522 | D11: 137.48867 | E11: 76.726981 | F11: 86.336795 | G11: 104.6158 | H11: 129.63611 | I11: 162.00492 | J11: 198.1175 | K11: 223.62401
A12: independent | B12: y10_usd_m | C12: 10.059904 | D12: 6.3107075 | E12: 2.4667659 | F12: 2.9759405 | G12: 4.0435459 | H12: 5.6951784 | I12: 7.860019 | J12: 10.38551 | K12: 12.390951
A13: independent | B13: peak_cr | C13: 2688.1092 | D13: 5113.8986 | E13: 2624.2896 | F13: 2920.7918 | G13: 3654.199 | H13: 4809.5594 | I13: 6305.2037 | J13: 7728.9648 | K13: 8561.5327
A14: correlated | B14: net | C14: -560.11291 | D14: -1278.8762 | E14: -2469.5795 | F14: -2201.5317 | G14: -1708.0241 | H14: -1143.3172 | I14: -752.36764 | J14: -565.89715 | K14: -481.23426
A15: correlated | B15: ratio | C15: -1.1872412 | D15: -1.5156207 | E15: -4.5892692 | F15: -3.5035132 | G15: -2.1773294 | H15: -0.95464656 | I15: -0.39326529 | J15: -0.22133552 | K15: -0.16359089
A16: correlated | B16: ltv60 | C16: -304.03099 | D16: -709.48176 | E16: -1832.8516 | F16: -1579.5547 | G16: -1125.0901 | H16: -497.90569 | I16: -206.76743 | J16: -129.20998 | K16: -101.04572
A17: correlated | B17: cac | C17: 256.08192 | D17: 569.39447 | E17: 252.81092 | F17: 297.09461 | G17: 383.51344 | H17: 517.83648 | I17: 693.79341 | J17: 905.31621 | K17: 1070.7917
... A29: weekly | B29: peak_cr | C29: 2688.1092 | D29: 3911.7973 | E29: 2408.8332 | F29: 2615.6276 | G29: 3056.6644 | H29: 3689.4135 | I29: 4494.4403 | J29: 5452.0485 | K29: 6198.7276
A31: Probabilities (share of draws)
A32: variant | B32: metric | C32: mean
A33: independent | B33: p_net_pos | C33: 0
A34: independent | B34: p_ratio_ge1 | C34: 0
A35: independent | B35: p_ratio_ge3 | C35: 0
A36: independent | B36: p_payback_le24 | C36: 0
A37: independent | B37: p_y10_ge100 | C37: 0
A38: independent | B38: p_y10_ge50 | C38: 0
A39: correlated | B39: p_net_pos | C39: 0
A40: correlated | B40: p_ratio_ge1 | C40: 0
A41: correlated | B41: p_ratio_ge3 | C41: 0
A42: correlated | B42: p_payback_le24 | C42: 0
A43: correlated | B43: p_y10_ge100 | C43: 0
A44: correlated | B44: p_y10_ge50 | C44: 0.001
... A50: weekly | B50: p_y10_ge50 | C50: 0
A52: Drivers of net value per saver (rank regression; variance_share sums to 100% per variant)
A53: variant | B53: input | C53: spearman | D53: variance_share | E53: rank_model_r2
A54: correlated | B54: pay_flat | C54: -0.77659609 | D54: 0.73673659 | E54: 0.8923178
A55: correlated | B55: cac_target@ng | C55: -0.264373 | D55: 0.097977375 | E55: 0.8923178
A56: correlated | B56: cac_target@gig | C56: -0.26394152 | D56: 0.080724648 | E56: 0.8923178
A57: correlated | B57: fail_billed | C57: -0.17400266 | D57: 0.031178533 | E57: 0.8923178
A58: correlated | B58: ret_m12@ng | C58: -0.3051775 | D58: 0.028847473 | E58: 0.8923178
A59: correlated | B59: ret_m12@gig | C59: -0.30450205 | D59: 0.0058723156 | E59: 0.8923178
A60: correlated | B60: churn_late | C60: 0.30450205 | D60: 0.0058723156 | E60: 0.8923178
A61: correlated | B61: cost_support | C61: -0.049856096 | D61: 0.0035030395 | E61: 0.8923178
A62: correlated | B62: ret_m24_ratio | C62: -0.070617104 | D62: 0.0019749741 | E62: 0.8923178
A63: correlated | B63: pay_pct | C63: -0.051081448 | D63: 0.0015819087 | E63: 0.8923178
A64: correlated | B64: debits_success@gig | C64: -0.19364801 | D64: 0.00099601262 | E64: 0.8923178
A65: correlated | B65: gold_margin | C65: 0.02220519 | D65: 0.00087223151 | E65: 0.8923178
... A245: weekly | B245: lsp_fee | C245: 0.011115365 | D245: 9.751479e-09 | E245: 0.86447873
A247: What moves the odds: P(net > 0) with the driver in its worst / best fifth
A248: variant | B248: input | C248: p_net_pos_worst_fifth | D248: p_net_pos_best_fifth | E248: p_ratio_ge3_best_fifth
A249: independent | B249: pay_flat | C249: 0 | D249: 0 | E249: 0
A250: independent | B250: cac_target@ng | C250: 0 | D250: 0 | E250: 0
A251: independent | B251: cac_target@gig | C251: 0 | D251: 0 | E251: 0
A252: independent | B252: fail_billed | C252: 0 | D252: 0 | E252: 0
A253: independent | B253: ret_m12@ng | C253: 0 | D253: 0 | E253: 0
A254: independent | B254: churn_late | C254: 0 | D254: 0 | E254: 0
A255: independent | B255: ret_m12@gig | C255: 0 | D255: 0 | E255: 0
A256: independent | B256: cost_support | C256: 0 | D256: 0 | E256: 0
A257: correlated | B257: pay_flat | C257: 0 | D257: 0 | E257: 0
A258: correlated | B258: cac_target@ng | C258: 0 | D258: 0 | E258: 0
A259: correlated | B259: cac_target@gig | C259: 0 | D259: 0 | E259: 0
A260: correlated | B260: fail_billed | C260: 0 | D260: 0 | E260: 0
... A272: weekly | B272: pay_flat | C272: 0 | D272: 0 | E272: 0
A274: Histogram of net value per saver (Rs; 1st to 99th percentile)
A275: variant | B275: lo | C275: hi | D275: share
A276: independent | B276: -3024.7815 | C276: -2936.7043 | D276: 0.0126
A277: independent | B277: -2936.7043 | C277: -2848.6271 | D277: 0.0046
A278: independent | B278: -2848.6271 | C278: -2760.5499 | D278: 0.0066
A279: independent | B279: -2760.5499 | C279: -2672.4726 | D279: 0.0079
A280: independent | B280: -2672.4726 | C280: -2584.3954 | D280: 0.0086
A281: independent | B281: -2584.3954 | C281: -2496.3182 | D281: 0.0108
A282: independent | B282: -2496.3182 | C282: -2408.241 | D282: 0.012
A283: independent | B283: -2408.241 | C283: -2320.1638 | D283: 0.0128
A284: independent | B284: -2320.1638 | C284: -2232.0866 | D284: 0.0171
A285: independent | B285: -2232.0866 | C285: -2144.0094 | D285: 0.0209
A286: independent | B286: -2144.0094 | C286: -2055.9322 | D286: 0.0209
A287: independent | B287: -2055.9322 | C287: -1967.855 | D287: 0.0227
... A365: weekly | B365: -398.63151 | C365: -353.7792 | D365: 0.0255

Sheet Sensitivity (net)
A1: Sensitivity on net value per saver: one input at a time, and debit cost x retention
A2: Each input moved to the 10th and 90th percentile of its distribution, all others at the middle case. Break-even = the value at which the average saver's net value reaches zero with all else at the middle case (blank = no value in a wide range gets there). Grid: the whole retention curve, both halves, at one percentile.
A4: One at a time (sorted by swing)
A5: input | B5: p10_value | C5: base_value | D5: p90_value | E5: net_at_p10 | F5: net_at_base | G5: net_at_p90 | H5: swing | I5: breakeven_value
A6: pay_flat | B6: 0 | C6: 0 | D6: 1 | E6: -670.67244 | F6: -670.67244 | G6: -1339.3036 | H6: 668.63114
A7: cac_target@ng | B7: 231.32466 | C7: 499.23942 | D7: 1077.4467 | E7: -536.71506 | F7: -670.67244 | G7: -959.77609 | H7: 423.06103
A8: cac_target@gig | B8: 208.85587 | C8: 450.11998 | D8: 970.08527 | E8: -550.04038 | F8: -670.67244 | G8: -930.65508 | H8: 380.6147
A9: ret_m12@ng | B9: 0.13393555 | C9: 0.24154255 | D9: 0.37752691 | E9: -629.64356 | F9: -670.67244 | G9: -718.77742 | H9: 89.13386
A10: daily_amount@ng | B10: 29.444239 | C10: 52.440442 | D10: 93.396878 | E10: -643.38013 | F10: -670.67244 | G10: -719.28027 | H10: 75.900144
A11: cost_support | B11: 2.9383602 | C11: 6 | D11: 12.251731 | E11: -647.30703 | F11: -670.67244 | G11: -718.38356 | H11: 71.076539
A12: ret_m12@gig | B12: 0.095141785 | C12: 0.18988518 | D12: 0.31859088 | E12: -640.39908 | F12: -670.67244 | G12: -708.20204 | H12: 67.802952
A13: pay_pct | B13: 0.018082207 | C13: 0.022467437 | D13: 0.028842481 | E13: -643.38936 | F13: -670.67244 | G13: -710.3353 | H13: 66.945944
A14: gold_margin | B14: 0.0087749172 | C14: 0.013547728 | D14: 0.019325602 | E14: -686.92797 | F14: -670.67244 | G14: -650.9938 | H14: 35.934166
A15: cost_tech | B15: 3.2649111 | C15: 5.1010205 | D15: 7.8091098 | E15: -656.65986 | F15: -670.67244 | G15: -691.33967 | H15: 34.679806
A16: daily_amount@gig | B16: 22.780347 | C16: 36.055513 | D16: 57.066734 | E16: -658.79862 | F16: -670.67244 | G16: -689.46568 | H16: 30.667055
A17: cost_notice | B17: 0.015 | C17: 0.075 | D17: 0.135 | E17: -656.93544 | F17: -670.67244 | G17: -684.40944 | H17: 27.473997
... A69: fail_billed | B69: 0 | C69: 0 | D69: 1 | E69: -670.67244 | F69: -670.67244 | G69: -670.67244 | H69: 0
A71: Net value per saver: debit cost (rows) x retention percentile
A72: cost_debit | B72: retention_percentile | C72: ret_m12_gig | D72: net | E72: ratio
A73: 0.25 | B73: 0.1 | C73: 0.095141785 | D73: -531.68247 | E73: -0.12008681
A74: 0.25 | B74: 0.25 | C74: 0.1352575 | D74: -546.30892 | E74: -0.15090011
A75: 0.25 | B75: 0.5 | C75: 0.18988518 | D75: -565.14424 | E75: -0.19058016
A76: 0.25 | B76: 0.75 | C76: 0.25411221 | D76: -586.17305 | E76: -0.23488122
A77: 0.25 | B77: 0.9 | C77: 0.31859088 | D77: -606.56162 | E77: -0.27783349
A78: 0.5 | B78: 0.1 | C78: 0.095141785 | D78: -552.74896 | E78: -0.16446724
A79: 0.5 | B79: 0.25 | C79: 0.1352575 | D79: -573.10497 | E79: -0.20735092
A80: 0.5 | B80: 0.5 | C80: 0.18988518 | D80: -599.39908 | E80: -0.26274427
A81: 0.5 | B81: 0.75 | C81: 0.25411221 | D81: -628.81605 | E81: -0.32471653
A82: 0.5 | B82: 0.9 | C82: 0.31859088 | D82: -657.38675 | E82: -0.38490596
A83: 1 | B83: 0.1 | C83: 0.095141785 | D83: -594.88194 | E83: -0.2532281
A84: 1 | B84: 0.25 | C84: 0.1352575 | D84: -626.69708 | E84: -0.32025253
... A102: 5.9 | B102: 0.9 | C102: 0.31859088 | D102: -1755.2095 | E102: -2.6976713

Sheet Break-even minimum
A1: The flip: what daily minimum makes one saver break even?
A2: Written by model/flip.py. Every saver puts in exactly the minimum per successful debit; everything else at the evidence middle, so the savers a higher minimum would lose are NOT counted. Flat fee steps from Rs 5.90 to Rs 17.70 above Rs 1,000 a debit.
A4: Break-even amount per case (first Rs 50 step with net value >= 0)
A5: case | B5: design | C5: breakeven_amount | D5: monthly_gig | E5: share_income_gig | F5: best_net_at_or_below_1000
A6: best_case_flat_failed_free | B6: daily | C6: 700 | D6: 11900 | E6: 0.63429455 | F6: 2320.8566
A7: best_case_percent | B7: daily | F7: -234.73858
A8: evidence_flat_failed_billed | B8: daily | C8: 4650 | D8: 79050 | E8: 4.2135281 | F8: -929.77315
A9: evidence_flat_failed_free | B9: daily | C9: 3050 | D9: 51850 | E9: 2.763712 | F9: -387.38245
A10: evidence_flat_failed_free | B10: weekly | C10: 5150 | D10: 19388.993 | E10: 1.0334733 | F10: -521.92226
A11: evidence_percent | B11: daily | F11: -680.24856
A12: plan | B12: daily | C12: 450 | D12: 9000 | E12: 0.47971857 | F12: 785.40801
A14: Monte Carlo by amount (2,000 draws each): share of futures with net value > 0
A15: amount | B15: p_pos | C15: p_pos_flat | D15: p_pos_percent | E15: p50
A16: 50 | B16: 0 | C16: 0 | D16: 0 | E16: -1119.268
A17: 100 | B17: 0 | C17: 0 | D17: 0 | E17: -1170.1185
A18: 150 | B18: 0 | C18: 0 | D18: 0 | E18: -1215.3033
A19: 200 | B19: 0 | C19: 0 | D19: 0 | E19: -1251.0523
A20: 250 | B20: 0 | C20: 0 | D20: 0 | E20: -1296.2345
A21: 300 | B21: 0 | C21: 0 | D21: 0 | E21: -1337.3254
A22: 350 | B22: 0 | C22: 0 | D22: 0 | E22: -1381.3871
A23: 400 | B23: 0 | C23: 0 | D23: 0 | E23: -1419.785
A24: 450 | B24: 0 | C24: 0 | D24: 0 | E24: -1446.1921
A25: 500 | B25: 0 | C25: 0 | D25: 0 | E25: -1480.2356
A26: 550 | B26: 0 | C26: 0 | D26: 0 | E26: -1494.7918
A27: 600 | B27: 0 | C27: 0 | D27: 0 | E27: -1514.6226
... A51: 5000 | B51: 0.3445 | C51: 0.67748279 | D51: 0 | E51: -2599.4076

Sheet Cross-sell and LTV
A1: Everything we could sell, and what one customer is worth with it
A2: Cross-sell: take rate x ticket x yearly take-up per ACTIVE saver (take-up is the researchers' estimate; research/xs_*.csv). LTV: model/ltv.py, per customer won, 5 years discounted; cross-sell from month 1, before selling costs; replaces the model's own lines.
A4: Cross-sell map (Rs per active saver a year)
A5: product | B5: group | C5: rs_per_active_saver_year_low | D5: mid | E5: high | F5: take_rate_mid | G5: verdict | H5: evidence
A6: Small personal loan, referral only | B6: loans | C6: 1.5 | D6: 15 | E6: 140 | F6: 2% of loan | G6: small | H6: XL-13, XL-41, XL-42, XL-29, XL-37, XL-45, XL-48
A7: Gold loan | B7: loans | C7: 1.5 | D7: 22.5 | E7: 180 | F7: 1% of loan | G7: small; safest loan to refer | H7: XL-17, XL-29, XL-32, XL-52
A8: Business or property loan | B8: loans | C8: 2.5 | D8: 30 | E8: 150 | F8: 2% of loan | G8: small; shopkeepers only | H8: XL-14, XL-16, XL-43, XL-53
A9: Credit card backed by an FD | B9: loans | C9: 1.5 | D9: 15 | E9: 75 | F9: Rs 750 per card (assumed) | G9: small; fits the story | H9: XL-20, XL-40, XL-54
A10: Home loan (affordable housing) | B10: loans | C10: 1.2 | D10: 11 | E10: 75 | F10: 0.5% of loan | G10: small: big fee, very rare | H10: XL-15, XL-24..XL-27, XL-30, XL-51
A11: Auto-rickshaw or used-car loan | B11: loans | C11: 0.75 | D11: 9 | E11: 120 | F11: 1% of loan | G11: small | H11: XL-18, XL-44, XL-54
A12: Phone / consumer-durable EMI | B12: loans | C12: 0.5 | D12: 8 | E12: 45 | F12: 2% of loan (assumed) | G12: small; sold at the shop | H12: XL-29, XL-35, XL-54
A13: Two-wheeler loan incl. EV | B13: loans | C13: 0.7 | D13: 4.7 | E13: 48 | F13: 1% of loan | G13: small; most riders own a bike | H13: XL-19, XL-21..XL-23, XL-31, XL-36, XL-50
A14: Microfinance group loans | B14: loans | F14: no data | G14: needs field staff | H14: XL-33, XL-34
A15: Personal loan we guarantee (before defaults) | B15: loans (excluded from total) | C15: 6.8 | D15: 37.5 | E15: 351 | F15: 5% of loan, minus defaults | G15: not advised: we carry defaults | H15: XL-02, XL-07, XL-10, XL-11, XL-49
A16: Mobile recharge | B16: other | C16: 2.6 | D16: 13 | E16: 39 | F16: 2% of recharge | G16: small; others do it free | H16: XO-25, XO-33
A17: Bill payments | B17: other | C17: 1.2 | D17: 12 | E17: 54 | F17: Rs 2 per bill | G17: small | H17: XO-26
A18: Term life (small cover) | B18: other | C18: 0.4 | D18: 7.5 | E18: 36 | F18: 25% of year-1 premium | G18: small; caps proposed | H18: XO-20, XO-32
A19: Accident or hospital-cash cover | B19: other | C19: 0.6 | D19: 7.2 | E19: 45 | F19: 15% of premium | G19: small | H19: XO-19, XO-09, XO-10, XO-30, XO-35, XO-31
A20: Two-wheeler insurance | B20: other | C20: 0.9 | D20: 7.1 | E20: 33.2 | F20: 4.75% blended | G20: small | H20: XO-18, XO-21, XO-22
A21: NPS / NPS Lite | B21: other | C21: 0.3 | D21: 6 | E21: 10 | F21: Rs 200 once | G21: small; money locked to 60 | H21: XO-16, XO-17
A22: Choti SIP incentive (Rs 250 SIP) | B22: other | C22: 1.7 | D22: 5.6 | E22: 18 | F22: Rs 500 once, after 24 months | G22: small; equity only | H22: XO-01..XO-04
A23: Equity SIP trail | B23: other | C23: 0.4 | D23: 2.3 | E23: 10.8 | F23: 0.75% of balance a year | G23: small | H23: XO-05..XO-08
A24: Device insurance | B24: other | C24: 0.2 | D24: 2.3 | E24: 9.4 | F24: 15% (no published rate) | G24: small | H24: XO-34, XO-19
A25: PMJJBY / PMSBY | B25: other | C25: 0 | D25: 0 | E25: 1.5 | F25: Rs 30 once; Rs 0 online | G25: not reachable; offer free | H25: XO-12, XO-13, XO-23
A26: Atal Pension Yojana | B26: other | C26: 0 | D26: 0 | E26: 2.5 | F26: paid to banks only | G26: not reachable | H26: XO-14, XO-15
A27: Money transfer, account referral, e-Shram | B27: other | C27: 0 | D27: 0 | E27: 0 | F27: no data or nil | G27: not reachable | H27: XO-27, XO-28, XO-29
A28: TOTAL loans | B28: loans | C28: 10.15 | D28: 115.2 | E28: 833 | G28: sum of products; high = every product at its best at once (not plausible) | H28: XL-54, XO-39
A29: TOTAL other | B29: other | C29: 8.3 | D29: 63 | E29: 259.4 | G29: sum of products; high = every product at its best at once (not plausible) | H29: XL-54, XO-39
A30: TOTAL all cross-sell | B30: all | C30: 18.45 | D30: 178.2 | E30: 1092.4 | G30: vs gap of Rs 1,029 per active saver a year
A32: One customer, case by case (Rs per customer won)
A33: case | B33: cac | C33: savings_pv | D33: cross_sell_pv | E33: serve_pv | F33: ltv60 | G33: net60 | H33: payback_month
A34: plan_as_is | B34: 256.08192 | C34: 66.337271 | D34: 48.628363 | E34: 418.99663 | F34: -304.03099 | G34: -560.11291
A35: evidence_savings_only | B35: 474.6797 | C35: 49.059528 | D35: 0 | E35: 257.44119 | F35: -208.38166 | G35: -683.06136
A36: evidence_everything_mid | B36: 474.6797 | C36: 49.059528 | D36: 113.33024 | E36: 257.44119 | F36: -95.051421 | G36: -569.73112
A37: evidence_everything_best | B37: 474.6797 | C37: 49.059528 | D37: 694.73599 | E37: 257.44119 | F37: 486.35433 | G37: 11.674626 | H37: 32
A38: plan_everything_mid | B38: 256.08192 | C38: 66.337271 | D38: 114.1115 | E38: 418.99663 | F38: -238.54786 | G38: -494.62977
A39: evidence_model_lines | B39: 474.6797 | C39: 49.059528 | D39: 12.388925 | E39: 257.44119 | F39: -195.99273 | G39: -670.67244

Sheet Redesign - shopkeepers
A1: The redesign: shopkeepers
A2: model/redesign.py and redesign_deck.py: shopkeepers save into debt funds (no fee per debit); partner lenders make Rs 50k-2.5 lakh unsecured loans; we earn 1-3% minus clawback. Futures = Monte Carlo draws; 'pays back' = net value per customer won > 0 within 5 years.
A4: Inputs this version adds or changes
A5: input | B5: dist | C5: low | D5: mode | E5: high | F5: basis | G5: evidence
A6: wc_loans_year | B6: triangular | C6: 0.02 | D6: 0.08 | E6: 0.2 | F6: unsecured loans a year per active saver: ordinary fintech users ~3.6% take any product a year; riders 6% ever took a digital loan; Paytm's engaged device merchants at most ~20% a year; mode near the middle (geometric mean) | G6: XL-04, XL-37, TB-31, XB-06
A7: wc_ticket | B7: triangular | C7: 50000 | D7: 150000 | E7: 250000 | F7: Rs per loan: Paytm merchant loans averaged ~Rs 2.05 lakh; Bachatt lends up to Rs 5 lakh; founder's idea up to Rs 2 lakh; smaller shops borrow less | G7: XB-08, XB-10, founder
A8: wc_fee | B8: triangular | C8: 0.01 | D8: 0.02 | E8: 0.03 | F8: referral fee as a share of the loan: lead-based sourcing pays 1-3%; Paisabazaar earns at most 4.6% incl. cards | G8: XL-13, XL-41, XL-42, XL-45, XL-09
A9: wc_clawback | B9: triangular | C9: 0 | D9: 0.025 | E9: 0.05 | F9: share of fees clawed back on early defaults: merchant-loan ECL 4.5-5% (lenders' books) | G9: XB-07, XL-13, XL-21, XL-47
A10: fund_trail | B10: triangular | C10: 0.002 | D10: 0.003 | E10: 0.005 | F10: distributor trail on debt funds, regular minus direct plan | G10: XB-04
A11: incentive_share | B11: uniform | C11: 0 | D11: 0.25 | E11: 0.5 | F11: share of savers who are new B30 or women investors in eligible (non-liquid, non-low-duration) funds | G11: XB-05
A12: xs_other | B12: lognormal | C12: 14 | D12: 105.9623 | E12: 802 | F12: everything else per active saver a year (insurance, funds, pension, bills, recharge, gold/home/vehicle/phone loans, FD card): the cross-sell map without personal and business loans; P5 = all low, P95 = all at their best | G12: crosssell_map.csv
A14: Each step: share of futures that pay back
A15: case | B15: p_net_pos | C15: net_p50 | D15: p_payback_le_36
A16: loans only while saving | B16: 0.13175 | C16: -350.8725 | D16: 0.1375
A17: proven savers keep borrowing | B17: 0.202 | C17: -277.89108 | D17: 0.20425
A18: proven savers keep borrowing, take-up 20% | B18: 0.428 | C18: -69.071785 | D18: 0.4345
A19: proven savers keep borrowing, cost to win at most Rs 250 | B19: 0.442 | C19: -30.014055 | D19: 0.44575
A20: proven savers keep borrowing, take-up 20%, cost to win at most Rs 250 | B20: 0.813 | C20: 196.62433 | D20: 0.8225
A22: Grid: fixed cost to win x fixed loans a year per proven saver
A23: cac | B23: loans_year | C23: p_net_pos | D23: net_p50
A24: 150 | B24: 0.05 | C24: 0.362 | D24: -44.192313
A25: 150 | B25: 0.1 | C25: 0.6805 | D25: 67.218269
A26: 150 | B26: 0.2 | C26: 0.933 | D26: 279.74028
A27: 150 | B27: 0.3 | C27: 0.987 | D27: 493.2465
A28: 250 | B28: 0.05 | C28: 0.1975 | D28: -144.19231
A29: 250 | B29: 0.1 | C29: 0.4195 | D29: -32.781731
A30: 250 | B30: 0.2 | C30: 0.802 | D30: 179.74028
A31: 250 | B31: 0.3 | C31: 0.9285 | D31: 393.2465
A32: 400 | B32: 0.05 | C32: 0.0965 | D32: -294.19231
A33: 400 | B33: 0.1 | C33: 0.187 | D33: -182.78173
A34: 400 | B34: 0.2 | C34: 0.5555 | D34: 29.740278
A35: 400 | B35: 0.3 | C35: 0.791 | D35: 243.2465
... A39: 500 | B39: 0.3 | C39: 0.6765 | D39: 143.2465
A41: Target case and today's evidence (Rs per customer won, 5 years discounted)
A42: item | B42: value
A43: target_cac | B43: 250
A44: target_savings | B44: 30.621873
A45: target_loans | B45: 436.60188
A46: target_other | B46: 73.672531
A47: target_serve | B47: 111.15282
A48: target_net | B48: 179.74347
A49: target_payback | B49: 21
A50: target_loans_per_customer | B50: 0.23321337
A51: one_loan | B51: 2818.5093
A52: loan_ticket_mid | B52: 150000
