Workbook
Name in_signups_run: 'Inputs'!$C$3
Name in_ramp_months: 'Inputs'!$C$4
Name in_r3: 'Inputs'!$C$6
Name in_r12: 'Inputs'!$C$7
Name in_churn_late: 'Inputs'!$C$8
Name in_daily: 'Inputs'!$C$10
Name in_days: 'Inputs'!$C$11
Name in_amount_growth: 'Inputs'!$C$12
Name in_term: 'Inputs'!$C$14
Name in_rollover: 'Inputs'!$C$15
Name in_withdraw_m: 'Inputs'!$C$16
Name in_trail: 'Inputs'!$C$17
Name in_fund_return: 'Inputs'!$C$18
Name in_early_takeup_mult: 'Inputs'!$C$20
Name in_early_approval_mult: 'Inputs'!$C$21
Name in_signup_growth: 'Inputs'!$C$23
Name in_takeup_growth: 'Inputs'!$C$24
Name in_approval_growth: 'Inputs'!$C$25
Name in_ticket_growth: 'Inputs'!$C$26
Name in_topup_share: 'Inputs'!$C$27
Name in_topup_size: 'Inputs'!$C$28
Name in_upi_12: 'Inputs'!$C$30
Name in_upi_ramp: 'Inputs'!$C$31
Name in_visit_every: 'Inputs'!$C$32
Name in_capacity: 'Inputs'!$C$33
Name in_extra_capacity_cost: 'Inputs'!$C$34
Name in_apply: 'Inputs'!$C$36
Name in_eligible: 'Inputs'!$C$37
Name in_approved_first: 'Inputs'!$C$38
Name in_approved_repeat: 'Inputs'!$C$39
Name in_tenure: 'Inputs'!$C$40
Name in_ticket: 'Inputs'!$C$41
Name in_fee: 'Inputs'!$C$42
Name in_taken_back: 'Inputs'!$C$43
Name in_rate: 'Inputs'!$C$44
Name in_loss: 'Inputs'!$C$45
Name in_leaver_loan: 'Inputs'!$C$46
Name in_owed: 'Inputs'!$C$48
Name in_recovered: 'Inputs'!$C$49
Name in_early_cured: 'Inputs'!$C$50
Name in_fee_early: 'Inputs'!$C$51
Name in_fee_b3: 'Inputs'!$C$52
Name in_card_share: 'Inputs'!$C$54
Name in_card_fee: 'Inputs'!$C$55
Name in_hlth_small_takeup: 'Inputs'!$C$57
Name in_hlth_small_ticket: 'Inputs'!$C$58
Name in_hlth_small_comm: 'Inputs'!$C$59
Name in_hlth_small_renew: 'Inputs'!$C$60
Name in_hlth_small_renew_comm: 'Inputs'!$C$61
Name in_hlth_family_takeup: 'Inputs'!$C$63
Name in_hlth_family_ticket: 'Inputs'!$C$64
Name in_hlth_family_comm: 'Inputs'!$C$65
Name in_hlth_family_renew: 'Inputs'!$C$66
Name in_hlth_family_renew_comm: 'Inputs'!$C$67
Name in_life_term_takeup: 'Inputs'!$C$69
Name in_life_term_ticket: 'Inputs'!$C$70
Name in_life_term_comm: 'Inputs'!$C$71
Name in_life_term_renew: 'Inputs'!$C$72
Name in_life_term_renew_comm: 'Inputs'!$C$73
Name in_accident_takeup: 'Inputs'!$C$75

Sheet Read me
A1: Cohort model: one street agent, 60 months, one cohort of sign-ups a month
A3: WHAT TO EDIT
A4: Only the BLUE cells on the Inputs sheet (column C, 'Likely'). Yellow-filled blue cells are operator decisions or open choices (still saving at month 12, the fund commission, card share, loan tenure, sign-ups). Low / High / Shape beside them are the Monte Carlo ranges, shown for reference; the formulas use only the Likely column. Every cell comment says where the number comes from.
A5: Example: to test 40 of 100 still saving at month 12, type 0.40 into 'Still saving at month 12'; the Summary NPVs move at once.
A6: Black = formulas. Green = a link to another sheet. Nothing else should be typed over.
A8: HOW THE SHEETS FLOW
A9: Inputs -> Retention curve (ages 1-60) -> Age profile (one sign-up's saving, fund, UPI and KYC lines by age) -> Sign-ups by age (which cohort is which age in each month) -> Cohort x age (the marketplace lines - loans, top-ups, cards, the 17 products and collections - one row per cohort and age, because take-up and approvals grow with the calendar year) -> Monthly (age-profile lines = SUMPRODUCT with Sign-ups by age; marketplace lines = SUMIFS of Cohort x age by calendar month; then salary, extra capacity, KYC, the P&L, the discount factor and NPV) -> Summary. Cohort triangle shows savers still saving by cohort and month.
A11: HOW IT IS BUILT (approximations, also in model/cohort_engine.py)
A12: Retention: drop-off at a steady monthly rate within months 1-3 (to r3), 4-12 (to r12), then churn_late. A saver who stops withdraws his whole balance. The balance builds over a 12-month term; at a term end the rollover share stays, the rest is paid out; a share is withdrawn mid-term each month.
A13: Marketplace: loans, cards and all 17 products are offered from month 1 (Inputs: first month a saver is offered; the operator, 16 Oct: 'the marketplace opens as soon as possible... It's not at our cost'). There is no marketplace cost line: costs are salary, extra capacity, KYC per sign-up and support (0).
A14: Loans: savers offered the marketplace (still saving) with no loan running apply at a monthly hazard; first loans use the first-loan approval, repeat loans the repeat approval. A borrower is out of the applicant pool while his loan runs (tenure rounded to whole months) and returns, if still saving, the month after it ends. Churn does not depend on having a loan. A saver who stops keeps paying, gets no repeat.
A15: Overdue loans: p90 = loss / (owed x (1 - recovered)) is the share of loans that ever go 90+ days bad. Fees per loan made = early_cured x fee_early, paid ~9 months after the loan, plus p90 x recovered x fee_b3, paid ~18 months after; fees due after month 60 are not counted. The lender carries the loss itself. Insurance commissions sit at the IRDAI draft distributor caps.
... A28: Inputs not yet in dist_agreed_v1.csv (taken from COHORT_INPUTS and its addenda): 3 keys, e.g. nps_comm, recharge_renew, bills_renew.

Sheet Summary
A1: One street agent, 60 months: cumulative P&L at the likely values (undiscounted)
A2: Every number in this first block is a formula on the other sheets; change a blue cell on Inputs and it moves. Built 2026-10-16 by model/build_cohort_xlsx.py.
A4: Measure | B4: Value | C4: Unit
A5: Cumulative P&L at 36 months | B5: =INDEX(Monthly!BH2:BH61,36) | C5: Rs, undiscounted (operator, round 5)
A6: Cumulative P&L at 60 months | B6: =INDEX(Monthly!BH2:BH61,60) | C6: Rs, undiscounted
A7: Payback month (cumulative P&L turns positive) | B7: =IF(MIN(Monthly!BJ2:BJ61)>60,"never within 60 months",MIN(Monthly!BJ2:BJ61)) | C7: month (and stays positive)
A8: Peak cash need (lowest cumulative P&L) | B8: =MIN(0,MIN(Monthly!BH2:BH61)) | C8: Rs (negative: the cash needed is its size)
A9: NPV (legacy, 20% discount): NPV at 36 months | B9: =SUMPRODUCT(Monthly!BD2:BD37,Monthly!BK2:BK37) | C9: Rs, reference only
A10: NPV (legacy, 20% discount): NPV at 60 months | B10: =SUMPRODUCT(Monthly!BD2:BD61,Monthly!BK2:BK61) | C10: Rs, reference only
A11: Our fees on home loans and LAP in 60 months | B11: =SUM(Monthly!AT2:AT61)+SUM(Monthly!AU2:AU61) | C11: Rs
A12: Agent pay on balance, 60 months | B12: =SUM(Monthly!BB2:BB61) | C12: Rs (0.25% a year of his savers' balance)
A13: Value per sign-up, his first 5 years, discounted to his sign-up month (a month-1 sign-up) | B13: =SUM('Age profile'!U2:U61)+SUMPRODUCT('Cohort x age'!CE2:CE61,'Age profile'!T2:T61)/INDEX(Monthly!B2:B61,1) | C13: Rs (before the agent's salary)
A14: Agent's salary per sign-up (for comparison) | B14: =in_salary/in_signups_run | C14: Rs
A15: Year-1 P&L (months 1-12) | B15: =SUM(Monthly!BD2:BD13) | C15: Rs
A16: Cumulative cash at month 60 | B16: =INDEX(Monthly!BH2:BH61,60) | C16: Rs
A17: Savers still saving at month 60 | B17: =INDEX(Monthly!C2:C61,60) | C17: savers
A18: Peak cash visits a day | B18: =MAX(Monthly!G2:G61) | C18: visits a day
A19: Share of savers on UPI at month 60 | B19: =INDEX(Monthly!H2:H61,60) | C19: share
A20: UPI share needed at month 60 to stay within one agent's visits | B20: =INDEX(Monthly!I2:I61,60) | C20: share
A21: Extra capacity cost in month 60 | B21: =INDEX(Monthly!AX2:AX61,60) | C21: Rs a month
A22: Extra capacity cost, 60 months, not discounted | B22: =SUM(Monthly!AX2:AX61) | C22: Rs
A23: Extra capacity cost, 60 months, discounted | B23: =SUMPRODUCT(Monthly!AX2:AX61,Monthly!BE2:BE61) | C23: Rs
A24: Loans per 100 savers offered the marketplace, a year (first + repeat) | B24: =100*SUM(Monthly!O2:O61)/(SUM(Monthly!E2:E61)/12) | C24: loans
A25: Loans made in 60 months | B25: =SUM(Monthly!O2:O61) | C25: loans
A26: Implied share of loans that ever go 90+ days bad (p90) | B26: =d_p90 | C26: CRIF NG-015 10.2%; MAC-03 3.6%
A27: Early brought back + p90 | B27: =d_check | C27: page check: at most 50%
A28: Page check | B28: =d_check_flag
A29: 31-90 day collection fees per loan made | B29: =d_dpd | C29: Rs a loan, paid ~9 months after the loan
A30: 90+ recovery fees per loan made | B30: =d_rec | C30: Rs a loan, paid ~18 months after the loan
A31: Cross-sell money per saver offered the marketplace, a year, all 17 products (old: Rs 63) | B31: =(SUM(Monthly!AC2:AC61)+SUM(Monthly!AD2:AD61)+SUM(Monthly!AE2:AE61)+SUM(Monthly!AF2:AF61)+SUM(Monthly!AG2:AG61)+SUM(Monthly!AH2:AH61)+SUM(Monthly!AI2:AI61)+SUM(Monthly!AJ2:AJ61)+SUM(Monthly!AK2:AK61)+SUM(Monthly!AL2:AL61)+SUM(Monthly!AM2:AM61)+SUM(Monthly!AN2:AN61)+SUM(Monthly!AO2:AO61)+SUM(Monthly!AP2:AP61)+SUM(Monthly!AQ2:AQ61)+SUM(Monthly!AR2:AR61)+SUM(Monthly!AS2:AS61)+SUM(Monthly!AT2:AT61)+SUM(Monthly!AU2:AU61))/(SUM(Monthly!E2:E61)/12) | C31: Rs a saver offered, a year (60-month book)
A32: Small health / hospital cash | B32: =SUM(Monthly!AC2:AC61)/(SUM(Monthly!E2:E61)/12) | C32: Rs a saver offered, a year
A33: Family health cover | B33: =SUM(Monthly!AD2:AD61)/(SUM(Monthly!E2:E61)/12) | C33: Rs a saver offered, a year
A34: Term life (small cover) | B34: =SUM(Monthly!AE2:AE61)/(SUM(Monthly!E2:E61)/12) | C34: Rs a saver offered, a year
A35: Personal accident | B35: =SUM(Monthly!AF2:AF61)/(SUM(Monthly!E2:E61)/12) | C35: Rs a saver offered, a year
A36: Two-wheeler insurance | B36: =SUM(Monthly!AG2:AG61)/(SUM(Monthly!E2:E61)/12) | C36: Rs a saver offered, a year
A37: Mobile / device insurance | B37: =SUM(Monthly!AH2:AH61)/(SUM(Monthly!E2:E61)/12) | C37: Rs a saver offered, a year
A38: Shop insurance (fire and burglary) | B38: =SUM(Monthly!AI2:AI61)/(SUM(Monthly!E2:E61)/12) | C38: Rs a saver offered, a year
A39: Equity/hybrid SIP trail | B39: =SUM(Monthly!AJ2:AJ61)/(SUM(Monthly!E2:E61)/12) | C39: Rs a saver offered, a year
A40: Choti SIP incentive | B40: =SUM(Monthly!AK2:AK61)/(SUM(Monthly!E2:E61)/12) | C40: Rs a saver offered, a year
A41: NPS | B41: =SUM(Monthly!AL2:AL61)/(SUM(Monthly!E2:E61)/12) | C41: Rs a saver offered, a year
A42: Digital gold | B42: =SUM(Monthly!AM2:AM61)/(SUM(Monthly!E2:E61)/12) | C42: Rs a saver offered, a year
A43: FD via partner banks | B43: =SUM(Monthly!AN2:AN61)/(SUM(Monthly!E2:E61)/12) | C43: Rs a saver offered, a year
A44: Mobile recharge | B44: =SUM(Monthly!AO2:AO61)/(SUM(Monthly!E2:E61)/12) | C44: Rs a saver offered, a year
A45: Bill payments | B45: =SUM(Monthly!AP2:AP61)/(SUM(Monthly!E2:E61)/12) | C45: Rs a saver offered, a year
A46: Gold loan (other lenders) | B46: =SUM(Monthly!AQ2:AQ61)/(SUM(Monthly!E2:E61)/12) | C46: Rs a saver offered, a year
A47: Consumer-durable loan | B47: =SUM(Monthly!AR2:AR61)/(SUM(Monthly!E2:E61)/12) | C47: Rs a saver offered, a year
A48: Two-wheeler / e-rickshaw loan | B48: =SUM(Monthly!AS2:AS61)/(SUM(Monthly!E2:E61)/12) | C48: Rs a saver offered, a year
A49: Home loan (affordable housing) | B49: =SUM(Monthly!AT2:AT61)/(SUM(Monthly!E2:E61)/12) | C49: Rs a saver offered, a year
A50: Loan against property (shop or home) | B50: =SUM(Monthly!AU2:AU61)/(SUM(Monthly!E2:E61)/12) | C50: Rs a saver offered, a year
A51: All-in revenue per active saver a year, 60-month average | B51: =SUM(Monthly!AV2:AV61)/(SUM(Monthly!C2:C61)/12) | C51: Rs (fund + loans + cards + products + collections)
A52: All-in revenue per active saver a year, month-60 run rate | B52: =12*INDEX(Monthly!AV2:AV61,60)/INDEX(Monthly!C2:C61,60) | C52: Rs
A53: Top-ups per 100 borrowers a year (still saving, loan running) | B53: =100*SUM(Monthly!P2:P61)/(SUM(Monthly!S2:S61)/12) | C53: top-ups
A54: Money lent in 60 months (first, repeat and top-up loans) | B54: =SUM(Monthly!R2:R61) | C54: Rs
A55: Cards issued in 60 months | B55: =SUM(Monthly!W2:W61) | C55: cards
A56: money lent in year 1 | B56: =SUM(Monthly!R2:R13) | C56: Rs
A57: money lent in year 2 | B57: =SUM(Monthly!R14:R25) | C57: Rs
A58: money lent in year 3 | B58: =SUM(Monthly!R26:R37) | C58: Rs
A59: money lent in year 4 | B59: =SUM(Monthly!R38:R49) | C59: Rs
A60: money lent in year 5 | B60: =SUM(Monthly!R50:R61) | C60: Rs
A61: average ticket of first and repeat loans, year 1 | B61: =IF(SUM(Monthly!O2:O13)>0,SUM(Monthly!Q2:Q13)/SUM(Monthly!O2:O13),0) | C61: Rs
A62: average ticket of first and repeat loans, year 2 | B62: =IF(SUM(Monthly!O14:O25)>0,SUM(Monthly!Q14:Q25)/SUM(Monthly!O14:O25),0) | C62: Rs
A63: average ticket of first and repeat loans, year 3 | B63: =IF(SUM(Monthly!O26:O37)>0,SUM(Monthly!Q26:Q37)/SUM(Monthly!O26:O37),0) | C63: Rs
A64: average ticket of first and repeat loans, year 4 | B64: =IF(SUM(Monthly!O38:O49)>0,SUM(Monthly!Q38:Q49)/SUM(Monthly!O38:O49),0) | C64: Rs
A65: average ticket of first and repeat loans, year 5 | B65: =IF(SUM(Monthly!O50:O61)>0,SUM(Monthly!Q50:Q61)/SUM(Monthly!O50:O61),0) | C65: Rs
A66: Income, 60 months, discounted | B66: =SUMPRODUCT(Monthly!AV2:AV61,Monthly!BE2:BE61) | C66: Rs
A67: Costs, 60 months, discounted | B67: =SUMPRODUCT(Monthly!BC2:BC61,Monthly!BE2:BE61) | C67: Rs
A70: Monte Carlo results (pasted from model/cohort_mc.py, 10,000 draws, 16 Oct 2026)
A71: VALUES ONLY: these do not recalculate when you change Inputs. Re-run model/cohort_mc.py, then this builder, to refresh them. seed 20261016; Latin hypercube sampling; correlation ON (bad years linked, rho -0.5, agreed); 33 r3/r12 pairs redrawn to keep r12 < r3
A73: Measure | B73: p5 | C73: p10 | D73: p25 | E73: p50 | F73: p75 | G73: p90 | H73: p95 | I73: mean | J73: value | K73: unit
A74: Cumulative P&L at 36 months | B74: -576520.46 | C74: -542585.76 | D74: -475338.08 | E74: -382577.5 | F74: -269235.84 | G74: -143777.91 | H74: -59721.951 | I74: -358944.17 | K74: Rs, undiscounted
A75: Cumulative P&L at 60 months | B75: -543603.23 | C75: -422901.45 | D75: -193178.87 | E75: 138148.46 | F75: 557789.1 | G75: 1017688.4 | H75: 1328446.3 | I75: 235614.1 | K75: Rs, undiscounted
A76: P(cumulative P&L at 36 months > 0) | J76: 0.0301 | K76: share of draws
A77: P(cumulative P&L at 60 months > 0) | J77: 0.6054 | K77: share of draws
A78: Payback month (cumulative P&L turns positive) | C78: 41 | E78: 56 | G78: never within 60 months | K78: month
A79: Peak cash need (lowest cumulative P&L) | B79: -612116.62 | C79: -554558.61 | D79: -475693.89 | E79: -397851.04 | F79: -340069.99 | G79: -293213.95 | H79: -266934.45 | I79: -414506.25 | K79: Rs
A80: Year-1 P&L | B80: -259517.53 | C80: -255907.27 | D80: -249319.5 | E80: -242034.03 | F80: -233998.7 | G80: -225110.26 | H80: -219339.02 | I80: -241093.51 | K80: Rs
A81: Share of draws that never pay back within 60 months | J81: 0.3946 | K81: share of draws
A82: NPV (legacy, 20% discount): NPV at 36 months | B82: -460462.01 | C82: -437517.59 | D82: -391808.84 | E82: -328903.5 | F82: -252241.45 | G82: -166900.53 | H82: -109157.04 | I82: -312862.6 | K82: Rs
A83: NPV (legacy, 20% discount): NPV at 60 months | B83: -449694.46 | C83: -384898.25 | D83: -264096.53 | E83: -88652.2 | F83: 132881.6 | G83: 373356.12 | H83: 535380.13 | I83: -38077.776 | K83: Rs
A84: Value per sign-up, his first 5 years (undiscounted) | B84: 899.48018 | C84: 1007.5065 | D84: 1217.3621 | E84: 1491.6674 | F84: 1806.1605 | G84: 2150.6159 | H84: 2368.2176 | I84: 1543.62 | K84: Rs
A85: Home loans and LAP made per agent in 60 months | B85: 16.442516 | C85: 18.991131 | D85: 23.917245 | E85: 30.605579 | F85: 38.7164 | G85: 47.457935 | H85: 52.978221 | I85: 32.136905 | K85: loans
A86: Home-loan and LAP money per agent in 60 months | B86: 32645199 | C86: 38980778 | D86: 51965398 | E86: 70730404 | F86: 95595852 | G86: 1.2289045e+08 | H86: 1.413344e+08 | I86: 76930579 | K86: Rs
A87: Our fees on home loans and LAP per agent in 60 months | B87: 202522.41 | C87: 240175.39 | D87: 319577.77 | E87: 438535.96 | F87: 597577.73 | G87: 774230.93 | H87: 907400.94 | I87: 481413.27 | K87: Rs
A88: Agent pay on balance per agent in 60 months | B88: 193297.73 | C88: 216030.36 | D88: 264406.59 | E88: 327218.62 | F88: 403946.48 | G88: 486991.89 | H88: 540229.7 | I88: 341734.59 | K88: Rs
A89: Agent pay on balance in month 60 | B89: 6651.7176 | C89: 7518.1257 | D89: 9291.7849 | E89: 11745.575 | F89: 14780.46 | G89: 18086.269 | H89: 20234.837 | I89: 12371.765 | K89: Rs a month
A90: Loans per 100 savers offered the marketplace, a year (first + repeat) | B90: 1.8490102 | C90: 2.136459 | D90: 2.7609511 | E90: 3.6149638 | F90: 4.6913486 | G90: 5.8126156 | H90: 6.5803157 | I90: 3.8283351 | K90: loans
A91: First loans per 100 savers offered the marketplace, a year | B91: 1.8453933 | C91: 2.1327275 | D91: 2.754887 | E91: 3.6055294 | F91: 4.6817249 | G91: 5.7960226 | H91: 6.5571099 | I91: 3.8180835 | K91: loans
A92: Repeat loans as a share of all loans (60 months) | B92: 0.00036166251 | C92: 0.00051792559 | D92: 0.00095573078 | E92: 0.0018591715 | F92: 0.0032553397 | G92: 0.005078969 | H92: 0.0062823638 | I92: 0.00240854 | K92: share
A93: UPI share needed at month 60 to stay within one agent's cash visits | B93: 0 | C93: 0 | D93: 0 | E93: 0.055546978 | F93: 0.19806667 | G93: 0.29978556 | H93: 0.35740037 | I93: 0.10772019 | K93: share
... A95: Peak cash visits a day | B95: 203.83074 | C95: 221.69365 | D95: 257.05259 | E95: 303.61446 | F95: 356.93691 | G95: 406.47822 | H95: 441.09462 | I95: 310.47874 | K95: visits a day
A96: Share of draws that need extra cash-collection capacity | J96: 0.1778 | K96: share of draws
A97: Extra capacity cost in month 60 | B97: 0 | C97: 0 | D97: 0 | E97: 0 | F97: 0 | G97: 1705.5571 | H97: 3431.2895 | I97: 469.89947 | K97: Rs a month
A98: Extra capacity cost, 60 months, discounted | B98: 0 | C98: 0 | D98: 0 | E98: 0 | F98: 0 | G98: 6103.6022 | H98: 20041.382 | I98: 3224.9769 | K98: Rs
A99: Cross-sell money per saver offered the marketplace, a year, all 17 products | B99: 211.24277 | C99: 228.27157 | D99: 259.71759 | E99: 305.20831 | F99: 358.11994 | G99: 418.24261 | H99: 458.85609 | I99: 315.98793 | K99: Rs
A100: 31-90 day collection fees per loan made | B100: 50.082659 | C100: 58.605379 | D100: 74.768831 | E100: 98.874265 | F100: 128.18604 | G100: 157.93335 | H100: 176.1525 | I100: 104.21694 | K100: Rs a loan
A101: 90+ recovery fees per loan made | B101: 44.776714 | C101: 52.594104 | D101: 68.111535 | E101: 90.723147 | F101: 117.89074 | G101: 146.82785 | H101: 165.80611 | I101: 96.050747 | K101: Rs a loan
A102: Implied share of loans that ever go 90+ days bad (p90) | B102: 0.063863921 | C102: 0.069823808 | D102: 0.08150646 | E102: 0.096781297 | F102: 0.11315243 | G102: 0.12703656 | H102: 0.13446644 | I102: 0.09769166 | K102: share of loans
A103: Early brought back + p90 | B103: 0.22558663 | C103: 0.24042683 | D103: 0.26845401 | E103: 0.30423228 | F103: 0.34191308 | G103: 0.37497731 | H103: 0.39478884 | I103: 0.30602468 | K103: share of loans
A104: Share of draws where early brought back + p90 is above 50% | J104: 0 | K104: share of draws
A105: Collection fees in the pilot year | B105: 2.8196944 | C105: 3.6228368 | D105: 5.3192261 | E105: 8.1053808 | F105: 12.323199 | G105: 17.667614 | H105: 21.545546 | I105: 9.6739407 | K105: Rs
...

Sheet Inputs
A1: Group | B1: Input | C1: Likely (edit me) | D1: Low | E1: High | F1: Shape | G1: Unit | H1: Key | I1: Where the number comes from
A2: Sign-ups
B3: Sign-ups a month once up to speed | C3: 30 | D3: 20 | E3: 45 | F3: pert | G3: sign-ups a month | H3: signups_run | I3: dist_agreed_v1.csv
B4: Months for a new agent to reach full speed | C4: 3 | D4: 0 | E4: 6 | F4: triangular | G4: months | H4: ramp_months | I4: dist_agreed_v1.csv
A5: Retention
B6: Still saving at month 3 | C6: 0.8 | D6: 0.6 | E6: 0.92 | F6: pert | G6: share | H6: r3 | I6: dist_agreed_v1.csv
B7: Still saving at month 12 | C7: 0.55 | D7: 0.25 | E7: 0.72 | F7: pert | G7: share | H7: r12 | I7: dist_agreed_v1.csv (file matches the operator decision)
B8: Monthly drop-off after month 12 | C8: 0.015 | D8: 0.01 | E8: 0.03 | F8: pert | G8: share | H8: churn_late | I8: dist_agreed_v1.csv
A9: Saving
B10: Daily amount at sign-up (Rs) | C10: 350 | D10: 200 | E10: 500 | F10: triangular | G10: Rs a day | H10: daily | I10: dist_agreed_v1.csv
B11: Deposit days a month | C11: 20 | D11: 16 | E11: 24 | F11: pert | G11: days a month | H11: days | I11: dist_agreed_v1.csv
B12: Growth in his daily amount per year saved | C12: 0.05 | D12: 0 | E12: 0.1 | F12: pert | G12: share | H12: amount_growth | I12: dist_agreed_v1.csv
A13: The fund
B14: Savings term (months) | C14: 12 | D14: 12 | E14: 12 | F14: fixed | G14: months | H14: term | I14: dist_agreed_v1.csv
B15: Share of the balance left in the fund at each term end | C15: 0.25 | D15: 0 | E15: 0.6 | F15: pert | G15: share | H15: rollover | I15: dist_agreed_v1.csv
B16: Share of the balance withdrawn mid-term, each month | C16: 0.01 | D16: 0 | E16: 0.03 | F16: pert | G16: share | H16: withdraw_m | I16: dist_agreed_v1.csv
B17: Fund commission a year (debt fund) | C17: 0.0035 | D17: 0.002 | E17: 0.005 | F17: pert | G17: share | H17: trail | I17: dist_agreed_v1.csv (file matches the operator decision)
B18: Saver's net return on the fund, a year | C18: 0.07 | D18: 0.06 | E18: 0.075 | F18: pert | G18: share | H18: fund_return | I18: dist_agreed_v1.csv
A19: Early months (a saver's months 1-6)
B20: Take-up factor in a saver's months 1-6 | C20: 0.5 | D20: 0.25 | E20: 0.75 | F20: pert | G20: share | H20: early_takeup_mult | I20: dist_agreed_v1.csv
B21: Approval factor in a saver's months 1-6 (first loans, cards) | C21: 0.6 | D21: 0.4 | E21: 0.8 | F21: pert | G21: share | H21: early_approval_mult | I21: dist_agreed_v1.csv
A22: Growth with the pool's history (addendum 4)
B23: Sign-ups grow each year from year 2 (cap 100 a month) | C23: 0.1 | D23: 0 | E23: 0.2 | F23: pert | G23: share | H23: signup_growth | I23: dist_agreed_v1.csv
B24: Every take-up rises each calendar year with the pool's history (cap 2x) | C24: 0.05 | D24: 0 | E24: 0.15 | F24: pert | G24: share | H24: takeup_growth | I24: dist_agreed_v1.csv
B25: First-loan and card approval rise each calendar year (cap 80% absolute) | C25: 0.1 | D25: 0 | E25: 0.2 | F25: pert | G25: share | H25: approval_growth | I25: dist_agreed_v1.csv
B26: Next loan bigger for each year repaid (cap Rs 5 lakh) | C26: 0.1 | D26: 0 | E26: 0.2 | F26: pert | G26: share | H26: ticket_growth | I26: dist_agreed_v1.csv
B27: Borrowers with 12+ EMIs paid who take a top-up, a year | C27: 0.15 | D27: 0.05 | E27: 0.3 | F27: pert | G27: share | H27: topup_share | I27: dist_agreed_v1.csv
B28: Top-up size, share of his original ticket | C28: 0.4 | D28: 0.25 | E28: 0.6 | F28: pert | G28: share | H28: topup_size | I28: dist_agreed_v1.csv
A29: UPI and cash visits
B30: Share of active savers on UPI by month 12 | C30: 0.3 | D30: 0.1 | E30: 0.6 | F30: pert | G30: share | H30: upi_12 | I30: dist_agreed_v1.csv
B31: Age at which the UPI share reaches its month-12 level | C31: 12 | D31: 12 | E31: 12 | F31: fixed | G31: age (months) | H31: upi_ramp | I31: dist_agreed_v1.csv
B32: Days between cash visits | C32: 2.5 | D32: 2.5 | E32: 2.5 | F32: fixed | G32: days | H32: visit_every | I32: dist_agreed_v1.csv
B33: Cash visits one agent can make a day | C33: 400 | D33: 300 | E33: 450 | F33: triangular | G33: visits a day | H33: capacity | I33: dist_agreed_v1.csv
B34: Extra capacity cost a month per 400 visits a day (Rs) | C34: 20000 | D34: 20000 | E34: 20000 | F34: fixed | G34: Rs a month | H34: extra_capacity_cost | I34: dist_agreed_v1.csv
A35: Loans
B36: Proven savers with no loan running who apply, a year | C36: 0.18 | D36: 0.08 | E36: 0.35 | F36: pert | G36: share a year | H36: apply | I36: dist_agreed_v1.csv
B37: Applicants eligible | C37: 0.45 | D37: 0.25 | E37: 0.65 | F37: pert | G37: share | H37: eligible | I37: dist_agreed_v1.csv
B38: Approved, first loan | C38: 0.35 | D38: 0.2 | E38: 0.5 | F38: pert | G38: share | H38: approved_first | I38: dist_agreed_v1.csv
B39: Approved, repeat loan | C39: 0.7 | D39: 0.5 | E39: 0.85 | F39: pert | G39: share | H39: approved_repeat | I39: dist_agreed_v1.csv
B40: Loan tenure (months) | C40: 36 | D40: 24 | E40: 48 | F40: pert | G40: months | H40: tenure | I40: dist_agreed_v1.csv (file matches the operator decision)
B41: Loan size (Rs) | C41: 250000 | D41: 25000 | E41: 500000 | F41: pert | G41: Rs | H41: ticket | I41: dist_agreed_v1.csv
B42: Origination fee | C42: 0.02625 | D42: 0.015 | E42: 0.035 | F42: pert | G42: share | H42: fee | I42: dist_agreed_v1.csv
B43: Fees taken back | C43: 0.025 | D43: 0 | E43: 0.05 | F43: triangular | G43: share | H43: taken_back | I43: dist_agreed_v1.csv
B44: Loan interest rate a year (EMI basis) | C44: 0.26 | D44: 0.26 | E44: 0.26 | F44: fixed | G44: share | H44: rate | I44: dist_agreed_v1.csv
B45: Money lost on loans, after recoveries | C45: 0.03 | D45: 0.015 | E45: 0.05 | F45: pert | G45: share | H45: loss | I45: dist_agreed_v1.csv
B46: A saver who stops keeps paying his loan (1 = yes) | C46: 1 | D46: 1 | E46: 1 | F46: fixed | G46: 1 = yes | H46: leaver_loan | I46: dist_agreed_v1.csv
A47: Overdue loans (per account)
B48: Share of the loan still owed when it goes 90+ days bad | C48: 0.5 | D48: 0.5 | E48: 0.5 | F48: fixed | G48: share | H48: owed | I48: dist_agreed_v1.csv
B49: Recovered after 90 days | C49: 0.35 | D49: 0.3 | E49: 0.5 | F49: pert | G49: share | H49: recovered | I49: dist_agreed_v1.csv
B50: Loans that fall 31-90 days behind and our agent brings back | C50: 0.2 | D50: 0.1 | E50: 0.35 | F50: pert | G50: share | H50: early_cured | I50: dist_agreed_v1.csv
B51: Our fee per early account brought back (Rs) | C51: 450 | D51: 200 | E51: 1000 | F51: pert | G51: Rs an account | H51: fee_early | I51: dist_agreed_v1.csv
B52: Our fee per 90+ account recovered (Rs) | C52: 2500 | D52: 1000 | E52: 5000 | F52: pert | G52: Rs an account | H52: fee_b3 | I52: dist_agreed_v1.csv
A53: Cards
B54: Savers reaching month 7 who get a card | C54: 0.03 | D54: 0.01 | E54: 0.06 | F54: pert | G54: share | H54: card_share | I54: dist_agreed_v1.csv (file matches the operator decision)
B55: Fee per card (Rs) | C55: 1000 | D55: 300 | E55: 2000 | F55: pert | G55: Rs a card | H55: card_fee | I55: dist_agreed_v1.csv
A56: Cross-sell: Small health / hospital cash
B57: Small health / hospital cash: take-up a year (savers offered who don't hold it) | C57: 0.06 | D57: 0.02 | E57: 0.15 | F57: pert | G57: share a year | H57: hlth_small_takeup | I57: dist_agreed_v1.csv
B58: Small health / hospital cash: ticket | C58: 800 | D58: 300 | E58: 1500 | F58: pert | G58: Rs | H58: hlth_small_ticket | I58: dist_agreed_v1.csv
B59: Small health / hospital cash: our commission | C59: 0.14 | D59: 0.1 | E59: 0.15 | F59: pert | G59: share | H59: hlth_small_comm | I59: dist_agreed_v1.csv
B60: Small health / hospital cash: renews / continues a year | C60: 0.5 | D60: 0.3 | E60: 0.7 | F60: pert | G60: share | H60: hlth_small_renew | I60: dist_agreed_v1.csv
B61: Small health / hospital cash: renewal commission | C61: 0.05 | D61: 0.05 | E61: 0.05 | F61: fixed | G61: share | H61: hlth_small_renew_comm | I61: dist_agreed_v1.csv
A62: Cross-sell: Family health cover
B63: Family health cover: take-up a year (savers offered who don't hold it) | C63: 0.02 | D63: 0.005 | E63: 0.05 | F63: pert | G63: share a year | H63: hlth_family_takeup | I63: dist_agreed_v1.csv
B64: Family health cover: ticket | C64: 8000 | D64: 5500 | E64: 15000 | F64: pert | G64: Rs | H64: hlth_family_ticket | I64: dist_agreed_v1.csv
B65: Family health cover: our commission | C65: 0.14 | D65: 0.1 | E65: 0.15 | F65: pert | G65: share | H65: hlth_family_comm | I65: dist_agreed_v1.csv
B66: Family health cover: renews / continues a year | C66: 0.75 | D66: 0.6 | E66: 0.89 | F66: pert | G66: share | H66: hlth_family_renew | I66: dist_agreed_v1.csv
B67: Family health cover: renewal commission | C67: 0.05 | D67: 0.05 | E67: 0.05 | F67: fixed | G67: share | H67: hlth_family_renew_comm | I67: dist_agreed_v1.csv
A68: Cross-sell: Term life (small cover)
B69: Term life (small cover): take-up a year (savers offered who don't hold it) | C69: 0.03 | D69: 0.01 | E69: 0.06 | F69: pert | G69: share a year | H69: life_term_takeup | I69: dist_agreed_v1.csv
B70: Term life (small cover): ticket | C70: 1000 | D70: 500 | E70: 2000 | F70: pert | G70: Rs | H70: life_term_ticket | I70: dist_agreed_v1.csv
B71: Term life (small cover): our commission | C71: 0.2 | D71: 0.075 | E71: 0.25 | F71: pert | G71: share | H71: life_term_comm | I71: dist_agreed_v1.csv
B72: Term life (small cover): renews / continues a year | C72: 0.75 | D72: 0.6 | E72: 0.85 | F72: pert | G72: share | H72: life_term_renew | I72: dist_agreed_v1.csv
B73: Term life (small cover): renewal commission | C73: 0.075 | D73: 0.075 | E73: 0.075 | F73: fixed | G73: share | H73: life_term_renew_comm | I73: dist_agreed_v1.csv
A74: Cross-sell: Personal accident
B75: Personal accident: take-up a year (savers offered who don't hold it) | C75: 0.05 | D75: 0.02 | E75: 0.1 | F75: pert | G75: share a year | H75: accident_takeup | I75: dist_agreed_v1.csv
B76: Personal accident: ticket | C76: 250 | D76: 100 | E76: 500 | F76: pert | G76: Rs | H76: accident_ticket | I76: dist_agreed_v1.csv
B77: Personal accident: our commission | C77: 0.14 | D77: 0.1 | E77: 0.15 | F77: pert | G77: share | H77: accident_comm | I77: dist_agreed_v1.csv
B78: Personal accident: renews / continues a year | C78: 0.5 | D78: 0.3 | E78: 0.7 | F78: pert | G78: share | H78: accident_renew | I78: dist_agreed_v1.csv
B79: Personal accident: renewal commission | C79: 0.05 | D79: 0.05 | E79: 0.05 | F79: fixed | G79: share | H79: accident_renew_comm | I79: dist_agreed_v1.csv
A80: Cross-sell: Two-wheeler insurance
B81: Two-wheeler insurance: take-up a year (savers offered who don't hold it) | C81: 0.15 | D81: 0.05 | E81: 0.3 | F81: pert | G81: share a year | H81: two_wheeler_takeup | I81: dist_agreed_v1.csv
B82: Two-wheeler insurance: ticket | C82: 1000 | D82: 714 | E82: 1200 | F82: pert | G82: Rs | H82: two_wheeler_ticket | I82: dist_agreed_v1.csv
B83: Two-wheeler insurance: our commission | C83: 0.0475 | D83: 0.025 | E83: 0.0905 | F83: pert | G83: share | H83: two_wheeler_comm | I83: dist_agreed_v1.csv
B84: Two-wheeler insurance: renews / continues a year | C84: 0.7 | D84: 0.5 | E84: 0.85 | F84: pert | G84: share | H84: two_wheeler_renew | I84: dist_agreed_v1.csv
A85: Cross-sell: Mobile / device insurance
B86: Mobile / device insurance: take-up a year (savers offered who don't hold it) | C86: 0.03 | D86: 0.01 | E86: 0.06 | F86: pert | G86: share a year | H86: device_takeup | I86: dist_agreed_v1.csv
B87: Mobile / device insurance: ticket | C87: 500 | D87: 209 | E87: 899 | F87: triangular | G87: Rs | H87: device_ticket | I87: dist_agreed_v1.csv
B88: Mobile / device insurance: our commission | C88: 0.13 | D88: 0.1 | E88: 0.15 | F88: pert | G88: share | H88: device_comm | I88: dist_agreed_v1.csv
A89: Cross-sell: Shop insurance (fire and burglary)
B90: Shop insurance (fire and burglary): take-up a year (savers offered who don't hold it) | C90: 0.03 | D90: 0.01 | E90: 0.08 | F90: pert | G90: share a year | H90: shop_takeup | I90: dist_agreed_v1.csv
B91: Shop insurance (fire and burglary): ticket | C91: 700 | D91: 250 | E91: 2600 | F91: pert | G91: Rs | H91: shop_ticket | I91: dist_agreed_v1.csv
B92: Shop insurance (fire and burglary): our commission | C92: 0.14 | D92: 0.1 | E92: 0.15 | F92: pert | G92: share | H92: shop_comm | I92: dist_agreed_v1.csv
B93: Shop insurance (fire and burglary): renews / continues a year | C93: 0.65 | D93: 0.5 | E93: 0.8 | F93: pert | G93: share | H93: shop_renew | I93: dist_agreed_v1.csv
B94: Shop insurance (fire and burglary): renewal commission | C94: 0.05 | D94: 0.05 | E94: 0.05 | F94: fixed | G94: share | H94: shop_renew_comm | I94: dist_agreed_v1.csv
A95: Cross-sell: Equity/hybrid SIP trail
B96: Equity/hybrid SIP trail: take-up a year (savers offered who don't hold it) | C96: 0.1 | D96: 0.05 | E96: 0.2 | F96: pert | G96: share a year | H96: sip_takeup | I96: dist_agreed_v1.csv
B97: Equity/hybrid SIP trail: SIP a month (Rs) | C97: 500 | D97: 250 | E97: 1000 | F97: pert | G97: Rs | H97: sip_ticket | I97: dist_agreed_v1.csv
B98: Equity/hybrid SIP trail: trail a year, of the SIP balance | C98: 0.0075 | D98: 0.005 | E98: 0.009 | F98: pert | G98: share | H98: sip_comm | I98: dist_agreed_v1.csv
B99: Equity/hybrid SIP trail: SIP survives a year | C99: 0.65 | D99: 0.5 | E99: 0.8 | F99: pert | G99: share | H99: sip_renew | I99: dist_agreed_v1.csv
A100: Cross-sell: Choti SIP incentive
...

Sheet Retention curve
A1: Age (month since sign-up) | B1: Monthly drop-off after this month | C1: Still saving (share of sign-ups) | D1: Stopped this month
A2: 1 | B2: =IF(A2<=3,d_h1,IF(A2<=12,d_h2,in_churn_late)) | C2: 1 | D2: 0
A3: 2 | B3: =IF(A3<=3,d_h1,IF(A3<=12,d_h2,in_churn_late)) | C3: =C2*(1-B2) | D3: =C2-C3
A4: 3 | B4: =IF(A4<=3,d_h1,IF(A4<=12,d_h2,in_churn_late)) | C4: =C3*(1-B3) | D4: =C3-C4
A5: 4 | B5: =IF(A5<=3,d_h1,IF(A5<=12,d_h2,in_churn_late)) | C5: =C4*(1-B4) | D5: =C4-C5
A6: 5 | B6: =IF(A6<=3,d_h1,IF(A6<=12,d_h2,in_churn_late)) | C6: =C5*(1-B5) | D6: =C5-C6
A7: 6 | B7: =IF(A7<=3,d_h1,IF(A7<=12,d_h2,in_churn_late)) | C7: =C6*(1-B6) | D7: =C6-C7
A8: 7 | B8: =IF(A8<=3,d_h1,IF(A8<=12,d_h2,in_churn_late)) | C8: =C7*(1-B7) | D8: =C7-C8
A9: 8 | B9: =IF(A9<=3,d_h1,IF(A9<=12,d_h2,in_churn_late)) | C9: =C8*(1-B8) | D9: =C8-C9
A10: 9 | B10: =IF(A10<=3,d_h1,IF(A10<=12,d_h2,in_churn_late)) | C10: =C9*(1-B9) | D10: =C9-C10
A11: 10 | B11: =IF(A11<=3,d_h1,IF(A11<=12,d_h2,in_churn_late)) | C11: =C10*(1-B10) | D11: =C10-C11
A12: 11 | B12: =IF(A12<=3,d_h1,IF(A12<=12,d_h2,in_churn_late)) | C12: =C11*(1-B11) | D12: =C11-C12
A13: 12 | B13: =IF(A13<=3,d_h1,IF(A13<=12,d_h2,in_churn_late)) | C13: =C12*(1-B12) | D13: =C12-C13
A14: 13 | B14: =IF(A14<=3,d_h1,IF(A14<=12,d_h2,in_churn_late)) | C14: =C13*(1-B13) | D14: =C13-C14
... A61: 60 | B61: =IF(A61<=3,d_h1,IF(A61<=12,d_h2,in_churn_late)) | C61: =C60*(1-B60) | D61: =C60-C61
A63: Months 1-3 drop at d_h1 (so month 4 = r3), months 4-12 at d_h2 (so month 13 = r12), then churn_late. 'Still saving at month m' = survived m monthly drop-offs (the v2 convention).

Sheet Age profile
A1: Age (month since sign-up) | B1: Still saving | C1: Stopped this month | D1: Deposit per active saver (Rs) | E1: Deposits (Rs) | F1: Balance at the month's start, per active saver (Rs) | G1: Balance at the month's end, per active saver, with his return (Rs) | H1: Average balance in the fund (Rs) | I1: Withdrawn this month (Rs) | J1: Share on UPI | K1: Cash savers | L1: Cash visits a day | M1: Savers offered the marketplace (still saving) | N1: Early take-up factor | O1: Early approval factor | P1: Card window: early factors in the first card months (helper) | Q1: Fund commission (Rs) | R1: KYC cost (Rs) | S1: Support cost (Rs) | T1: Discount factor at his age | U1: Fund commission less KYC and support, discounted to his sign-up month (Rs)
A2: 1 | B2: ='Retention curve'!C2 | C2: ='Retention curve'!D2 | D2: =in_daily*in_days*(1+in_amount_growth)^INT((A2-1)/in_term) | E2: =B2*D2 | F2: =IF(A2=1,0,G1*IF(MOD(A2-1,in_term)=0,in_rollover,1)) | G2: =F2*(1-in_withdraw_m)+D2+(F2*(1-in_withdraw_m)+0.5*D2)*d_rm | H2: =B2*(F2*(1-in_withdraw_m)+0.5*D2) | I2: =B2*in_withdraw_m*F2+IF(A2=1,0,C2*G1+IF(MOD(A2-1,in_term)=0,B2*(1-in_rollover)*G1,0)) | J2: =in_upi_12*MIN(1,(A2-1)/(in_upi_ramp-1)) | K2: =B2*(1-J2) | L2: =K2/in_visit_every | M2: =IF(A2>=in_marketplace_from,B2,0) | N2: =IF(A2<=in_early_months,in_early_takeup_mult,1) | O2: =IF(A2<=in_early_months,in_early_approval_mult,1) | P2: =IF(AND(A2>=in_marketplace_from,A2<in_marketplace_from+in_card_months),N2*O2,0) | Q2: =H2*in_trail/12 | R2: =IF(A2=1,in_kyc_cost,0) | S2: =B2*in_support_cost | T2: =1/(1+d_dm)^(A2-1) | U2: =(Q2-R2-S2)*T2
A3: 2 | B3: ='Retention curve'!C3 | C3: ='Retention curve'!D3 | D3: =in_daily*in_days*(1+in_amount_growth)^INT((A3-1)/in_term) | E3: =B3*D3 | F3: =IF(A3=1,0,G2*IF(MOD(A3-1,in_term)=0,in_rollover,1)) | G3: =F3*(1-in_withdraw_m)+D3+(F3*(1-in_withdraw_m)+0.5*D3)*d_rm | H3: =B3*(F3*(1-in_withdraw_m)+0.5*D3) | I3: =B3*in_withdraw_m*F3+IF(A3=1,0,C3*G2+IF(MOD(A3-1,in_term)=0,B3*(1-in_rollover)*G2,0)) | J3: =in_upi_12*MIN(1,(A3-1)/(in_upi_ramp-1)) | K3: =B3*(1-J3) | L3: =K3/in_visit_every | M3: =IF(A3>=in_marketplace_from,B3,0) | N3: =IF(A3<=in_early_months,in_early_takeup_mult,1) | O3: =IF(A3<=in_early_months,in_early_approval_mult,1) | P3: =IF(AND(A3>=in_marketplace_from,A3<in_marketplace_from+in_card_months),N3*O3,0) | Q3: =H3*in_trail/12 | R3: =IF(A3=1,in_kyc_cost,0) | S3: =B3*in_support_cost | T3: =1/(1+d_dm)^(A3-1) | U3: =(Q3-R3-S3)*T3
A4: 3 | B4: ='Retention curve'!C4 | C4: ='Retention curve'!D4 | D4: =in_daily*in_days*(1+in_amount_growth)^INT((A4-1)/in_term) | E4: =B4*D4 | F4: =IF(A4=1,0,G3*IF(MOD(A4-1,in_term)=0,in_rollover,1)) | G4: =F4*(1-in_withdraw_m)+D4+(F4*(1-in_withdraw_m)+0.5*D4)*d_rm | H4: =B4*(F4*(1-in_withdraw_m)+0.5*D4) | I4: =B4*in_withdraw_m*F4+IF(A4=1,0,C4*G3+IF(MOD(A4-1,in_term)=0,B4*(1-in_rollover)*G3,0)) | J4: =in_upi_12*MIN(1,(A4-1)/(in_upi_ramp-1)) | K4: =B4*(1-J4) | L4: =K4/in_visit_every | M4: =IF(A4>=in_marketplace_from,B4,0) | N4: =IF(A4<=in_early_months,in_early_takeup_mult,1) | O4: =IF(A4<=in_early_months,in_early_approval_mult,1) | P4: =IF(AND(A4>=in_marketplace_from,A4<in_marketplace_from+in_card_months),N4*O4,0) | Q4: =H4*in_trail/12 | R4: =IF(A4=1,in_kyc_cost,0) | S4: =B4*in_support_cost | T4: =1/(1+d_dm)^(A4-1) | U4: =(Q4-R4-S4)*T4
A5: 4 | B5: ='Retention curve'!C5 | C5: ='Retention curve'!D5 | D5: =in_daily*in_days*(1+in_amount_growth)^INT((A5-1)/in_term) | E5: =B5*D5 | F5: =IF(A5=1,0,G4*IF(MOD(A5-1,in_term)=0,in_rollover,1)) | G5: =F5*(1-in_withdraw_m)+D5+(F5*(1-in_withdraw_m)+0.5*D5)*d_rm | H5: =B5*(F5*(1-in_withdraw_m)+0.5*D5) | I5: =B5*in_withdraw_m*F5+IF(A5=1,0,C5*G4+IF(MOD(A5-1,in_term)=0,B5*(1-in_rollover)*G4,0)) | J5: =in_upi_12*MIN(1,(A5-1)/(in_upi_ramp-1)) | K5: =B5*(1-J5) | L5: =K5/in_visit_every | M5: =IF(A5>=in_marketplace_from,B5,0) | N5: =IF(A5<=in_early_months,in_early_takeup_mult,1) | O5: =IF(A5<=in_early_months,in_early_approval_mult,1) | P5: =IF(AND(A5>=in_marketplace_from,A5<in_marketplace_from+in_card_months),N5*O5,0) | Q5: =H5*in_trail/12 | R5: =IF(A5=1,in_kyc_cost,0) | S5: =B5*in_support_cost | T5: =1/(1+d_dm)^(A5-1) | U5: =(Q5-R5-S5)*T5
A6: 5 | B6: ='Retention curve'!C6 | C6: ='Retention curve'!D6 | D6: =in_daily*in_days*(1+in_amount_growth)^INT((A6-1)/in_term) | E6: =B6*D6 | F6: =IF(A6=1,0,G5*IF(MOD(A6-1,in_term)=0,in_rollover,1)) | G6: =F6*(1-in_withdraw_m)+D6+(F6*(1-in_withdraw_m)+0.5*D6)*d_rm | H6: =B6*(F6*(1-in_withdraw_m)+0.5*D6) | I6: =B6*in_withdraw_m*F6+IF(A6=1,0,C6*G5+IF(MOD(A6-1,in_term)=0,B6*(1-in_rollover)*G5,0)) | J6: =in_upi_12*MIN(1,(A6-1)/(in_upi_ramp-1)) | K6: =B6*(1-J6) | L6: =K6/in_visit_every | M6: =IF(A6>=in_marketplace_from,B6,0) | N6: =IF(A6<=in_early_months,in_early_takeup_mult,1) | O6: =IF(A6<=in_early_months,in_early_approval_mult,1) | P6: =IF(AND(A6>=in_marketplace_from,A6<in_marketplace_from+in_card_months),N6*O6,0) | Q6: =H6*in_trail/12 | R6: =IF(A6=1,in_kyc_cost,0) | S6: =B6*in_support_cost | T6: =1/(1+d_dm)^(A6-1) | U6: =(Q6-R6-S6)*T6
A7: 6 | B7: ='Retention curve'!C7 | C7: ='Retention curve'!D7 | D7: =in_daily*in_days*(1+in_amount_growth)^INT((A7-1)/in_term) | E7: =B7*D7 | F7: =IF(A7=1,0,G6*IF(MOD(A7-1,in_term)=0,in_rollover,1)) | G7: =F7*(1-in_withdraw_m)+D7+(F7*(1-in_withdraw_m)+0.5*D7)*d_rm | H7: =B7*(F7*(1-in_withdraw_m)+0.5*D7) | I7: =B7*in_withdraw_m*F7+IF(A7=1,0,C7*G6+IF(MOD(A7-1,in_term)=0,B7*(1-in_rollover)*G6,0)) | J7: =in_upi_12*MIN(1,(A7-1)/(in_upi_ramp-1)) | K7: =B7*(1-J7) | L7: =K7/in_visit_every | M7: =IF(A7>=in_marketplace_from,B7,0) | N7: =IF(A7<=in_early_months,in_early_takeup_mult,1) | O7: =IF(A7<=in_early_months,in_early_approval_mult,1) | P7: =IF(AND(A7>=in_marketplace_from,A7<in_marketplace_from+in_card_months),N7*O7,0) | Q7: =H7*in_trail/12 | R7: =IF(A7=1,in_kyc_cost,0) | S7: =B7*in_support_cost | T7: =1/(1+d_dm)^(A7-1) | U7: =(Q7-R7-S7)*T7
A8: 7 | B8: ='Retention curve'!C8 | C8: ='Retention curve'!D8 | D8: =in_daily*in_days*(1+in_amount_growth)^INT((A8-1)/in_term) | E8: =B8*D8 | F8: =IF(A8=1,0,G7*IF(MOD(A8-1,in_term)=0,in_rollover,1)) | G8: =F8*(1-in_withdraw_m)+D8+(F8*(1-in_withdraw_m)+0.5*D8)*d_rm | H8: =B8*(F8*(1-in_withdraw_m)+0.5*D8) | I8: =B8*in_withdraw_m*F8+IF(A8=1,0,C8*G7+IF(MOD(A8-1,in_term)=0,B8*(1-in_rollover)*G7,0)) | J8: =in_upi_12*MIN(1,(A8-1)/(in_upi_ramp-1)) | K8: =B8*(1-J8) | L8: =K8/in_visit_every | M8: =IF(A8>=in_marketplace_from,B8,0) | N8: =IF(A8<=in_early_months,in_early_takeup_mult,1) | O8: =IF(A8<=in_early_months,in_early_approval_mult,1) | P8: =IF(AND(A8>=in_marketplace_from,A8<in_marketplace_from+in_card_months),N8*O8,0) | Q8: =H8*in_trail/12 | R8: =IF(A8=1,in_kyc_cost,0) | S8: =B8*in_support_cost | T8: =1/(1+d_dm)^(A8-1) | U8: =(Q8-R8-S8)*T8
A9: 8 | B9: ='Retention curve'!C9 | C9: ='Retention curve'!D9 | D9: =in_daily*in_days*(1+in_amount_growth)^INT((A9-1)/in_term) | E9: =B9*D9 | F9: =IF(A9=1,0,G8*IF(MOD(A9-1,in_term)=0,in_rollover,1)) | G9: =F9*(1-in_withdraw_m)+D9+(F9*(1-in_withdraw_m)+0.5*D9)*d_rm | H9: =B9*(F9*(1-in_withdraw_m)+0.5*D9) | I9: =B9*in_withdraw_m*F9+IF(A9=1,0,C9*G8+IF(MOD(A9-1,in_term)=0,B9*(1-in_rollover)*G8,0)) | J9: =in_upi_12*MIN(1,(A9-1)/(in_upi_ramp-1)) | K9: =B9*(1-J9) | L9: =K9/in_visit_every | M9: =IF(A9>=in_marketplace_from,B9,0) | N9: =IF(A9<=in_early_months,in_early_takeup_mult,1) | O9: =IF(A9<=in_early_months,in_early_approval_mult,1) | P9: =IF(AND(A9>=in_marketplace_from,A9<in_marketplace_from+in_card_months),N9*O9,0) | Q9: =H9*in_trail/12 | R9: =IF(A9=1,in_kyc_cost,0) | S9: =B9*in_support_cost | T9: =1/(1+d_dm)^(A9-1) | U9: =(Q9-R9-S9)*T9
A10: 9 | B10: ='Retention curve'!C10 | C10: ='Retention curve'!D10 | D10: =in_daily*in_days*(1+in_amount_growth)^INT((A10-1)/in_term) | E10: =B10*D10 | F10: =IF(A10=1,0,G9*IF(MOD(A10-1,in_term)=0,in_rollover,1)) | G10: =F10*(1-in_withdraw_m)+D10+(F10*(1-in_withdraw_m)+0.5*D10)*d_rm | H10: =B10*(F10*(1-in_withdraw_m)+0.5*D10) | I10: =B10*in_withdraw_m*F10+IF(A10=1,0,C10*G9+IF(MOD(A10-1,in_term)=0,B10*(1-in_rollover)*G9,0)) | J10: =in_upi_12*MIN(1,(A10-1)/(in_upi_ramp-1)) | K10: =B10*(1-J10) | L10: =K10/in_visit_every | M10: =IF(A10>=in_marketplace_from,B10,0) | N10: =IF(A10<=in_early_months,in_early_takeup_mult,1) | O10: =IF(A10<=in_early_months,in_early_approval_mult,1) | P10: =IF(AND(A10>=in_marketplace_from,A10<in_marketplace_from+in_card_months),N10*O10,0) | Q10: =H10*in_trail/12 | R10: =IF(A10=1,in_kyc_cost,0) | S10: =B10*in_support_cost | T10: =1/(1+d_dm)^(A10-1) | U10: =(Q10-R10-S10)*T10
A11: 10 | B11: ='Retention curve'!C11 | C11: ='Retention curve'!D11 | D11: =in_daily*in_days*(1+in_amount_growth)^INT((A11-1)/in_term) | E11: =B11*D11 | F11: =IF(A11=1,0,G10*IF(MOD(A11-1,in_term)=0,in_rollover,1)) | G11: =F11*(1-in_withdraw_m)+D11+(F11*(1-in_withdraw_m)+0.5*D11)*d_rm | H11: =B11*(F11*(1-in_withdraw_m)+0.5*D11) | I11: =B11*in_withdraw_m*F11+IF(A11=1,0,C11*G10+IF(MOD(A11-1,in_term)=0,B11*(1-in_rollover)*G10,0)) | J11: =in_upi_12*MIN(1,(A11-1)/(in_upi_ramp-1)) | K11: =B11*(1-J11) | L11: =K11/in_visit_every | M11: =IF(A11>=in_marketplace_from,B11,0) | N11: =IF(A11<=in_early_months,in_early_takeup_mult,1) | O11: =IF(A11<=in_early_months,in_early_approval_mult,1) | P11: =IF(AND(A11>=in_marketplace_from,A11<in_marketplace_from+in_card_months),N11*O11,0) | Q11: =H11*in_trail/12 | R11: =IF(A11=1,in_kyc_cost,0) | S11: =B11*in_support_cost | T11: =1/(1+d_dm)^(A11-1) | U11: =(Q11-R11-S11)*T11
A12: 11 | B12: ='Retention curve'!C12 | C12: ='Retention curve'!D12 | D12: =in_daily*in_days*(1+in_amount_growth)^INT((A12-1)/in_term) | E12: =B12*D12 | F12: =IF(A12=1,0,G11*IF(MOD(A12-1,in_term)=0,in_rollover,1)) | G12: =F12*(1-in_withdraw_m)+D12+(F12*(1-in_withdraw_m)+0.5*D12)*d_rm | H12: =B12*(F12*(1-in_withdraw_m)+0.5*D12) | I12: =B12*in_withdraw_m*F12+IF(A12=1,0,C12*G11+IF(MOD(A12-1,in_term)=0,B12*(1-in_rollover)*G11,0)) | J12: =in_upi_12*MIN(1,(A12-1)/(in_upi_ramp-1)) | K12: =B12*(1-J12) | L12: =K12/in_visit_every | M12: =IF(A12>=in_marketplace_from,B12,0) | N12: =IF(A12<=in_early_months,in_early_takeup_mult,1) | O12: =IF(A12<=in_early_months,in_early_approval_mult,1) | P12: =IF(AND(A12>=in_marketplace_from,A12<in_marketplace_from+in_card_months),N12*O12,0) | Q12: =H12*in_trail/12 | R12: =IF(A12=1,in_kyc_cost,0) | S12: =B12*in_support_cost | T12: =1/(1+d_dm)^(A12-1) | U12: =(Q12-R12-S12)*T12
A13: 12 | B13: ='Retention curve'!C13 | C13: ='Retention curve'!D13 | D13: =in_daily*in_days*(1+in_amount_growth)^INT((A13-1)/in_term) | E13: =B13*D13 | F13: =IF(A13=1,0,G12*IF(MOD(A13-1,in_term)=0,in_rollover,1)) | G13: =F13*(1-in_withdraw_m)+D13+(F13*(1-in_withdraw_m)+0.5*D13)*d_rm | H13: =B13*(F13*(1-in_withdraw_m)+0.5*D13) | I13: =B13*in_withdraw_m*F13+IF(A13=1,0,C13*G12+IF(MOD(A13-1,in_term)=0,B13*(1-in_rollover)*G12,0)) | J13: =in_upi_12*MIN(1,(A13-1)/(in_upi_ramp-1)) | K13: =B13*(1-J13) | L13: =K13/in_visit_every | M13: =IF(A13>=in_marketplace_from,B13,0) | N13: =IF(A13<=in_early_months,in_early_takeup_mult,1) | O13: =IF(A13<=in_early_months,in_early_approval_mult,1) | P13: =IF(AND(A13>=in_marketplace_from,A13<in_marketplace_from+in_card_months),N13*O13,0) | Q13: =H13*in_trail/12 | R13: =IF(A13=1,in_kyc_cost,0) | S13: =B13*in_support_cost | T13: =1/(1+d_dm)^(A13-1) | U13: =(Q13-R13-S13)*T13
... A61: 60 | B61: ='Retention curve'!C61 | C61: ='Retention curve'!D61 | D61: =in_daily*in_days*(1+in_amount_growth)^INT((A61-1)/in_term) | E61: =B61*D61 | F61: =IF(A61=1,0,G60*IF(MOD(A61-1,in_term)=0,in_rollover,1)) | G61: =F61*(1-in_withdraw_m)+D61+(F61*(1-in_withdraw_m)+0.5*D61)*d_rm | H61: =B61*(F61*(1-in_withdraw_m)+0.5*D61) | I61: =B61*in_withdraw_m*F61+IF(A61=1,0,C61*G60+IF(MOD(A61-1,in_term)=0,B61*(1-in_rollover)*G60,0)) | J61: =in_upi_12*MIN(1,(A61-1)/(in_upi_ramp-1)) | K61: =B61*(1-J61) | L61: =K61/in_visit_every | M61: =IF(A61>=in_marketplace_from,B61,0) | N61: =IF(A61<=in_early_months,in_early_takeup_mult,1) | O61: =IF(A61<=in_early_months,in_early_approval_mult,1) | P61: =IF(AND(A61>=in_marketplace_from,A61<in_marketplace_from+in_card_months),N61*O61,0) | Q61: =H61*in_trail/12 | R61: =IF(A61=1,in_kyc_cost,0) | S61: =B61*in_support_cost | T61: =1/(1+d_dm)^(A61-1) | U61: =(Q61-R61-S61)*T61
A63: Per sign-up. The marketplace lines (loans, top-ups, cards, the 17 products, collections) depend on the calendar year as well as his age, because take-up and approvals grow with the pool's history: they are on 'Cohort x age'.

Sheet Cohort x age
A1: Sign-up month (cohort) | B1: Age | C1: Calendar month | D1: Calendar year | E1: Cohort's sign-ups | F1: Still saving | G1: Take-up factor (early months x pool history, cap) | H1: First-loan approval (cap 80%) | I1: Card factor (take-up x approval) | J1: No loan yet | K1: Repaid a loan, can apply for a repeat | L1: First loans | M1: Repeat loans | N1: Loans made | O1: Loans per active saver (helper) | P1: Savers with a loan running | Q1: Loan applications | R1: Loans with an EMI due | S1: Top-up window (helper) | T1: Top-ups | U1: Money lent, first and repeat loans (Rs) | V1: Money lent, with top-ups (Rs) | W1: Loans for collections (top-ups pro rata) | X1: Overdue accounts brought back, 31-90 days | Y1: Overdue accounts recovered, 90+ | Z1: Cards issued (the share held back by the early factors follows in the next 6 months) | AA1: Origination fees net of taken back (Rs) | AB1: 31-90 day collection fees (Rs) | AC1: 90+ recovery fees (Rs) | AD1: Card fees (Rs) | AE1: Small health / hospital cash: never held it (share of active savers) | AF1: Small health / hospital cash: take-ups per active saver | AG1: Small health / hospital cash (Rs) | AH1: Family health cover: never held it (share of active savers) | AI1: Family health cover: take-ups per active saver | AJ1: Family health cover (Rs) | AK1: Term life (small cover): never held it (share of active savers) | AL1: Term life (small cover): take-ups per active saver | AM1: Term life (small cover) (Rs) | AN1: Personal accident: never held it (share of active savers) | AO1: Personal accident: take-ups per active saver | AP1: Personal accident (Rs) | AQ1: Two-wheeler insurance: never held it (share of active savers) | AR1: Two-wheeler insurance: take-ups per active saver | AS1: Two-wheeler insurance (Rs) | AT1: Mobile / device insurance: never held it (share of active savers) | AU1: Mobile / device insurance (Rs) | AV1: Shop insurance (fire and burglary): never held it (share of active savers) | AW1: Shop insurance (fire and burglary): take-ups per active saver | AX1: Shop insurance (fire and burglary) (Rs) | AY1: Equity/hybrid SIP trail: never held it (share of active savers) | AZ1: Equity/hybrid SIP trail: holders per active saver | BA1: Equity/hybrid SIP trail: SIP months held per active saver (helper) | BB1: Equity/hybrid SIP trail (Rs) | BC1: Choti SIP incentive: never held it (share of active savers) | BD1: Choti SIP incentive: take-ups per active saver | BE1: Choti SIP incentive (Rs) | BF1: NPS: never held it (share of active savers) | BG1: NPS (Rs) | BH1: Digital gold: never held it (share of active savers) | BI1: Digital gold: holders per active saver | BJ1: Digital gold (Rs) | BK1: FD via partner banks: never held it (share of active savers) | BL1: FD via partner banks (Rs) | BM1: Mobile recharge: never held it (share of active savers) | BN1: Mobile recharge: holders per active saver | BO1: Mobile recharge (Rs) | BP1: Bill payments: never held it (share of active savers) | BQ1: Bill payments: holders per active saver | BR1: Bill payments (Rs) | BS1: Gold loan (other lenders): never held it (share of active savers) | BT1: Gold loan (other lenders) (Rs) | BU1: Consumer-durable loan: never held it (share of active savers) | BV1: Consumer-durable loan (Rs) | BW1: Two-wheeler / e-rickshaw loan: never held it (share of active savers) | BX1: Two-wheeler / e-rickshaw loan (Rs) | BY1: Home loan (affordable housing): never had one (share of active savers) | BZ1: Home loan (affordable housing): approval (cap 80%) | CA1: Home loan (affordable housing) (Rs) | CB1: Loan against property (shop or home): never had one (share of active savers) | CC1: Loan against property (shop or home): approval (cap 80%) | CD1: Loan against property (shop or home) (Rs) | CE1: Marketplace income (Rs)
A2: 1 | B2: 1 | C2: =A2+B2-1 | D2: =INT((C2-1)/12)+1 | E2: =INDEX(Monthly!$B$2:$B$61,A2) | F2: =E2*INDEX('Age profile'!$B$2:$B$61,B2) | G2: =MIN(in_takeup_cap,INDEX('Age profile'!$N$2:$N$61,B2)*(1+in_takeup_growth)^(D2-1)) | H2: =MIN(in_approval_cap,in_approved_first*INDEX('Age profile'!$O$2:$O$61,B2)*(1+in_approval_growth)^(D2-1)) | I2: =G2*MIN(in_takeup_cap,INDEX('Age profile'!$O$2:$O$61,B2)*(1+in_approval_growth)^(D2-1)) | J2: =E2 | K2: 0 | L2: =IF(B2>=in_marketplace_from,J2*d_hz*G2*in_eligible*H2,0) | M2: =IF(B2>=in_marketplace_from,K2*d_hz*G2*in_eligible*in_approved_repeat,0) | N2: =L2+M2 | O2: =N2/F2 | P2: =F2-J2-K2 | Q2: =IF(B2>=in_marketplace_from,(J2+K2)*d_hz*G2,0) | R2: =SUMIFS(N2:N61,B2:B61,">="&(B2-d_T),B2:B61,"<="&(B2-1)) | S2: 0 | T2: =F2*d_u*S2 | U2: =L2*in_ticket+M2*d_rep_ticket | V2: =U2+T2*d_topup_amt | W2: =N2+T2*d_topup_ratio | X2: =SUMIFS(W2:W61,B2:B61,B2-in_dpd_lag)*d_cured | Y2: =SUMIFS(W2:W61,B2:B61,B2-in_rec_lag)*d_recd | Z2: =IF(AND(B2>=in_marketplace_from,B2<in_marketplace_from+in_card_months),in_card_share/in_card_months*F2*I2,IF(AND(B2>=in_marketplace_from+in_card_months,B2<in_marketplace_from+2*in_card_months),in_card_share*d_card_rem/in_card_months*F2*MIN(in_takeup_cap,(1+in_takeup_growth)^(D2-1))*MIN(in_takeup_cap,(1+in_approval_growth)^(D2-1)),0)) | AA2: =V2*in_fee*(1-in_taken_back) | AB2: =SUMIFS(W2:W61,B2:B61,B2-in_dpd_lag)*d_dpd | AC2: =SUMIFS(W2:W61,B2:B61,B2-in_rec_lag)*d_rec | AD2: =Z2*in_card_fee | AE2: 1 | AF2: =AE2*IF(B2>=in_marketplace_from,d_hz_hlth_small*G2,0) | AG2: =F2*AF2*in_hlth_small_ticket*in_hlth_small_comm*in_ins_partner_share+F2*in_hlth_small_ticket*in_hlth_small_renew_comm*in_ins_partner_share*(in_hlth_small_renew^1*SUMIFS(AF2:AF61,B2:B61,B2-12)+in_hlth_small_renew^2*SUMIFS(AF2:AF61,B2:B61,B2-24)+in_hlth_small_renew^3*SUMIFS(AF2:AF61,B2:B61,B2-36)+in_hlth_small_renew^4*SUMIFS(AF2:AF61,B2:B61,B2-48)) | AH2: 1 | AI2: =AH2*IF(B2>=in_marketplace_from,d_hz_hlth_family*G2,0) | AJ2: =F2*AI2*in_hlth_family_ticket*in_hlth_family_comm*in_ins_partner_share+F2*in_hlth_family_ticket*in_hlth_family_renew_comm*in_ins_partner_share*(in_hlth_family_renew^1*SUMIFS(AI2:AI61,B2:B61,B2-12)+in_hlth_family_renew^2*SUMIFS(AI2:AI61,B2:B61,B2-24)+in_hlth_family_renew^3*SUMIFS(AI2:AI61,B2:B61,B2-36)+in_hlth_family_renew^4*SUMIFS(AI2:AI61,B2:B61,B2-48)) | AK2: 1 | AL2: =AK2*IF(B2>=in_marketplace_from,d_hz_life_term*G2,0) | AM2: =F2*AL2*in_life_term_ticket*in_life_term_comm*in_ins_partner_share+F2*in_life_term_ticket*in_life_term_renew_comm*in_ins_partner_share*(in_life_term_renew^1*SUMIFS(AL2:AL61,B2:B61,B2-12)+in_life_term_renew^2*SUMIFS(AL2:AL61,B2:B61,B2-24)+in_life_term_renew^3*SUMIFS(AL2:AL61,B2:B61,B2-36)+in_life_term_renew^4*SUMIFS(AL2:AL61,B2:B61,B2-48)) | AN2: 1 | AO2: =AN2*IF(B2>=in_marketplace_from,d_hz_accident*G2,0) | AP2: =F2*AO2*in_accident_ticket*in_accident_comm*in_ins_partner_share+F2*in_accident_ticket*in_accident_renew_comm*in_ins_partner_share*(in_accident_renew^1*SUMIFS(AO2:AO61,B2:B61,B2-12)+in_accident_renew^2*SUMIFS(AO2:AO61,B2:B61,B2-24)+in_accident_renew^3*SUMIFS(AO2:AO61,B2:B61,B2-36)+in_accident_renew^4*SUMIFS(AO2:AO61,B2:B61,B2-48)) | AQ2: 1 | AR2: =AQ2*IF(B2>=in_marketplace_from,d_hz_two_wheeler*G2,0) | AS2: =F2*AR2*in_two_wheeler_ticket*in_two_wheeler_comm*in_ins_partner_share+F2*in_two_wheeler_ticket*in_two_wheeler_comm*in_ins_partner_share*(in_two_wheeler_renew^1*SUMIFS(AR2:AR61,B2:B61,B2-12)+in_two_wheeler_renew^2*SUMIFS(AR2:AR61,B2:B61,B2-24)+in_two_wheeler_renew^3*SUMIFS(AR2:AR61,B2:B61,B2-36)+in_two_wheeler_renew^4*SUMIFS(AR2:AR61,B2:B61,B2-48)) | AT2: 1 | AU2: =F2*AT2*IF(B2>=in_marketplace_from,d_hz_device*G2,0)*in_device_ticket*in_device_comm*in_ins_partner_share | AV2: 1 | AW2: =AV2*IF(B2>=in_marketplace_from,d_hz_shop*G2,0) | AX2: =F2*AW2*in_shop_ticket*in_shop_comm*in_ins_partner_share+F2*in_shop_ticket*in_shop_renew_comm*in_ins_partner_share*(in_shop_renew^1*SUMIFS(AW2:AW61,B2:B61,B2-12)+in_shop_renew^2*SUMIFS(AW2:AW61,B2:B61,B2-24)+in_shop_renew^3*SUMIFS(AW2:AW61,B2:B61,B2-36)+in_shop_renew^4*SUMIFS(AW2:AW61,B2:B61,B2-48)) | AY2: 1 | AZ2: =AY2*IF(B2>=in_marketplace_from,d_hz_sip*G2,0) | BA2: 0 | BB2: =F2*in_sip_ticket*(BA2+0.5*AZ2)*in_sip_comm/12 | BC2: 1 | BD2: =BC2*IF(B2>=in_marketplace_from,d_hz_choti*G2,0) | BE2: =F2*SUMIFS(BD2:BD61,B2:B61,B2-in_choti_months)*in_choti_renew*in_choti_ticket | BF2: 1 | BG2: =F2*BF2*IF(B2>=in_marketplace_from,d_hz_nps*G2,0)*in_nps_ticket*in_nps_comm | BH2: 1 | BI2: =BH2*IF(B2>=in_marketplace_from,d_hz_gold*G2,0) | BJ2: =F2*BI2*in_gold_ticket*in_gold_comm | BK2: 1 | BL2: =F2*BK2*IF(B2>=in_marketplace_from,d_hz_fd*G2,0)*in_fd_ticket*in_fd_comm | BM2: 1 | BN2: =BM2*IF(B2>=in_marketplace_from,d_hz_recharge*G2,0) | BO2: =F2*BN2*in_recharge_ticket*in_recharge_comm/12 | BP2: 1 | BQ2: =BP2*IF(B2>=in_marketplace_from,d_hz_bills*G2,0) | BR2: =F2*BQ2*in_bills_ticket*in_bills_comm/12 | BS2: 1 | BT2: =F2*BS2*IF(B2>=in_marketplace_from,d_hz_loan_gold*G2,0)*in_loan_gold_ticket*in_loan_gold_comm | BU2: 1 | BV2: =F2*BU2*IF(B2>=in_marketplace_from,d_hz_loan_cd*G2,0)*in_loan_cd_ticket*in_loan_cd_comm | BW2: 1 | BX2: =F2*BW2*IF(B2>=in_marketplace_from,d_hz_loan_vehicle*G2,0)*in_loan_vehicle_ticket*in_loan_vehicle_comm | BY2: 1 | BZ2: =MIN(in_approval_cap,in_loan_home_approval*INDEX('Age profile'!$O$2:$O$61,B2)*(1+in_approval_growth)^(D2-1)) | CA2: =F2*BY2*IF(B2>=in_marketplace_from,d_hz_loan_home*G2,0)*BZ2*in_loan_home_ticket*in_loan_home_comm | CB2: 1 | CC2: =MIN(in_approval_cap,in_loan_lap_approval*INDEX('Age profile'!$O$2:$O$61,B2)*(1+in_approval_growth)^(D2-1)) | CD2: =F2*CB2*IF(B2>=in_marketplace_from,d_hz_loan_lap*G2,0)*CC2*in_loan_lap_ticket*in_loan_lap_comm | CE2: =AA2+AB2+AC2+AD2+AG2+AJ2+AM2+AP2+AS2+AU2+AX2+BB2+BE2+BG2+BJ2+BL2+BO2+BR2+BT2+BV2+BX2+CA2+CD2
A3: 1 | B3: 2 | C3: =A3+B3-1 | D3: =INT((C3-1)/12)+1 | E3: =INDEX(Monthly!$B$2:$B$61,A3) | F3: =E3*INDEX('Age profile'!$B$2:$B$61,B3) | G3: =MIN(in_takeup_cap,INDEX('Age profile'!$N$2:$N$61,B3)*(1+in_takeup_growth)^(D3-1)) | H3: =MIN(in_approval_cap,in_approved_first*INDEX('Age profile'!$O$2:$O$61,B3)*(1+in_approval_growth)^(D3-1)) | I3: =G3*MIN(in_takeup_cap,INDEX('Age profile'!$O$2:$O$61,B3)*(1+in_approval_growth)^(D3-1)) | J3: =(J2-L2)*F3/F2 | K3: =(K2-M2)*F3/F2+SUMIFS(O2:O2,B2:B2,B3-1-d_T)*F3 | L3: =IF(B3>=in_marketplace_from,J3*d_hz*G3*in_eligible*H3,0) | M3: =IF(B3>=in_marketplace_from,K3*d_hz*G3*in_eligible*in_approved_repeat,0) | N3: =L3+M3 | O3: =N3/F3 | P3: =F3-J3-K3 | Q3: =IF(B3>=in_marketplace_from,(J3+K3)*d_hz*G3,0) | R3: =SUMIFS(N2:N61,B2:B61,">="&(B3-d_T),B2:B61,"<="&(B3-1)) | S3: =(1-d_u)*S2+IF(d_T>in_topup_lag,SUMIFS(O2:O61,B2:B61,B3-in_topup_lag)-d_udrop*SUMIFS(O2:O61,B2:B61,B3-d_T),0) | T3: =F3*d_u*S3 | U3: =L3*in_ticket+M3*d_rep_ticket | V3: =U3+T3*d_topup_amt | W3: =N3+T3*d_topup_ratio | X3: =SUMIFS(W2:W61,B2:B61,B3-in_dpd_lag)*d_cured | Y3: =SUMIFS(W2:W61,B2:B61,B3-in_rec_lag)*d_recd | Z3: =IF(AND(B3>=in_marketplace_from,B3<in_marketplace_from+in_card_months),in_card_share/in_card_months*F3*I3,IF(AND(B3>=in_marketplace_from+in_card_months,B3<in_marketplace_from+2*in_card_months),in_card_share*d_card_rem/in_card_months*F3*MIN(in_takeup_cap,(1+in_takeup_growth)^(D3-1))*MIN(in_takeup_cap,(1+in_approval_growth)^(D3-1)),0)) | AA3: =V3*in_fee*(1-in_taken_back) | AB3: =SUMIFS(W2:W61,B2:B61,B3-in_dpd_lag)*d_dpd | AC3: =SUMIFS(W2:W61,B2:B61,B3-in_rec_lag)*d_rec | AD3: =Z3*in_card_fee | AE3: =AE2*(1-IF(B2>=in_marketplace_from,d_hz_hlth_small*G2,0)) | AF3: =AE3*IF(B3>=in_marketplace_from,d_hz_hlth_small*G3,0) | AG3: =F3*AF3*in_hlth_small_ticket*in_hlth_small_comm*in_ins_partner_share+F3*in_hlth_small_ticket*in_hlth_small_renew_comm*in_ins_partner_share*(in_hlth_small_renew^1*SUMIFS(AF2:AF61,B2:B61,B3-12)+in_hlth_small_renew^2*SUMIFS(AF2:AF61,B2:B61,B3-24)+in_hlth_small_renew^3*SUMIFS(AF2:AF61,B2:B61,B3-36)+in_hlth_small_renew^4*SUMIFS(AF2:AF61,B2:B61,B3-48)) | AH3: =AH2*(1-IF(B2>=in_marketplace_from,d_hz_hlth_family*G2,0)) | AI3: =AH3*IF(B3>=in_marketplace_from,d_hz_hlth_family*G3,0) | AJ3: =F3*AI3*in_hlth_family_ticket*in_hlth_family_comm*in_ins_partner_share+F3*in_hlth_family_ticket*in_hlth_family_renew_comm*in_ins_partner_share*(in_hlth_family_renew^1*SUMIFS(AI2:AI61,B2:B61,B3-12)+in_hlth_family_renew^2*SUMIFS(AI2:AI61,B2:B61,B3-24)+in_hlth_family_renew^3*SUMIFS(AI2:AI61,B2:B61,B3-36)+in_hlth_family_renew^4*SUMIFS(AI2:AI61,B2:B61,B3-48)) | AK3: =AK2*(1-IF(B2>=in_marketplace_from,d_hz_life_term*G2,0)) | AL3: =AK3*IF(B3>=in_marketplace_from,d_hz_life_term*G3,0) | AM3: =F3*AL3*in_life_term_ticket*in_life_term_comm*in_ins_partner_share+F3*in_life_term_ticket*in_life_term_renew_comm*in_ins_partner_share*(in_life_term_renew^1*SUMIFS(AL2:AL61,B2:B61,B3-12)+in_life_term_renew^2*SUMIFS(AL2:AL61,B2:B61,B3-24)+in_life_term_renew^3*SUMIFS(AL2:AL61,B2:B61,B3-36)+in_life_term_renew^4*SUMIFS(AL2:AL61,B2:B61,B3-48)) | AN3: =AN2*(1-IF(B2>=in_marketplace_from,d_hz_accident*G2,0)) | AO3: =AN3*IF(B3>=in_marketplace_from,d_hz_accident*G3,0) | AP3: =F3*AO3*in_accident_ticket*in_accident_comm*in_ins_partner_share+F3*in_accident_ticket*in_accident_renew_comm*in_ins_partner_share*(in_accident_renew^1*SUMIFS(AO2:AO61,B2:B61,B3-12)+in_accident_renew^2*SUMIFS(AO2:AO61,B2:B61,B3-24)+in_accident_renew^3*SUMIFS(AO2:AO61,B2:B61,B3-36)+in_accident_renew^4*SUMIFS(AO2:AO61,B2:B61,B3-48)) | AQ3: =AQ2*(1-IF(B2>=in_marketplace_from,d_hz_two_wheeler*G2,0)) | AR3: =AQ3*IF(B3>=in_marketplace_from,d_hz_two_wheeler*G3,0) | AS3: =F3*AR3*in_two_wheeler_ticket*in_two_wheeler_comm*in_ins_partner_share+F3*in_two_wheeler_ticket*in_two_wheeler_comm*in_ins_partner_share*(in_two_wheeler_renew^1*SUMIFS(AR2:AR61,B2:B61,B3-12)+in_two_wheeler_renew^2*SUMIFS(AR2:AR61,B2:B61,B3-24)+in_two_wheeler_renew^3*SUMIFS(AR2:AR61,B2:B61,B3-36)+in_two_wheeler_renew^4*SUMIFS(AR2:AR61,B2:B61,B3-48)) | AT3: =AT2*(1-IF(B2>=in_marketplace_from,d_hz_device*G2,0)) | AU3: =F3*AT3*IF(B3>=in_marketplace_from,d_hz_device*G3,0)*in_device_ticket*in_device_comm*in_ins_partner_share | AV3: =AV2*(1-IF(B2>=in_marketplace_from,d_hz_shop*G2,0)) | AW3: =AV3*IF(B3>=in_marketplace_from,d_hz_shop*G3,0) | AX3: =F3*AW3*in_shop_ticket*in_shop_comm*in_ins_partner_share+F3*in_shop_ticket*in_shop_renew_comm*in_ins_partner_share*(in_shop_renew^1*SUMIFS(AW2:AW61,B2:B61,B3-12)+in_shop_renew^2*SUMIFS(AW2:AW61,B2:B61,B3-24)+in_shop_renew^3*SUMIFS(AW2:AW61,B2:B61,B3-36)+in_shop_renew^4*SUMIFS(AW2:AW61,B2:B61,B3-48)) | AY3: =AY2*(1-IF(B2>=in_marketplace_from,d_hz_sip*G2,0)) | AZ3: =AZ2*d_rho_sip+AY3*IF(B3>=in_marketplace_from,d_hz_sip*G3,0) | BA3: =d_rho_sip*(BA2+AZ2) | BB3: =F3*in_sip_ticket*(BA3+0.5*AZ3)*in_sip_comm/12 | BC3: =BC2*(1-IF(B2>=in_marketplace_from,d_hz_choti*G2,0)) | BD3: =BC3*IF(B3>=in_marketplace_from,d_hz_choti*G3,0) | BE3: =F3*SUMIFS(BD2:BD61,B2:B61,B3-in_choti_months)*in_choti_renew*in_choti_ticket | BF3: =BF2*(1-IF(B2>=in_marketplace_from,d_hz_nps*G2,0)) | BG3: =F3*BF3*IF(B3>=in_marketplace_from,d_hz_nps*G3,0)*in_nps_ticket*in_nps_comm | BH3: =BH2*(1-IF(B2>=in_marketplace_from,d_hz_gold*G2,0)) | BI3: =BI2*d_rho_gold+BH3*IF(B3>=in_marketplace_from,d_hz_gold*G3,0) | BJ3: =F3*BI3*in_gold_ticket*in_gold_comm | BK3: =BK2*(1-IF(B2>=in_marketplace_from,d_hz_fd*G2,0)) | BL3: =F3*BK3*IF(B3>=in_marketplace_from,d_hz_fd*G3,0)*in_fd_ticket*in_fd_comm | BM3: =BM2*(1-IF(B2>=in_marketplace_from,d_hz_recharge*G2,0)) | BN3: =BN2*d_rho_recharge+BM3*IF(B3>=in_marketplace_from,d_hz_recharge*G3,0) | BO3: =F3*BN3*in_recharge_ticket*in_recharge_comm/12 | BP3: =BP2*(1-IF(B2>=in_marketplace_from,d_hz_bills*G2,0)) | BQ3: =BQ2*d_rho_bills+BP3*IF(B3>=in_marketplace_from,d_hz_bills*G3,0) | BR3: =F3*BQ3*in_bills_ticket*in_bills_comm/12 | BS3: =BS2*(1-IF(B2>=in_marketplace_from,d_hz_loan_gold*G2,0)) | BT3: =F3*BS3*IF(B3>=in_marketplace_from,d_hz_loan_gold*G3,0)*in_loan_gold_ticket*in_loan_gold_comm | BU3: =BU2*(1-IF(B2>=in_marketplace_from,d_hz_loan_cd*G2,0)) | BV3: =F3*BU3*IF(B3>=in_marketplace_from,d_hz_loan_cd*G3,0)*in_loan_cd_ticket*in_loan_cd_comm | BW3: =BW2*(1-IF(B2>=in_marketplace_from,d_hz_loan_vehicle*G2,0)) | BX3: =F3*BW3*IF(B3>=in_marketplace_from,d_hz_loan_vehicle*G3,0)*in_loan_vehicle_ticket*in_loan_vehicle_comm | BY3: =BY2*(1-IF(B2>=in_marketplace_from,d_hz_loan_home*G2,0)*BZ2) | BZ3: =MIN(in_approval_cap,in_loan_home_approval*INDEX('Age profile'!$O$2:$O$61,B3)*(1+in_approval_growth)^(D3-1)) | CA3: =F3*BY3*IF(B3>=in_marketplace_from,d_hz_loan_home*G3,0)*BZ3*in_loan_home_ticket*in_loan_home_comm | CB3: =CB2*(1-IF(B2>=in_marketplace_from,d_hz_loan_lap*G2,0)*CC2) | CC3: =MIN(in_approval_cap,in_loan_lap_approval*INDEX('Age profile'!$O$2:$O$61,B3)*(1+in_approval_growth)^(D3-1)) | CD3: =F3*CB3*IF(B3>=in_marketplace_from,d_hz_loan_lap*G3,0)*CC3*in_loan_lap_ticket*in_loan_lap_comm | CE3: =AA3+AB3+AC3+AD3+AG3+AJ3+AM3+AP3+AS3+AU3+AX3+BB3+BE3+BG3+BJ3+BL3+BO3+BR3+BT3+BV3+BX3+CA3+CD3
A4: 1 | B4: 3 | C4: =A4+B4-1 | D4: =INT((C4-1)/12)+1 | E4: =INDEX(Monthly!$B$2:$B$61,A4) | F4: =E4*INDEX('Age profile'!$B$2:$B$61,B4) | G4: =MIN(in_takeup_cap,INDEX('Age profile'!$N$2:$N$61,B4)*(1+in_takeup_growth)^(D4-1)) | H4: =MIN(in_approval_cap,in_approved_first*INDEX('Age profile'!$O$2:$O$61,B4)*(1+in_approval_growth)^(D4-1)) | I4: =G4*MIN(in_takeup_cap,INDEX('Age profile'!$O$2:$O$61,B4)*(1+in_approval_growth)^(D4-1)) | J4: =(J3-L3)*F4/F3 | K4: =(K3-M3)*F4/F3+SUMIFS(O2:O3,B2:B3,B4-1-d_T)*F4 | L4: =IF(B4>=in_marketplace_from,J4*d_hz*G4*in_eligible*H4,0) | M4: =IF(B4>=in_marketplace_from,K4*d_hz*G4*in_eligible*in_approved_repeat,0) | N4: =L4+M4 | O4: =N4/F4 | P4: =F4-J4-K4 | Q4: =IF(B4>=in_marketplace_from,(J4+K4)*d_hz*G4,0) | R4: =SUMIFS(N2:N61,B2:B61,">="&(B4-d_T),B2:B61,"<="&(B4-1)) | S4: =(1-d_u)*S3+IF(d_T>in_topup_lag,SUMIFS(O2:O61,B2:B61,B4-in_topup_lag)-d_udrop*SUMIFS(O2:O61,B2:B61,B4-d_T),0) | T4: =F4*d_u*S4 | U4: =L4*in_ticket+M4*d_rep_ticket | V4: =U4+T4*d_topup_amt | W4: =N4+T4*d_topup_ratio | X4: =SUMIFS(W2:W61,B2:B61,B4-in_dpd_lag)*d_cured | Y4: =SUMIFS(W2:W61,B2:B61,B4-in_rec_lag)*d_recd | Z4: =IF(AND(B4>=in_marketplace_from,B4<in_marketplace_from+in_card_months),in_card_share/in_card_months*F4*I4,IF(AND(B4>=in_marketplace_from+in_card_months,B4<in_marketplace_from+2*in_card_months),in_card_share*d_card_rem/in_card_months*F4*MIN(in_takeup_cap,(1+in_takeup_growth)^(D4-1))*MIN(in_takeup_cap,(1+in_approval_growth)^(D4-1)),0)) | AA4: =V4*in_fee*(1-in_taken_back) | AB4: =SUMIFS(W2:W61,B2:B61,B4-in_dpd_lag)*d_dpd | AC4: =SUMIFS(W2:W61,B2:B61,B4-in_rec_lag)*d_rec | AD4: =Z4*in_card_fee | AE4: =AE3*(1-IF(B3>=in_marketplace_from,d_hz_hlth_small*G3,0)) | AF4: =AE4*IF(B4>=in_marketplace_from,d_hz_hlth_small*G4,0) | AG4: =F4*AF4*in_hlth_small_ticket*in_hlth_small_comm*in_ins_partner_share+F4*in_hlth_small_ticket*in_hlth_small_renew_comm*in_ins_partner_share*(in_hlth_small_renew^1*SUMIFS(AF2:AF61,B2:B61,B4-12)+in_hlth_small_renew^2*SUMIFS(AF2:AF61,B2:B61,B4-24)+in_hlth_small_renew^3*SUMIFS(AF2:AF61,B2:B61,B4-36)+in_hlth_small_renew^4*SUMIFS(AF2:AF61,B2:B61,B4-48)) | AH4: =AH3*(1-IF(B3>=in_marketplace_from,d_hz_hlth_family*G3,0)) | AI4: =AH4*IF(B4>=in_marketplace_from,d_hz_hlth_family*G4,0) | AJ4: =F4*AI4*in_hlth_family_ticket*in_hlth_family_comm*in_ins_partner_share+F4*in_hlth_family_ticket*in_hlth_family_renew_comm*in_ins_partner_share*(in_hlth_family_renew^1*SUMIFS(AI2:AI61,B2:B61,B4-12)+in_hlth_family_renew^2*SUMIFS(AI2:AI61,B2:B61,B4-24)+in_hlth_family_renew^3*SUMIFS(AI2:AI61,B2:B61,B4-36)+in_hlth_family_renew^4*SUMIFS(AI2:AI61,B2:B61,B4-48)) | AK4: =AK3*(1-IF(B3>=in_marketplace_from,d_hz_life_term*G3,0)) | AL4: =AK4*IF(B4>=in_marketplace_from,d_hz_life_term*G4,0) | AM4: =F4*AL4*in_life_term_ticket*in_life_term_comm*in_ins_partner_share+F4*in_life_term_ticket*in_life_term_renew_comm*in_ins_partner_share*(in_life_term_renew^1*SUMIFS(AL2:AL61,B2:B61,B4-12)+in_life_term_renew^2*SUMIFS(AL2:AL61,B2:B61,B4-24)+in_life_term_renew^3*SUMIFS(AL2:AL61,B2:B61,B4-36)+in_life_term_renew^4*SUMIFS(AL2:AL61,B2:B61,B4-48)) | AN4: =AN3*(1-IF(B3>=in_marketplace_from,d_hz_accident*G3,0)) | AO4: =AN4*IF(B4>=in_marketplace_from,d_hz_accident*G4,0) | AP4: =F4*AO4*in_accident_ticket*in_accident_comm*in_ins_partner_share+F4*in_accident_ticket*in_accident_renew_comm*in_ins_partner_share*(in_accident_renew^1*SUMIFS(AO2:AO61,B2:B61,B4-12)+in_accident_renew^2*SUMIFS(AO2:AO61,B2:B61,B4-24)+in_accident_renew^3*SUMIFS(AO2:AO61,B2:B61,B4-36)+in_accident_renew^4*SUMIFS(AO2:AO61,B2:B61,B4-48)) | AQ4: =AQ3*(1-IF(B3>=in_marketplace_from,d_hz_two_wheeler*G3,0)) | AR4: =AQ4*IF(B4>=in_marketplace_from,d_hz_two_wheeler*G4,0) | AS4: =F4*AR4*in_two_wheeler_ticket*in_two_wheeler_comm*in_ins_partner_share+F4*in_two_wheeler_ticket*in_two_wheeler_comm*in_ins_partner_share*(in_two_wheeler_renew^1*SUMIFS(AR2:AR61,B2:B61,B4-12)+in_two_wheeler_renew^2*SUMIFS(AR2:AR61,B2:B61,B4-24)+in_two_wheeler_renew^3*SUMIFS(AR2:AR61,B2:B61,B4-36)+in_two_wheeler_renew^4*SUMIFS(AR2:AR61,B2:B61,B4-48)) | AT4: =AT3*(1-IF(B3>=in_marketplace_from,d_hz_device*G3,0)) | AU4: =F4*AT4*IF(B4>=in_marketplace_from,d_hz_device*G4,0)*in_device_ticket*in_device_comm*in_ins_partner_share | AV4: =AV3*(1-IF(B3>=in_marketplace_from,d_hz_shop*G3,0)) | AW4: =AV4*IF(B4>=in_marketplace_from,d_hz_shop*G4,0) | AX4: =F4*AW4*in_shop_ticket*in_shop_comm*in_ins_partner_share+F4*in_shop_ticket*in_shop_renew_comm*in_ins_partner_share*(in_shop_renew^1*SUMIFS(AW2:AW61,B2:B61,B4-12)+in_shop_renew^2*SUMIFS(AW2:AW61,B2:B61,B4-24)+in_shop_renew^3*SUMIFS(AW2:AW61,B2:B61,B4-36)+in_shop_renew^4*SUMIFS(AW2:AW61,B2:B61,B4-48)) | AY4: =AY3*(1-IF(B3>=in_marketplace_from,d_hz_sip*G3,0)) | AZ4: =AZ3*d_rho_sip+AY4*IF(B4>=in_marketplace_from,d_hz_sip*G4,0) | BA4: =d_rho_sip*(BA3+AZ3) | BB4: =F4*in_sip_ticket*(BA4+0.5*AZ4)*in_sip_comm/12 | BC4: =BC3*(1-IF(B3>=in_marketplace_from,d_hz_choti*G3,0)) | BD4: =BC4*IF(B4>=in_marketplace_from,d_hz_choti*G4,0) | BE4: =F4*SUMIFS(BD2:BD61,B2:B61,B4-in_choti_months)*in_choti_renew*in_choti_ticket | BF4: =BF3*(1-IF(B3>=in_marketplace_from,d_hz_nps*G3,0)) | BG4: =F4*BF4*IF(B4>=in_marketplace_from,d_hz_nps*G4,0)*in_nps_ticket*in_nps_comm | BH4: =BH3*(1-IF(B3>=in_marketplace_from,d_hz_gold*G3,0)) | BI4: =BI3*d_rho_gold+BH4*IF(B4>=in_marketplace_from,d_hz_gold*G4,0) | BJ4: =F4*BI4*in_gold_ticket*in_gold_comm | BK4: =BK3*(1-IF(B3>=in_marketplace_from,d_hz_fd*G3,0)) | BL4: =F4*BK4*IF(B4>=in_marketplace_from,d_hz_fd*G4,0)*in_fd_ticket*in_fd_comm | BM4: =BM3*(1-IF(B3>=in_marketplace_from,d_hz_recharge*G3,0)) | BN4: =BN3*d_rho_recharge+BM4*IF(B4>=in_marketplace_from,d_hz_recharge*G4,0) | BO4: =F4*BN4*in_recharge_ticket*in_recharge_comm/12 | BP4: =BP3*(1-IF(B3>=in_marketplace_from,d_hz_bills*G3,0)) | BQ4: =BQ3*d_rho_bills+BP4*IF(B4>=in_marketplace_from,d_hz_bills*G4,0) | BR4: =F4*BQ4*in_bills_ticket*in_bills_comm/12 | BS4: =BS3*(1-IF(B3>=in_marketplace_from,d_hz_loan_gold*G3,0)) | BT4: =F4*BS4*IF(B4>=in_marketplace_from,d_hz_loan_gold*G4,0)*in_loan_gold_ticket*in_loan_gold_comm | BU4: =BU3*(1-IF(B3>=in_marketplace_from,d_hz_loan_cd*G3,0)) | BV4: =F4*BU4*IF(B4>=in_marketplace_from,d_hz_loan_cd*G4,0)*in_loan_cd_ticket*in_loan_cd_comm | BW4: =BW3*(1-IF(B3>=in_marketplace_from,d_hz_loan_vehicle*G3,0)) | BX4: =F4*BW4*IF(B4>=in_marketplace_from,d_hz_loan_vehicle*G4,0)*in_loan_vehicle_ticket*in_loan_vehicle_comm | BY4: =BY3*(1-IF(B3>=in_marketplace_from,d_hz_loan_home*G3,0)*BZ3) | BZ4: =MIN(in_approval_cap,in_loan_home_approval*INDEX('Age profile'!$O$2:$O$61,B4)*(1+in_approval_growth)^(D4-1)) | CA4: =F4*BY4*IF(B4>=in_marketplace_from,d_hz_loan_home*G4,0)*BZ4*in_loan_home_ticket*in_loan_home_comm | CB4: =CB3*(1-IF(B3>=in_marketplace_from,d_hz_loan_lap*G3,0)*CC3) | CC4: =MIN(in_approval_cap,in_loan_lap_approval*INDEX('Age profile'!$O$2:$O$61,B4)*(1+in_approval_growth)^(D4-1)) | CD4: =F4*CB4*IF(B4>=in_marketplace_from,d_hz_loan_lap*G4,0)*CC4*in_loan_lap_ticket*in_loan_lap_comm | CE4: =AA4+AB4+AC4+AD4+AG4+AJ4+AM4+AP4+AS4+AU4+AX4+BB4+BE4+BG4+BJ4+BL4+BO4+BR4+BT4+BV4+BX4+CA4+CD4
A5: 1 | B5: 4 | C5: =A5+B5-1 | D5: =INT((C5-1)/12)+1 | E5: =INDEX(Monthly!$B$2:$B$61,A5) | F5: =E5*INDEX('Age profile'!$B$2:$B$61,B5) | G5: =MIN(in_takeup_cap,INDEX('Age profile'!$N$2:$N$61,B5)*(1+in_takeup_growth)^(D5-1)) | H5: =MIN(in_approval_cap,in_approved_first*INDEX('Age profile'!$O$2:$O$61,B5)*(1+in_approval_growth)^(D5-1)) | I5: =G5*MIN(in_takeup_cap,INDEX('Age profile'!$O$2:$O$61,B5)*(1+in_approval_growth)^(D5-1)) | J5: =(J4-L4)*F5/F4 | K5: =(K4-M4)*F5/F4+SUMIFS(O2:O4,B2:B4,B5-1-d_T)*F5 | L5: =IF(B5>=in_marketplace_from,J5*d_hz*G5*in_eligible*H5,0) | M5: =IF(B5>=in_marketplace_from,K5*d_hz*G5*in_eligible*in_approved_repeat,0) | N5: =L5+M5 | O5: =N5/F5 | P5: =F5-J5-K5 | Q5: =IF(B5>=in_marketplace_from,(J5+K5)*d_hz*G5,0) | R5: =SUMIFS(N2:N61,B2:B61,">="&(B5-d_T),B2:B61,"<="&(B5-1)) | S5: =(1-d_u)*S4+IF(d_T>in_topup_lag,SUMIFS(O2:O61,B2:B61,B5-in_topup_lag)-d_udrop*SUMIFS(O2:O61,B2:B61,B5-d_T),0) | T5: =F5*d_u*S5 | U5: =L5*in_ticket+M5*d_rep_ticket | V5: =U5+T5*d_topup_amt | W5: =N5+T5*d_topup_ratio | X5: =SUMIFS(W2:W61,B2:B61,B5-in_dpd_lag)*d_cured | Y5: =SUMIFS(W2:W61,B2:B61,B5-in_rec_lag)*d_recd | Z5: =IF(AND(B5>=in_marketplace_from,B5<in_marketplace_from+in_card_months),in_card_share/in_card_months*F5*I5,IF(AND(B5>=in_marketplace_from+in_card_months,B5<in_marketplace_from+2*in_card_months),in_card_share*d_card_rem/in_card_months*F5*MIN(in_takeup_cap,(1+in_takeup_growth)^(D5-1))*MIN(in_takeup_cap,(1+in_approval_growth)^(D5-1)),0)) | AA5: =V5*in_fee*(1-in_taken_back) | AB5: =SUMIFS(W2:W61,B2:B61,B5-in_dpd_lag)*d_dpd | AC5: =SUMIFS(W2:W61,B2:B61,B5-in_rec_lag)*d_rec | AD5: =Z5*in_card_fee | AE5: =AE4*(1-IF(B4>=in_marketplace_from,d_hz_hlth_small*G4,0)) | AF5: =AE5*IF(B5>=in_marketplace_from,d_hz_hlth_small*G5,0) | AG5: =F5*AF5*in_hlth_small_ticket*in_hlth_small_comm*in_ins_partner_share+F5*in_hlth_small_ticket*in_hlth_small_renew_comm*in_ins_partner_share*(in_hlth_small_renew^1*SUMIFS(AF2:AF61,B2:B61,B5-12)+in_hlth_small_renew^2*SUMIFS(AF2:AF61,B2:B61,B5-24)+in_hlth_small_renew^3*SUMIFS(AF2:AF61,B2:B61,B5-36)+in_hlth_small_renew^4*SUMIFS(AF2:AF61,B2:B61,B5-48)) | AH5: =AH4*(1-IF(B4>=in_marketplace_from,d_hz_hlth_family*G4,0)) | AI5: =AH5*IF(B5>=in_marketplace_from,d_hz_hlth_family*G5,0) | AJ5: =F5*AI5*in_hlth_family_ticket*in_hlth_family_comm*in_ins_partner_share+F5*in_hlth_family_ticket*in_hlth_family_renew_comm*in_ins_partner_share*(in_hlth_family_renew^1*SUMIFS(AI2:AI61,B2:B61,B5-12)+in_hlth_family_renew^2*SUMIFS(AI2:AI61,B2:B61,B5-24)+in_hlth_family_renew^3*SUMIFS(AI2:AI61,B2:B61,B5-36)+in_hlth_family_renew^4*SUMIFS(AI2:AI61,B2:B61,B5-48)) | AK5: =AK4*(1-IF(B4>=in_marketplace_from,d_hz_life_term*G4,0)) | AL5: =AK5*IF(B5>=in_marketplace_from,d_hz_life_term*G5,0) | AM5: =F5*AL5*in_life_term_ticket*in_life_term_comm*in_ins_partner_share+F5*in_life_term_ticket*in_life_term_renew_comm*in_ins_partner_share*(in_life_term_renew^1*SUMIFS(AL2:AL61,B2:B61,B5-12)+in_life_term_renew^2*SUMIFS(AL2:AL61,B2:B61,B5-24)+in_life_term_renew^3*SUMIFS(AL2:AL61,B2:B61,B5-36)+in_life_term_renew^4*SUMIFS(AL2:AL61,B2:B61,B5-48)) | AN5: =AN4*(1-IF(B4>=in_marketplace_from,d_hz_accident*G4,0)) | AO5: =AN5*IF(B5>=in_marketplace_from,d_hz_accident*G5,0) | AP5: =F5*AO5*in_accident_ticket*in_accident_comm*in_ins_partner_share+F5*in_accident_ticket*in_accident_renew_comm*in_ins_partner_share*(in_accident_renew^1*SUMIFS(AO2:AO61,B2:B61,B5-12)+in_accident_renew^2*SUMIFS(AO2:AO61,B2:B61,B5-24)+in_accident_renew^3*SUMIFS(AO2:AO61,B2:B61,B5-36)+in_accident_renew^4*SUMIFS(AO2:AO61,B2:B61,B5-48)) | AQ5: =AQ4*(1-IF(B4>=in_marketplace_from,d_hz_two_wheeler*G4,0)) | AR5: =AQ5*IF(B5>=in_marketplace_from,d_hz_two_wheeler*G5,0) | AS5: =F5*AR5*in_two_wheeler_ticket*in_two_wheeler_comm*in_ins_partner_share+F5*in_two_wheeler_ticket*in_two_wheeler_comm*in_ins_partner_share*(in_two_wheeler_renew^1*SUMIFS(AR2:AR61,B2:B61,B5-12)+in_two_wheeler_renew^2*SUMIFS(AR2:AR61,B2:B61,B5-24)+in_two_wheeler_renew^3*SUMIFS(AR2:AR61,B2:B61,B5-36)+in_two_wheeler_renew^4*SUMIFS(AR2:AR61,B2:B61,B5-48)) | AT5: =AT4*(1-IF(B4>=in_marketplace_from,d_hz_device*G4,0)) | AU5: =F5*AT5*IF(B5>=in_marketplace_from,d_hz_device*G5,0)*in_device_ticket*in_device_comm*in_ins_partner_share | AV5: =AV4*(1-IF(B4>=in_marketplace_from,d_hz_shop*G4,0)) | AW5: =AV5*IF(B5>=in_marketplace_from,d_hz_shop*G5,0) | AX5: =F5*AW5*in_shop_ticket*in_shop_comm*in_ins_partner_share+F5*in_shop_ticket*in_shop_renew_comm*in_ins_partner_share*(in_shop_renew^1*SUMIFS(AW2:AW61,B2:B61,B5-12)+in_shop_renew^2*SUMIFS(AW2:AW61,B2:B61,B5-24)+in_shop_renew^3*SUMIFS(AW2:AW61,B2:B61,B5-36)+in_shop_renew^4*SUMIFS(AW2:AW61,B2:B61,B5-48)) | AY5: =AY4*(1-IF(B4>=in_marketplace_from,d_hz_sip*G4,0)) | AZ5: =AZ4*d_rho_sip+AY5*IF(B5>=in_marketplace_from,d_hz_sip*G5,0) | BA5: =d_rho_sip*(BA4+AZ4) | BB5: =F5*in_sip_ticket*(BA5+0.5*AZ5)*in_sip_comm/12 | BC5: =BC4*(1-IF(B4>=in_marketplace_from,d_hz_choti*G4,0)) | BD5: =BC5*IF(B5>=in_marketplace_from,d_hz_choti*G5,0) | BE5: =F5*SUMIFS(BD2:BD61,B2:B61,B5-in_choti_months)*in_choti_renew*in_choti_ticket | BF5: =BF4*(1-IF(B4>=in_marketplace_from,d_hz_nps*G4,0)) | BG5: =F5*BF5*IF(B5>=in_marketplace_from,d_hz_nps*G5,0)*in_nps_ticket*in_nps_comm | BH5: =BH4*(1-IF(B4>=in_marketplace_from,d_hz_gold*G4,0)) | BI5: =BI4*d_rho_gold+BH5*IF(B5>=in_marketplace_from,d_hz_gold*G5,0) | BJ5: =F5*BI5*in_gold_ticket*in_gold_comm | BK5: =BK4*(1-IF(B4>=in_marketplace_from,d_hz_fd*G4,0)) | BL5: =F5*BK5*IF(B5>=in_marketplace_from,d_hz_fd*G5,0)*in_fd_ticket*in_fd_comm | BM5: =BM4*(1-IF(B4>=in_marketplace_from,d_hz_recharge*G4,0)) | BN5: =BN4*d_rho_recharge+BM5*IF(B5>=in_marketplace_from,d_hz_recharge*G5,0) | BO5: =F5*BN5*in_recharge_ticket*in_recharge_comm/12 | BP5: =BP4*(1-IF(B4>=in_marketplace_from,d_hz_bills*G4,0)) | BQ5: =BQ4*d_rho_bills+BP5*IF(B5>=in_marketplace_from,d_hz_bills*G5,0) | BR5: =F5*BQ5*in_bills_ticket*in_bills_comm/12 | BS5: =BS4*(1-IF(B4>=in_marketplace_from,d_hz_loan_gold*G4,0)) | BT5: =F5*BS5*IF(B5>=in_marketplace_from,d_hz_loan_gold*G5,0)*in_loan_gold_ticket*in_loan_gold_comm | BU5: =BU4*(1-IF(B4>=in_marketplace_from,d_hz_loan_cd*G4,0)) | BV5: =F5*BU5*IF(B5>=in_marketplace_from,d_hz_loan_cd*G5,0)*in_loan_cd_ticket*in_loan_cd_comm | BW5: =BW4*(1-IF(B4>=in_marketplace_from,d_hz_loan_vehicle*G4,0)) | BX5: =F5*BW5*IF(B5>=in_marketplace_from,d_hz_loan_vehicle*G5,0)*in_loan_vehicle_ticket*in_loan_vehicle_comm | BY5: =BY4*(1-IF(B4>=in_marketplace_from,d_hz_loan_home*G4,0)*BZ4) | BZ5: =MIN(in_approval_cap,in_loan_home_approval*INDEX('Age profile'!$O$2:$O$61,B5)*(1+in_approval_growth)^(D5-1)) | CA5: =F5*BY5*IF(B5>=in_marketplace_from,d_hz_loan_home*G5,0)*BZ5*in_loan_home_ticket*in_loan_home_comm | CB5: =CB4*(1-IF(B4>=in_marketplace_from,d_hz_loan_lap*G4,0)*CC4) | CC5: =MIN(in_approval_cap,in_loan_lap_approval*INDEX('Age profile'!$O$2:$O$61,B5)*(1+in_approval_growth)^(D5-1)) | CD5: =F5*CB5*IF(B5>=in_marketplace_from,d_hz_loan_lap*G5,0)*CC5*in_loan_lap_ticket*in_loan_lap_comm | CE5: =AA5+AB5+AC5+AD5+AG5+AJ5+AM5+AP5+AS5+AU5+AX5+BB5+BE5+BG5+BJ5+BL5+BO5+BR5+BT5+BV5+BX5+CA5+CD5
A6: 1 | B6: 5 | C6: =A6+B6-1 | D6: =INT((C6-1)/12)+1 | E6: =INDEX(Monthly!$B$2:$B$61,A6) | F6: =E6*INDEX('Age profile'!$B$2:$B$61,B6) | G6: =MIN(in_takeup_cap,INDEX('Age profile'!$N$2:$N$61,B6)*(1+in_takeup_growth)^(D6-1)) | H6: =MIN(in_approval_cap,in_approved_first*INDEX('Age profile'!$O$2:$O$61,B6)*(1+in_approval_growth)^(D6-1)) | I6: =G6*MIN(in_takeup_cap,INDEX('Age profile'!$O$2:$O$61,B6)*(1+in_approval_growth)^(D6-1)) | J6: =(J5-L5)*F6/F5 | K6: =(K5-M5)*F6/F5+SUMIFS(O2:O5,B2:B5,B6-1-d_T)*F6 | L6: =IF(B6>=in_marketplace_from,J6*d_hz*G6*in_eligible*H6,0) | M6: =IF(B6>=in_marketplace_from,K6*d_hz*G6*in_eligible*in_approved_repeat,0) | N6: =L6+M6 | O6: =N6/F6 | P6: =F6-J6-K6 | Q6: =IF(B6>=in_marketplace_from,(J6+K6)*d_hz*G6,0) | R6: =SUMIFS(N2:N61,B2:B61,">="&(B6-d_T),B2:B61,"<="&(B6-1)) | S6: =(1-d_u)*S5+IF(d_T>in_topup_lag,SUMIFS(O2:O61,B2:B61,B6-in_topup_lag)-d_udrop*SUMIFS(O2:O61,B2:B61,B6-d_T),0) | T6: =F6*d_u*S6 | U6: =L6*in_ticket+M6*d_rep_ticket | V6: =U6+T6*d_topup_amt | W6: =N6+T6*d_topup_ratio | X6: =SUMIFS(W2:W61,B2:B61,B6-in_dpd_lag)*d_cured | Y6: =SUMIFS(W2:W61,B2:B61,B6-in_rec_lag)*d_recd | Z6: =IF(AND(B6>=in_marketplace_from,B6<in_marketplace_from+in_card_months),in_card_share/in_card_months*F6*I6,IF(AND(B6>=in_marketplace_from+in_card_months,B6<in_marketplace_from+2*in_card_months),in_card_share*d_card_rem/in_card_months*F6*MIN(in_takeup_cap,(1+in_takeup_growth)^(D6-1))*MIN(in_takeup_cap,(1+in_approval_growth)^(D6-1)),0)) | AA6: =V6*in_fee*(1-in_taken_back) | AB6: =SUMIFS(W2:W61,B2:B61,B6-in_dpd_lag)*d_dpd | AC6: =SUMIFS(W2:W61,B2:B61,B6-in_rec_lag)*d_rec | AD6: =Z6*in_card_fee | AE6: =AE5*(1-IF(B5>=in_marketplace_from,d_hz_hlth_small*G5,0)) | AF6: =AE6*IF(B6>=in_marketplace_from,d_hz_hlth_small*G6,0) | AG6: =F6*AF6*in_hlth_small_ticket*in_hlth_small_comm*in_ins_partner_share+F6*in_hlth_small_ticket*in_hlth_small_renew_comm*in_ins_partner_share*(in_hlth_small_renew^1*SUMIFS(AF2:AF61,B2:B61,B6-12)+in_hlth_small_renew^2*SUMIFS(AF2:AF61,B2:B61,B6-24)+in_hlth_small_renew^3*SUMIFS(AF2:AF61,B2:B61,B6-36)+in_hlth_small_renew^4*SUMIFS(AF2:AF61,B2:B61,B6-48)) | AH6: =AH5*(1-IF(B5>=in_marketplace_from,d_hz_hlth_family*G5,0)) | AI6: =AH6*IF(B6>=in_marketplace_from,d_hz_hlth_family*G6,0) | AJ6: =F6*AI6*in_hlth_family_ticket*in_hlth_family_comm*in_ins_partner_share+F6*in_hlth_family_ticket*in_hlth_family_renew_comm*in_ins_partner_share*(in_hlth_family_renew^1*SUMIFS(AI2:AI61,B2:B61,B6-12)+in_hlth_family_renew^2*SUMIFS(AI2:AI61,B2:B61,B6-24)+in_hlth_family_renew^3*SUMIFS(AI2:AI61,B2:B61,B6-36)+in_hlth_family_renew^4*SUMIFS(AI2:AI61,B2:B61,B6-48)) | AK6: =AK5*(1-IF(B5>=in_marketplace_from,d_hz_life_term*G5,0)) | AL6: =AK6*IF(B6>=in_marketplace_from,d_hz_life_term*G6,0) | AM6: =F6*AL6*in_life_term_ticket*in_life_term_comm*in_ins_partner_share+F6*in_life_term_ticket*in_life_term_renew_comm*in_ins_partner_share*(in_life_term_renew^1*SUMIFS(AL2:AL61,B2:B61,B6-12)+in_life_term_renew^2*SUMIFS(AL2:AL61,B2:B61,B6-24)+in_life_term_renew^3*SUMIFS(AL2:AL61,B2:B61,B6-36)+in_life_term_renew^4*SUMIFS(AL2:AL61,B2:B61,B6-48)) | AN6: =AN5*(1-IF(B5>=in_marketplace_from,d_hz_accident*G5,0)) | AO6: =AN6*IF(B6>=in_marketplace_from,d_hz_accident*G6,0) | AP6: =F6*AO6*in_accident_ticket*in_accident_comm*in_ins_partner_share+F6*in_accident_ticket*in_accident_renew_comm*in_ins_partner_share*(in_accident_renew^1*SUMIFS(AO2:AO61,B2:B61,B6-12)+in_accident_renew^2*SUMIFS(AO2:AO61,B2:B61,B6-24)+in_accident_renew^3*SUMIFS(AO2:AO61,B2:B61,B6-36)+in_accident_renew^4*SUMIFS(AO2:AO61,B2:B61,B6-48)) | AQ6: =AQ5*(1-IF(B5>=in_marketplace_from,d_hz_two_wheeler*G5,0)) | AR6: =AQ6*IF(B6>=in_marketplace_from,d_hz_two_wheeler*G6,0) | AS6: =F6*AR6*in_two_wheeler_ticket*in_two_wheeler_comm*in_ins_partner_share+F6*in_two_wheeler_ticket*in_two_wheeler_comm*in_ins_partner_share*(in_two_wheeler_renew^1*SUMIFS(AR2:AR61,B2:B61,B6-12)+in_two_wheeler_renew^2*SUMIFS(AR2:AR61,B2:B61,B6-24)+in_two_wheeler_renew^3*SUMIFS(AR2:AR61,B2:B61,B6-36)+in_two_wheeler_renew^4*SUMIFS(AR2:AR61,B2:B61,B6-48)) | AT6: =AT5*(1-IF(B5>=in_marketplace_from,d_hz_device*G5,0)) | AU6: =F6*AT6*IF(B6>=in_marketplace_from,d_hz_device*G6,0)*in_device_ticket*in_device_comm*in_ins_partner_share | AV6: =AV5*(1-IF(B5>=in_marketplace_from,d_hz_shop*G5,0)) | AW6: =AV6*IF(B6>=in_marketplace_from,d_hz_shop*G6,0) | AX6: =F6*AW6*in_shop_ticket*in_shop_comm*in_ins_partner_share+F6*in_shop_ticket*in_shop_renew_comm*in_ins_partner_share*(in_shop_renew^1*SUMIFS(AW2:AW61,B2:B61,B6-12)+in_shop_renew^2*SUMIFS(AW2:AW61,B2:B61,B6-24)+in_shop_renew^3*SUMIFS(AW2:AW61,B2:B61,B6-36)+in_shop_renew^4*SUMIFS(AW2:AW61,B2:B61,B6-48)) | AY6: =AY5*(1-IF(B5>=in_marketplace_from,d_hz_sip*G5,0)) | AZ6: =AZ5*d_rho_sip+AY6*IF(B6>=in_marketplace_from,d_hz_sip*G6,0) | BA6: =d_rho_sip*(BA5+AZ5) | BB6: =F6*in_sip_ticket*(BA6+0.5*AZ6)*in_sip_comm/12 | BC6: =BC5*(1-IF(B5>=in_marketplace_from,d_hz_choti*G5,0)) | BD6: =BC6*IF(B6>=in_marketplace_from,d_hz_choti*G6,0) | BE6: =F6*SUMIFS(BD2:BD61,B2:B61,B6-in_choti_months)*in_choti_renew*in_choti_ticket | BF6: =BF5*(1-IF(B5>=in_marketplace_from,d_hz_nps*G5,0)) | BG6: =F6*BF6*IF(B6>=in_marketplace_from,d_hz_nps*G6,0)*in_nps_ticket*in_nps_comm | BH6: =BH5*(1-IF(B5>=in_marketplace_from,d_hz_gold*G5,0)) | BI6: =BI5*d_rho_gold+BH6*IF(B6>=in_marketplace_from,d_hz_gold*G6,0) | BJ6: =F6*BI6*in_gold_ticket*in_gold_comm | BK6: =BK5*(1-IF(B5>=in_marketplace_from,d_hz_fd*G5,0)) | BL6: =F6*BK6*IF(B6>=in_marketplace_from,d_hz_fd*G6,0)*in_fd_ticket*in_fd_comm | BM6: =BM5*(1-IF(B5>=in_marketplace_from,d_hz_recharge*G5,0)) | BN6: =BN5*d_rho_recharge+BM6*IF(B6>=in_marketplace_from,d_hz_recharge*G6,0) | BO6: =F6*BN6*in_recharge_ticket*in_recharge_comm/12 | BP6: =BP5*(1-IF(B5>=in_marketplace_from,d_hz_bills*G5,0)) | BQ6: =BQ5*d_rho_bills+BP6*IF(B6>=in_marketplace_from,d_hz_bills*G6,0) | BR6: =F6*BQ6*in_bills_ticket*in_bills_comm/12 | BS6: =BS5*(1-IF(B5>=in_marketplace_from,d_hz_loan_gold*G5,0)) | BT6: =F6*BS6*IF(B6>=in_marketplace_from,d_hz_loan_gold*G6,0)*in_loan_gold_ticket*in_loan_gold_comm | BU6: =BU5*(1-IF(B5>=in_marketplace_from,d_hz_loan_cd*G5,0)) | BV6: =F6*BU6*IF(B6>=in_marketplace_from,d_hz_loan_cd*G6,0)*in_loan_cd_ticket*in_loan_cd_comm | BW6: =BW5*(1-IF(B5>=in_marketplace_from,d_hz_loan_vehicle*G5,0)) | BX6: =F6*BW6*IF(B6>=in_marketplace_from,d_hz_loan_vehicle*G6,0)*in_loan_vehicle_ticket*in_loan_vehicle_comm | BY6: =BY5*(1-IF(B5>=in_marketplace_from,d_hz_loan_home*G5,0)*BZ5) | BZ6: =MIN(in_approval_cap,in_loan_home_approval*INDEX('Age profile'!$O$2:$O$61,B6)*(1+in_approval_growth)^(D6-1)) | CA6: =F6*BY6*IF(B6>=in_marketplace_from,d_hz_loan_home*G6,0)*BZ6*in_loan_home_ticket*in_loan_home_comm | CB6: =CB5*(1-IF(B5>=in_marketplace_from,d_hz_loan_lap*G5,0)*CC5) | CC6: =MIN(in_approval_cap,in_loan_lap_approval*INDEX('Age profile'!$O$2:$O$61,B6)*(1+in_approval_growth)^(D6-1)) | CD6: =F6*CB6*IF(B6>=in_marketplace_from,d_hz_loan_lap*G6,0)*CC6*in_loan_lap_ticket*in_loan_lap_comm | CE6: =AA6+AB6+AC6+AD6+AG6+AJ6+AM6+AP6+AS6+AU6+AX6+BB6+BE6+BG6+BJ6+BL6+BO6+BR6+BT6+BV6+BX6+CA6+CD6
A7: 1 | B7: 6 | C7: =A7+B7-1 | D7: =INT((C7-1)/12)+1 | E7: =INDEX(Monthly!$B$2:$B$61,A7) | F7: =E7*INDEX('Age profile'!$B$2:$B$61,B7) | G7: =MIN(in_takeup_cap,INDEX('Age profile'!$N$2:$N$61,B7)*(1+in_takeup_growth)^(D7-1)) | H7: =MIN(in_approval_cap,in_approved_first*INDEX('Age profile'!$O$2:$O$61,B7)*(1+in_approval_growth)^(D7-1)) | I7: =G7*MIN(in_takeup_cap,INDEX('Age profile'!$O$2:$O$61,B7)*(1+in_approval_growth)^(D7-1)) | J7: =(J6-L6)*F7/F6 | K7: =(K6-M6)*F7/F6+SUMIFS(O2:O6,B2:B6,B7-1-d_T)*F7 | L7: =IF(B7>=in_marketplace_from,J7*d_hz*G7*in_eligible*H7,0) | M7: =IF(B7>=in_marketplace_from,K7*d_hz*G7*in_eligible*in_approved_repeat,0) | N7: =L7+M7 | O7: =N7/F7 | P7: =F7-J7-K7 | Q7: =IF(B7>=in_marketplace_from,(J7+K7)*d_hz*G7,0) | R7: =SUMIFS(N2:N61,B2:B61,">="&(B7-d_T),B2:B61,"<="&(B7-1)) | S7: =(1-d_u)*S6+IF(d_T>in_topup_lag,SUMIFS(O2:O61,B2:B61,B7-in_topup_lag)-d_udrop*SUMIFS(O2:O61,B2:B61,B7-d_T),0) | T7: =F7*d_u*S7 | U7: =L7*in_ticket+M7*d_rep_ticket | V7: =U7+T7*d_topup_amt | W7: =N7+T7*d_topup_ratio | X7: =SUMIFS(W2:W61,B2:B61,B7-in_dpd_lag)*d_cured | Y7: =SUMIFS(W2:W61,B2:B61,B7-in_rec_lag)*d_recd | Z7: =IF(AND(B7>=in_marketplace_from,B7<in_marketplace_from+in_card_months),in_card_share/in_card_months*F7*I7,IF(AND(B7>=in_marketplace_from+in_card_months,B7<in_marketplace_from+2*in_card_months),in_card_share*d_card_rem/in_card_months*F7*MIN(in_takeup_cap,(1+in_takeup_growth)^(D7-1))*MIN(in_takeup_cap,(1+in_approval_growth)^(D7-1)),0)) | AA7: =V7*in_fee*(1-in_taken_back) | AB7: =SUMIFS(W2:W61,B2:B61,B7-in_dpd_lag)*d_dpd | AC7: =SUMIFS(W2:W61,B2:B61,B7-in_rec_lag)*d_rec | AD7: =Z7*in_card_fee | AE7: =AE6*(1-IF(B6>=in_marketplace_from,d_hz_hlth_small*G6,0)) | AF7: =AE7*IF(B7>=in_marketplace_from,d_hz_hlth_small*G7,0) | AG7: =F7*AF7*in_hlth_small_ticket*in_hlth_small_comm*in_ins_partner_share+F7*in_hlth_small_ticket*in_hlth_small_renew_comm*in_ins_partner_share*(in_hlth_small_renew^1*SUMIFS(AF2:AF61,B2:B61,B7-12)+in_hlth_small_renew^2*SUMIFS(AF2:AF61,B2:B61,B7-24)+in_hlth_small_renew^3*SUMIFS(AF2:AF61,B2:B61,B7-36)+in_hlth_small_renew^4*SUMIFS(AF2:AF61,B2:B61,B7-48)) | AH7: =AH6*(1-IF(B6>=in_marketplace_from,d_hz_hlth_family*G6,0)) | AI7: =AH7*IF(B7>=in_marketplace_from,d_hz_hlth_family*G7,0) | AJ7: =F7*AI7*in_hlth_family_ticket*in_hlth_family_comm*in_ins_partner_share+F7*in_hlth_family_ticket*in_hlth_family_renew_comm*in_ins_partner_share*(in_hlth_family_renew^1*SUMIFS(AI2:AI61,B2:B61,B7-12)+in_hlth_family_renew^2*SUMIFS(AI2:AI61,B2:B61,B7-24)+in_hlth_family_renew^3*SUMIFS(AI2:AI61,B2:B61,B7-36)+in_hlth_family_renew^4*SUMIFS(AI2:AI61,B2:B61,B7-48)) | AK7: =AK6*(1-IF(B6>=in_marketplace_from,d_hz_life_term*G6,0)) | AL7: =AK7*IF(B7>=in_marketplace_from,d_hz_life_term*G7,0) | AM7: =F7*AL7*in_life_term_ticket*in_life_term_comm*in_ins_partner_share+F7*in_life_term_ticket*in_life_term_renew_comm*in_ins_partner_share*(in_life_term_renew^1*SUMIFS(AL2:AL61,B2:B61,B7-12)+in_life_term_renew^2*SUMIFS(AL2:AL61,B2:B61,B7-24)+in_life_term_renew^3*SUMIFS(AL2:AL61,B2:B61,B7-36)+in_life_term_renew^4*SUMIFS(AL2:AL61,B2:B61,B7-48)) | AN7: =AN6*(1-IF(B6>=in_marketplace_from,d_hz_accident*G6,0)) | AO7: =AN7*IF(B7>=in_marketplace_from,d_hz_accident*G7,0) | AP7: =F7*AO7*in_accident_ticket*in_accident_comm*in_ins_partner_share+F7*in_accident_ticket*in_accident_renew_comm*in_ins_partner_share*(in_accident_renew^1*SUMIFS(AO2:AO61,B2:B61,B7-12)+in_accident_renew^2*SUMIFS(AO2:AO61,B2:B61,B7-24)+in_accident_renew^3*SUMIFS(AO2:AO61,B2:B61,B7-36)+in_accident_renew^4*SUMIFS(AO2:AO61,B2:B61,B7-48)) | AQ7: =AQ6*(1-IF(B6>=in_marketplace_from,d_hz_two_wheeler*G6,0)) | AR7: =AQ7*IF(B7>=in_marketplace_from,d_hz_two_wheeler*G7,0) | AS7: =F7*AR7*in_two_wheeler_ticket*in_two_wheeler_comm*in_ins_partner_share+F7*in_two_wheeler_ticket*in_two_wheeler_comm*in_ins_partner_share*(in_two_wheeler_renew^1*SUMIFS(AR2:AR61,B2:B61,B7-12)+in_two_wheeler_renew^2*SUMIFS(AR2:AR61,B2:B61,B7-24)+in_two_wheeler_renew^3*SUMIFS(AR2:AR61,B2:B61,B7-36)+in_two_wheeler_renew^4*SUMIFS(AR2:AR61,B2:B61,B7-48)) | AT7: =AT6*(1-IF(B6>=in_marketplace_from,d_hz_device*G6,0)) | AU7: =F7*AT7*IF(B7>=in_marketplace_from,d_hz_device*G7,0)*in_device_ticket*in_device_comm*in_ins_partner_share | AV7: =AV6*(1-IF(B6>=in_marketplace_from,d_hz_shop*G6,0)) | AW7: =AV7*IF(B7>=in_marketplace_from,d_hz_shop*G7,0) | AX7: =F7*AW7*in_shop_ticket*in_shop_comm*in_ins_partner_share+F7*in_shop_ticket*in_shop_renew_comm*in_ins_partner_share*(in_shop_renew^1*SUMIFS(AW2:AW61,B2:B61,B7-12)+in_shop_renew^2*SUMIFS(AW2:AW61,B2:B61,B7-24)+in_shop_renew^3*SUMIFS(AW2:AW61,B2:B61,B7-36)+in_shop_renew^4*SUMIFS(AW2:AW61,B2:B61,B7-48)) | AY7: =AY6*(1-IF(B6>=in_marketplace_from,d_hz_sip*G6,0)) | AZ7: =AZ6*d_rho_sip+AY7*IF(B7>=in_marketplace_from,d_hz_sip*G7,0) | BA7: =d_rho_sip*(BA6+AZ6) | BB7: =F7*in_sip_ticket*(BA7+0.5*AZ7)*in_sip_comm/12 | BC7: =BC6*(1-IF(B6>=in_marketplace_from,d_hz_choti*G6,0)) | BD7: =BC7*IF(B7>=in_marketplace_from,d_hz_choti*G7,0) | BE7: =F7*SUMIFS(BD2:BD61,B2:B61,B7-in_choti_months)*in_choti_renew*in_choti_ticket | BF7: =BF6*(1-IF(B6>=in_marketplace_from,d_hz_nps*G6,0)) | BG7: =F7*BF7*IF(B7>=in_marketplace_from,d_hz_nps*G7,0)*in_nps_ticket*in_nps_comm | BH7: =BH6*(1-IF(B6>=in_marketplace_from,d_hz_gold*G6,0)) | BI7: =BI6*d_rho_gold+BH7*IF(B7>=in_marketplace_from,d_hz_gold*G7,0) | BJ7: =F7*BI7*in_gold_ticket*in_gold_comm | BK7: =BK6*(1-IF(B6>=in_marketplace_from,d_hz_fd*G6,0)) | BL7: =F7*BK7*IF(B7>=in_marketplace_from,d_hz_fd*G7,0)*in_fd_ticket*in_fd_comm | BM7: =BM6*(1-IF(B6>=in_marketplace_from,d_hz_recharge*G6,0)) | BN7: =BN6*d_rho_recharge+BM7*IF(B7>=in_marketplace_from,d_hz_recharge*G7,0) | BO7: =F7*BN7*in_recharge_ticket*in_recharge_comm/12 | BP7: =BP6*(1-IF(B6>=in_marketplace_from,d_hz_bills*G6,0)) | BQ7: =BQ6*d_rho_bills+BP7*IF(B7>=in_marketplace_from,d_hz_bills*G7,0) | BR7: =F7*BQ7*in_bills_ticket*in_bills_comm/12 | BS7: =BS6*(1-IF(B6>=in_marketplace_from,d_hz_loan_gold*G6,0)) | BT7: =F7*BS7*IF(B7>=in_marketplace_from,d_hz_loan_gold*G7,0)*in_loan_gold_ticket*in_loan_gold_comm | BU7: =BU6*(1-IF(B6>=in_marketplace_from,d_hz_loan_cd*G6,0)) | BV7: =F7*BU7*IF(B7>=in_marketplace_from,d_hz_loan_cd*G7,0)*in_loan_cd_ticket*in_loan_cd_comm | BW7: =BW6*(1-IF(B6>=in_marketplace_from,d_hz_loan_vehicle*G6,0)) | BX7: =F7*BW7*IF(B7>=in_marketplace_from,d_hz_loan_vehicle*G7,0)*in_loan_vehicle_ticket*in_loan_vehicle_comm | BY7: =BY6*(1-IF(B6>=in_marketplace_from,d_hz_loan_home*G6,0)*BZ6) | BZ7: =MIN(in_approval_cap,in_loan_home_approval*INDEX('Age profile'!$O$2:$O$61,B7)*(1+in_approval_growth)^(D7-1)) | CA7: =F7*BY7*IF(B7>=in_marketplace_from,d_hz_loan_home*G7,0)*BZ7*in_loan_home_ticket*in_loan_home_comm | CB7: =CB6*(1-IF(B6>=in_marketplace_from,d_hz_loan_lap*G6,0)*CC6) | CC7: =MIN(in_approval_cap,in_loan_lap_approval*INDEX('Age profile'!$O$2:$O$61,B7)*(1+in_approval_growth)^(D7-1)) | CD7: =F7*CB7*IF(B7>=in_marketplace_from,d_hz_loan_lap*G7,0)*CC7*in_loan_lap_ticket*in_loan_lap_comm | CE7: =AA7+AB7+AC7+AD7+AG7+AJ7+AM7+AP7+AS7+AU7+AX7+BB7+BE7+BG7+BJ7+BL7+BO7+BR7+BT7+BV7+BX7+CA7+CD7
A8: 1 | B8: 7 | C8: =A8+B8-1 | D8: =INT((C8-1)/12)+1 | E8: =INDEX(Monthly!$B$2:$B$61,A8) | F8: =E8*INDEX('Age profile'!$B$2:$B$61,B8) | G8: =MIN(in_takeup_cap,INDEX('Age profile'!$N$2:$N$61,B8)*(1+in_takeup_growth)^(D8-1)) | H8: =MIN(in_approval_cap,in_approved_first*INDEX('Age profile'!$O$2:$O$61,B8)*(1+in_approval_growth)^(D8-1)) | I8: =G8*MIN(in_takeup_cap,INDEX('Age profile'!$O$2:$O$61,B8)*(1+in_approval_growth)^(D8-1)) | J8: =(J7-L7)*F8/F7 | K8: =(K7-M7)*F8/F7+SUMIFS(O2:O7,B2:B7,B8-1-d_T)*F8 | L8: =IF(B8>=in_marketplace_from,J8*d_hz*G8*in_eligible*H8,0) | M8: =IF(B8>=in_marketplace_from,K8*d_hz*G8*in_eligible*in_approved_repeat,0) | N8: =L8+M8 | O8: =N8/F8 | P8: =F8-J8-K8 | Q8: =IF(B8>=in_marketplace_from,(J8+K8)*d_hz*G8,0) | R8: =SUMIFS(N2:N61,B2:B61,">="&(B8-d_T),B2:B61,"<="&(B8-1)) | S8: =(1-d_u)*S7+IF(d_T>in_topup_lag,SUMIFS(O2:O61,B2:B61,B8-in_topup_lag)-d_udrop*SUMIFS(O2:O61,B2:B61,B8-d_T),0) | T8: =F8*d_u*S8 | U8: =L8*in_ticket+M8*d_rep_ticket | V8: =U8+T8*d_topup_amt | W8: =N8+T8*d_topup_ratio | X8: =SUMIFS(W2:W61,B2:B61,B8-in_dpd_lag)*d_cured | Y8: =SUMIFS(W2:W61,B2:B61,B8-in_rec_lag)*d_recd | Z8: =IF(AND(B8>=in_marketplace_from,B8<in_marketplace_from+in_card_months),in_card_share/in_card_months*F8*I8,IF(AND(B8>=in_marketplace_from+in_card_months,B8<in_marketplace_from+2*in_card_months),in_card_share*d_card_rem/in_card_months*F8*MIN(in_takeup_cap,(1+in_takeup_growth)^(D8-1))*MIN(in_takeup_cap,(1+in_approval_growth)^(D8-1)),0)) | AA8: =V8*in_fee*(1-in_taken_back) | AB8: =SUMIFS(W2:W61,B2:B61,B8-in_dpd_lag)*d_dpd | AC8: =SUMIFS(W2:W61,B2:B61,B8-in_rec_lag)*d_rec | AD8: =Z8*in_card_fee | AE8: =AE7*(1-IF(B7>=in_marketplace_from,d_hz_hlth_small*G7,0)) | AF8: =AE8*IF(B8>=in_marketplace_from,d_hz_hlth_small*G8,0) | AG8: =F8*AF8*in_hlth_small_ticket*in_hlth_small_comm*in_ins_partner_share+F8*in_hlth_small_ticket*in_hlth_small_renew_comm*in_ins_partner_share*(in_hlth_small_renew^1*SUMIFS(AF2:AF61,B2:B61,B8-12)+in_hlth_small_renew^2*SUMIFS(AF2:AF61,B2:B61,B8-24)+in_hlth_small_renew^3*SUMIFS(AF2:AF61,B2:B61,B8-36)+in_hlth_small_renew^4*SUMIFS(AF2:AF61,B2:B61,B8-48)) | AH8: =AH7*(1-IF(B7>=in_marketplace_from,d_hz_hlth_family*G7,0)) | AI8: =AH8*IF(B8>=in_marketplace_from,d_hz_hlth_family*G8,0) | AJ8: =F8*AI8*in_hlth_family_ticket*in_hlth_family_comm*in_ins_partner_share+F8*in_hlth_family_ticket*in_hlth_family_renew_comm*in_ins_partner_share*(in_hlth_family_renew^1*SUMIFS(AI2:AI61,B2:B61,B8-12)+in_hlth_family_renew^2*SUMIFS(AI2:AI61,B2:B61,B8-24)+in_hlth_family_renew^3*SUMIFS(AI2:AI61,B2:B61,B8-36)+in_hlth_family_renew^4*SUMIFS(AI2:AI61,B2:B61,B8-48)) | AK8: =AK7*(1-IF(B7>=in_marketplace_from,d_hz_life_term*G7,0)) | AL8: =AK8*IF(B8>=in_marketplace_from,d_hz_life_term*G8,0) | AM8: =F8*AL8*in_life_term_ticket*in_life_term_comm*in_ins_partner_share+F8*in_life_term_ticket*in_life_term_renew_comm*in_ins_partner_share*(in_life_term_renew^1*SUMIFS(AL2:AL61,B2:B61,B8-12)+in_life_term_renew^2*SUMIFS(AL2:AL61,B2:B61,B8-24)+in_life_term_renew^3*SUMIFS(AL2:AL61,B2:B61,B8-36)+in_life_term_renew^4*SUMIFS(AL2:AL61,B2:B61,B8-48)) | AN8: =AN7*(1-IF(B7>=in_marketplace_from,d_hz_accident*G7,0)) | AO8: =AN8*IF(B8>=in_marketplace_from,d_hz_accident*G8,0) | AP8: =F8*AO8*in_accident_ticket*in_accident_comm*in_ins_partner_share+F8*in_accident_ticket*in_accident_renew_comm*in_ins_partner_share*(in_accident_renew^1*SUMIFS(AO2:AO61,B2:B61,B8-12)+in_accident_renew^2*SUMIFS(AO2:AO61,B2:B61,B8-24)+in_accident_renew^3*SUMIFS(AO2:AO61,B2:B61,B8-36)+in_accident_renew^4*SUMIFS(AO2:AO61,B2:B61,B8-48)) | AQ8: =AQ7*(1-IF(B7>=in_marketplace_from,d_hz_two_wheeler*G7,0)) | AR8: =AQ8*IF(B8>=in_marketplace_from,d_hz_two_wheeler*G8,0) | AS8: =F8*AR8*in_two_wheeler_ticket*in_two_wheeler_comm*in_ins_partner_share+F8*in_two_wheeler_ticket*in_two_wheeler_comm*in_ins_partner_share*(in_two_wheeler_renew^1*SUMIFS(AR2:AR61,B2:B61,B8-12)+in_two_wheeler_renew^2*SUMIFS(AR2:AR61,B2:B61,B8-24)+in_two_wheeler_renew^3*SUMIFS(AR2:AR61,B2:B61,B8-36)+in_two_wheeler_renew^4*SUMIFS(AR2:AR61,B2:B61,B8-48)) | AT8: =AT7*(1-IF(B7>=in_marketplace_from,d_hz_device*G7,0)) | AU8: =F8*AT8*IF(B8>=in_marketplace_from,d_hz_device*G8,0)*in_device_ticket*in_device_comm*in_ins_partner_share | AV8: =AV7*(1-IF(B7>=in_marketplace_from,d_hz_shop*G7,0)) | AW8: =AV8*IF(B8>=in_marketplace_from,d_hz_shop*G8,0) | AX8: =F8*AW8*in_shop_ticket*in_shop_comm*in_ins_partner_share+F8*in_shop_ticket*in_shop_renew_comm*in_ins_partner_share*(in_shop_renew^1*SUMIFS(AW2:AW61,B2:B61,B8-12)+in_shop_renew^2*SUMIFS(AW2:AW61,B2:B61,B8-24)+in_shop_renew^3*SUMIFS(AW2:AW61,B2:B61,B8-36)+in_shop_renew^4*SUMIFS(AW2:AW61,B2:B61,B8-48)) | AY8: =AY7*(1-IF(B7>=in_marketplace_from,d_hz_sip*G7,0)) | AZ8: =AZ7*d_rho_sip+AY8*IF(B8>=in_marketplace_from,d_hz_sip*G8,0) | BA8: =d_rho_sip*(BA7+AZ7) | BB8: =F8*in_sip_ticket*(BA8+0.5*AZ8)*in_sip_comm/12 | BC8: =BC7*(1-IF(B7>=in_marketplace_from,d_hz_choti*G7,0)) | BD8: =BC8*IF(B8>=in_marketplace_from,d_hz_choti*G8,0) | BE8: =F8*SUMIFS(BD2:BD61,B2:B61,B8-in_choti_months)*in_choti_renew*in_choti_ticket | BF8: =BF7*(1-IF(B7>=in_marketplace_from,d_hz_nps*G7,0)) | BG8: =F8*BF8*IF(B8>=in_marketplace_from,d_hz_nps*G8,0)*in_nps_ticket*in_nps_comm | BH8: =BH7*(1-IF(B7>=in_marketplace_from,d_hz_gold*G7,0)) | BI8: =BI7*d_rho_gold+BH8*IF(B8>=in_marketplace_from,d_hz_gold*G8,0) | BJ8: =F8*BI8*in_gold_ticket*in_gold_comm | BK8: =BK7*(1-IF(B7>=in_marketplace_from,d_hz_fd*G7,0)) | BL8: =F8*BK8*IF(B8>=in_marketplace_from,d_hz_fd*G8,0)*in_fd_ticket*in_fd_comm | BM8: =BM7*(1-IF(B7>=in_marketplace_from,d_hz_recharge*G7,0)) | BN8: =BN7*d_rho_recharge+BM8*IF(B8>=in_marketplace_from,d_hz_recharge*G8,0) | BO8: =F8*BN8*in_recharge_ticket*in_recharge_comm/12 | BP8: =BP7*(1-IF(B7>=in_marketplace_from,d_hz_bills*G7,0)) | BQ8: =BQ7*d_rho_bills+BP8*IF(B8>=in_marketplace_from,d_hz_bills*G8,0) | BR8: =F8*BQ8*in_bills_ticket*in_bills_comm/12 | BS8: =BS7*(1-IF(B7>=in_marketplace_from,d_hz_loan_gold*G7,0)) | BT8: =F8*BS8*IF(B8>=in_marketplace_from,d_hz_loan_gold*G8,0)*in_loan_gold_ticket*in_loan_gold_comm | BU8: =BU7*(1-IF(B7>=in_marketplace_from,d_hz_loan_cd*G7,0)) | BV8: =F8*BU8*IF(B8>=in_marketplace_from,d_hz_loan_cd*G8,0)*in_loan_cd_ticket*in_loan_cd_comm | BW8: =BW7*(1-IF(B7>=in_marketplace_from,d_hz_loan_vehicle*G7,0)) | BX8: =F8*BW8*IF(B8>=in_marketplace_from,d_hz_loan_vehicle*G8,0)*in_loan_vehicle_ticket*in_loan_vehicle_comm | BY8: =BY7*(1-IF(B7>=in_marketplace_from,d_hz_loan_home*G7,0)*BZ7) | BZ8: =MIN(in_approval_cap,in_loan_home_approval*INDEX('Age profile'!$O$2:$O$61,B8)*(1+in_approval_growth)^(D8-1)) | CA8: =F8*BY8*IF(B8>=in_marketplace_from,d_hz_loan_home*G8,0)*BZ8*in_loan_home_ticket*in_loan_home_comm | CB8: =CB7*(1-IF(B7>=in_marketplace_from,d_hz_loan_lap*G7,0)*CC7) | CC8: =MIN(in_approval_cap,in_loan_lap_approval*INDEX('Age profile'!$O$2:$O$61,B8)*(1+in_approval_growth)^(D8-1)) | CD8: =F8*CB8*IF(B8>=in_marketplace_from,d_hz_loan_lap*G8,0)*CC8*in_loan_lap_ticket*in_loan_lap_comm | CE8: =AA8+AB8+AC8+AD8+AG8+AJ8+AM8+AP8+AS8+AU8+AX8+BB8+BE8+BG8+BJ8+BL8+BO8+BR8+BT8+BV8+BX8+CA8+CD8
A9: 1 | B9: 8 | C9: =A9+B9-1 | D9: =INT((C9-1)/12)+1 | E9: =INDEX(Monthly!$B$2:$B$61,A9) | F9: =E9*INDEX('Age profile'!$B$2:$B$61,B9) | G9: =MIN(in_takeup_cap,INDEX('Age profile'!$N$2:$N$61,B9)*(1+in_takeup_growth)^(D9-1)) | H9: =MIN(in_approval_cap,in_approved_first*INDEX('Age profile'!$O$2:$O$61,B9)*(1+in_approval_growth)^(D9-1)) | I9: =G9*MIN(in_takeup_cap,INDEX('Age profile'!$O$2:$O$61,B9)*(1+in_approval_growth)^(D9-1)) | J9: =(J8-L8)*F9/F8 | K9: =(K8-M8)*F9/F8+SUMIFS(O2:O8,B2:B8,B9-1-d_T)*F9 | L9: =IF(B9>=in_marketplace_from,J9*d_hz*G9*in_eligible*H9,0) | M9: =IF(B9>=in_marketplace_from,K9*d_hz*G9*in_eligible*in_approved_repeat,0) | N9: =L9+M9 | O9: =N9/F9 | P9: =F9-J9-K9 | Q9: =IF(B9>=in_marketplace_from,(J9+K9)*d_hz*G9,0) | R9: =SUMIFS(N2:N61,B2:B61,">="&(B9-d_T),B2:B61,"<="&(B9-1)) | S9: =(1-d_u)*S8+IF(d_T>in_topup_lag,SUMIFS(O2:O61,B2:B61,B9-in_topup_lag)-d_udrop*SUMIFS(O2:O61,B2:B61,B9-d_T),0) | T9: =F9*d_u*S9 | U9: =L9*in_ticket+M9*d_rep_ticket | V9: =U9+T9*d_topup_amt | W9: =N9+T9*d_topup_ratio | X9: =SUMIFS(W2:W61,B2:B61,B9-in_dpd_lag)*d_cured | Y9: =SUMIFS(W2:W61,B2:B61,B9-in_rec_lag)*d_recd | Z9: =IF(AND(B9>=in_marketplace_from,B9<in_marketplace_from+in_card_months),in_card_share/in_card_months*F9*I9,IF(AND(B9>=in_marketplace_from+in_card_months,B9<in_marketplace_from+2*in_card_months),in_card_share*d_card_rem/in_card_months*F9*MIN(in_takeup_cap,(1+in_takeup_growth)^(D9-1))*MIN(in_takeup_cap,(1+in_approval_growth)^(D9-1)),0)) | AA9: =V9*in_fee*(1-in_taken_back) | AB9: =SUMIFS(W2:W61,B2:B61,B9-in_dpd_lag)*d_dpd | AC9: =SUMIFS(W2:W61,B2:B61,B9-in_rec_lag)*d_rec | AD9: =Z9*in_card_fee | AE9: =AE8*(1-IF(B8>=in_marketplace_from,d_hz_hlth_small*G8,0)) | AF9: =AE9*IF(B9>=in_marketplace_from,d_hz_hlth_small*G9,0) | AG9: =F9*AF9*in_hlth_small_ticket*in_hlth_small_comm*in_ins_partner_share+F9*in_hlth_small_ticket*in_hlth_small_renew_comm*in_ins_partner_share*(in_hlth_small_renew^1*SUMIFS(AF2:AF61,B2:B61,B9-12)+in_hlth_small_renew^2*SUMIFS(AF2:AF61,B2:B61,B9-24)+in_hlth_small_renew^3*SUMIFS(AF2:AF61,B2:B61,B9-36)+in_hlth_small_renew^4*SUMIFS(AF2:AF61,B2:B61,B9-48)) | AH9: =AH8*(1-IF(B8>=in_marketplace_from,d_hz_hlth_family*G8,0)) | AI9: =AH9*IF(B9>=in_marketplace_from,d_hz_hlth_family*G9,0) | AJ9: =F9*AI9*in_hlth_family_ticket*in_hlth_family_comm*in_ins_partner_share+F9*in_hlth_family_ticket*in_hlth_family_renew_comm*in_ins_partner_share*(in_hlth_family_renew^1*SUMIFS(AI2:AI61,B2:B61,B9-12)+in_hlth_family_renew^2*SUMIFS(AI2:AI61,B2:B61,B9-24)+in_hlth_family_renew^3*SUMIFS(AI2:AI61,B2:B61,B9-36)+in_hlth_family_renew^4*SUMIFS(AI2:AI61,B2:B61,B9-48)) | AK9: =AK8*(1-IF(B8>=in_marketplace_from,d_hz_life_term*G8,0)) | AL9: =AK9*IF(B9>=in_marketplace_from,d_hz_life_term*G9,0) | AM9: =F9*AL9*in_life_term_ticket*in_life_term_comm*in_ins_partner_share+F9*in_life_term_ticket*in_life_term_renew_comm*in_ins_partner_share*(in_life_term_renew^1*SUMIFS(AL2:AL61,B2:B61,B9-12)+in_life_term_renew^2*SUMIFS(AL2:AL61,B2:B61,B9-24)+in_life_term_renew^3*SUMIFS(AL2:AL61,B2:B61,B9-36)+in_life_term_renew^4*SUMIFS(AL2:AL61,B2:B61,B9-48)) | AN9: =AN8*(1-IF(B8>=in_marketplace_from,d_hz_accident*G8,0)) | AO9: =AN9*IF(B9>=in_marketplace_from,d_hz_accident*G9,0) | AP9: =F9*AO9*in_accident_ticket*in_accident_comm*in_ins_partner_share+F9*in_accident_ticket*in_accident_renew_comm*in_ins_partner_share*(in_accident_renew^1*SUMIFS(AO2:AO61,B2:B61,B9-12)+in_accident_renew^2*SUMIFS(AO2:AO61,B2:B61,B9-24)+in_accident_renew^3*SUMIFS(AO2:AO61,B2:B61,B9-36)+in_accident_renew^4*SUMIFS(AO2:AO61,B2:B61,B9-48)) | AQ9: =AQ8*(1-IF(B8>=in_marketplace_from,d_hz_two_wheeler*G8,0)) | AR9: =AQ9*IF(B9>=in_marketplace_from,d_hz_two_wheeler*G9,0) | AS9: =F9*AR9*in_two_wheeler_ticket*in_two_wheeler_comm*in_ins_partner_share+F9*in_two_wheeler_ticket*in_two_wheeler_comm*in_ins_partner_share*(in_two_wheeler_renew^1*SUMIFS(AR2:AR61,B2:B61,B9-12)+in_two_wheeler_renew^2*SUMIFS(AR2:AR61,B2:B61,B9-24)+in_two_wheeler_renew^3*SUMIFS(AR2:AR61,B2:B61,B9-36)+in_two_wheeler_renew^4*SUMIFS(AR2:AR61,B2:B61,B9-48)) | AT9: =AT8*(1-IF(B8>=in_marketplace_from,d_hz_device*G8,0)) | AU9: =F9*AT9*IF(B9>=in_marketplace_from,d_hz_device*G9,0)*in_device_ticket*in_device_comm*in_ins_partner_share | AV9: =AV8*(1-IF(B8>=in_marketplace_from,d_hz_shop*G8,0)) | AW9: =AV9*IF(B9>=in_marketplace_from,d_hz_shop*G9,0) | AX9: =F9*AW9*in_shop_ticket*in_shop_comm*in_ins_partner_share+F9*in_shop_ticket*in_shop_renew_comm*in_ins_partner_share*(in_shop_renew^1*SUMIFS(AW2:AW61,B2:B61,B9-12)+in_shop_renew^2*SUMIFS(AW2:AW61,B2:B61,B9-24)+in_shop_renew^3*SUMIFS(AW2:AW61,B2:B61,B9-36)+in_shop_renew^4*SUMIFS(AW2:AW61,B2:B61,B9-48)) | AY9: =AY8*(1-IF(B8>=in_marketplace_from,d_hz_sip*G8,0)) | AZ9: =AZ8*d_rho_sip+AY9*IF(B9>=in_marketplace_from,d_hz_sip*G9,0) | BA9: =d_rho_sip*(BA8+AZ8) | BB9: =F9*in_sip_ticket*(BA9+0.5*AZ9)*in_sip_comm/12 | BC9: =BC8*(1-IF(B8>=in_marketplace_from,d_hz_choti*G8,0)) | BD9: =BC9*IF(B9>=in_marketplace_from,d_hz_choti*G9,0) | BE9: =F9*SUMIFS(BD2:BD61,B2:B61,B9-in_choti_months)*in_choti_renew*in_choti_ticket | BF9: =BF8*(1-IF(B8>=in_marketplace_from,d_hz_nps*G8,0)) | BG9: =F9*BF9*IF(B9>=in_marketplace_from,d_hz_nps*G9,0)*in_nps_ticket*in_nps_comm | BH9: =BH8*(1-IF(B8>=in_marketplace_from,d_hz_gold*G8,0)) | BI9: =BI8*d_rho_gold+BH9*IF(B9>=in_marketplace_from,d_hz_gold*G9,0) | BJ9: =F9*BI9*in_gold_ticket*in_gold_comm | BK9: =BK8*(1-IF(B8>=in_marketplace_from,d_hz_fd*G8,0)) | BL9: =F9*BK9*IF(B9>=in_marketplace_from,d_hz_fd*G9,0)*in_fd_ticket*in_fd_comm | BM9: =BM8*(1-IF(B8>=in_marketplace_from,d_hz_recharge*G8,0)) | BN9: =BN8*d_rho_recharge+BM9*IF(B9>=in_marketplace_from,d_hz_recharge*G9,0) | BO9: =F9*BN9*in_recharge_ticket*in_recharge_comm/12 | BP9: =BP8*(1-IF(B8>=in_marketplace_from,d_hz_bills*G8,0)) | BQ9: =BQ8*d_rho_bills+BP9*IF(B9>=in_marketplace_from,d_hz_bills*G9,0) | BR9: =F9*BQ9*in_bills_ticket*in_bills_comm/12 | BS9: =BS8*(1-IF(B8>=in_marketplace_from,d_hz_loan_gold*G8,0)) | BT9: =F9*BS9*IF(B9>=in_marketplace_from,d_hz_loan_gold*G9,0)*in_loan_gold_ticket*in_loan_gold_comm | BU9: =BU8*(1-IF(B8>=in_marketplace_from,d_hz_loan_cd*G8,0)) | BV9: =F9*BU9*IF(B9>=in_marketplace_from,d_hz_loan_cd*G9,0)*in_loan_cd_ticket*in_loan_cd_comm | BW9: =BW8*(1-IF(B8>=in_marketplace_from,d_hz_loan_vehicle*G8,0)) | BX9: =F9*BW9*IF(B9>=in_marketplace_from,d_hz_loan_vehicle*G9,0)*in_loan_vehicle_ticket*in_loan_vehicle_comm | BY9: =BY8*(1-IF(B8>=in_marketplace_from,d_hz_loan_home*G8,0)*BZ8) | BZ9: =MIN(in_approval_cap,in_loan_home_approval*INDEX('Age profile'!$O$2:$O$61,B9)*(1+in_approval_growth)^(D9-1)) | CA9: =F9*BY9*IF(B9>=in_marketplace_from,d_hz_loan_home*G9,0)*BZ9*in_loan_home_ticket*in_loan_home_comm | CB9: =CB8*(1-IF(B8>=in_marketplace_from,d_hz_loan_lap*G8,0)*CC8) | CC9: =MIN(in_approval_cap,in_loan_lap_approval*INDEX('Age profile'!$O$2:$O$61,B9)*(1+in_approval_growth)^(D9-1)) | CD9: =F9*CB9*IF(B9>=in_marketplace_from,d_hz_loan_lap*G9,0)*CC9*in_loan_lap_ticket*in_loan_lap_comm | CE9: =AA9+AB9+AC9+AD9+AG9+AJ9+AM9+AP9+AS9+AU9+AX9+BB9+BE9+BG9+BJ9+BL9+BO9+BR9+BT9+BV9+BX9+CA9+CD9
A10: 1 | B10: 9 | C10: =A10+B10-1 | D10: =INT((C10-1)/12)+1 | E10: =INDEX(Monthly!$B$2:$B$61,A10) | F10: =E10*INDEX('Age profile'!$B$2:$B$61,B10) | G10: =MIN(in_takeup_cap,INDEX('Age profile'!$N$2:$N$61,B10)*(1+in_takeup_growth)^(D10-1)) | H10: =MIN(in_approval_cap,in_approved_first*INDEX('Age profile'!$O$2:$O$61,B10)*(1+in_approval_growth)^(D10-1)) | I10: =G10*MIN(in_takeup_cap,INDEX('Age profile'!$O$2:$O$61,B10)*(1+in_approval_growth)^(D10-1)) | J10: =(J9-L9)*F10/F9 | K10: =(K9-M9)*F10/F9+SUMIFS(O2:O9,B2:B9,B10-1-d_T)*F10 | L10: =IF(B10>=in_marketplace_from,J10*d_hz*G10*in_eligible*H10,0) | M10: =IF(B10>=in_marketplace_from,K10*d_hz*G10*in_eligible*in_approved_repeat,0) | N10: =L10+M10 | O10: =N10/F10 | P10: =F10-J10-K10 | Q10: =IF(B10>=in_marketplace_from,(J10+K10)*d_hz*G10,0) | R10: =SUMIFS(N2:N61,B2:B61,">="&(B10-d_T),B2:B61,"<="&(B10-1)) | S10: =(1-d_u)*S9+IF(d_T>in_topup_lag,SUMIFS(O2:O61,B2:B61,B10-in_topup_lag)-d_udrop*SUMIFS(O2:O61,B2:B61,B10-d_T),0) | T10: =F10*d_u*S10 | U10: =L10*in_ticket+M10*d_rep_ticket | V10: =U10+T10*d_topup_amt | W10: =N10+T10*d_topup_ratio | X10: =SUMIFS(W2:W61,B2:B61,B10-in_dpd_lag)*d_cured | Y10: =SUMIFS(W2:W61,B2:B61,B10-in_rec_lag)*d_recd | Z10: =IF(AND(B10>=in_marketplace_from,B10<in_marketplace_from+in_card_months),in_card_share/in_card_months*F10*I10,IF(AND(B10>=in_marketplace_from+in_card_months,B10<in_marketplace_from+2*in_card_months),in_card_share*d_card_rem/in_card_months*F10*MIN(in_takeup_cap,(1+in_takeup_growth)^(D10-1))*MIN(in_takeup_cap,(1+in_approval_growth)^(D10-1)),0)) | AA10: =V10*in_fee*(1-in_taken_back) | AB10: =SUMIFS(W2:W61,B2:B61,B10-in_dpd_lag)*d_dpd | AC10: =SUMIFS(W2:W61,B2:B61,B10-in_rec_lag)*d_rec | AD10: =Z10*in_card_fee | AE10: =AE9*(1-IF(B9>=in_marketplace_from,d_hz_hlth_small*G9,0)) | AF10: =AE10*IF(B10>=in_marketplace_from,d_hz_hlth_small*G10,0) | AG10: =F10*AF10*in_hlth_small_ticket*in_hlth_small_comm*in_ins_partner_share+F10*in_hlth_small_ticket*in_hlth_small_renew_comm*in_ins_partner_share*(in_hlth_small_renew^1*SUMIFS(AF2:AF61,B2:B61,B10-12)+in_hlth_small_renew^2*SUMIFS(AF2:AF61,B2:B61,B10-24)+in_hlth_small_renew^3*SUMIFS(AF2:AF61,B2:B61,B10-36)+in_hlth_small_renew^4*SUMIFS(AF2:AF61,B2:B61,B10-48)) | AH10: =AH9*(1-IF(B9>=in_marketplace_from,d_hz_hlth_family*G9,0)) | AI10: =AH10*IF(B10>=in_marketplace_from,d_hz_hlth_family*G10,0) | AJ10: =F10*AI10*in_hlth_family_ticket*in_hlth_family_comm*in_ins_partner_share+F10*in_hlth_family_ticket*in_hlth_family_renew_comm*in_ins_partner_share*(in_hlth_family_renew^1*SUMIFS(AI2:AI61,B2:B61,B10-12)+in_hlth_family_renew^2*SUMIFS(AI2:AI61,B2:B61,B10-24)+in_hlth_family_renew^3*SUMIFS(AI2:AI61,B2:B61,B10-36)+in_hlth_family_renew^4*SUMIFS(AI2:AI61,B2:B61,B10-48)) | AK10: =AK9*(1-IF(B9>=in_marketplace_from,d_hz_life_term*G9,0)) | AL10: =AK10*IF(B10>=in_marketplace_from,d_hz_life_term*G10,0) | AM10: =F10*AL10*in_life_term_ticket*in_life_term_comm*in_ins_partner_share+F10*in_life_term_ticket*in_life_term_renew_comm*in_ins_partner_share*(in_life_term_renew^1*SUMIFS(AL2:AL61,B2:B61,B10-12)+in_life_term_renew^2*SUMIFS(AL2:AL61,B2:B61,B10-24)+in_life_term_renew^3*SUMIFS(AL2:AL61,B2:B61,B10-36)+in_life_term_renew^4*SUMIFS(AL2:AL61,B2:B61,B10-48)) | AN10: =AN9*(1-IF(B9>=in_marketplace_from,d_hz_accident*G9,0)) | AO10: =AN10*IF(B10>=in_marketplace_from,d_hz_accident*G10,0) | AP10: =F10*AO10*in_accident_ticket*in_accident_comm*in_ins_partner_share+F10*in_accident_ticket*in_accident_renew_comm*in_ins_partner_share*(in_accident_renew^1*SUMIFS(AO2:AO61,B2:B61,B10-12)+in_accident_renew^2*SUMIFS(AO2:AO61,B2:B61,B10-24)+in_accident_renew^3*SUMIFS(AO2:AO61,B2:B61,B10-36)+in_accident_renew^4*SUMIFS(AO2:AO61,B2:B61,B10-48)) | AQ10: =AQ9*(1-IF(B9>=in_marketplace_from,d_hz_two_wheeler*G9,0)) | AR10: =AQ10*IF(B10>=in_marketplace_from,d_hz_two_wheeler*G10,0) | AS10: =F10*AR10*in_two_wheeler_ticket*in_two_wheeler_comm*in_ins_partner_share+F10*in_two_wheeler_ticket*in_two_wheeler_comm*in_ins_partner_share*(in_two_wheeler_renew^1*SUMIFS(AR2:AR61,B2:B61,B10-12)+in_two_wheeler_renew^2*SUMIFS(AR2:AR61,B2:B61,B10-24)+in_two_wheeler_renew^3*SUMIFS(AR2:AR61,B2:B61,B10-36)+in_two_wheeler_renew^4*SUMIFS(AR2:AR61,B2:B61,B10-48)) | AT10: =AT9*(1-IF(B9>=in_marketplace_from,d_hz_device*G9,0)) | AU10: =F10*AT10*IF(B10>=in_marketplace_from,d_hz_device*G10,0)*in_device_ticket*in_device_comm*in_ins_partner_share | AV10: =AV9*(1-IF(B9>=in_marketplace_from,d_hz_shop*G9,0)) | AW10: =AV10*IF(B10>=in_marketplace_from,d_hz_shop*G10,0) | AX10: =F10*AW10*in_shop_ticket*in_shop_comm*in_ins_partner_share+F10*in_shop_ticket*in_shop_renew_comm*in_ins_partner_share*(in_shop_renew^1*SUMIFS(AW2:AW61,B2:B61,B10-12)+in_shop_renew^2*SUMIFS(AW2:AW61,B2:B61,B10-24)+in_shop_renew^3*SUMIFS(AW2:AW61,B2:B61,B10-36)+in_shop_renew^4*SUMIFS(AW2:AW61,B2:B61,B10-48)) | AY10: =AY9*(1-IF(B9>=in_marketplace_from,d_hz_sip*G9,0)) | AZ10: =AZ9*d_rho_sip+AY10*IF(B10>=in_marketplace_from,d_hz_sip*G10,0) | BA10: =d_rho_sip*(BA9+AZ9) | BB10: =F10*in_sip_ticket*(BA10+0.5*AZ10)*in_sip_comm/12 | BC10: =BC9*(1-IF(B9>=in_marketplace_from,d_hz_choti*G9,0)) | BD10: =BC10*IF(B10>=in_marketplace_from,d_hz_choti*G10,0) | BE10: =F10*SUMIFS(BD2:BD61,B2:B61,B10-in_choti_months)*in_choti_renew*in_choti_ticket | BF10: =BF9*(1-IF(B9>=in_marketplace_from,d_hz_nps*G9,0)) | BG10: =F10*BF10*IF(B10>=in_marketplace_from,d_hz_nps*G10,0)*in_nps_ticket*in_nps_comm | BH10: =BH9*(1-IF(B9>=in_marketplace_from,d_hz_gold*G9,0)) | BI10: =BI9*d_rho_gold+BH10*IF(B10>=in_marketplace_from,d_hz_gold*G10,0) | BJ10: =F10*BI10*in_gold_ticket*in_gold_comm | BK10: =BK9*(1-IF(B9>=in_marketplace_from,d_hz_fd*G9,0)) | BL10: =F10*BK10*IF(B10>=in_marketplace_from,d_hz_fd*G10,0)*in_fd_ticket*in_fd_comm | BM10: =BM9*(1-IF(B9>=in_marketplace_from,d_hz_recharge*G9,0)) | BN10: =BN9*d_rho_recharge+BM10*IF(B10>=in_marketplace_from,d_hz_recharge*G10,0) | BO10: =F10*BN10*in_recharge_ticket*in_recharge_comm/12 | BP10: =BP9*(1-IF(B9>=in_marketplace_from,d_hz_bills*G9,0)) | BQ10: =BQ9*d_rho_bills+BP10*IF(B10>=in_marketplace_from,d_hz_bills*G10,0) | BR10: =F10*BQ10*in_bills_ticket*in_bills_comm/12 | BS10: =BS9*(1-IF(B9>=in_marketplace_from,d_hz_loan_gold*G9,0)) | BT10: =F10*BS10*IF(B10>=in_marketplace_from,d_hz_loan_gold*G10,0)*in_loan_gold_ticket*in_loan_gold_comm | BU10: =BU9*(1-IF(B9>=in_marketplace_from,d_hz_loan_cd*G9,0)) | BV10: =F10*BU10*IF(B10>=in_marketplace_from,d_hz_loan_cd*G10,0)*in_loan_cd_ticket*in_loan_cd_comm | BW10: =BW9*(1-IF(B9>=in_marketplace_from,d_hz_loan_vehicle*G9,0)) | BX10: =F10*BW10*IF(B10>=in_marketplace_from,d_hz_loan_vehicle*G10,0)*in_loan_vehicle_ticket*in_loan_vehicle_comm | BY10: =BY9*(1-IF(B9>=in_marketplace_from,d_hz_loan_home*G9,0)*BZ9) | BZ10: =MIN(in_approval_cap,in_loan_home_approval*INDEX('Age profile'!$O$2:$O$61,B10)*(1+in_approval_growth)^(D10-1)) | CA10: =F10*BY10*IF(B10>=in_marketplace_from,d_hz_loan_home*G10,0)*BZ10*in_loan_home_ticket*in_loan_home_comm | CB10: =CB9*(1-IF(B9>=in_marketplace_from,d_hz_loan_lap*G9,0)*CC9) | CC10: =MIN(in_approval_cap,in_loan_lap_approval*INDEX('Age profile'!$O$2:$O$61,B10)*(1+in_approval_growth)^(D10-1)) | CD10: =F10*CB10*IF(B10>=in_marketplace_from,d_hz_loan_lap*G10,0)*CC10*in_loan_lap_ticket*in_loan_lap_comm | CE10: =AA10+AB10+AC10+AD10+AG10+AJ10+AM10+AP10+AS10+AU10+AX10+BB10+BE10+BG10+BJ10+BL10+BO10+BR10+BT10+BV10+BX10+CA10+CD10
A11: 1 | B11: 10 | C11: =A11+B11-1 | D11: =INT((C11-1)/12)+1 | E11: =INDEX(Monthly!$B$2:$B$61,A11) | F11: =E11*INDEX('Age profile'!$B$2:$B$61,B11) | G11: =MIN(in_takeup_cap,INDEX('Age profile'!$N$2:$N$61,B11)*(1+in_takeup_growth)^(D11-1)) | H11: =MIN(in_approval_cap,in_approved_first*INDEX('Age profile'!$O$2:$O$61,B11)*(1+in_approval_growth)^(D11-1)) | I11: =G11*MIN(in_takeup_cap,INDEX('Age profile'!$O$2:$O$61,B11)*(1+in_approval_growth)^(D11-1)) | J11: =(J10-L10)*F11/F10 | K11: =(K10-M10)*F11/F10+SUMIFS(O2:O10,B2:B10,B11-1-d_T)*F11 | L11: =IF(B11>=in_marketplace_from,J11*d_hz*G11*in_eligible*H11,0) | M11: =IF(B11>=in_marketplace_from,K11*d_hz*G11*in_eligible*in_approved_repeat,0) | N11: =L11+M11 | O11: =N11/F11 | P11: =F11-J11-K11 | Q11: =IF(B11>=in_marketplace_from,(J11+K11)*d_hz*G11,0) | R11: =SUMIFS(N2:N61,B2:B61,">="&(B11-d_T),B2:B61,"<="&(B11-1)) | S11: =(1-d_u)*S10+IF(d_T>in_topup_lag,SUMIFS(O2:O61,B2:B61,B11-in_topup_lag)-d_udrop*SUMIFS(O2:O61,B2:B61,B11-d_T),0) | T11: =F11*d_u*S11 | U11: =L11*in_ticket+M11*d_rep_ticket | V11: =U11+T11*d_topup_amt | W11: =N11+T11*d_topup_ratio | X11: =SUMIFS(W2:W61,B2:B61,B11-in_dpd_lag)*d_cured | Y11: =SUMIFS(W2:W61,B2:B61,B11-in_rec_lag)*d_recd | Z11: =IF(AND(B11>=in_marketplace_from,B11<in_marketplace_from+in_card_months),in_card_share/in_card_months*F11*I11,IF(AND(B11>=in_marketplace_from+in_card_months,B11<in_marketplace_from+2*in_card_months),in_card_share*d_card_rem/in_card_months*F11*MIN(in_takeup_cap,(1+in_takeup_growth)^(D11-1))*MIN(in_takeup_cap,(1+in_approval_growth)^(D11-1)),0)) | AA11: =V11*in_fee*(1-in_taken_back) | AB11: =SUMIFS(W2:W61,B2:B61,B11-in_dpd_lag)*d_dpd | AC11: =SUMIFS(W2:W61,B2:B61,B11-in_rec_lag)*d_rec | AD11: =Z11*in_card_fee | AE11: =AE10*(1-IF(B10>=in_marketplace_from,d_hz_hlth_small*G10,0)) | AF11: =AE11*IF(B11>=in_marketplace_from,d_hz_hlth_small*G11,0) | AG11: =F11*AF11*in_hlth_small_ticket*in_hlth_small_comm*in_ins_partner_share+F11*in_hlth_small_ticket*in_hlth_small_renew_comm*in_ins_partner_share*(in_hlth_small_renew^1*SUMIFS(AF2:AF61,B2:B61,B11-12)+in_hlth_small_renew^2*SUMIFS(AF2:AF61,B2:B61,B11-24)+in_hlth_small_renew^3*SUMIFS(AF2:AF61,B2:B61,B11-36)+in_hlth_small_renew^4*SUMIFS(AF2:AF61,B2:B61,B11-48)) | AH11: =AH10*(1-IF(B10>=in_marketplace_from,d_hz_hlth_family*G10,0)) | AI11: =AH11*IF(B11>=in_marketplace_from,d_hz_hlth_family*G11,0) | AJ11: =F11*AI11*in_hlth_family_ticket*in_hlth_family_comm*in_ins_partner_share+F11*in_hlth_family_ticket*in_hlth_family_renew_comm*in_ins_partner_share*(in_hlth_family_renew^1*SUMIFS(AI2:AI61,B2:B61,B11-12)+in_hlth_family_renew^2*SUMIFS(AI2:AI61,B2:B61,B11-24)+in_hlth_family_renew^3*SUMIFS(AI2:AI61,B2:B61,B11-36)+in_hlth_family_renew^4*SUMIFS(AI2:AI61,B2:B61,B11-48)) | AK11: =AK10*(1-IF(B10>=in_marketplace_from,d_hz_life_term*G10,0)) | AL11: =AK11*IF(B11>=in_marketplace_from,d_hz_life_term*G11,0) | AM11: =F11*AL11*in_life_term_ticket*in_life_term_comm*in_ins_partner_share+F11*in_life_term_ticket*in_life_term_renew_comm*in_ins_partner_share*(in_life_term_renew^1*SUMIFS(AL2:AL61,B2:B61,B11-12)+in_life_term_renew^2*SUMIFS(AL2:AL61,B2:B61,B11-24)+in_life_term_renew^3*SUMIFS(AL2:AL61,B2:B61,B11-36)+in_life_term_renew^4*SUMIFS(AL2:AL61,B2:B61,B11-48)) | AN11: =AN10*(1-IF(B10>=in_marketplace_from,d_hz_accident*G10,0)) | AO11: =AN11*IF(B11>=in_marketplace_from,d_hz_accident*G11,0) | AP11: =F11*AO11*in_accident_ticket*in_accident_comm*in_ins_partner_share+F11*in_accident_ticket*in_accident_renew_comm*in_ins_partner_share*(in_accident_renew^1*SUMIFS(AO2:AO61,B2:B61,B11-12)+in_accident_renew^2*SUMIFS(AO2:AO61,B2:B61,B11-24)+in_accident_renew^3*SUMIFS(AO2:AO61,B2:B61,B11-36)+in_accident_renew^4*SUMIFS(AO2:AO61,B2:B61,B11-48)) | AQ11: =AQ10*(1-IF(B10>=in_marketplace_from,d_hz_two_wheeler*G10,0)) | AR11: =AQ11*IF(B11>=in_marketplace_from,d_hz_two_wheeler*G11,0) | AS11: =F11*AR11*in_two_wheeler_ticket*in_two_wheeler_comm*in_ins_partner_share+F11*in_two_wheeler_ticket*in_two_wheeler_comm*in_ins_partner_share*(in_two_wheeler_renew^1*SUMIFS(AR2:AR61,B2:B61,B11-12)+in_two_wheeler_renew^2*SUMIFS(AR2:AR61,B2:B61,B11-24)+in_two_wheeler_renew^3*SUMIFS(AR2:AR61,B2:B61,B11-36)+in_two_wheeler_renew^4*SUMIFS(AR2:AR61,B2:B61,B11-48)) | AT11: =AT10*(1-IF(B10>=in_marketplace_from,d_hz_device*G10,0)) | AU11: =F11*AT11*IF(B11>=in_marketplace_from,d_hz_device*G11,0)*in_device_ticket*in_device_comm*in_ins_partner_share | AV11: =AV10*(1-IF(B10>=in_marketplace_from,d_hz_shop*G10,0)) | AW11: =AV11*IF(B11>=in_marketplace_from,d_hz_shop*G11,0) | AX11: =F11*AW11*in_shop_ticket*in_shop_comm*in_ins_partner_share+F11*in_shop_ticket*in_shop_renew_comm*in_ins_partner_share*(in_shop_renew^1*SUMIFS(AW2:AW61,B2:B61,B11-12)+in_shop_renew^2*SUMIFS(AW2:AW61,B2:B61,B11-24)+in_shop_renew^3*SUMIFS(AW2:AW61,B2:B61,B11-36)+in_shop_renew^4*SUMIFS(AW2:AW61,B2:B61,B11-48)) | AY11: =AY10*(1-IF(B10>=in_marketplace_from,d_hz_sip*G10,0)) | AZ11: =AZ10*d_rho_sip+AY11*IF(B11>=in_marketplace_from,d_hz_sip*G11,0) | BA11: =d_rho_sip*(BA10+AZ10) | BB11: =F11*in_sip_ticket*(BA11+0.5*AZ11)*in_sip_comm/12 | BC11: =BC10*(1-IF(B10>=in_marketplace_from,d_hz_choti*G10,0)) | BD11: =BC11*IF(B11>=in_marketplace_from,d_hz_choti*G11,0) | BE11: =F11*SUMIFS(BD2:BD61,B2:B61,B11-in_choti_months)*in_choti_renew*in_choti_ticket | BF11: =BF10*(1-IF(B10>=in_marketplace_from,d_hz_nps*G10,0)) | BG11: =F11*BF11*IF(B11>=in_marketplace_from,d_hz_nps*G11,0)*in_nps_ticket*in_nps_comm | BH11: =BH10*(1-IF(B10>=in_marketplace_from,d_hz_gold*G10,0)) | BI11: =BI10*d_rho_gold+BH11*IF(B11>=in_marketplace_from,d_hz_gold*G11,0) | BJ11: =F11*BI11*in_gold_ticket*in_gold_comm | BK11: =BK10*(1-IF(B10>=in_marketplace_from,d_hz_fd*G10,0)) | BL11: =F11*BK11*IF(B11>=in_marketplace_from,d_hz_fd*G11,0)*in_fd_ticket*in_fd_comm | BM11: =BM10*(1-IF(B10>=in_marketplace_from,d_hz_recharge*G10,0)) | BN11: =BN10*d_rho_recharge+BM11*IF(B11>=in_marketplace_from,d_hz_recharge*G11,0) | BO11: =F11*BN11*in_recharge_ticket*in_recharge_comm/12 | BP11: =BP10*(1-IF(B10>=in_marketplace_from,d_hz_bills*G10,0)) | BQ11: =BQ10*d_rho_bills+BP11*IF(B11>=in_marketplace_from,d_hz_bills*G11,0) | BR11: =F11*BQ11*in_bills_ticket*in_bills_comm/12 | BS11: =BS10*(1-IF(B10>=in_marketplace_from,d_hz_loan_gold*G10,0)) | BT11: =F11*BS11*IF(B11>=in_marketplace_from,d_hz_loan_gold*G11,0)*in_loan_gold_ticket*in_loan_gold_comm | BU11: =BU10*(1-IF(B10>=in_marketplace_from,d_hz_loan_cd*G10,0)) | BV11: =F11*BU11*IF(B11>=in_marketplace_from,d_hz_loan_cd*G11,0)*in_loan_cd_ticket*in_loan_cd_comm | BW11: =BW10*(1-IF(B10>=in_marketplace_from,d_hz_loan_vehicle*G10,0)) | BX11: =F11*BW11*IF(B11>=in_marketplace_from,d_hz_loan_vehicle*G11,0)*in_loan_vehicle_ticket*in_loan_vehicle_comm | BY11: =BY10*(1-IF(B10>=in_marketplace_from,d_hz_loan_home*G10,0)*BZ10) | BZ11: =MIN(in_approval_cap,in_loan_home_approval*INDEX('Age profile'!$O$2:$O$61,B11)*(1+in_approval_growth)^(D11-1)) | CA11: =F11*BY11*IF(B11>=in_marketplace_from,d_hz_loan_home*G11,0)*BZ11*in_loan_home_ticket*in_loan_home_comm | CB11: =CB10*(1-IF(B10>=in_marketplace_from,d_hz_loan_lap*G10,0)*CC10) | CC11: =MIN(in_approval_cap,in_loan_lap_approval*INDEX('Age profile'!$O$2:$O$61,B11)*(1+in_approval_growth)^(D11-1)) | CD11: =F11*CB11*IF(B11>=in_marketplace_from,d_hz_loan_lap*G11,0)*CC11*in_loan_lap_ticket*in_loan_lap_comm | CE11: =AA11+AB11+AC11+AD11+AG11+AJ11+AM11+AP11+AS11+AU11+AX11+BB11+BE11+BG11+BJ11+BL11+BO11+BR11+BT11+BV11+BX11+CA11+CD11
A12: 1 | B12: 11 | C12: =A12+B12-1 | D12: =INT((C12-1)/12)+1 | E12: =INDEX(Monthly!$B$2:$B$61,A12) | F12: =E12*INDEX('Age profile'!$B$2:$B$61,B12) | G12: =MIN(in_takeup_cap,INDEX('Age profile'!$N$2:$N$61,B12)*(1+in_takeup_growth)^(D12-1)) | H12: =MIN(in_approval_cap,in_approved_first*INDEX('Age profile'!$O$2:$O$61,B12)*(1+in_approval_growth)^(D12-1)) | I12: =G12*MIN(in_takeup_cap,INDEX('Age profile'!$O$2:$O$61,B12)*(1+in_approval_growth)^(D12-1)) | J12: =(J11-L11)*F12/F11 | K12: =(K11-M11)*F12/F11+SUMIFS(O2:O11,B2:B11,B12-1-d_T)*F12 | L12: =IF(B12>=in_marketplace_from,J12*d_hz*G12*in_eligible*H12,0) | M12: =IF(B12>=in_marketplace_from,K12*d_hz*G12*in_eligible*in_approved_repeat,0) | N12: =L12+M12 | O12: =N12/F12 | P12: =F12-J12-K12 | Q12: =IF(B12>=in_marketplace_from,(J12+K12)*d_hz*G12,0) | R12: =SUMIFS(N2:N61,B2:B61,">="&(B12-d_T),B2:B61,"<="&(B12-1)) | S12: =(1-d_u)*S11+IF(d_T>in_topup_lag,SUMIFS(O2:O61,B2:B61,B12-in_topup_lag)-d_udrop*SUMIFS(O2:O61,B2:B61,B12-d_T),0) | T12: =F12*d_u*S12 | U12: =L12*in_ticket+M12*d_rep_ticket | V12: =U12+T12*d_topup_amt | W12: =N12+T12*d_topup_ratio | X12: =SUMIFS(W2:W61,B2:B61,B12-in_dpd_lag)*d_cured | Y12: =SUMIFS(W2:W61,B2:B61,B12-in_rec_lag)*d_recd | Z12: =IF(AND(B12>=in_marketplace_from,B12<in_marketplace_from+in_card_months),in_card_share/in_card_months*F12*I12,IF(AND(B12>=in_marketplace_from+in_card_months,B12<in_marketplace_from+2*in_card_months),in_card_share*d_card_rem/in_card_months*F12*MIN(in_takeup_cap,(1+in_takeup_growth)^(D12-1))*MIN(in_takeup_cap,(1+in_approval_growth)^(D12-1)),0)) | AA12: =V12*in_fee*(1-in_taken_back) | AB12: =SUMIFS(W2:W61,B2:B61,B12-in_dpd_lag)*d_dpd | AC12: =SUMIFS(W2:W61,B2:B61,B12-in_rec_lag)*d_rec | AD12: =Z12*in_card_fee | AE12: =AE11*(1-IF(B11>=in_marketplace_from,d_hz_hlth_small*G11,0)) | AF12: =AE12*IF(B12>=in_marketplace_from,d_hz_hlth_small*G12,0) | AG12: =F12*AF12*in_hlth_small_ticket*in_hlth_small_comm*in_ins_partner_share+F12*in_hlth_small_ticket*in_hlth_small_renew_comm*in_ins_partner_share*(in_hlth_small_renew^1*SUMIFS(AF2:AF61,B2:B61,B12-12)+in_hlth_small_renew^2*SUMIFS(AF2:AF61,B2:B61,B12-24)+in_hlth_small_renew^3*SUMIFS(AF2:AF61,B2:B61,B12-36)+in_hlth_small_renew^4*SUMIFS(AF2:AF61,B2:B61,B12-48)) | AH12: =AH11*(1-IF(B11>=in_marketplace_from,d_hz_hlth_family*G11,0)) | AI12: =AH12*IF(B12>=in_marketplace_from,d_hz_hlth_family*G12,0) | AJ12: =F12*AI12*in_hlth_family_ticket*in_hlth_family_comm*in_ins_partner_share+F12*in_hlth_family_ticket*in_hlth_family_renew_comm*in_ins_partner_share*(in_hlth_family_renew^1*SUMIFS(AI2:AI61,B2:B61,B12-12)+in_hlth_family_renew^2*SUMIFS(AI2:AI61,B2:B61,B12-24)+in_hlth_family_renew^3*SUMIFS(AI2:AI61,B2:B61,B12-36)+in_hlth_family_renew^4*SUMIFS(AI2:AI61,B2:B61,B12-48)) | AK12: =AK11*(1-IF(B11>=in_marketplace_from,d_hz_life_term*G11,0)) | AL12: =AK12*IF(B12>=in_marketplace_from,d_hz_life_term*G12,0) | AM12: =F12*AL12*in_life_term_ticket*in_life_term_comm*in_ins_partner_share+F12*in_life_term_ticket*in_life_term_renew_comm*in_ins_partner_share*(in_life_term_renew^1*SUMIFS(AL2:AL61,B2:B61,B12-12)+in_life_term_renew^2*SUMIFS(AL2:AL61,B2:B61,B12-24)+in_life_term_renew^3*SUMIFS(AL2:AL61,B2:B61,B12-36)+in_life_term_renew^4*SUMIFS(AL2:AL61,B2:B61,B12-48)) | AN12: =AN11*(1-IF(B11>=in_marketplace_from,d_hz_accident*G11,0)) | AO12: =AN12*IF(B12>=in_marketplace_from,d_hz_accident*G12,0) | AP12: =F12*AO12*in_accident_ticket*in_accident_comm*in_ins_partner_share+F12*in_accident_ticket*in_accident_renew_comm*in_ins_partner_share*(in_accident_renew^1*SUMIFS(AO2:AO61,B2:B61,B12-12)+in_accident_renew^2*SUMIFS(AO2:AO61,B2:B61,B12-24)+in_accident_renew^3*SUMIFS(AO2:AO61,B2:B61,B12-36)+in_accident_renew^4*SUMIFS(AO2:AO61,B2:B61,B12-48)) | AQ12: =AQ11*(1-IF(B11>=in_marketplace_from,d_hz_two_wheeler*G11,0)) | AR12: =AQ12*IF(B12>=in_marketplace_from,d_hz_two_wheeler*G12,0) | AS12: =F12*AR12*in_two_wheeler_ticket*in_two_wheeler_comm*in_ins_partner_share+F12*in_two_wheeler_ticket*in_two_wheeler_comm*in_ins_partner_share*(in_two_wheeler_renew^1*SUMIFS(AR2:AR61,B2:B61,B12-12)+in_two_wheeler_renew^2*SUMIFS(AR2:AR61,B2:B61,B12-24)+in_two_wheeler_renew^3*SUMIFS(AR2:AR61,B2:B61,B12-36)+in_two_wheeler_renew^4*SUMIFS(AR2:AR61,B2:B61,B12-48)) | AT12: =AT11*(1-IF(B11>=in_marketplace_from,d_hz_device*G11,0)) | AU12: =F12*AT12*IF(B12>=in_marketplace_from,d_hz_device*G12,0)*in_device_ticket*in_device_comm*in_ins_partner_share | AV12: =AV11*(1-IF(B11>=in_marketplace_from,d_hz_shop*G11,0)) | AW12: =AV12*IF(B12>=in_marketplace_from,d_hz_shop*G12,0) | AX12: =F12*AW12*in_shop_ticket*in_shop_comm*in_ins_partner_share+F12*in_shop_ticket*in_shop_renew_comm*in_ins_partner_share*(in_shop_renew^1*SUMIFS(AW2:AW61,B2:B61,B12-12)+in_shop_renew^2*SUMIFS(AW2:AW61,B2:B61,B12-24)+in_shop_renew^3*SUMIFS(AW2:AW61,B2:B61,B12-36)+in_shop_renew^4*SUMIFS(AW2:AW61,B2:B61,B12-48)) | AY12: =AY11*(1-IF(B11>=in_marketplace_from,d_hz_sip*G11,0)) | AZ12: =AZ11*d_rho_sip+AY12*IF(B12>=in_marketplace_from,d_hz_sip*G12,0) | BA12: =d_rho_sip*(BA11+AZ11) | BB12: =F12*in_sip_ticket*(BA12+0.5*AZ12)*in_sip_comm/12 | BC12: =BC11*(1-IF(B11>=in_marketplace_from,d_hz_choti*G11,0)) | BD12: =BC12*IF(B12>=in_marketplace_from,d_hz_choti*G12,0) | BE12: =F12*SUMIFS(BD2:BD61,B2:B61,B12-in_choti_months)*in_choti_renew*in_choti_ticket | BF12: =BF11*(1-IF(B11>=in_marketplace_from,d_hz_nps*G11,0)) | BG12: =F12*BF12*IF(B12>=in_marketplace_from,d_hz_nps*G12,0)*in_nps_ticket*in_nps_comm | BH12: =BH11*(1-IF(B11>=in_marketplace_from,d_hz_gold*G11,0)) | BI12: =BI11*d_rho_gold+BH12*IF(B12>=in_marketplace_from,d_hz_gold*G12,0) | BJ12: =F12*BI12*in_gold_ticket*in_gold_comm | BK12: =BK11*(1-IF(B11>=in_marketplace_from,d_hz_fd*G11,0)) | BL12: =F12*BK12*IF(B12>=in_marketplace_from,d_hz_fd*G12,0)*in_fd_ticket*in_fd_comm | BM12: =BM11*(1-IF(B11>=in_marketplace_from,d_hz_recharge*G11,0)) | BN12: =BN11*d_rho_recharge+BM12*IF(B12>=in_marketplace_from,d_hz_recharge*G12,0) | BO12: =F12*BN12*in_recharge_ticket*in_recharge_comm/12 | BP12: =BP11*(1-IF(B11>=in_marketplace_from,d_hz_bills*G11,0)) | BQ12: =BQ11*d_rho_bills+BP12*IF(B12>=in_marketplace_from,d_hz_bills*G12,0) | BR12: =F12*BQ12*in_bills_ticket*in_bills_comm/12 | BS12: =BS11*(1-IF(B11>=in_marketplace_from,d_hz_loan_gold*G11,0)) | BT12: =F12*BS12*IF(B12>=in_marketplace_from,d_hz_loan_gold*G12,0)*in_loan_gold_ticket*in_loan_gold_comm | BU12: =BU11*(1-IF(B11>=in_marketplace_from,d_hz_loan_cd*G11,0)) | BV12: =F12*BU12*IF(B12>=in_marketplace_from,d_hz_loan_cd*G12,0)*in_loan_cd_ticket*in_loan_cd_comm | BW12: =BW11*(1-IF(B11>=in_marketplace_from,d_hz_loan_vehicle*G11,0)) | BX12: =F12*BW12*IF(B12>=in_marketplace_from,d_hz_loan_vehicle*G12,0)*in_loan_vehicle_ticket*in_loan_vehicle_comm | BY12: =BY11*(1-IF(B11>=in_marketplace_from,d_hz_loan_home*G11,0)*BZ11) | BZ12: =MIN(in_approval_cap,in_loan_home_approval*INDEX('Age profile'!$O$2:$O$61,B12)*(1+in_approval_growth)^(D12-1)) | CA12: =F12*BY12*IF(B12>=in_marketplace_from,d_hz_loan_home*G12,0)*BZ12*in_loan_home_ticket*in_loan_home_comm | CB12: =CB11*(1-IF(B11>=in_marketplace_from,d_hz_loan_lap*G11,0)*CC11) | CC12: =MIN(in_approval_cap,in_loan_lap_approval*INDEX('Age profile'!$O$2:$O$61,B12)*(1+in_approval_growth)^(D12-1)) | CD12: =F12*CB12*IF(B12>=in_marketplace_from,d_hz_loan_lap*G12,0)*CC12*in_loan_lap_ticket*in_loan_lap_comm | CE12: =AA12+AB12+AC12+AD12+AG12+AJ12+AM12+AP12+AS12+AU12+AX12+BB12+BE12+BG12+BJ12+BL12+BO12+BR12+BT12+BV12+BX12+CA12+CD12
A13: 1 | B13: 12 | C13: =A13+B13-1 | D13: =INT((C13-1)/12)+1 | E13: =INDEX(Monthly!$B$2:$B$61,A13) | F13: =E13*INDEX('Age profile'!$B$2:$B$61,B13) | G13: =MIN(in_takeup_cap,INDEX('Age profile'!$N$2:$N$61,B13)*(1+in_takeup_growth)^(D13-1)) | H13: =MIN(in_approval_cap,in_approved_first*INDEX('Age profile'!$O$2:$O$61,B13)*(1+in_approval_growth)^(D13-1)) | I13: =G13*MIN(in_takeup_cap,INDEX('Age profile'!$O$2:$O$61,B13)*(1+in_approval_growth)^(D13-1)) | J13: =(J12-L12)*F13/F12 | K13: =(K12-M12)*F13/F12+SUMIFS(O2:O12,B2:B12,B13-1-d_T)*F13 | L13: =IF(B13>=in_marketplace_from,J13*d_hz*G13*in_eligible*H13,0) | M13: =IF(B13>=in_marketplace_from,K13*d_hz*G13*in_eligible*in_approved_repeat,0) | N13: =L13+M13 | O13: =N13/F13 | P13: =F13-J13-K13 | Q13: =IF(B13>=in_marketplace_from,(J13+K13)*d_hz*G13,0) | R13: =SUMIFS(N2:N61,B2:B61,">="&(B13-d_T),B2:B61,"<="&(B13-1)) | S13: =(1-d_u)*S12+IF(d_T>in_topup_lag,SUMIFS(O2:O61,B2:B61,B13-in_topup_lag)-d_udrop*SUMIFS(O2:O61,B2:B61,B13-d_T),0) | T13: =F13*d_u*S13 | U13: =L13*in_ticket+M13*d_rep_ticket | V13: =U13+T13*d_topup_amt | W13: =N13+T13*d_topup_ratio | X13: =SUMIFS(W2:W61,B2:B61,B13-in_dpd_lag)*d_cured | Y13: =SUMIFS(W2:W61,B2:B61,B13-in_rec_lag)*d_recd | Z13: =IF(AND(B13>=in_marketplace_from,B13<in_marketplace_from+in_card_months),in_card_share/in_card_months*F13*I13,IF(AND(B13>=in_marketplace_from+in_card_months,B13<in_marketplace_from+2*in_card_months),in_card_share*d_card_rem/in_card_months*F13*MIN(in_takeup_cap,(1+in_takeup_growth)^(D13-1))*MIN(in_takeup_cap,(1+in_approval_growth)^(D13-1)),0)) | AA13: =V13*in_fee*(1-in_taken_back) | AB13: =SUMIFS(W2:W61,B2:B61,B13-in_dpd_lag)*d_dpd | AC13: =SUMIFS(W2:W61,B2:B61,B13-in_rec_lag)*d_rec | AD13: =Z13*in_card_fee | AE13: =AE12*(1-IF(B12>=in_marketplace_from,d_hz_hlth_small*G12,0)) | AF13: =AE13*IF(B13>=in_marketplace_from,d_hz_hlth_small*G13,0) | AG13: =F13*AF13*in_hlth_small_ticket*in_hlth_small_comm*in_ins_partner_share+F13*in_hlth_small_ticket*in_hlth_small_renew_comm*in_ins_partner_share*(in_hlth_small_renew^1*SUMIFS(AF2:AF61,B2:B61,B13-12)+in_hlth_small_renew^2*SUMIFS(AF2:AF61,B2:B61,B13-24)+in_hlth_small_renew^3*SUMIFS(AF2:AF61,B2:B61,B13-36)+in_hlth_small_renew^4*SUMIFS(AF2:AF61,B2:B61,B13-48)) | AH13: =AH12*(1-IF(B12>=in_marketplace_from,d_hz_hlth_family*G12,0)) | AI13: =AH13*IF(B13>=in_marketplace_from,d_hz_hlth_family*G13,0) | AJ13: =F13*AI13*in_hlth_family_ticket*in_hlth_family_comm*in_ins_partner_share+F13*in_hlth_family_ticket*in_hlth_family_renew_comm*in_ins_partner_share*(in_hlth_family_renew^1*SUMIFS(AI2:AI61,B2:B61,B13-12)+in_hlth_family_renew^2*SUMIFS(AI2:AI61,B2:B61,B13-24)+in_hlth_family_renew^3*SUMIFS(AI2:AI61,B2:B61,B13-36)+in_hlth_family_renew^4*SUMIFS(AI2:AI61,B2:B61,B13-48)) | AK13: =AK12*(1-IF(B12>=in_marketplace_from,d_hz_life_term*G12,0)) | AL13: =AK13*IF(B13>=in_marketplace_from,d_hz_life_term*G13,0) | AM13: =F13*AL13*in_life_term_ticket*in_life_term_comm*in_ins_partner_share+F13*in_life_term_ticket*in_life_term_renew_comm*in_ins_partner_share*(in_life_term_renew^1*SUMIFS(AL2:AL61,B2:B61,B13-12)+in_life_term_renew^2*SUMIFS(AL2:AL61,B2:B61,B13-24)+in_life_term_renew^3*SUMIFS(AL2:AL61,B2:B61,B13-36)+in_life_term_renew^4*SUMIFS(AL2:AL61,B2:B61,B13-48)) | AN13: =AN12*(1-IF(B12>=in_marketplace_from,d_hz_accident*G12,0)) | AO13: =AN13*IF(B13>=in_marketplace_from,d_hz_accident*G13,0) | AP13: =F13*AO13*in_accident_ticket*in_accident_comm*in_ins_partner_share+F13*in_accident_ticket*in_accident_renew_comm*in_ins_partner_share*(in_accident_renew^1*SUMIFS(AO2:AO61,B2:B61,B13-12)+in_accident_renew^2*SUMIFS(AO2:AO61,B2:B61,B13-24)+in_accident_renew^3*SUMIFS(AO2:AO61,B2:B61,B13-36)+in_accident_renew^4*SUMIFS(AO2:AO61,B2:B61,B13-48)) | AQ13: =AQ12*(1-IF(B12>=in_marketplace_from,d_hz_two_wheeler*G12,0)) | AR13: =AQ13*IF(B13>=in_marketplace_from,d_hz_two_wheeler*G13,0) | AS13: =F13*AR13*in_two_wheeler_ticket*in_two_wheeler_comm*in_ins_partner_share+F13*in_two_wheeler_ticket*in_two_wheeler_comm*in_ins_partner_share*(in_two_wheeler_renew^1*SUMIFS(AR2:AR61,B2:B61,B13-12)+in_two_wheeler_renew^2*SUMIFS(AR2:AR61,B2:B61,B13-24)+in_two_wheeler_renew^3*SUMIFS(AR2:AR61,B2:B61,B13-36)+in_two_wheeler_renew^4*SUMIFS(AR2:AR61,B2:B61,B13-48)) | AT13: =AT12*(1-IF(B12>=in_marketplace_from,d_hz_device*G12,0)) | AU13: =F13*AT13*IF(B13>=in_marketplace_from,d_hz_device*G13,0)*in_device_ticket*in_device_comm*in_ins_partner_share | AV13: =AV12*(1-IF(B12>=in_marketplace_from,d_hz_shop*G12,0)) | AW13: =AV13*IF(B13>=in_marketplace_from,d_hz_shop*G13,0) | AX13: =F13*AW13*in_shop_ticket*in_shop_comm*in_ins_partner_share+F13*in_shop_ticket*in_shop_renew_comm*in_ins_partner_share*(in_shop_renew^1*SUMIFS(AW2:AW61,B2:B61,B13-12)+in_shop_renew^2*SUMIFS(AW2:AW61,B2:B61,B13-24)+in_shop_renew^3*SUMIFS(AW2:AW61,B2:B61,B13-36)+in_shop_renew^4*SUMIFS(AW2:AW61,B2:B61,B13-48)) | AY13: =AY12*(1-IF(B12>=in_marketplace_from,d_hz_sip*G12,0)) | AZ13: =AZ12*d_rho_sip+AY13*IF(B13>=in_marketplace_from,d_hz_sip*G13,0) | BA13: =d_rho_sip*(BA12+AZ12) | BB13: =F13*in_sip_ticket*(BA13+0.5*AZ13)*in_sip_comm/12 | BC13: =BC12*(1-IF(B12>=in_marketplace_from,d_hz_choti*G12,0)) | BD13: =BC13*IF(B13>=in_marketplace_from,d_hz_choti*G13,0) | BE13: =F13*SUMIFS(BD2:BD61,B2:B61,B13-in_choti_months)*in_choti_renew*in_choti_ticket | BF13: =BF12*(1-IF(B12>=in_marketplace_from,d_hz_nps*G12,0)) | BG13: =F13*BF13*IF(B13>=in_marketplace_from,d_hz_nps*G13,0)*in_nps_ticket*in_nps_comm | BH13: =BH12*(1-IF(B12>=in_marketplace_from,d_hz_gold*G12,0)) | BI13: =BI12*d_rho_gold+BH13*IF(B13>=in_marketplace_from,d_hz_gold*G13,0) | BJ13: =F13*BI13*in_gold_ticket*in_gold_comm | BK13: =BK12*(1-IF(B12>=in_marketplace_from,d_hz_fd*G12,0)) | BL13: =F13*BK13*IF(B13>=in_marketplace_from,d_hz_fd*G13,0)*in_fd_ticket*in_fd_comm | BM13: =BM12*(1-IF(B12>=in_marketplace_from,d_hz_recharge*G12,0)) | BN13: =BN12*d_rho_recharge+BM13*IF(B13>=in_marketplace_from,d_hz_recharge*G13,0) | BO13: =F13*BN13*in_recharge_ticket*in_recharge_comm/12 | BP13: =BP12*(1-IF(B12>=in_marketplace_from,d_hz_bills*G12,0)) | BQ13: =BQ12*d_rho_bills+BP13*IF(B13>=in_marketplace_from,d_hz_bills*G13,0) | BR13: =F13*BQ13*in_bills_ticket*in_bills_comm/12 | BS13: =BS12*(1-IF(B12>=in_marketplace_from,d_hz_loan_gold*G12,0)) | BT13: =F13*BS13*IF(B13>=in_marketplace_from,d_hz_loan_gold*G13,0)*in_loan_gold_ticket*in_loan_gold_comm | BU13: =BU12*(1-IF(B12>=in_marketplace_from,d_hz_loan_cd*G12,0)) | BV13: =F13*BU13*IF(B13>=in_marketplace_from,d_hz_loan_cd*G13,0)*in_loan_cd_ticket*in_loan_cd_comm | BW13: =BW12*(1-IF(B12>=in_marketplace_from,d_hz_loan_vehicle*G12,0)) | BX13: =F13*BW13*IF(B13>=in_marketplace_from,d_hz_loan_vehicle*G13,0)*in_loan_vehicle_ticket*in_loan_vehicle_comm | BY13: =BY12*(1-IF(B12>=in_marketplace_from,d_hz_loan_home*G12,0)*BZ12) | BZ13: =MIN(in_approval_cap,in_loan_home_approval*INDEX('Age profile'!$O$2:$O$61,B13)*(1+in_approval_growth)^(D13-1)) | CA13: =F13*BY13*IF(B13>=in_marketplace_from,d_hz_loan_home*G13,0)*BZ13*in_loan_home_ticket*in_loan_home_comm | CB13: =CB12*(1-IF(B12>=in_marketplace_from,d_hz_loan_lap*G12,0)*CC12) | CC13: =MIN(in_approval_cap,in_loan_lap_approval*INDEX('Age profile'!$O$2:$O$61,B13)*(1+in_approval_growth)^(D13-1)) | CD13: =F13*CB13*IF(B13>=in_marketplace_from,d_hz_loan_lap*G13,0)*CC13*in_loan_lap_ticket*in_loan_lap_comm | CE13: =AA13+AB13+AC13+AD13+AG13+AJ13+AM13+AP13+AS13+AU13+AX13+BB13+BE13+BG13+BJ13+BL13+BO13+BR13+BT13+BV13+BX13+CA13+CD13
A14: 1 | B14: 13 | C14: =A14+B14-1 | D14: =INT((C14-1)/12)+1 | E14: =INDEX(Monthly!$B$2:$B$61,A14) | F14: =E14*INDEX('Age profile'!$B$2:$B$61,B14) | G14: =MIN(in_takeup_cap,INDEX('Age profile'!$N$2:$N$61,B14)*(1+in_takeup_growth)^(D14-1)) | H14: =MIN(in_approval_cap,in_approved_first*INDEX('Age profile'!$O$2:$O$61,B14)*(1+in_approval_growth)^(D14-1)) | I14: =G14*MIN(in_takeup_cap,INDEX('Age profile'!$O$2:$O$61,B14)*(1+in_approval_growth)^(D14-1)) | J14: =(J13-L13)*F14/F13 | K14: =(K13-M13)*F14/F13+SUMIFS(O2:O13,B2:B13,B14-1-d_T)*F14 | L14: =IF(B14>=in_marketplace_from,J14*d_hz*G14*in_eligible*H14,0) | M14: =IF(B14>=in_marketplace_from,K14*d_hz*G14*in_eligible*in_approved_repeat,0) | N14: =L14+M14 | O14: =N14/F14 | P14: =F14-J14-K14 | Q14: =IF(B14>=in_marketplace_from,(J14+K14)*d_hz*G14,0) | R14: =SUMIFS(N2:N61,B2:B61,">="&(B14-d_T),B2:B61,"<="&(B14-1)) | S14: =(1-d_u)*S13+IF(d_T>in_topup_lag,SUMIFS(O2:O61,B2:B61,B14-in_topup_lag)-d_udrop*SUMIFS(O2:O61,B2:B61,B14-d_T),0) | T14: =F14*d_u*S14 | U14: =L14*in_ticket+M14*d_rep_ticket | V14: =U14+T14*d_topup_amt | W14: =N14+T14*d_topup_ratio | X14: =SUMIFS(W2:W61,B2:B61,B14-in_dpd_lag)*d_cured | Y14: =SUMIFS(W2:W61,B2:B61,B14-in_rec_lag)*d_recd | Z14: =IF(AND(B14>=in_marketplace_from,B14<in_marketplace_from+in_card_months),in_card_share/in_card_months*F14*I14,IF(AND(B14>=in_marketplace_from+in_card_months,B14<in_marketplace_from+2*in_card_months),in_card_share*d_card_rem/in_card_months*F14*MIN(in_takeup_cap,(1+in_takeup_growth)^(D14-1))*MIN(in_takeup_cap,(1+in_approval_growth)^(D14-1)),0)) | AA14: =V14*in_fee*(1-in_taken_back) | AB14: =SUMIFS(W2:W61,B2:B61,B14-in_dpd_lag)*d_dpd | AC14: =SUMIFS(W2:W61,B2:B61,B14-in_rec_lag)*d_rec | AD14: =Z14*in_card_fee | AE14: =AE13*(1-IF(B13>=in_marketplace_from,d_hz_hlth_small*G13,0)) | AF14: =AE14*IF(B14>=in_marketplace_from,d_hz_hlth_small*G14,0) | AG14: =F14*AF14*in_hlth_small_ticket*in_hlth_small_comm*in_ins_partner_share+F14*in_hlth_small_ticket*in_hlth_small_renew_comm*in_ins_partner_share*(in_hlth_small_renew^1*SUMIFS(AF2:AF61,B2:B61,B14-12)+in_hlth_small_renew^2*SUMIFS(AF2:AF61,B2:B61,B14-24)+in_hlth_small_renew^3*SUMIFS(AF2:AF61,B2:B61,B14-36)+in_hlth_small_renew^4*SUMIFS(AF2:AF61,B2:B61,B14-48)) | AH14: =AH13*(1-IF(B13>=in_marketplace_from,d_hz_hlth_family*G13,0)) | AI14: =AH14*IF(B14>=in_marketplace_from,d_hz_hlth_family*G14,0) | AJ14: =F14*AI14*in_hlth_family_ticket*in_hlth_family_comm*in_ins_partner_share+F14*in_hlth_family_ticket*in_hlth_family_renew_comm*in_ins_partner_share*(in_hlth_family_renew^1*SUMIFS(AI2:AI61,B2:B61,B14-12)+in_hlth_family_renew^2*SUMIFS(AI2:AI61,B2:B61,B14-24)+in_hlth_family_renew^3*SUMIFS(AI2:AI61,B2:B61,B14-36)+in_hlth_family_renew^4*SUMIFS(AI2:AI61,B2:B61,B14-48)) | AK14: =AK13*(1-IF(B13>=in_marketplace_from,d_hz_life_term*G13,0)) | AL14: =AK14*IF(B14>=in_marketplace_from,d_hz_life_term*G14,0) | AM14: =F14*AL14*in_life_term_ticket*in_life_term_comm*in_ins_partner_share+F14*in_life_term_ticket*in_life_term_renew_comm*in_ins_partner_share*(in_life_term_renew^1*SUMIFS(AL2:AL61,B2:B61,B14-12)+in_life_term_renew^2*SUMIFS(AL2:AL61,B2:B61,B14-24)+in_life_term_renew^3*SUMIFS(AL2:AL61,B2:B61,B14-36)+in_life_term_renew^4*SUMIFS(AL2:AL61,B2:B61,B14-48)) | AN14: =AN13*(1-IF(B13>=in_marketplace_from,d_hz_accident*G13,0)) | AO14: =AN14*IF(B14>=in_marketplace_from,d_hz_accident*G14,0) | AP14: =F14*AO14*in_accident_ticket*in_accident_comm*in_ins_partner_share+F14*in_accident_ticket*in_accident_renew_comm*in_ins_partner_share*(in_accident_renew^1*SUMIFS(AO2:AO61,B2:B61,B14-12)+in_accident_renew^2*SUMIFS(AO2:AO61,B2:B61,B14-24)+in_accident_renew^3*SUMIFS(AO2:AO61,B2:B61,B14-36)+in_accident_renew^4*SUMIFS(AO2:AO61,B2:B61,B14-48)) | AQ14: =AQ13*(1-IF(B13>=in_marketplace_from,d_hz_two_wheeler*G13,0)) | AR14: =AQ14*IF(B14>=in_marketplace_from,d_hz_two_wheeler*G14,0) | AS14: =F14*AR14*in_two_wheeler_ticket*in_two_wheeler_comm*in_ins_partner_share+F14*in_two_wheeler_ticket*in_two_wheeler_comm*in_ins_partner_share*(in_two_wheeler_renew^1*SUMIFS(AR2:AR61,B2:B61,B14-12)+in_two_wheeler_renew^2*SUMIFS(AR2:AR61,B2:B61,B14-24)+in_two_wheeler_renew^3*SUMIFS(AR2:AR61,B2:B61,B14-36)+in_two_wheeler_renew^4*SUMIFS(AR2:AR61,B2:B61,B14-48)) | AT14: =AT13*(1-IF(B13>=in_marketplace_from,d_hz_device*G13,0)) | AU14: =F14*AT14*IF(B14>=in_marketplace_from,d_hz_device*G14,0)*in_device_ticket*in_device_comm*in_ins_partner_share | AV14: =AV13*(1-IF(B13>=in_marketplace_from,d_hz_shop*G13,0)) | AW14: =AV14*IF(B14>=in_marketplace_from,d_hz_shop*G14,0) | AX14: =F14*AW14*in_shop_ticket*in_shop_comm*in_ins_partner_share+F14*in_shop_ticket*in_shop_renew_comm*in_ins_partner_share*(in_shop_renew^1*SUMIFS(AW2:AW61,B2:B61,B14-12)+in_shop_renew^2*SUMIFS(AW2:AW61,B2:B61,B14-24)+in_shop_renew^3*SUMIFS(AW2:AW61,B2:B61,B14-36)+in_shop_renew^4*SUMIFS(AW2:AW61,B2:B61,B14-48)) | AY14: =AY13*(1-IF(B13>=in_marketplace_from,d_hz_sip*G13,0)) | AZ14: =AZ13*d_rho_sip+AY14*IF(B14>=in_marketplace_from,d_hz_sip*G14,0) | BA14: =d_rho_sip*(BA13+AZ13) | BB14: =F14*in_sip_ticket*(BA14+0.5*AZ14)*in_sip_comm/12 | BC14: =BC13*(1-IF(B13>=in_marketplace_from,d_hz_choti*G13,0)) | BD14: =BC14*IF(B14>=in_marketplace_from,d_hz_choti*G14,0) | BE14: =F14*SUMIFS(BD2:BD61,B2:B61,B14-in_choti_months)*in_choti_renew*in_choti_ticket | BF14: =BF13*(1-IF(B13>=in_marketplace_from,d_hz_nps*G13,0)) | BG14: =F14*BF14*IF(B14>=in_marketplace_from,d_hz_nps*G14,0)*in_nps_ticket*in_nps_comm | BH14: =BH13*(1-IF(B13>=in_marketplace_from,d_hz_gold*G13,0)) | BI14: =BI13*d_rho_gold+BH14*IF(B14>=in_marketplace_from,d_hz_gold*G14,0) | BJ14: =F14*BI14*in_gold_ticket*in_gold_comm | BK14: =BK13*(1-IF(B13>=in_marketplace_from,d_hz_fd*G13,0)) | BL14: =F14*BK14*IF(B14>=in_marketplace_from,d_hz_fd*G14,0)*in_fd_ticket*in_fd_comm | BM14: =BM13*(1-IF(B13>=in_marketplace_from,d_hz_recharge*G13,0)) | BN14: =BN13*d_rho_recharge+BM14*IF(B14>=in_marketplace_from,d_hz_recharge*G14,0) | BO14: =F14*BN14*in_recharge_ticket*in_recharge_comm/12 | BP14: =BP13*(1-IF(B13>=in_marketplace_from,d_hz_bills*G13,0)) | BQ14: =BQ13*d_rho_bills+BP14*IF(B14>=in_marketplace_from,d_hz_bills*G14,0) | BR14: =F14*BQ14*in_bills_ticket*in_bills_comm/12 | BS14: =BS13*(1-IF(B13>=in_marketplace_from,d_hz_loan_gold*G13,0)) | BT14: =F14*BS14*IF(B14>=in_marketplace_from,d_hz_loan_gold*G14,0)*in_loan_gold_ticket*in_loan_gold_comm | BU14: =BU13*(1-IF(B13>=in_marketplace_from,d_hz_loan_cd*G13,0)) | BV14: =F14*BU14*IF(B14>=in_marketplace_from,d_hz_loan_cd*G14,0)*in_loan_cd_ticket*in_loan_cd_comm | BW14: =BW13*(1-IF(B13>=in_marketplace_from,d_hz_loan_vehicle*G13,0)) | BX14: =F14*BW14*IF(B14>=in_marketplace_from,d_hz_loan_vehicle*G14,0)*in_loan_vehicle_ticket*in_loan_vehicle_comm | BY14: =BY13*(1-IF(B13>=in_marketplace_from,d_hz_loan_home*G13,0)*BZ13) | BZ14: =MIN(in_approval_cap,in_loan_home_approval*INDEX('Age profile'!$O$2:$O$61,B14)*(1+in_approval_growth)^(D14-1)) | CA14: =F14*BY14*IF(B14>=in_marketplace_from,d_hz_loan_home*G14,0)*BZ14*in_loan_home_ticket*in_loan_home_comm | CB14: =CB13*(1-IF(B13>=in_marketplace_from,d_hz_loan_lap*G13,0)*CC13) | CC14: =MIN(in_approval_cap,in_loan_lap_approval*INDEX('Age profile'!$O$2:$O$61,B14)*(1+in_approval_growth)^(D14-1)) | CD14: =F14*CB14*IF(B14>=in_marketplace_from,d_hz_loan_lap*G14,0)*CC14*in_loan_lap_ticket*in_loan_lap_comm | CE14: =AA14+AB14+AC14+AD14+AG14+AJ14+AM14+AP14+AS14+AU14+AX14+BB14+BE14+BG14+BJ14+BL14+BO14+BR14+BT14+BV14+BX14+CA14+CD14
A15: 1 | B15: 14 | C15: =A15+B15-1 | D15: =INT((C15-1)/12)+1 | E15: =INDEX(Monthly!$B$2:$B$61,A15) | F15: =E15*INDEX('Age profile'!$B$2:$B$61,B15) | G15: =MIN(in_takeup_cap,INDEX('Age profile'!$N$2:$N$61,B15)*(1+in_takeup_growth)^(D15-1)) | H15: =MIN(in_approval_cap,in_approved_first*INDEX('Age profile'!$O$2:$O$61,B15)*(1+in_approval_growth)^(D15-1)) | I15: =G15*MIN(in_takeup_cap,INDEX('Age profile'!$O$2:$O$61,B15)*(1+in_approval_growth)^(D15-1)) | J15: =(J14-L14)*F15/F14 | K15: =(K14-M14)*F15/F14+SUMIFS(O2:O14,B2:B14,B15-1-d_T)*F15 | L15: =IF(B15>=in_marketplace_from,J15*d_hz*G15*in_eligible*H15,0) | M15: =IF(B15>=in_marketplace_from,K15*d_hz*G15*in_eligible*in_approved_repeat,0) | N15: =L15+M15 | O15: =N15/F15 | P15: =F15-J15-K15 | Q15: =IF(B15>=in_marketplace_from,(J15+K15)*d_hz*G15,0) | R15: =SUMIFS(N2:N61,B2:B61,">="&(B15-d_T),B2:B61,"<="&(B15-1)) | S15: =(1-d_u)*S14+IF(d_T>in_topup_lag,SUMIFS(O2:O61,B2:B61,B15-in_topup_lag)-d_udrop*SUMIFS(O2:O61,B2:B61,B15-d_T),0) | T15: =F15*d_u*S15 | U15: =L15*in_ticket+M15*d_rep_ticket | V15: =U15+T15*d_topup_amt | W15: =N15+T15*d_topup_ratio | X15: =SUMIFS(W2:W61,B2:B61,B15-in_dpd_lag)*d_cured | Y15: =SUMIFS(W2:W61,B2:B61,B15-in_rec_lag)*d_recd | Z15: =IF(AND(B15>=in_marketplace_from,B15<in_marketplace_from+in_card_months),in_card_share/in_card_months*F15*I15,IF(AND(B15>=in_marketplace_from+in_card_months,B15<in_marketplace_from+2*in_card_months),in_card_share*d_card_rem/in_card_months*F15*MIN(in_takeup_cap,(1+in_takeup_growth)^(D15-1))*MIN(in_takeup_cap,(1+in_approval_growth)^(D15-1)),0)) | AA15: =V15*in_fee*(1-in_taken_back) | AB15: =SUMIFS(W2:W61,B2:B61,B15-in_dpd_lag)*d_dpd | AC15: =SUMIFS(W2:W61,B2:B61,B15-in_rec_lag)*d_rec | AD15: =Z15*in_card_fee | AE15: =AE14*(1-IF(B14>=in_marketplace_from,d_hz_hlth_small*G14,0)) | AF15: =AE15*IF(B15>=in_marketplace_from,d_hz_hlth_small*G15,0) | AG15: =F15*AF15*in_hlth_small_ticket*in_hlth_small_comm*in_ins_partner_share+F15*in_hlth_small_ticket*in_hlth_small_renew_comm*in_ins_partner_share*(in_hlth_small_renew^1*SUMIFS(AF2:AF61,B2:B61,B15-12)+in_hlth_small_renew^2*SUMIFS(AF2:AF61,B2:B61,B15-24)+in_hlth_small_renew^3*SUMIFS(AF2:AF61,B2:B61,B15-36)+in_hlth_small_renew^4*SUMIFS(AF2:AF61,B2:B61,B15-48)) | AH15: =AH14*(1-IF(B14>=in_marketplace_from,d_hz_hlth_family*G14,0)) | AI15: =AH15*IF(B15>=in_marketplace_from,d_hz_hlth_family*G15,0) | AJ15: =F15*AI15*in_hlth_family_ticket*in_hlth_family_comm*in_ins_partner_share+F15*in_hlth_family_ticket*in_hlth_family_renew_comm*in_ins_partner_share*(in_hlth_family_renew^1*SUMIFS(AI2:AI61,B2:B61,B15-12)+in_hlth_family_renew^2*SUMIFS(AI2:AI61,B2:B61,B15-24)+in_hlth_family_renew^3*SUMIFS(AI2:AI61,B2:B61,B15-36)+in_hlth_family_renew^4*SUMIFS(AI2:AI61,B2:B61,B15-48)) | AK15: =AK14*(1-IF(B14>=in_marketplace_from,d_hz_life_term*G14,0)) | AL15: =AK15*IF(B15>=in_marketplace_from,d_hz_life_term*G15,0) | AM15: =F15*AL15*in_life_term_ticket*in_life_term_comm*in_ins_partner_share+F15*in_life_term_ticket*in_life_term_renew_comm*in_ins_partner_share*(in_life_term_renew^1*SUMIFS(AL2:AL61,B2:B61,B15-12)+in_life_term_renew^2*SUMIFS(AL2:AL61,B2:B61,B15-24)+in_life_term_renew^3*SUMIFS(AL2:AL61,B2:B61,B15-36)+in_life_term_renew^4*SUMIFS(AL2:AL61,B2:B61,B15-48)) | AN15: =AN14*(1-IF(B14>=in_marketplace_from,d_hz_accident*G14,0)) | AO15: =AN15*IF(B15>=in_marketplace_from,d_hz_accident*G15,0) | AP15: =F15*AO15*in_accident_ticket*in_accident_comm*in_ins_partner_share+F15*in_accident_ticket*in_accident_renew_comm*in_ins_partner_share*(in_accident_renew^1*SUMIFS(AO2:AO61,B2:B61,B15-12)+in_accident_renew^2*SUMIFS(AO2:AO61,B2:B61,B15-24)+in_accident_renew^3*SUMIFS(AO2:AO61,B2:B61,B15-36)+in_accident_renew^4*SUMIFS(AO2:AO61,B2:B61,B15-48)) | AQ15: =AQ14*(1-IF(B14>=in_marketplace_from,d_hz_two_wheeler*G14,0)) | AR15: =AQ15*IF(B15>=in_marketplace_from,d_hz_two_wheeler*G15,0) | AS15: =F15*AR15*in_two_wheeler_ticket*in_two_wheeler_comm*in_ins_partner_share+F15*in_two_wheeler_ticket*in_two_wheeler_comm*in_ins_partner_share*(in_two_wheeler_renew^1*SUMIFS(AR2:AR61,B2:B61,B15-12)+in_two_wheeler_renew^2*SUMIFS(AR2:AR61,B2:B61,B15-24)+in_two_wheeler_renew^3*SUMIFS(AR2:AR61,B2:B61,B15-36)+in_two_wheeler_renew^4*SUMIFS(AR2:AR61,B2:B61,B15-48)) | AT15: =AT14*(1-IF(B14>=in_marketplace_from,d_hz_device*G14,0)) | AU15: =F15*AT15*IF(B15>=in_marketplace_from,d_hz_device*G15,0)*in_device_ticket*in_device_comm*in_ins_partner_share | AV15: =AV14*(1-IF(B14>=in_marketplace_from,d_hz_shop*G14,0)) | AW15: =AV15*IF(B15>=in_marketplace_from,d_hz_shop*G15,0) | AX15: =F15*AW15*in_shop_ticket*in_shop_comm*in_ins_partner_share+F15*in_shop_ticket*in_shop_renew_comm*in_ins_partner_share*(in_shop_renew^1*SUMIFS(AW2:AW61,B2:B61,B15-12)+in_shop_renew^2*SUMIFS(AW2:AW61,B2:B61,B15-24)+in_shop_renew^3*SUMIFS(AW2:AW61,B2:B61,B15-36)+in_shop_renew^4*SUMIFS(AW2:AW61,B2:B61,B15-48)) | AY15: =AY14*(1-IF(B14>=in_marketplace_from,d_hz_sip*G14,0)) | AZ15: =AZ14*d_rho_sip+AY15*IF(B15>=in_marketplace_from,d_hz_sip*G15,0) | BA15: =d_rho_sip*(BA14+AZ14) | BB15: =F15*in_sip_ticket*(BA15+0.5*AZ15)*in_sip_comm/12 | BC15: =BC14*(1-IF(B14>=in_marketplace_from,d_hz_choti*G14,0)) | BD15: =BC15*IF(B15>=in_marketplace_from,d_hz_choti*G15,0) | BE15: =F15*SUMIFS(BD2:BD61,B2:B61,B15-in_choti_months)*in_choti_renew*in_choti_ticket | BF15: =BF14*(1-IF(B14>=in_marketplace_from,d_hz_nps*G14,0)) | BG15: =F15*BF15*IF(B15>=in_marketplace_from,d_hz_nps*G15,0)*in_nps_ticket*in_nps_comm | BH15: =BH14*(1-IF(B14>=in_marketplace_from,d_hz_gold*G14,0)) | BI15: =BI14*d_rho_gold+BH15*IF(B15>=in_marketplace_from,d_hz_gold*G15,0) | BJ15: =F15*BI15*in_gold_ticket*in_gold_comm | BK15: =BK14*(1-IF(B14>=in_marketplace_from,d_hz_fd*G14,0)) | BL15: =F15*BK15*IF(B15>=in_marketplace_from,d_hz_fd*G15,0)*in_fd_ticket*in_fd_comm | BM15: =BM14*(1-IF(B14>=in_marketplace_from,d_hz_recharge*G14,0)) | BN15: =BN14*d_rho_recharge+BM15*IF(B15>=in_marketplace_from,d_hz_recharge*G15,0) | BO15: =F15*BN15*in_recharge_ticket*in_recharge_comm/12 | BP15: =BP14*(1-IF(B14>=in_marketplace_from,d_hz_bills*G14,0)) | BQ15: =BQ14*d_rho_bills+BP15*IF(B15>=in_marketplace_from,d_hz_bills*G15,0) | BR15: =F15*BQ15*in_bills_ticket*in_bills_comm/12 | BS15: =BS14*(1-IF(B14>=in_marketplace_from,d_hz_loan_gold*G14,0)) | BT15: =F15*BS15*IF(B15>=in_marketplace_from,d_hz_loan_gold*G15,0)*in_loan_gold_ticket*in_loan_gold_comm | BU15: =BU14*(1-IF(B14>=in_marketplace_from,d_hz_loan_cd*G14,0)) | BV15: =F15*BU15*IF(B15>=in_marketplace_from,d_hz_loan_cd*G15,0)*in_loan_cd_ticket*in_loan_cd_comm | BW15: =BW14*(1-IF(B14>=in_marketplace_from,d_hz_loan_vehicle*G14,0)) | BX15: =F15*BW15*IF(B15>=in_marketplace_from,d_hz_loan_vehicle*G15,0)*in_loan_vehicle_ticket*in_loan_vehicle_comm | BY15: =BY14*(1-IF(B14>=in_marketplace_from,d_hz_loan_home*G14,0)*BZ14) | BZ15: =MIN(in_approval_cap,in_loan_home_approval*INDEX('Age profile'!$O$2:$O$61,B15)*(1+in_approval_growth)^(D15-1)) | CA15: =F15*BY15*IF(B15>=in_marketplace_from,d_hz_loan_home*G15,0)*BZ15*in_loan_home_ticket*in_loan_home_comm | CB15: =CB14*(1-IF(B14>=in_marketplace_from,d_hz_loan_lap*G14,0)*CC14) | CC15: =MIN(in_approval_cap,in_loan_lap_approval*INDEX('Age profile'!$O$2:$O$61,B15)*(1+in_approval_growth)^(D15-1)) | CD15: =F15*CB15*IF(B15>=in_marketplace_from,d_hz_loan_lap*G15,0)*CC15*in_loan_lap_ticket*in_loan_lap_comm | CE15: =AA15+AB15+AC15+AD15+AG15+AJ15+AM15+AP15+AS15+AU15+AX15+BB15+BE15+BG15+BJ15+BL15+BO15+BR15+BT15+BV15+BX15+CA15+CD15
A16: 1 | B16: 15 | C16: =A16+B16-1 | D16: =INT((C16-1)/12)+1 | E16: =INDEX(Monthly!$B$2:$B$61,A16) | F16: =E16*INDEX('Age profile'!$B$2:$B$61,B16) | G16: =MIN(in_takeup_cap,INDEX('Age profile'!$N$2:$N$61,B16)*(1+in_takeup_growth)^(D16-1)) | H16: =MIN(in_approval_cap,in_approved_first*INDEX('Age profile'!$O$2:$O$61,B16)*(1+in_approval_growth)^(D16-1)) | I16: =G16*MIN(in_takeup_cap,INDEX('Age profile'!$O$2:$O$61,B16)*(1+in_approval_growth)^(D16-1)) | J16: =(J15-L15)*F16/F15 | K16: =(K15-M15)*F16/F15+SUMIFS(O2:O15,B2:B15,B16-1-d_T)*F16 | L16: =IF(B16>=in_marketplace_from,J16*d_hz*G16*in_eligible*H16,0) | M16: =IF(B16>=in_marketplace_from,K16*d_hz*G16*in_eligible*in_approved_repeat,0) | N16: =L16+M16 | O16: =N16/F16 | P16: =F16-J16-K16 | Q16: =IF(B16>=in_marketplace_from,(J16+K16)*d_hz*G16,0) | R16: =SUMIFS(N2:N61,B2:B61,">="&(B16-d_T),B2:B61,"<="&(B16-1)) | S16: =(1-d_u)*S15+IF(d_T>in_topup_lag,SUMIFS(O2:O61,B2:B61,B16-in_topup_lag)-d_udrop*SUMIFS(O2:O61,B2:B61,B16-d_T),0) | T16: =F16*d_u*S16 | U16: =L16*in_ticket+M16*d_rep_ticket | V16: =U16+T16*d_topup_amt | W16: =N16+T16*d_topup_ratio | X16: =SUMIFS(W2:W61,B2:B61,B16-in_dpd_lag)*d_cured | Y16: =SUMIFS(W2:W61,B2:B61,B16-in_rec_lag)*d_recd | Z16: =IF(AND(B16>=in_marketplace_from,B16<in_marketplace_from+in_card_months),in_card_share/in_card_months*F16*I16,IF(AND(B16>=in_marketplace_from+in_card_months,B16<in_marketplace_from+2*in_card_months),in_card_share*d_card_rem/in_card_months*F16*MIN(in_takeup_cap,(1+in_takeup_growth)^(D16-1))*MIN(in_takeup_cap,(1+in_approval_growth)^(D16-1)),0)) | AA16: =V16*in_fee*(1-in_taken_back) | AB16: =SUMIFS(W2:W61,B2:B61,B16-in_dpd_lag)*d_dpd | AC16: =SUMIFS(W2:W61,B2:B61,B16-in_rec_lag)*d_rec | AD16: =Z16*in_card_fee | AE16: =AE15*(1-IF(B15>=in_marketplace_from,d_hz_hlth_small*G15,0)) | AF16: =AE16*IF(B16>=in_marketplace_from,d_hz_hlth_small*G16,0) | AG16: =F16*AF16*in_hlth_small_ticket*in_hlth_small_comm*in_ins_partner_share+F16*in_hlth_small_ticket*in_hlth_small_renew_comm*in_ins_partner_share*(in_hlth_small_renew^1*SUMIFS(AF2:AF61,B2:B61,B16-12)+in_hlth_small_renew^2*SUMIFS(AF2:AF61,B2:B61,B16-24)+in_hlth_small_renew^3*SUMIFS(AF2:AF61,B2:B61,B16-36)+in_hlth_small_renew^4*SUMIFS(AF2:AF61,B2:B61,B16-48)) | AH16: =AH15*(1-IF(B15>=in_marketplace_from,d_hz_hlth_family*G15,0)) | AI16: =AH16*IF(B16>=in_marketplace_from,d_hz_hlth_family*G16,0) | AJ16: =F16*AI16*in_hlth_family_ticket*in_hlth_family_comm*in_ins_partner_share+F16*in_hlth_family_ticket*in_hlth_family_renew_comm*in_ins_partner_share*(in_hlth_family_renew^1*SUMIFS(AI2:AI61,B2:B61,B16-12)+in_hlth_family_renew^2*SUMIFS(AI2:AI61,B2:B61,B16-24)+in_hlth_family_renew^3*SUMIFS(AI2:AI61,B2:B61,B16-36)+in_hlth_family_renew^4*SUMIFS(AI2:AI61,B2:B61,B16-48)) | AK16: =AK15*(1-IF(B15>=in_marketplace_from,d_hz_life_term*G15,0)) | AL16: =AK16*IF(B16>=in_marketplace_from,d_hz_life_term*G16,0) | AM16: =F16*AL16*in_life_term_ticket*in_life_term_comm*in_ins_partner_share+F16*in_life_term_ticket*in_life_term_renew_comm*in_ins_partner_share*(in_life_term_renew^1*SUMIFS(AL2:AL61,B2:B61,B16-12)+in_life_term_renew^2*SUMIFS(AL2:AL61,B2:B61,B16-24)+in_life_term_renew^3*SUMIFS(AL2:AL61,B2:B61,B16-36)+in_life_term_renew^4*SUMIFS(AL2:AL61,B2:B61,B16-48)) | AN16: =AN15*(1-IF(B15>=in_marketplace_from,d_hz_accident*G15,0)) | AO16: =AN16*IF(B16>=in_marketplace_from,d_hz_accident*G16,0) | AP16: =F16*AO16*in_accident_ticket*in_accident_comm*in_ins_partner_share+F16*in_accident_ticket*in_accident_renew_comm*in_ins_partner_share*(in_accident_renew^1*SUMIFS(AO2:AO61,B2:B61,B16-12)+in_accident_renew^2*SUMIFS(AO2:AO61,B2:B61,B16-24)+in_accident_renew^3*SUMIFS(AO2:AO61,B2:B61,B16-36)+in_accident_renew^4*SUMIFS(AO2:AO61,B2:B61,B16-48)) | AQ16: =AQ15*(1-IF(B15>=in_marketplace_from,d_hz_two_wheeler*G15,0)) | AR16: =AQ16*IF(B16>=in_marketplace_from,d_hz_two_wheeler*G16,0) | AS16: =F16*AR16*in_two_wheeler_ticket*in_two_wheeler_comm*in_ins_partner_share+F16*in_two_wheeler_ticket*in_two_wheeler_comm*in_ins_partner_share*(in_two_wheeler_renew^1*SUMIFS(AR2:AR61,B2:B61,B16-12)+in_two_wheeler_renew^2*SUMIFS(AR2:AR61,B2:B61,B16-24)+in_two_wheeler_renew^3*SUMIFS(AR2:AR61,B2:B61,B16-36)+in_two_wheeler_renew^4*SUMIFS(AR2:AR61,B2:B61,B16-48)) | AT16: =AT15*(1-IF(B15>=in_marketplace_from,d_hz_device*G15,0)) | AU16: =F16*AT16*IF(B16>=in_marketplace_from,d_hz_device*G16,0)*in_device_ticket*in_device_comm*in_ins_partner_share | AV16: =AV15*(1-IF(B15>=in_marketplace_from,d_hz_shop*G15,0)) | AW16: =AV16*IF(B16>=in_marketplace_from,d_hz_shop*G16,0) | AX16: =F16*AW16*in_shop_ticket*in_shop_comm*in_ins_partner_share+F16*in_shop_ticket*in_shop_renew_comm*in_ins_partner_share*(in_shop_renew^1*SUMIFS(AW2:AW61,B2:B61,B16-12)+in_shop_renew^2*SUMIFS(AW2:AW61,B2:B61,B16-24)+in_shop_renew^3*SUMIFS(AW2:AW61,B2:B61,B16-36)+in_shop_renew^4*SUMIFS(AW2:AW61,B2:B61,B16-48)) | AY16: =AY15*(1-IF(B15>=in_marketplace_from,d_hz_sip*G15,0)) | AZ16: =AZ15*d_rho_sip+AY16*IF(B16>=in_marketplace_from,d_hz_sip*G16,0) | BA16: =d_rho_sip*(BA15+AZ15) | BB16: =F16*in_sip_ticket*(BA16+0.5*AZ16)*in_sip_comm/12 | BC16: =BC15*(1-IF(B15>=in_marketplace_from,d_hz_choti*G15,0)) | BD16: =BC16*IF(B16>=in_marketplace_from,d_hz_choti*G16,0) | BE16: =F16*SUMIFS(BD2:BD61,B2:B61,B16-in_choti_months)*in_choti_renew*in_choti_ticket | BF16: =BF15*(1-IF(B15>=in_marketplace_from,d_hz_nps*G15,0)) | BG16: =F16*BF16*IF(B16>=in_marketplace_from,d_hz_nps*G16,0)*in_nps_ticket*in_nps_comm | BH16: =BH15*(1-IF(B15>=in_marketplace_from,d_hz_gold*G15,0)) | BI16: =BI15*d_rho_gold+BH16*IF(B16>=in_marketplace_from,d_hz_gold*G16,0) | BJ16: =F16*BI16*in_gold_ticket*in_gold_comm | BK16: =BK15*(1-IF(B15>=in_marketplace_from,d_hz_fd*G15,0)) | BL16: =F16*BK16*IF(B16>=in_marketplace_from,d_hz_fd*G16,0)*in_fd_ticket*in_fd_comm | BM16: =BM15*(1-IF(B15>=in_marketplace_from,d_hz_recharge*G15,0)) | BN16: =BN15*d_rho_recharge+BM16*IF(B16>=in_marketplace_from,d_hz_recharge*G16,0) | BO16: =F16*BN16*in_recharge_ticket*in_recharge_comm/12 | BP16: =BP15*(1-IF(B15>=in_marketplace_from,d_hz_bills*G15,0)) | BQ16: =BQ15*d_rho_bills+BP16*IF(B16>=in_marketplace_from,d_hz_bills*G16,0) | BR16: =F16*BQ16*in_bills_ticket*in_bills_comm/12 | BS16: =BS15*(1-IF(B15>=in_marketplace_from,d_hz_loan_gold*G15,0)) | BT16: =F16*BS16*IF(B16>=in_marketplace_from,d_hz_loan_gold*G16,0)*in_loan_gold_ticket*in_loan_gold_comm | BU16: =BU15*(1-IF(B15>=in_marketplace_from,d_hz_loan_cd*G15,0)) | BV16: =F16*BU16*IF(B16>=in_marketplace_from,d_hz_loan_cd*G16,0)*in_loan_cd_ticket*in_loan_cd_comm | BW16: =BW15*(1-IF(B15>=in_marketplace_from,d_hz_loan_vehicle*G15,0)) | BX16: =F16*BW16*IF(B16>=in_marketplace_from,d_hz_loan_vehicle*G16,0)*in_loan_vehicle_ticket*in_loan_vehicle_comm | BY16: =BY15*(1-IF(B15>=in_marketplace_from,d_hz_loan_home*G15,0)*BZ15) | BZ16: =MIN(in_approval_cap,in_loan_home_approval*INDEX('Age profile'!$O$2:$O$61,B16)*(1+in_approval_growth)^(D16-1)) | CA16: =F16*BY16*IF(B16>=in_marketplace_from,d_hz_loan_home*G16,0)*BZ16*in_loan_home_ticket*in_loan_home_comm | CB16: =CB15*(1-IF(B15>=in_marketplace_from,d_hz_loan_lap*G15,0)*CC15) | CC16: =MIN(in_approval_cap,in_loan_lap_approval*INDEX('Age profile'!$O$2:$O$61,B16)*(1+in_approval_growth)^(D16-1)) | CD16: =F16*CB16*IF(B16>=in_marketplace_from,d_hz_loan_lap*G16,0)*CC16*in_loan_lap_ticket*in_loan_lap_comm | CE16: =AA16+AB16+AC16+AD16+AG16+AJ16+AM16+AP16+AS16+AU16+AX16+BB16+BE16+BG16+BJ16+BL16+BO16+BR16+BT16+BV16+BX16+CA16+CD16
A17: 1 | B17: 16 | C17: =A17+B17-1 | D17: =INT((C17-1)/12)+1 | E17: =INDEX(Monthly!$B$2:$B$61,A17) | F17: =E17*INDEX('Age profile'!$B$2:$B$61,B17) | G17: =MIN(in_takeup_cap,INDEX('Age profile'!$N$2:$N$61,B17)*(1+in_takeup_growth)^(D17-1)) | H17: =MIN(in_approval_cap,in_approved_first*INDEX('Age profile'!$O$2:$O$61,B17)*(1+in_approval_growth)^(D17-1)) | I17: =G17*MIN(in_takeup_cap,INDEX('Age profile'!$O$2:$O$61,B17)*(1+in_approval_growth)^(D17-1)) | J17: =(J16-L16)*F17/F16 | K17: =(K16-M16)*F17/F16+SUMIFS(O2:O16,B2:B16,B17-1-d_T)*F17 | L17: =IF(B17>=in_marketplace_from,J17*d_hz*G17*in_eligible*H17,0) | M17: =IF(B17>=in_marketplace_from,K17*d_hz*G17*in_eligible*in_approved_repeat,0) | N17: =L17+M17 | O17: =N17/F17 | P17: =F17-J17-K17 | Q17: =IF(B17>=in_marketplace_from,(J17+K17)*d_hz*G17,0) | R17: =SUMIFS(N2:N61,B2:B61,">="&(B17-d_T),B2:B61,"<="&(B17-1)) | S17: =(1-d_u)*S16+IF(d_T>in_topup_lag,SUMIFS(O2:O61,B2:B61,B17-in_topup_lag)-d_udrop*SUMIFS(O2:O61,B2:B61,B17-d_T),0) | T17: =F17*d_u*S17 | U17: =L17*in_ticket+M17*d_rep_ticket | V17: =U17+T17*d_topup_amt | W17: =N17+T17*d_topup_ratio | X17: =SUMIFS(W2:W61,B2:B61,B17-in_dpd_lag)*d_cured | Y17: =SUMIFS(W2:W61,B2:B61,B17-in_rec_lag)*d_recd | Z17: =IF(AND(B17>=in_marketplace_from,B17<in_marketplace_from+in_card_months),in_card_share/in_card_months*F17*I17,IF(AND(B17>=in_marketplace_from+in_card_months,B17<in_marketplace_from+2*in_card_months),in_card_share*d_card_rem/in_card_months*F17*MIN(in_takeup_cap,(1+in_takeup_growth)^(D17-1))*MIN(in_takeup_cap,(1+in_approval_growth)^(D17-1)),0)) | AA17: =V17*in_fee*(1-in_taken_back) | AB17: =SUMIFS(W2:W61,B2:B61,B17-in_dpd_lag)*d_dpd | AC17: =SUMIFS(W2:W61,B2:B61,B17-in_rec_lag)*d_rec | AD17: =Z17*in_card_fee | AE17: =AE16*(1-IF(B16>=in_marketplace_from,d_hz_hlth_small*G16,0)) | AF17: =AE17*IF(B17>=in_marketplace_from,d_hz_hlth_small*G17,0) | AG17: =F17*AF17*in_hlth_small_ticket*in_hlth_small_comm*in_ins_partner_share+F17*in_hlth_small_ticket*in_hlth_small_renew_comm*in_ins_partner_share*(in_hlth_small_renew^1*SUMIFS(AF2:AF61,B2:B61,B17-12)+in_hlth_small_renew^2*SUMIFS(AF2:AF61,B2:B61,B17-24)+in_hlth_small_renew^3*SUMIFS(AF2:AF61,B2:B61,B17-36)+in_hlth_small_renew^4*SUMIFS(AF2:AF61,B2:B61,B17-48)) | AH17: =AH16*(1-IF(B16>=in_marketplace_from,d_hz_hlth_family*G16,0)) | AI17: =AH17*IF(B17>=in_marketplace_from,d_hz_hlth_family*G17,0) | AJ17: =F17*AI17*in_hlth_family_ticket*in_hlth_family_comm*in_ins_partner_share+F17*in_hlth_family_ticket*in_hlth_family_renew_comm*in_ins_partner_share*(in_hlth_family_renew^1*SUMIFS(AI2:AI61,B2:B61,B17-12)+in_hlth_family_renew^2*SUMIFS(AI2:AI61,B2:B61,B17-24)+in_hlth_family_renew^3*SUMIFS(AI2:AI61,B2:B61,B17-36)+in_hlth_family_renew^4*SUMIFS(AI2:AI61,B2:B61,B17-48)) | AK17: =AK16*(1-IF(B16>=in_marketplace_from,d_hz_life_term*G16,0)) | AL17: =AK17*IF(B17>=in_marketplace_from,d_hz_life_term*G17,0) | AM17: =F17*AL17*in_life_term_ticket*in_life_term_comm*in_ins_partner_share+F17*in_life_term_ticket*in_life_term_renew_comm*in_ins_partner_share*(in_life_term_renew^1*SUMIFS(AL2:AL61,B2:B61,B17-12)+in_life_term_renew^2*SUMIFS(AL2:AL61,B2:B61,B17-24)+in_life_term_renew^3*SUMIFS(AL2:AL61,B2:B61,B17-36)+in_life_term_renew^4*SUMIFS(AL2:AL61,B2:B61,B17-48)) | AN17: =AN16*(1-IF(B16>=in_marketplace_from,d_hz_accident*G16,0)) | AO17: =AN17*IF(B17>=in_marketplace_from,d_hz_accident*G17,0) | AP17: =F17*AO17*in_accident_ticket*in_accident_comm*in_ins_partner_share+F17*in_accident_ticket*in_accident_renew_comm*in_ins_partner_share*(in_accident_renew^1*SUMIFS(AO2:AO61,B2:B61,B17-12)+in_accident_renew^2*SUMIFS(AO2:AO61,B2:B61,B17-24)+in_accident_renew^3*SUMIFS(AO2:AO61,B2:B61,B17-36)+in_accident_renew^4*SUMIFS(AO2:AO61,B2:B61,B17-48)) | AQ17: =AQ16*(1-IF(B16>=in_marketplace_from,d_hz_two_wheeler*G16,0)) | AR17: =AQ17*IF(B17>=in_marketplace_from,d_hz_two_wheeler*G17,0) | AS17: =F17*AR17*in_two_wheeler_ticket*in_two_wheeler_comm*in_ins_partner_share+F17*in_two_wheeler_ticket*in_two_wheeler_comm*in_ins_partner_share*(in_two_wheeler_renew^1*SUMIFS(AR2:AR61,B2:B61,B17-12)+in_two_wheeler_renew^2*SUMIFS(AR2:AR61,B2:B61,B17-24)+in_two_wheeler_renew^3*SUMIFS(AR2:AR61,B2:B61,B17-36)+in_two_wheeler_renew^4*SUMIFS(AR2:AR61,B2:B61,B17-48)) | AT17: =AT16*(1-IF(B16>=in_marketplace_from,d_hz_device*G16,0)) | AU17: =F17*AT17*IF(B17>=in_marketplace_from,d_hz_device*G17,0)*in_device_ticket*in_device_comm*in_ins_partner_share | AV17: =AV16*(1-IF(B16>=in_marketplace_from,d_hz_shop*G16,0)) | AW17: =AV17*IF(B17>=in_marketplace_from,d_hz_shop*G17,0) | AX17: =F17*AW17*in_shop_ticket*in_shop_comm*in_ins_partner_share+F17*in_shop_ticket*in_shop_renew_comm*in_ins_partner_share*(in_shop_renew^1*SUMIFS(AW2:AW61,B2:B61,B17-12)+in_shop_renew^2*SUMIFS(AW2:AW61,B2:B61,B17-24)+in_shop_renew^3*SUMIFS(AW2:AW61,B2:B61,B17-36)+in_shop_renew^4*SUMIFS(AW2:AW61,B2:B61,B17-48)) | AY17: =AY16*(1-IF(B16>=in_marketplace_from,d_hz_sip*G16,0)) | AZ17: =AZ16*d_rho_sip+AY17*IF(B17>=in_marketplace_from,d_hz_sip*G17,0) | BA17: =d_rho_sip*(BA16+AZ16) | BB17: =F17*in_sip_ticket*(BA17+0.5*AZ17)*in_sip_comm/12 | BC17: =BC16*(1-IF(B16>=in_marketplace_from,d_hz_choti*G16,0)) | BD17: =BC17*IF(B17>=in_marketplace_from,d_hz_choti*G17,0) | BE17: =F17*SUMIFS(BD2:BD61,B2:B61,B17-in_choti_months)*in_choti_renew*in_choti_ticket | BF17: =BF16*(1-IF(B16>=in_marketplace_from,d_hz_nps*G16,0)) | BG17: =F17*BF17*IF(B17>=in_marketplace_from,d_hz_nps*G17,0)*in_nps_ticket*in_nps_comm | BH17: =BH16*(1-IF(B16>=in_marketplace_from,d_hz_gold*G16,0)) | BI17: =BI16*d_rho_gold+BH17*IF(B17>=in_marketplace_from,d_hz_gold*G17,0) | BJ17: =F17*BI17*in_gold_ticket*in_gold_comm | BK17: =BK16*(1-IF(B16>=in_marketplace_from,d_hz_fd*G16,0)) | BL17: =F17*BK17*IF(B17>=in_marketplace_from,d_hz_fd*G17,0)*in_fd_ticket*in_fd_comm | BM17: =BM16*(1-IF(B16>=in_marketplace_from,d_hz_recharge*G16,0)) | BN17: =BN16*d_rho_recharge+BM17*IF(B17>=in_marketplace_from,d_hz_recharge*G17,0) | BO17: =F17*BN17*in_recharge_ticket*in_recharge_comm/12 | BP17: =BP16*(1-IF(B16>=in_marketplace_from,d_hz_bills*G16,0)) | BQ17: =BQ16*d_rho_bills+BP17*IF(B17>=in_marketplace_from,d_hz_bills*G17,0) | BR17: =F17*BQ17*in_bills_ticket*in_bills_comm/12 | BS17: =BS16*(1-IF(B16>=in_marketplace_from,d_hz_loan_gold*G16,0)) | BT17: =F17*BS17*IF(B17>=in_marketplace_from,d_hz_loan_gold*G17,0)*in_loan_gold_ticket*in_loan_gold_comm | BU17: =BU16*(1-IF(B16>=in_marketplace_from,d_hz_loan_cd*G16,0)) | BV17: =F17*BU17*IF(B17>=in_marketplace_from,d_hz_loan_cd*G17,0)*in_loan_cd_ticket*in_loan_cd_comm | BW17: =BW16*(1-IF(B16>=in_marketplace_from,d_hz_loan_vehicle*G16,0)) | BX17: =F17*BW17*IF(B17>=in_marketplace_from,d_hz_loan_vehicle*G17,0)*in_loan_vehicle_ticket*in_loan_vehicle_comm | BY17: =BY16*(1-IF(B16>=in_marketplace_from,d_hz_loan_home*G16,0)*BZ16) | BZ17: =MIN(in_approval_cap,in_loan_home_approval*INDEX('Age profile'!$O$2:$O$61,B17)*(1+in_approval_growth)^(D17-1)) | CA17: =F17*BY17*IF(B17>=in_marketplace_from,d_hz_loan_home*G17,0)*BZ17*in_loan_home_ticket*in_loan_home_comm | CB17: =CB16*(1-IF(B16>=in_marketplace_from,d_hz_loan_lap*G16,0)*CC16) | CC17: =MIN(in_approval_cap,in_loan_lap_approval*INDEX('Age profile'!$O$2:$O$61,B17)*(1+in_approval_growth)^(D17-1)) | CD17: =F17*CB17*IF(B17>=in_marketplace_from,d_hz_loan_lap*G17,0)*CC17*in_loan_lap_ticket*in_loan_lap_comm | CE17: =AA17+AB17+AC17+AD17+AG17+AJ17+AM17+AP17+AS17+AU17+AX17+BB17+BE17+BG17+BJ17+BL17+BO17+BR17+BT17+BV17+BX17+CA17+CD17
A18: 1 | B18: 17 | C18: =A18+B18-1 | D18: =INT((C18-1)/12)+1 | E18: =INDEX(Monthly!$B$2:$B$61,A18) | F18: =E18*INDEX('Age profile'!$B$2:$B$61,B18) | G18: =MIN(in_takeup_cap,INDEX('Age profile'!$N$2:$N$61,B18)*(1+in_takeup_growth)^(D18-1)) | H18: =MIN(in_approval_cap,in_approved_first*INDEX('Age profile'!$O$2:$O$61,B18)*(1+in_approval_growth)^(D18-1)) | I18: =G18*MIN(in_takeup_cap,INDEX('Age profile'!$O$2:$O$61,B18)*(1+in_approval_growth)^(D18-1)) | J18: =(J17-L17)*F18/F17 | K18: =(K17-M17)*F18/F17+SUMIFS(O2:O17,B2:B17,B18-1-d_T)*F18 | L18: =IF(B18>=in_marketplace_from,J18*d_hz*G18*in_eligible*H18,0) | M18: =IF(B18>=in_marketplace_from,K18*d_hz*G18*in_eligible*in_approved_repeat,0) | N18: =L18+M18 | O18: =N18/F18 | P18: =F18-J18-K18 | Q18: =IF(B18>=in_marketplace_from,(J18+K18)*d_hz*G18,0) | R18: =SUMIFS(N2:N61,B2:B61,">="&(B18-d_T),B2:B61,"<="&(B18-1)) | S18: =(1-d_u)*S17+IF(d_T>in_topup_lag,SUMIFS(O2:O61,B2:B61,B18-in_topup_lag)-d_udrop*SUMIFS(O2:O61,B2:B61,B18-d_T),0) | T18: =F18*d_u*S18 | U18: =L18*in_ticket+M18*d_rep_ticket | V18: =U18+T18*d_topup_amt | W18: =N18+T18*d_topup_ratio | X18: =SUMIFS(W2:W61,B2:B61,B18-in_dpd_lag)*d_cured | Y18: =SUMIFS(W2:W61,B2:B61,B18-in_rec_lag)*d_recd | Z18: =IF(AND(B18>=in_marketplace_from,B18<in_marketplace_from+in_card_months),in_card_share/in_card_months*F18*I18,IF(AND(B18>=in_marketplace_from+in_card_months,B18<in_marketplace_from+2*in_card_months),in_card_share*d_card_rem/in_card_months*F18*MIN(in_takeup_cap,(1+in_takeup_growth)^(D18-1))*MIN(in_takeup_cap,(1+in_approval_growth)^(D18-1)),0)) | AA18: =V18*in_fee*(1-in_taken_back) | AB18: =SUMIFS(W2:W61,B2:B61,B18-in_dpd_lag)*d_dpd | AC18: =SUMIFS(W2:W61,B2:B61,B18-in_rec_lag)*d_rec | AD18: =Z18*in_card_fee | AE18: =AE17*(1-IF(B17>=in_marketplace_from,d_hz_hlth_small*G17,0)) | AF18: =AE18*IF(B18>=in_marketplace_from,d_hz_hlth_small*G18,0) | AG18: =F18*AF18*in_hlth_small_ticket*in_hlth_small_comm*in_ins_partner_share+F18*in_hlth_small_ticket*in_hlth_small_renew_comm*in_ins_partner_share*(in_hlth_small_renew^1*SUMIFS(AF2:AF61,B2:B61,B18-12)+in_hlth_small_renew^2*SUMIFS(AF2:AF61,B2:B61,B18-24)+in_hlth_small_renew^3*SUMIFS(AF2:AF61,B2:B61,B18-36)+in_hlth_small_renew^4*SUMIFS(AF2:AF61,B2:B61,B18-48)) | AH18: =AH17*(1-IF(B17>=in_marketplace_from,d_hz_hlth_family*G17,0)) | AI18: =AH18*IF(B18>=in_marketplace_from,d_hz_hlth_family*G18,0) | AJ18: =F18*AI18*in_hlth_family_ticket*in_hlth_family_comm*in_ins_partner_share+F18*in_hlth_family_ticket*in_hlth_family_renew_comm*in_ins_partner_share*(in_hlth_family_renew^1*SUMIFS(AI2:AI61,B2:B61,B18-12)+in_hlth_family_renew^2*SUMIFS(AI2:AI61,B2:B61,B18-24)+in_hlth_family_renew^3*SUMIFS(AI2:AI61,B2:B61,B18-36)+in_hlth_family_renew^4*SUMIFS(AI2:AI61,B2:B61,B18-48)) | AK18: =AK17*(1-IF(B17>=in_marketplace_from,d_hz_life_term*G17,0)) | AL18: =AK18*IF(B18>=in_marketplace_from,d_hz_life_term*G18,0) | AM18: =F18*AL18*in_life_term_ticket*in_life_term_comm*in_ins_partner_share+F18*in_life_term_ticket*in_life_term_renew_comm*in_ins_partner_share*(in_life_term_renew^1*SUMIFS(AL2:AL61,B2:B61,B18-12)+in_life_term_renew^2*SUMIFS(AL2:AL61,B2:B61,B18-24)+in_life_term_renew^3*SUMIFS(AL2:AL61,B2:B61,B18-36)+in_life_term_renew^4*SUMIFS(AL2:AL61,B2:B61,B18-48)) | AN18: =AN17*(1-IF(B17>=in_marketplace_from,d_hz_accident*G17,0)) | AO18: =AN18*IF(B18>=in_marketplace_from,d_hz_accident*G18,0) | AP18: =F18*AO18*in_accident_ticket*in_accident_comm*in_ins_partner_share+F18*in_accident_ticket*in_accident_renew_comm*in_ins_partner_share*(in_accident_renew^1*SUMIFS(AO2:AO61,B2:B61,B18-12)+in_accident_renew^2*SUMIFS(AO2:AO61,B2:B61,B18-24)+in_accident_renew^3*SUMIFS(AO2:AO61,B2:B61,B18-36)+in_accident_renew^4*SUMIFS(AO2:AO61,B2:B61,B18-48)) | AQ18: =AQ17*(1-IF(B17>=in_marketplace_from,d_hz_two_wheeler*G17,0)) | AR18: =AQ18*IF(B18>=in_marketplace_from,d_hz_two_wheeler*G18,0) | AS18: =F18*AR18*in_two_wheeler_ticket*in_two_wheeler_comm*in_ins_partner_share+F18*in_two_wheeler_ticket*in_two_wheeler_comm*in_ins_partner_share*(in_two_wheeler_renew^1*SUMIFS(AR2:AR61,B2:B61,B18-12)+in_two_wheeler_renew^2*SUMIFS(AR2:AR61,B2:B61,B18-24)+in_two_wheeler_renew^3*SUMIFS(AR2:AR61,B2:B61,B18-36)+in_two_wheeler_renew^4*SUMIFS(AR2:AR61,B2:B61,B18-48)) | AT18: =AT17*(1-IF(B17>=in_marketplace_from,d_hz_device*G17,0)) | AU18: =F18*AT18*IF(B18>=in_marketplace_from,d_hz_device*G18,0)*in_device_ticket*in_device_comm*in_ins_partner_share | AV18: =AV17*(1-IF(B17>=in_marketplace_from,d_hz_shop*G17,0)) | AW18: =AV18*IF(B18>=in_marketplace_from,d_hz_shop*G18,0) | AX18: =F18*AW18*in_shop_ticket*in_shop_comm*in_ins_partner_share+F18*in_shop_ticket*in_shop_renew_comm*in_ins_partner_share*(in_shop_renew^1*SUMIFS(AW2:AW61,B2:B61,B18-12)+in_shop_renew^2*SUMIFS(AW2:AW61,B2:B61,B18-24)+in_shop_renew^3*SUMIFS(AW2:AW61,B2:B61,B18-36)+in_shop_renew^4*SUMIFS(AW2:AW61,B2:B61,B18-48)) | AY18: =AY17*(1-IF(B17>=in_marketplace_from,d_hz_sip*G17,0)) | AZ18: =AZ17*d_rho_sip+AY18*IF(B18>=in_marketplace_from,d_hz_sip*G18,0) | BA18: =d_rho_sip*(BA17+AZ17) | BB18: =F18*in_sip_ticket*(BA18+0.5*AZ18)*in_sip_comm/12 | BC18: =BC17*(1-IF(B17>=in_marketplace_from,d_hz_choti*G17,0)) | BD18: =BC18*IF(B18>=in_marketplace_from,d_hz_choti*G18,0) | BE18: =F18*SUMIFS(BD2:BD61,B2:B61,B18-in_choti_months)*in_choti_renew*in_choti_ticket | BF18: =BF17*(1-IF(B17>=in_marketplace_from,d_hz_nps*G17,0)) | BG18: =F18*BF18*IF(B18>=in_marketplace_from,d_hz_nps*G18,0)*in_nps_ticket*in_nps_comm | BH18: =BH17*(1-IF(B17>=in_marketplace_from,d_hz_gold*G17,0)) | BI18: =BI17*d_rho_gold+BH18*IF(B18>=in_marketplace_from,d_hz_gold*G18,0) | BJ18: =F18*BI18*in_gold_ticket*in_gold_comm | BK18: =BK17*(1-IF(B17>=in_marketplace_from,d_hz_fd*G17,0)) | BL18: =F18*BK18*IF(B18>=in_marketplace_from,d_hz_fd*G18,0)*in_fd_ticket*in_fd_comm | BM18: =BM17*(1-IF(B17>=in_marketplace_from,d_hz_recharge*G17,0)) | BN18: =BN17*d_rho_recharge+BM18*IF(B18>=in_marketplace_from,d_hz_recharge*G18,0) | BO18: =F18*BN18*in_recharge_ticket*in_recharge_comm/12 | BP18: =BP17*(1-IF(B17>=in_marketplace_from,d_hz_bills*G17,0)) | BQ18: =BQ17*d_rho_bills+BP18*IF(B18>=in_marketplace_from,d_hz_bills*G18,0) | BR18: =F18*BQ18*in_bills_ticket*in_bills_comm/12 | BS18: =BS17*(1-IF(B17>=in_marketplace_from,d_hz_loan_gold*G17,0)) | BT18: =F18*BS18*IF(B18>=in_marketplace_from,d_hz_loan_gold*G18,0)*in_loan_gold_ticket*in_loan_gold_comm | BU18: =BU17*(1-IF(B17>=in_marketplace_from,d_hz_loan_cd*G17,0)) | BV18: =F18*BU18*IF(B18>=in_marketplace_from,d_hz_loan_cd*G18,0)*in_loan_cd_ticket*in_loan_cd_comm | BW18: =BW17*(1-IF(B17>=in_marketplace_from,d_hz_loan_vehicle*G17,0)) | BX18: =F18*BW18*IF(B18>=in_marketplace_from,d_hz_loan_vehicle*G18,0)*in_loan_vehicle_ticket*in_loan_vehicle_comm | BY18: =BY17*(1-IF(B17>=in_marketplace_from,d_hz_loan_home*G17,0)*BZ17) | BZ18: =MIN(in_approval_cap,in_loan_home_approval*INDEX('Age profile'!$O$2:$O$61,B18)*(1+in_approval_growth)^(D18-1)) | CA18: =F18*BY18*IF(B18>=in_marketplace_from,d_hz_loan_home*G18,0)*BZ18*in_loan_home_ticket*in_loan_home_comm | CB18: =CB17*(1-IF(B17>=in_marketplace_from,d_hz_loan_lap*G17,0)*CC17) | CC18: =MIN(in_approval_cap,in_loan_lap_approval*INDEX('Age profile'!$O$2:$O$61,B18)*(1+in_approval_growth)^(D18-1)) | CD18: =F18*CB18*IF(B18>=in_marketplace_from,d_hz_loan_lap*G18,0)*CC18*in_loan_lap_ticket*in_loan_lap_comm | CE18: =AA18+AB18+AC18+AD18+AG18+AJ18+AM18+AP18+AS18+AU18+AX18+BB18+BE18+BG18+BJ18+BL18+BO18+BR18+BT18+BV18+BX18+CA18+CD18
A19: 1 | B19: 18 | C19: =A19+B19-1 | D19: =INT((C19-1)/12)+1 | E19: =INDEX(Monthly!$B$2:$B$61,A19) | F19: =E19*INDEX('Age profile'!$B$2:$B$61,B19) | G19: =MIN(in_takeup_cap,INDEX('Age profile'!$N$2:$N$61,B19)*(1+in_takeup_growth)^(D19-1)) | H19: =MIN(in_approval_cap,in_approved_first*INDEX('Age profile'!$O$2:$O$61,B19)*(1+in_approval_growth)^(D19-1)) | I19: =G19*MIN(in_takeup_cap,INDEX('Age profile'!$O$2:$O$61,B19)*(1+in_approval_growth)^(D19-1)) | J19: =(J18-L18)*F19/F18 | K19: =(K18-M18)*F19/F18+SUMIFS(O2:O18,B2:B18,B19-1-d_T)*F19 | L19: =IF(B19>=in_marketplace_from,J19*d_hz*G19*in_eligible*H19,0) | M19: =IF(B19>=in_marketplace_from,K19*d_hz*G19*in_eligible*in_approved_repeat,0) | N19: =L19+M19 | O19: =N19/F19 | P19: =F19-J19-K19 | Q19: =IF(B19>=in_marketplace_from,(J19+K19)*d_hz*G19,0) | R19: =SUMIFS(N2:N61,B2:B61,">="&(B19-d_T),B2:B61,"<="&(B19-1)) | S19: =(1-d_u)*S18+IF(d_T>in_topup_lag,SUMIFS(O2:O61,B2:B61,B19-in_topup_lag)-d_udrop*SUMIFS(O2:O61,B2:B61,B19-d_T),0) | T19: =F19*d_u*S19 | U19: =L19*in_ticket+M19*d_rep_ticket | V19: =U19+T19*d_topup_amt | W19: =N19+T19*d_topup_ratio | X19: =SUMIFS(W2:W61,B2:B61,B19-in_dpd_lag)*d_cured | Y19: =SUMIFS(W2:W61,B2:B61,B19-in_rec_lag)*d_recd | Z19: =IF(AND(B19>=in_marketplace_from,B19<in_marketplace_from+in_card_months),in_card_share/in_card_months*F19*I19,IF(AND(B19>=in_marketplace_from+in_card_months,B19<in_marketplace_from+2*in_card_months),in_card_share*d_card_rem/in_card_months*F19*MIN(in_takeup_cap,(1+in_takeup_growth)^(D19-1))*MIN(in_takeup_cap,(1+in_approval_growth)^(D19-1)),0)) | AA19: =V19*in_fee*(1-in_taken_back) | AB19: =SUMIFS(W2:W61,B2:B61,B19-in_dpd_lag)*d_dpd | AC19: =SUMIFS(W2:W61,B2:B61,B19-in_rec_lag)*d_rec | AD19: =Z19*in_card_fee | AE19: =AE18*(1-IF(B18>=in_marketplace_from,d_hz_hlth_small*G18,0)) | AF19: =AE19*IF(B19>=in_marketplace_from,d_hz_hlth_small*G19,0) | AG19: =F19*AF19*in_hlth_small_ticket*in_hlth_small_comm*in_ins_partner_share+F19*in_hlth_small_ticket*in_hlth_small_renew_comm*in_ins_partner_share*(in_hlth_small_renew^1*SUMIFS(AF2:AF61,B2:B61,B19-12)+in_hlth_small_renew^2*SUMIFS(AF2:AF61,B2:B61,B19-24)+in_hlth_small_renew^3*SUMIFS(AF2:AF61,B2:B61,B19-36)+in_hlth_small_renew^4*SUMIFS(AF2:AF61,B2:B61,B19-48)) | AH19: =AH18*(1-IF(B18>=in_marketplace_from,d_hz_hlth_family*G18,0)) | AI19: =AH19*IF(B19>=in_marketplace_from,d_hz_hlth_family*G19,0) | AJ19: =F19*AI19*in_hlth_family_ticket*in_hlth_family_comm*in_ins_partner_share+F19*in_hlth_family_ticket*in_hlth_family_renew_comm*in_ins_partner_share*(in_hlth_family_renew^1*SUMIFS(AI2:AI61,B2:B61,B19-12)+in_hlth_family_renew^2*SUMIFS(AI2:AI61,B2:B61,B19-24)+in_hlth_family_renew^3*SUMIFS(AI2:AI61,B2:B61,B19-36)+in_hlth_family_renew^4*SUMIFS(AI2:AI61,B2:B61,B19-48)) | AK19: =AK18*(1-IF(B18>=in_marketplace_from,d_hz_life_term*G18,0)) | AL19: =AK19*IF(B19>=in_marketplace_from,d_hz_life_term*G19,0) | AM19: =F19*AL19*in_life_term_ticket*in_life_term_comm*in_ins_partner_share+F19*in_life_term_ticket*in_life_term_renew_comm*in_ins_partner_share*(in_life_term_renew^1*SUMIFS(AL2:AL61,B2:B61,B19-12)+in_life_term_renew^2*SUMIFS(AL2:AL61,B2:B61,B19-24)+in_life_term_renew^3*SUMIFS(AL2:AL61,B2:B61,B19-36)+in_life_term_renew^4*SUMIFS(AL2:AL61,B2:B61,B19-48)) | AN19: =AN18*(1-IF(B18>=in_marketplace_from,d_hz_accident*G18,0)) | AO19: =AN19*IF(B19>=in_marketplace_from,d_hz_accident*G19,0) | AP19: =F19*AO19*in_accident_ticket*in_accident_comm*in_ins_partner_share+F19*in_accident_ticket*in_accident_renew_comm*in_ins_partner_share*(in_accident_renew^1*SUMIFS(AO2:AO61,B2:B61,B19-12)+in_accident_renew^2*SUMIFS(AO2:AO61,B2:B61,B19-24)+in_accident_renew^3*SUMIFS(AO2:AO61,B2:B61,B19-36)+in_accident_renew^4*SUMIFS(AO2:AO61,B2:B61,B19-48)) | AQ19: =AQ18*(1-IF(B18>=in_marketplace_from,d_hz_two_wheeler*G18,0)) | AR19: =AQ19*IF(B19>=in_marketplace_from,d_hz_two_wheeler*G19,0) | AS19: =F19*AR19*in_two_wheeler_ticket*in_two_wheeler_comm*in_ins_partner_share+F19*in_two_wheeler_ticket*in_two_wheeler_comm*in_ins_partner_share*(in_two_wheeler_renew^1*SUMIFS(AR2:AR61,B2:B61,B19-12)+in_two_wheeler_renew^2*SUMIFS(AR2:AR61,B2:B61,B19-24)+in_two_wheeler_renew^3*SUMIFS(AR2:AR61,B2:B61,B19-36)+in_two_wheeler_renew^4*SUMIFS(AR2:AR61,B2:B61,B19-48)) | AT19: =AT18*(1-IF(B18>=in_marketplace_from,d_hz_device*G18,0)) | AU19: =F19*AT19*IF(B19>=in_marketplace_from,d_hz_device*G19,0)*in_device_ticket*in_device_comm*in_ins_partner_share | AV19: =AV18*(1-IF(B18>=in_marketplace_from,d_hz_shop*G18,0)) | AW19: =AV19*IF(B19>=in_marketplace_from,d_hz_shop*G19,0) | AX19: =F19*AW19*in_shop_ticket*in_shop_comm*in_ins_partner_share+F19*in_shop_ticket*in_shop_renew_comm*in_ins_partner_share*(in_shop_renew^1*SUMIFS(AW2:AW61,B2:B61,B19-12)+in_shop_renew^2*SUMIFS(AW2:AW61,B2:B61,B19-24)+in_shop_renew^3*SUMIFS(AW2:AW61,B2:B61,B19-36)+in_shop_renew^4*SUMIFS(AW2:AW61,B2:B61,B19-48)) | AY19: =AY18*(1-IF(B18>=in_marketplace_from,d_hz_sip*G18,0)) | AZ19: =AZ18*d_rho_sip+AY19*IF(B19>=in_marketplace_from,d_hz_sip*G19,0) | BA19: =d_rho_sip*(BA18+AZ18) | BB19: =F19*in_sip_ticket*(BA19+0.5*AZ19)*in_sip_comm/12 | BC19: =BC18*(1-IF(B18>=in_marketplace_from,d_hz_choti*G18,0)) | BD19: =BC19*IF(B19>=in_marketplace_from,d_hz_choti*G19,0) | BE19: =F19*SUMIFS(BD2:BD61,B2:B61,B19-in_choti_months)*in_choti_renew*in_choti_ticket | BF19: =BF18*(1-IF(B18>=in_marketplace_from,d_hz_nps*G18,0)) | BG19: =F19*BF19*IF(B19>=in_marketplace_from,d_hz_nps*G19,0)*in_nps_ticket*in_nps_comm | BH19: =BH18*(1-IF(B18>=in_marketplace_from,d_hz_gold*G18,0)) | BI19: =BI18*d_rho_gold+BH19*IF(B19>=in_marketplace_from,d_hz_gold*G19,0) | BJ19: =F19*BI19*in_gold_ticket*in_gold_comm | BK19: =BK18*(1-IF(B18>=in_marketplace_from,d_hz_fd*G18,0)) | BL19: =F19*BK19*IF(B19>=in_marketplace_from,d_hz_fd*G19,0)*in_fd_ticket*in_fd_comm | BM19: =BM18*(1-IF(B18>=in_marketplace_from,d_hz_recharge*G18,0)) | BN19: =BN18*d_rho_recharge+BM19*IF(B19>=in_marketplace_from,d_hz_recharge*G19,0) | BO19: =F19*BN19*in_recharge_ticket*in_recharge_comm/12 | BP19: =BP18*(1-IF(B18>=in_marketplace_from,d_hz_bills*G18,0)) | BQ19: =BQ18*d_rho_bills+BP19*IF(B19>=in_marketplace_from,d_hz_bills*G19,0) | BR19: =F19*BQ19*in_bills_ticket*in_bills_comm/12 | BS19: =BS18*(1-IF(B18>=in_marketplace_from,d_hz_loan_gold*G18,0)) | BT19: =F19*BS19*IF(B19>=in_marketplace_from,d_hz_loan_gold*G19,0)*in_loan_gold_ticket*in_loan_gold_comm | BU19: =BU18*(1-IF(B18>=in_marketplace_from,d_hz_loan_cd*G18,0)) | BV19: =F19*BU19*IF(B19>=in_marketplace_from,d_hz_loan_cd*G19,0)*in_loan_cd_ticket*in_loan_cd_comm | BW19: =BW18*(1-IF(B18>=in_marketplace_from,d_hz_loan_vehicle*G18,0)) | BX19: =F19*BW19*IF(B19>=in_marketplace_from,d_hz_loan_vehicle*G19,0)*in_loan_vehicle_ticket*in_loan_vehicle_comm | BY19: =BY18*(1-IF(B18>=in_marketplace_from,d_hz_loan_home*G18,0)*BZ18) | BZ19: =MIN(in_approval_cap,in_loan_home_approval*INDEX('Age profile'!$O$2:$O$61,B19)*(1+in_approval_growth)^(D19-1)) | CA19: =F19*BY19*IF(B19>=in_marketplace_from,d_hz_loan_home*G19,0)*BZ19*in_loan_home_ticket*in_loan_home_comm | CB19: =CB18*(1-IF(B18>=in_marketplace_from,d_hz_loan_lap*G18,0)*CC18) | CC19: =MIN(in_approval_cap,in_loan_lap_approval*INDEX('Age profile'!$O$2:$O$61,B19)*(1+in_approval_growth)^(D19-1)) | CD19: =F19*CB19*IF(B19>=in_marketplace_from,d_hz_loan_lap*G19,0)*CC19*in_loan_lap_ticket*in_loan_lap_comm | CE19: =AA19+AB19+AC19+AD19+AG19+AJ19+AM19+AP19+AS19+AU19+AX19+BB19+BE19+BG19+BJ19+BL19+BO19+BR19+BT19+BV19+BX19+CA19+CD19
A20: 1 | B20: 19 | C20: =A20+B20-1 | D20: =INT((C20-1)/12)+1 | E20: =INDEX(Monthly!$B$2:$B$61,A20) | F20: =E20*INDEX('Age profile'!$B$2:$B$61,B20) | G20: =MIN(in_takeup_cap,INDEX('Age profile'!$N$2:$N$61,B20)*(1+in_takeup_growth)^(D20-1)) | H20: =MIN(in_approval_cap,in_approved_first*INDEX('Age profile'!$O$2:$O$61,B20)*(1+in_approval_growth)^(D20-1)) | I20: =G20*MIN(in_takeup_cap,INDEX('Age profile'!$O$2:$O$61,B20)*(1+in_approval_growth)^(D20-1)) | J20: =(J19-L19)*F20/F19 | K20: =(K19-M19)*F20/F19+SUMIFS(O2:O19,B2:B19,B20-1-d_T)*F20 | L20: =IF(B20>=in_marketplace_from,J20*d_hz*G20*in_eligible*H20,0) | M20: =IF(B20>=in_marketplace_from,K20*d_hz*G20*in_eligible*in_approved_repeat,0) | N20: =L20+M20 | O20: =N20/F20 | P20: =F20-J20-K20 | Q20: =IF(B20>=in_marketplace_from,(J20+K20)*d_hz*G20,0) | R20: =SUMIFS(N2:N61,B2:B61,">="&(B20-d_T),B2:B61,"<="&(B20-1)) | S20: =(1-d_u)*S19+IF(d_T>in_topup_lag,SUMIFS(O2:O61,B2:B61,B20-in_topup_lag)-d_udrop*SUMIFS(O2:O61,B2:B61,B20-d_T),0) | T20: =F20*d_u*S20 | U20: =L20*in_ticket+M20*d_rep_ticket | V20: =U20+T20*d_topup_amt | W20: =N20+T20*d_topup_ratio | X20: =SUMIFS(W2:W61,B2:B61,B20-in_dpd_lag)*d_cured | Y20: =SUMIFS(W2:W61,B2:B61,B20-in_rec_lag)*d_recd | Z20: =IF(AND(B20>=in_marketplace_from,B20<in_marketplace_from+in_card_months),in_card_share/in_card_months*F20*I20,IF(AND(B20>=in_marketplace_from+in_card_months,B20<in_marketplace_from+2*in_card_months),in_card_share*d_card_rem/in_card_months*F20*MIN(in_takeup_cap,(1+in_takeup_growth)^(D20-1))*MIN(in_takeup_cap,(1+in_approval_growth)^(D20-1)),0)) | AA20: =V20*in_fee*(1-in_taken_back) | AB20: =SUMIFS(W2:W61,B2:B61,B20-in_dpd_lag)*d_dpd | AC20: =SUMIFS(W2:W61,B2:B61,B20-in_rec_lag)*d_rec | AD20: =Z20*in_card_fee | AE20: =AE19*(1-IF(B19>=in_marketplace_from,d_hz_hlth_small*G19,0)) | AF20: =AE20*IF(B20>=in_marketplace_from,d_hz_hlth_small*G20,0) | AG20: =F20*AF20*in_hlth_small_ticket*in_hlth_small_comm*in_ins_partner_share+F20*in_hlth_small_ticket*in_hlth_small_renew_comm*in_ins_partner_share*(in_hlth_small_renew^1*SUMIFS(AF2:AF61,B2:B61,B20-12)+in_hlth_small_renew^2*SUMIFS(AF2:AF61,B2:B61,B20-24)+in_hlth_small_renew^3*SUMIFS(AF2:AF61,B2:B61,B20-36)+in_hlth_small_renew^4*SUMIFS(AF2:AF61,B2:B61,B20-48)) | AH20: =AH19*(1-IF(B19>=in_marketplace_from,d_hz_hlth_family*G19,0)) | AI20: =AH20*IF(B20>=in_marketplace_from,d_hz_hlth_family*G20,0) | AJ20: =F20*AI20*in_hlth_family_ticket*in_hlth_family_comm*in_ins_partner_share+F20*in_hlth_family_ticket*in_hlth_family_renew_comm*in_ins_partner_share*(in_hlth_family_renew^1*SUMIFS(AI2:AI61,B2:B61,B20-12)+in_hlth_family_renew^2*SUMIFS(AI2:AI61,B2:B61,B20-24)+in_hlth_family_renew^3*SUMIFS(AI2:AI61,B2:B61,B20-36)+in_hlth_family_renew^4*SUMIFS(AI2:AI61,B2:B61,B20-48)) | AK20: =AK19*(1-IF(B19>=in_marketplace_from,d_hz_life_term*G19,0)) | AL20: =AK20*IF(B20>=in_marketplace_from,d_hz_life_term*G20,0) | AM20: =F20*AL20*in_life_term_ticket*in_life_term_comm*in_ins_partner_share+F20*in_life_term_ticket*in_life_term_renew_comm*in_ins_partner_share*(in_life_term_renew^1*SUMIFS(AL2:AL61,B2:B61,B20-12)+in_life_term_renew^2*SUMIFS(AL2:AL61,B2:B61,B20-24)+in_life_term_renew^3*SUMIFS(AL2:AL61,B2:B61,B20-36)+in_life_term_renew^4*SUMIFS(AL2:AL61,B2:B61,B20-48)) | AN20: =AN19*(1-IF(B19>=in_marketplace_from,d_hz_accident*G19,0)) | AO20: =AN20*IF(B20>=in_marketplace_from,d_hz_accident*G20,0) | AP20: =F20*AO20*in_accident_ticket*in_accident_comm*in_ins_partner_share+F20*in_accident_ticket*in_accident_renew_comm*in_ins_partner_share*(in_accident_renew^1*SUMIFS(AO2:AO61,B2:B61,B20-12)+in_accident_renew^2*SUMIFS(AO2:AO61,B2:B61,B20-24)+in_accident_renew^3*SUMIFS(AO2:AO61,B2:B61,B20-36)+in_accident_renew^4*SUMIFS(AO2:AO61,B2:B61,B20-48)) | AQ20: =AQ19*(1-IF(B19>=in_marketplace_from,d_hz_two_wheeler*G19,0)) | AR20: =AQ20*IF(B20>=in_marketplace_from,d_hz_two_wheeler*G20,0) | AS20: =F20*AR20*in_two_wheeler_ticket*in_two_wheeler_comm*in_ins_partner_share+F20*in_two_wheeler_ticket*in_two_wheeler_comm*in_ins_partner_share*(in_two_wheeler_renew^1*SUMIFS(AR2:AR61,B2:B61,B20-12)+in_two_wheeler_renew^2*SUMIFS(AR2:AR61,B2:B61,B20-24)+in_two_wheeler_renew^3*SUMIFS(AR2:AR61,B2:B61,B20-36)+in_two_wheeler_renew^4*SUMIFS(AR2:AR61,B2:B61,B20-48)) | AT20: =AT19*(1-IF(B19>=in_marketplace_from,d_hz_device*G19,0)) | AU20: =F20*AT20*IF(B20>=in_marketplace_from,d_hz_device*G20,0)*in_device_ticket*in_device_comm*in_ins_partner_share | AV20: =AV19*(1-IF(B19>=in_marketplace_from,d_hz_shop*G19,0)) | AW20: =AV20*IF(B20>=in_marketplace_from,d_hz_shop*G20,0) | AX20: =F20*AW20*in_shop_ticket*in_shop_comm*in_ins_partner_share+F20*in_shop_ticket*in_shop_renew_comm*in_ins_partner_share*(in_shop_renew^1*SUMIFS(AW2:AW61,B2:B61,B20-12)+in_shop_renew^2*SUMIFS(AW2:AW61,B2:B61,B20-24)+in_shop_renew^3*SUMIFS(AW2:AW61,B2:B61,B20-36)+in_shop_renew^4*SUMIFS(AW2:AW61,B2:B61,B20-48)) | AY20: =AY19*(1-IF(B19>=in_marketplace_from,d_hz_sip*G19,0)) | AZ20: =AZ19*d_rho_sip+AY20*IF(B20>=in_marketplace_from,d_hz_sip*G20,0) | BA20: =d_rho_sip*(BA19+AZ19) | BB20: =F20*in_sip_ticket*(BA20+0.5*AZ20)*in_sip_comm/12 | BC20: =BC19*(1-IF(B19>=in_marketplace_from,d_hz_choti*G19,0)) | BD20: =BC20*IF(B20>=in_marketplace_from,d_hz_choti*G20,0) | BE20: =F20*SUMIFS(BD2:BD61,B2:B61,B20-in_choti_months)*in_choti_renew*in_choti_ticket | BF20: =BF19*(1-IF(B19>=in_marketplace_from,d_hz_nps*G19,0)) | BG20: =F20*BF20*IF(B20>=in_marketplace_from,d_hz_nps*G20,0)*in_nps_ticket*in_nps_comm | BH20: =BH19*(1-IF(B19>=in_marketplace_from,d_hz_gold*G19,0)) | BI20: =BI19*d_rho_gold+BH20*IF(B20>=in_marketplace_from,d_hz_gold*G20,0) | BJ20: =F20*BI20*in_gold_ticket*in_gold_comm | BK20: =BK19*(1-IF(B19>=in_marketplace_from,d_hz_fd*G19,0)) | BL20: =F20*BK20*IF(B20>=in_marketplace_from,d_hz_fd*G20,0)*in_fd_ticket*in_fd_comm | BM20: =BM19*(1-IF(B19>=in_marketplace_from,d_hz_recharge*G19,0)) | BN20: =BN19*d_rho_recharge+BM20*IF(B20>=in_marketplace_from,d_hz_recharge*G20,0) | BO20: =F20*BN20*in_recharge_ticket*in_recharge_comm/12 | BP20: =BP19*(1-IF(B19>=in_marketplace_from,d_hz_bills*G19,0)) | BQ20: =BQ19*d_rho_bills+BP20*IF(B20>=in_marketplace_from,d_hz_bills*G20,0) | BR20: =F20*BQ20*in_bills_ticket*in_bills_comm/12 | BS20: =BS19*(1-IF(B19>=in_marketplace_from,d_hz_loan_gold*G19,0)) | BT20: =F20*BS20*IF(B20>=in_marketplace_from,d_hz_loan_gold*G20,0)*in_loan_gold_ticket*in_loan_gold_comm | BU20: =BU19*(1-IF(B19>=in_marketplace_from,d_hz_loan_cd*G19,0)) | BV20: =F20*BU20*IF(B20>=in_marketplace_from,d_hz_loan_cd*G20,0)*in_loan_cd_ticket*in_loan_cd_comm | BW20: =BW19*(1-IF(B19>=in_marketplace_from,d_hz_loan_vehicle*G19,0)) | BX20: =F20*BW20*IF(B20>=in_marketplace_from,d_hz_loan_vehicle*G20,0)*in_loan_vehicle_ticket*in_loan_vehicle_comm | BY20: =BY19*(1-IF(B19>=in_marketplace_from,d_hz_loan_home*G19,0)*BZ19) | BZ20: =MIN(in_approval_cap,in_loan_home_approval*INDEX('Age profile'!$O$2:$O$61,B20)*(1+in_approval_growth)^(D20-1)) | CA20: =F20*BY20*IF(B20>=in_marketplace_from,d_hz_loan_home*G20,0)*BZ20*in_loan_home_ticket*in_loan_home_comm | CB20: =CB19*(1-IF(B19>=in_marketplace_from,d_hz_loan_lap*G19,0)*CC19) | CC20: =MIN(in_approval_cap,in_loan_lap_approval*INDEX('Age profile'!$O$2:$O$61,B20)*(1+in_approval_growth)^(D20-1)) | CD20: =F20*CB20*IF(B20>=in_marketplace_from,d_hz_loan_lap*G20,0)*CC20*in_loan_lap_ticket*in_loan_lap_comm | CE20: =AA20+AB20+AC20+AD20+AG20+AJ20+AM20+AP20+AS20+AU20+AX20+BB20+BE20+BG20+BJ20+BL20+BO20+BR20+BT20+BV20+BX20+CA20+CD20
A21: 1 | B21: 20 | C21: =A21+B21-1 | D21: =INT((C21-1)/12)+1 | E21: =INDEX(Monthly!$B$2:$B$61,A21) | F21: =E21*INDEX('Age profile'!$B$2:$B$61,B21) | G21: =MIN(in_takeup_cap,INDEX('Age profile'!$N$2:$N$61,B21)*(1+in_takeup_growth)^(D21-1)) | H21: =MIN(in_approval_cap,in_approved_first*INDEX('Age profile'!$O$2:$O$61,B21)*(1+in_approval_growth)^(D21-1)) | I21: =G21*MIN(in_takeup_cap,INDEX('Age profile'!$O$2:$O$61,B21)*(1+in_approval_growth)^(D21-1)) | J21: =(J20-L20)*F21/F20 | K21: =(K20-M20)*F21/F20+SUMIFS(O2:O20,B2:B20,B21-1-d_T)*F21 | L21: =IF(B21>=in_marketplace_from,J21*d_hz*G21*in_eligible*H21,0) | M21: =IF(B21>=in_marketplace_from,K21*d_hz*G21*in_eligible*in_approved_repeat,0) | N21: =L21+M21 | O21: =N21/F21 | P21: =F21-J21-K21 | Q21: =IF(B21>=in_marketplace_from,(J21+K21)*d_hz*G21,0) | R21: =SUMIFS(N2:N61,B2:B61,">="&(B21-d_T),B2:B61,"<="&(B21-1)) | S21: =(1-d_u)*S20+IF(d_T>in_topup_lag,SUMIFS(O2:O61,B2:B61,B21-in_topup_lag)-d_udrop*SUMIFS(O2:O61,B2:B61,B21-d_T),0) | T21: =F21*d_u*S21 | U21: =L21*in_ticket+M21*d_rep_ticket | V21: =U21+T21*d_topup_amt | W21: =N21+T21*d_topup_ratio | X21: =SUMIFS(W2:W61,B2:B61,B21-in_dpd_lag)*d_cured | Y21: =SUMIFS(W2:W61,B2:B61,B21-in_rec_lag)*d_recd | Z21: =IF(AND(B21>=in_marketplace_from,B21<in_marketplace_from+in_card_months),in_card_share/in_card_months*F21*I21,IF(AND(B21>=in_marketplace_from+in_card_months,B21<in_marketplace_from+2*in_card_months),in_card_share*d_card_rem/in_card_months*F21*MIN(in_takeup_cap,(1+in_takeup_growth)^(D21-1))*MIN(in_takeup_cap,(1+in_approval_growth)^(D21-1)),0)) | AA21: =V21*in_fee*(1-in_taken_back) | AB21: =SUMIFS(W2:W61,B2:B61,B21-in_dpd_lag)*d_dpd | AC21: =SUMIFS(W2:W61,B2:B61,B21-in_rec_lag)*d_rec | AD21: =Z21*in_card_fee | AE21: =AE20*(1-IF(B20>=in_marketplace_from,d_hz_hlth_small*G20,0)) | AF21: =AE21*IF(B21>=in_marketplace_from,d_hz_hlth_small*G21,0) | AG21: =F21*AF21*in_hlth_small_ticket*in_hlth_small_comm*in_ins_partner_share+F21*in_hlth_small_ticket*in_hlth_small_renew_comm*in_ins_partner_share*(in_hlth_small_renew^1*SUMIFS(AF2:AF61,B2:B61,B21-12)+in_hlth_small_renew^2*SUMIFS(AF2:AF61,B2:B61,B21-24)+in_hlth_small_renew^3*SUMIFS(AF2:AF61,B2:B61,B21-36)+in_hlth_small_renew^4*SUMIFS(AF2:AF61,B2:B61,B21-48)) | AH21: =AH20*(1-IF(B20>=in_marketplace_from,d_hz_hlth_family*G20,0)) | AI21: =AH21*IF(B21>=in_marketplace_from,d_hz_hlth_family*G21,0) | AJ21: =F21*AI21*in_hlth_family_ticket*in_hlth_family_comm*in_ins_partner_share+F21*in_hlth_family_ticket*in_hlth_family_renew_comm*in_ins_partner_share*(in_hlth_family_renew^1*SUMIFS(AI2:AI61,B2:B61,B21-12)+in_hlth_family_renew^2*SUMIFS(AI2:AI61,B2:B61,B21-24)+in_hlth_family_renew^3*SUMIFS(AI2:AI61,B2:B61,B21-36)+in_hlth_family_renew^4*SUMIFS(AI2:AI61,B2:B61,B21-48)) | AK21: =AK20*(1-IF(B20>=in_marketplace_from,d_hz_life_term*G20,0)) | AL21: =AK21*IF(B21>=in_marketplace_from,d_hz_life_term*G21,0) | AM21: =F21*AL21*in_life_term_ticket*in_life_term_comm*in_ins_partner_share+F21*in_life_term_ticket*in_life_term_renew_comm*in_ins_partner_share*(in_life_term_renew^1*SUMIFS(AL2:AL61,B2:B61,B21-12)+in_life_term_renew^2*SUMIFS(AL2:AL61,B2:B61,B21-24)+in_life_term_renew^3*SUMIFS(AL2:AL61,B2:B61,B21-36)+in_life_term_renew^4*SUMIFS(AL2:AL61,B2:B61,B21-48)) | AN21: =AN20*(1-IF(B20>=in_marketplace_from,d_hz_accident*G20,0)) | AO21: =AN21*IF(B21>=in_marketplace_from,d_hz_accident*G21,0) | AP21: =F21*AO21*in_accident_ticket*in_accident_comm*in_ins_partner_share+F21*in_accident_ticket*in_accident_renew_comm*in_ins_partner_share*(in_accident_renew^1*SUMIFS(AO2:AO61,B2:B61,B21-12)+in_accident_renew^2*SUMIFS(AO2:AO61,B2:B61,B21-24)+in_accident_renew^3*SUMIFS(AO2:AO61,B2:B61,B21-36)+in_accident_renew^4*SUMIFS(AO2:AO61,B2:B61,B21-48)) | AQ21: =AQ20*(1-IF(B20>=in_marketplace_from,d_hz_two_wheeler*G20,0)) | AR21: =AQ21*IF(B21>=in_marketplace_from,d_hz_two_wheeler*G21,0) | AS21: =F21*AR21*in_two_wheeler_ticket*in_two_wheeler_comm*in_ins_partner_share+F21*in_two_wheeler_ticket*in_two_wheeler_comm*in_ins_partner_share*(in_two_wheeler_renew^1*SUMIFS(AR2:AR61,B2:B61,B21-12)+in_two_wheeler_renew^2*SUMIFS(AR2:AR61,B2:B61,B21-24)+in_two_wheeler_renew^3*SUMIFS(AR2:AR61,B2:B61,B21-36)+in_two_wheeler_renew^4*SUMIFS(AR2:AR61,B2:B61,B21-48)) | AT21: =AT20*(1-IF(B20>=in_marketplace_from,d_hz_device*G20,0)) | AU21: =F21*AT21*IF(B21>=in_marketplace_from,d_hz_device*G21,0)*in_device_ticket*in_device_comm*in_ins_partner_share | AV21: =AV20*(1-IF(B20>=in_marketplace_from,d_hz_shop*G20,0)) | AW21: =AV21*IF(B21>=in_marketplace_from,d_hz_shop*G21,0) | AX21: =F21*AW21*in_shop_ticket*in_shop_comm*in_ins_partner_share+F21*in_shop_ticket*in_shop_renew_comm*in_ins_partner_share*(in_shop_renew^1*SUMIFS(AW2:AW61,B2:B61,B21-12)+in_shop_renew^2*SUMIFS(AW2:AW61,B2:B61,B21-24)+in_shop_renew^3*SUMIFS(AW2:AW61,B2:B61,B21-36)+in_shop_renew^4*SUMIFS(AW2:AW61,B2:B61,B21-48)) | AY21: =AY20*(1-IF(B20>=in_marketplace_from,d_hz_sip*G20,0)) | AZ21: =AZ20*d_rho_sip+AY21*IF(B21>=in_marketplace_from,d_hz_sip*G21,0) | BA21: =d_rho_sip*(BA20+AZ20) | BB21: =F21*in_sip_ticket*(BA21+0.5*AZ21)*in_sip_comm/12 | BC21: =BC20*(1-IF(B20>=in_marketplace_from,d_hz_choti*G20,0)) | BD21: =BC21*IF(B21>=in_marketplace_from,d_hz_choti*G21,0) | BE21: =F21*SUMIFS(BD2:BD61,B2:B61,B21-in_choti_months)*in_choti_renew*in_choti_ticket | BF21: =BF20*(1-IF(B20>=in_marketplace_from,d_hz_nps*G20,0)) | BG21: =F21*BF21*IF(B21>=in_marketplace_from,d_hz_nps*G21,0)*in_nps_ticket*in_nps_comm | BH21: =BH20*(1-IF(B20>=in_marketplace_from,d_hz_gold*G20,0)) | BI21: =BI20*d_rho_gold+BH21*IF(B21>=in_marketplace_from,d_hz_gold*G21,0) | BJ21: =F21*BI21*in_gold_ticket*in_gold_comm | BK21: =BK20*(1-IF(B20>=in_marketplace_from,d_hz_fd*G20,0)) | BL21: =F21*BK21*IF(B21>=in_marketplace_from,d_hz_fd*G21,0)*in_fd_ticket*in_fd_comm | BM21: =BM20*(1-IF(B20>=in_marketplace_from,d_hz_recharge*G20,0)) | BN21: =BN20*d_rho_recharge+BM21*IF(B21>=in_marketplace_from,d_hz_recharge*G21,0) | BO21: =F21*BN21*in_recharge_ticket*in_recharge_comm/12 | BP21: =BP20*(1-IF(B20>=in_marketplace_from,d_hz_bills*G20,0)) | BQ21: =BQ20*d_rho_bills+BP21*IF(B21>=in_marketplace_from,d_hz_bills*G21,0) | BR21: =F21*BQ21*in_bills_ticket*in_bills_comm/12 | BS21: =BS20*(1-IF(B20>=in_marketplace_from,d_hz_loan_gold*G20,0)) | BT21: =F21*BS21*IF(B21>=in_marketplace_from,d_hz_loan_gold*G21,0)*in_loan_gold_ticket*in_loan_gold_comm | BU21: =BU20*(1-IF(B20>=in_marketplace_from,d_hz_loan_cd*G20,0)) | BV21: =F21*BU21*IF(B21>=in_marketplace_from,d_hz_loan_cd*G21,0)*in_loan_cd_ticket*in_loan_cd_comm | BW21: =BW20*(1-IF(B20>=in_marketplace_from,d_hz_loan_vehicle*G20,0)) | BX21: =F21*BW21*IF(B21>=in_marketplace_from,d_hz_loan_vehicle*G21,0)*in_loan_vehicle_ticket*in_loan_vehicle_comm | BY21: =BY20*(1-IF(B20>=in_marketplace_from,d_hz_loan_home*G20,0)*BZ20) | BZ21: =MIN(in_approval_cap,in_loan_home_approval*INDEX('Age profile'!$O$2:$O$61,B21)*(1+in_approval_growth)^(D21-1)) | CA21: =F21*BY21*IF(B21>=in_marketplace_from,d_hz_loan_home*G21,0)*BZ21*in_loan_home_ticket*in_loan_home_comm | CB21: =CB20*(1-IF(B20>=in_marketplace_from,d_hz_loan_lap*G20,0)*CC20) | CC21: =MIN(in_approval_cap,in_loan_lap_approval*INDEX('Age profile'!$O$2:$O$61,B21)*(1+in_approval_growth)^(D21-1)) | CD21: =F21*CB21*IF(B21>=in_marketplace_from,d_hz_loan_lap*G21,0)*CC21*in_loan_lap_ticket*in_loan_lap_comm | CE21: =AA21+AB21+AC21+AD21+AG21+AJ21+AM21+AP21+AS21+AU21+AX21+BB21+BE21+BG21+BJ21+BL21+BO21+BR21+BT21+BV21+BX21+CA21+CD21
